{
  "type": "Feature",
  "properties": {
    "iso:country":"BG",
    "name:eng_x_preferred":[
        "\u041c\u0430\u0440\u0438\u0446\u0430 \u0441\u0435\u0432\u0435\u0440"
    ],
    "wof:name":"Maritsa Sever",
    "wof:placetype":"neighbourhood"
},
  "geometry": {"coordinates":[24.70773027191901,42.15274717171003],"type":"Point"}
}