{
  "type": "Feature",
  "properties": {
    "gn:admin1_code":"44",
    "gn:asciiname":"Krepost",
    "gn:country_code":"BG",
    "gn:dem":608,
    "gn:feature_class":"P",
    "gn:feature_code":"PPL",
    "gn:name":"Krepost",
    "gn:population":0,
    "gn:timezone":"Europe/Sofia",
    "iso:country":"BG",
    "name:bul_x_preferred":[
        "Krepost"
    ],
    "name:bul_x_variant":[
        "\u041a\u0440\u0435\u043f\u043e\u0441\u0442"
    ],
    "name:fra_x_preferred":[
        "Krepost"
    ],
    "wof:name":"Krepost",
    "wof:placetype":"locality"
},
  "geometry": {"coordinates":[25.51303,41.36505],"type":"Point"}
}