{
  "type": "Feature",
  "properties": {
    "gn:admin1_code":"41",
    "gn:admin2_code":"GAB05",
    "gn:asciiname":"Bekriite",
    "gn:cc2":"BG",
    "gn:country_code":"BG",
    "gn:dem":522,
    "gn:feature_class":"P",
    "gn:feature_code":"PPL",
    "gn:name":"Bekriite",
    "gn:population":0,
    "gn:timezone":"Europe/Sofia",
    "iso:country":"BG",
    "name:ara_x_preferred":[
        "\u0628\u064a\u0643\u0631\u064a\u064a\u062a"
    ],
    "name:bul_x_preferred":[
        "\u0411\u0435\u043a\u0440\u0438\u0438\u0442\u0435"
    ],
    "name:fas_x_preferred":[
        "\u0628\u06a9\u0631\u06cc\u06cc\u062a\u0647"
    ],
    "name:kaz_x_preferred":[
        "\u0411\u0435\u043a\u0440\u0438\u0438\u0442\u0435"
    ],
    "name:pol_x_preferred":[
        "Bekriite"
    ],
    "name:ron_x_preferred":[
        "Bekriite"
    ],
    "name:rus_x_preferred":[
        "\u0411\u0435\u043a\u0440\u0438\u0438\u0442\u0435"
    ],
    "name:ukr_x_preferred":[
        "\u0411\u0435\u043a\u0440\u0456\u0457\u0442\u0435"
    ],
    "name:und_x_variant":[
        "Kolibi Bekriite",
        "Bikriyts\u016d",
        "Bekriite"
    ],
    "wof:name":"Bekriite",
    "wof:placetype":"locality"
},
  "geometry": {"coordinates":[25.31667,42.93333],"type":"Point"}
}