{
  "type": "Feature",
  "properties": {
    "gn:admin1_code":"45",
    "gn:admin2_code":"KNL38",
    "gn:admin3_code":"KNL38-04",
    "gn:asciiname":"Smochevo",
    "gn:country_code":"BG",
    "gn:dem":675,
    "gn:feature_class":"P",
    "gn:feature_code":"PPL",
    "gn:name":"Smochevo",
    "gn:population":0,
    "gn:timezone":"Europe/Sofia",
    "iso:country":"BG",
    "name:bul_x_preferred":[
        "\u0421\u043c\u043e\u0447\u0435\u0432\u043e"
    ],
    "name:und_x_variant":[
        "Smotschewo",
        "Smochevo"
    ],
    "wof:name":"Smochevo",
    "wof:placetype":"locality"
},
  "geometry": {"coordinates":[23.09512,42.14827],"type":"Point"}
}