{
  "type": "Feature",
  "properties": {
    "gn:admin1_code":"44",
    "gn:admin2_code":"KRZ15",
    "gn:admin3_code":"KRZ15-35",
    "gn:asciiname":"Ribino",
    "gn:country_code":"BG",
    "gn:dem":404,
    "gn:feature_class":"P",
    "gn:feature_code":"PPLL",
    "gn:name":"Ribino",
    "gn:population":0,
    "gn:timezone":"Europe/Sofia",
    "iso:country":"BG",
    "name:bul_x_preferred":[
        "\u0420\u0438\u0431\u0438\u043d\u043e"
    ],
    "name:und_x_variant":[
        "Bal\u016dk",
        "Ribino"
    ],
    "wof:name":"Ribino",
    "wof:placetype":"locality"
},
  "geometry": {"coordinates":[25.51883,41.409],"type":"Point"}
}