{
  "type": "Feature",
  "properties": {
    "gn:admin1_code":"44",
    "gn:admin2_code":"KRZ35",
    "gn:admin3_code":"KRZ35-12",
    "gn:asciiname":"Kopitnik",
    "gn:cc2":"BG",
    "gn:country_code":"BG",
    "gn:dem":608,
    "gn:feature_class":"P",
    "gn:feature_code":"PPL",
    "gn:name":"Kopitnik",
    "gn:population":0,
    "gn:timezone":"Europe/Sofia",
    "iso:country":"BG",
    "name:bul_x_preferred":[
        "\u041a\u043e\u043f\u0438\u0442\u043d\u0438\u043a"
    ],
    "name:fas_x_preferred":[
        "\u06a9\u0648\u067e\u06cc\u062a\u0646\u06cc\u06a9"
    ],
    "name:kaz_x_preferred":[
        "\u041a\u043e\u043f\u0438\u0442\u043d\u0438\u043a"
    ],
    "name:ron_x_preferred":[
        "Kopitnik"
    ],
    "name:rus_x_preferred":[
        "\u041a\u043e\u043f\u0438\u0442\u043d\u0438\u043a"
    ],
    "name:ukr_x_preferred":[
        "\u041a\u043e\u043f\u0438\u0442\u043d\u0438\u043a"
    ],
    "name:und_x_variant":[
        "Yaylal\u016d",
        "Kopitnik"
    ],
    "wof:name":"Kopitnik",
    "wof:placetype":"locality"
},
  "geometry": {"coordinates":[25.21667,41.78333],"type":"Point"}
}