{
  "type": "Feature",
  "properties": {
    "gn:admin1_code":"44",
    "gn:admin2_code":"KRZ14",
    "gn:admin3_code":"KRZ14-10",
    "gn:asciiname":"Dedets",
    "gn:country_code":"BG",
    "gn:dem":372,
    "gn:feature_class":"P",
    "gn:feature_code":"PPL",
    "gn:name":"Dedets",
    "gn:population":0,
    "gn:timezone":"Europe/Sofia",
    "iso:country":"BG",
    "name:bul_x_preferred":[
        "\u0414\u0435\u0434\u0435\u0446"
    ],
    "name:und_x_variant":[
        "Dedeler",
        "Dedets"
    ],
    "wof:name":"Dedets",
    "wof:placetype":"locality"
},
  "geometry": {"coordinates":[25.22972,41.38504],"type":"Point"}
}