{
  "type": "Feature",
  "properties": {
    "gn:admin1_code":"62",
    "gn:admin2_code":"VTR13",
    "gn:asciiname":"Gabraka",
    "gn:cc2":"BG",
    "gn:country_code":"BG",
    "gn:dem":609,
    "gn:feature_class":"P",
    "gn:feature_code":"PPL",
    "gn:name":"Gabraka",
    "gn:population":0,
    "gn:timezone":"Europe/Sofia",
    "iso:country":"BG",
    "name:bul_x_preferred":[
        "\u0413\u0430\u0431\u0440\u0430\u043a\u0430"
    ],
    "name:und_x_variant":[
        "Gadrak",
        "Gabraka"
    ],
    "wof:name":"Gabraka",
    "wof:placetype":"locality"
},
  "geometry": {"coordinates":[25.86667000000001,42.83333],"type":"Point"}
}