{
  "type": "Feature",
  "properties": {
    "gn:admin1_code":"44",
    "gn:admin2_code":"KRZ21",
    "gn:asciiname":"Kamenets",
    "gn:country_code":"BG",
    "gn:dem":532,
    "gn:feature_class":"P",
    "gn:feature_code":"PPL",
    "gn:name":"Kamenets",
    "gn:population":0,
    "gn:timezone":"Europe/Sofia",
    "iso:country":"BG",
    "name:bul_x_preferred":[
        "\u041a\u0430\u043c\u0435\u043d\u0435\u0446"
    ],
    "name:ceb_x_preferred":[
        "Kamenets"
    ],
    "name:fra_x_preferred":[
        "Kamenets"
    ],
    "name:ita_x_preferred":[
        "Kamenec"
    ],
    "name:swe_x_preferred":[
        "Kamenets"
    ],
    "name:und_x_variant":[
        "Bektashi",
        "Bektash",
        "Bektaschi",
        "Bekta\u0161i",
        "Bektashler",
        "Kamenets"
    ],
    "wof:name":"Kamenets",
    "wof:placetype":"locality"
},
  "geometry": {"coordinates":[25.40734,41.47081],"type":"Point"}
}