{
  "type": "Feature",
  "properties": {
    "gn:gn_country":"BG",
    "gn:gn_fcode":"PPL",
    "gn:gn_pop":0,
    "iso:country":"BG",
    "name:bul_x_preferred":[
        "\u0414\u043e\u043b\u0435\u043d\u0438"
    ],
    "name:unk_x_variant":[
        "Dolen"
    ],
    "qs_pg:aaroncc":"BG",
    "qs_pg:gn_country":"BG",
    "qs_pg:gn_fcode":"PPL",
    "qs_pg:gn_pop":0,
    "qs_pg:name":"Doleni",
    "qs_pg:name_adm0":"Bulgaria",
    "qs_pg:name_adm1":"Blagoevgrad",
    "qs_pg:photos":23,
    "qs_pg:photos_1k":5,
    "qs_pg:photos_9k":1,
    "qs_pg:photos_9r":1,
    "qs_pg:photos_all":23,
    "qs_pg:photos_sr":1,
    "qs_pg:pop_sr":0,
    "qs_pg:qs_pg_placetype":"locality",
    "qs_pg:qs_pg_placetype_gp":"Town",
    "qs_pg:woe_adm0":23424771,
    "woe:adm0_id":23424771,
    "woe:name_adm0":"Bulgaria",
    "woe:name_adm1":"Blagoevgrad",
    "woe:placetype":"Town",
    "wof:name":"Doleni",
    "wof:placetype":"locality"
},
  "geometry": {"coordinates":[23.41667,41.56667],"type":"Point"}
}