{
  "type": "Feature",
  "properties": {
    "gn:admin1_code":"52",
    "gn:admin2_code":"RAZ29",
    "gn:admin3_code":"RAZ29-10",
    "gn:asciiname":"Nozharovo",
    "gn:cc2":"BG",
    "gn:country_code":"BG",
    "gn:dem":312,
    "gn:feature_class":"P",
    "gn:feature_code":"PPL",
    "gn:name":"Nozharovo",
    "gn:population":0,
    "gn:timezone":"Europe/Sofia",
    "iso:country":"BG",
    "name:bul_x_preferred":[
        "\u041d\u043e\u0436\u0430\u0440\u043e\u0432\u043e"
    ],
    "name:und_x_variant":[
        "K\u016dl\u016dch",
        "Nosharowo",
        "K\u016dl\u016dchkioy",
        "Nozharovo"
    ],
    "wof:name":"Nozharovo",
    "wof:placetype":"locality"
},
  "geometry": {"coordinates":[26.83333,43.63333],"type":"Point"}
}