{
  "type": "Feature",
  "properties": {
    "gn:admin1_code":"44",
    "gn:asciiname":"Parpori",
    "gn:country_code":"BG",
    "gn:dem":503,
    "gn:feature_class":"P",
    "gn:feature_code":"PPL",
    "gn:name":"Parpori",
    "gn:population":0,
    "gn:timezone":"Europe/Sofia",
    "iso:country":"BG",
    "name:bul_x_preferred":[
        "Parpori"
    ],
    "name:bul_x_variant":[
        "\u041f\u044a\u0440\u043f\u043e\u0440\u0438"
    ],
    "name:und_x_variant":[
        "P\u016drpori"
    ],
    "wof:name":"Parpori",
    "wof:placetype":"locality"
},
  "geometry": {"coordinates":[25.52809,41.43203],"type":"Point"}
}