{
  "type": "Feature",
  "properties": {
    "gn:admin1_code":"63",
    "gn:admin2_code":"VID37",
    "gn:admin3_code":"VID37-02",
    "gn:asciiname":"Gorni Lom",
    "gn:country_code":"BG",
    "gn:dem":426,
    "gn:feature_class":"P",
    "gn:feature_code":"PPL",
    "gn:name":"Gorni Lom",
    "gn:population":0,
    "gn:timezone":"Europe/Sofia",
    "iso:country":"BG",
    "name:bul_x_preferred":[
        "\u0413\u043e\u0440\u043d\u0438 \u041b\u043e\u043c"
    ],
    "wof:name":"Gorni Lom",
    "wof:placetype":"locality"
},
  "geometry": {"coordinates":[22.74634,43.48449],"type":"Point"}
}