{
  "type": "Feature",
  "properties": {
    "gn:admin1_code":"63",
    "gn:admin2_code":"VID37",
    "gn:admin3_code":"VID37-02",
    "gn:asciiname":"Gorni Lom",
    "gn:country_code":"BG",
    "gn:dem":426,
    "gn:feature_class":"P",
    "gn:feature_code":"PPL",
    "gn:name":"Gorni Lom",
    "gn:population":0,
    "gn:timezone":"Europe/Sofia",
    "iso:country":"BG",
    "name:bul_x_preferred":[
        "\u0413\u043e\u0440\u043d\u0438 \u041b\u043e\u043c"
    ],
    "name:ceb_x_preferred":[
        "Gorni Lom"
    ],
    "name:fas_x_preferred":[
        "\u06af\u0648\u0631\u0646\u06cc \u0644\u0648\u0645"
    ],
    "name:kat_x_preferred":[
        "\u10d2\u10dd\u10e0\u10dc\u10d8-\u10da\u10dd\u10db\u10d8"
    ],
    "name:kaz_x_preferred":[
        "\u0413\u043e\u0440\u043d\u0438-\u041b\u043e\u043c"
    ],
    "name:msa_x_preferred":[
        "Gorni Lom"
    ],
    "name:pol_x_preferred":[
        "Gorni \u0141om"
    ],
    "name:ron_x_preferred":[
        "Gorni Lom"
    ],
    "name:rus_x_preferred":[
        "\u0413\u043e\u0440\u043d\u0438-\u041b\u043e\u043c"
    ],
    "name:swe_x_preferred":[
        "Gorni Lom"
    ],
    "name:ukr_x_preferred":[
        "\u0413\u043e\u0440\u0456\u0448\u043d\u0456\u0439 \u041b\u043e\u043c"
    ],
    "wof:name":"Gorni Lom",
    "wof:placetype":"locality"
},
  "geometry": {"coordinates":[22.74634,43.48449],"type":"Point"}
}