{
  "type": "Feature",
  "properties": {
    "gn:admin1_code":"57",
    "gn:admin2_code":"SML18",
    "gn:admin3_code":"SML18-13",
    "gn:asciiname":"Sredets",
    "gn:country_code":"BG",
    "gn:dem":659,
    "gn:feature_class":"P",
    "gn:feature_code":"PPL",
    "gn:name":"Sredets",
    "gn:population":0,
    "gn:timezone":"Europe/Sofia",
    "iso:country":"BG",
    "name:azb_x_preferred":[
        "\u0633\u0631\u062f\u062a\u0633"
    ],
    "name:bul_x_preferred":[
        "\u0421\u0440\u0435\u0434\u0435\u0446"
    ],
    "name:ceb_x_preferred":[
        "Obshtina Sredets"
    ],
    "name:ckb_x_preferred":[
        "\u0633\u0631\u06ce\u062f\u06ce\u062a\u0633"
    ],
    "name:deu_x_preferred":[
        "Sredez"
    ],
    "name:fas_x_preferred":[
        "\u0627\u0633\u0631\u062f\u062a\u0633"
    ],
    "name:fra_x_preferred":[
        "Sr\u00e9d\u00e9ts"
    ],
    "name:jpn_x_preferred":[
        "\u30b9\u30ec\u30c7\u30c4"
    ],
    "name:nld_x_preferred":[
        "Sredets"
    ],
    "name:por_x_preferred":[
        "Sredec"
    ],
    "name:ron_x_preferred":[
        "Srede\u021b"
    ],
    "name:rus_x_preferred":[
        "\u0421\u0440\u0435\u0434\u0435\u0446"
    ],
    "name:slk_x_preferred":[
        "Sredec"
    ],
    "name:spa_x_preferred":[
        "Sredets"
    ],
    "name:srp_x_preferred":[
        "\u0421\u0440\u0435\u0434\u0435\u0446"
    ],
    "name:swe_x_preferred":[
        "Sredets"
    ],
    "name:tur_x_preferred":[
        "Karap\u0131nar"
    ],
    "name:ukr_x_preferred":[
        "\u0421\u0440\u0435\u0434\u0435\u0446\u044c"
    ],
    "name:vie_x_preferred":[
        "Sredets"
    ],
    "name:war_x_preferred":[
        "Sredets"
    ],
    "name:zho_x_preferred":[
        "\u65af\u96f7\u4ee3\u8328"
    ],
    "wof:name":"Sredets",
    "wof:placetype":"locality"
},
  "geometry": {"coordinates":[25.12385,41.49067],"type":"Point"}
}