{
  "type": "Feature",
  "properties": {
    "gn:admin1_code":"57",
    "gn:admin2_code":"SML18",
    "gn:admin3_code":"SML18-13",
    "gn:asciiname":"Sredets",
    "gn:country_code":"BG",
    "gn:dem":659,
    "gn:feature_class":"P",
    "gn:feature_code":"PPL",
    "gn:name":"Sredets",
    "gn:population":0,
    "gn:timezone":"Europe/Sofia",
    "iso:country":"BG",
    "name:bul_x_preferred":[
        "\u0421\u0440\u0435\u0434\u0435\u0446"
    ],
    "wof:name":"Sredets",
    "wof:placetype":"locality"
},
  "geometry": {"coordinates":[25.12385,41.49067],"type":"Point"}
}