{
  "type": "Feature",
  "properties": {
    "gn:admin1_code":"61",
    "gn:admin2_code":"VAR24",
    "gn:admin3_code":"VAR24-08",
    "gn:asciiname":"Zlatina",
    "gn:cc2":"BG",
    "gn:country_code":"BG",
    "gn:dem":42,
    "gn:feature_class":"P",
    "gn:feature_code":"PPL",
    "gn:name":"Zlatina",
    "gn:population":0,
    "gn:timezone":"Europe/Sofia",
    "iso:country":"BG",
    "name:bul_x_preferred":[
        "\u0417\u043b\u0430\u0442\u0438\u043d\u0430"
    ],
    "name:und_x_variant":[
        "Slatina",
        "Endzhe K\u2019oy",
        "Zlatina"
    ],
    "wof:name":"Zlatina",
    "wof:placetype":"locality"
},
  "geometry": {"coordinates":[27.41667,43.23333],"type":"Point"}
}