{
  "type": "Feature",
  "properties": {
    "iso:country":"BG",
    "name:eng_x_preferred":[
        "\u041a\u043e\u043c\u0430\u0442\u0435\u0432\u0441\u043a\u0438 \u0432\u044a\u0437\u0435\u043b"
    ],
    "wof:name":"Komatevski Vasel",
    "wof:placetype":"neighbourhood"
},
  "geometry": {"coordinates":[24.71608446313417,42.12584661671849],"type":"Point"}
}