{
  "type": "Feature",
  "properties": {
    "gn:gn_country":"BG",
    "gn:gn_fcode":"PPL",
    "gn:gn_pop":0,
    "iso:country":"BG",
    "name:bul_x_preferred":[
        "\u041f\u0435\u043f\u0435\u043b\u0438\u043d\u0430"
    ],
    "name:eng_x_preferred":[
        "Pepelina"
    ],
    "name:kaz_x_preferred":[
        "\u041f\u0435\u043f\u0435\u043b\u0438\u043d\u0430"
    ],
    "name:rum_x_preferred":[
        "Pepelina"
    ],
    "name:rus_x_preferred":[
        "\u041f\u0435\u043f\u0435\u043b\u0438\u043d\u0430"
    ],
    "name:ukr_x_preferred":[
        "\u041f\u0435\u043f\u0435\u043b\u0438\u043d\u0430"
    ],
    "qs_pg:aaroncc":"BG",
    "qs_pg:gn_country":"BG",
    "qs_pg:gn_fcode":"PPL",
    "qs_pg:gn_pop":0,
    "qs_pg:name":"Pepelina",
    "qs_pg:name_adm0":"Bulgaria",
    "qs_pg:name_adm1":"Ruse",
    "qs_pg:photos":8,
    "qs_pg:photos_1k":2,
    "qs_pg:photos_9k":1,
    "qs_pg:photos_9r":1,
    "qs_pg:photos_all":8,
    "qs_pg:photos_sr":1,
    "qs_pg:pop_sr":0,
    "qs_pg:qs_pg_placetype":"locality",
    "qs_pg:qs_pg_placetype_gp":"Town",
    "qs_pg:woe_adm0":23424771,
    "woe:adm0_id":23424771,
    "woe:name_adm0":"Bulgaria",
    "woe:name_adm1":"Ruse",
    "woe:placetype":"Town",
    "wof:name":"Pepelina",
    "wof:placetype":"locality"
},
  "geometry": {"coordinates":[25.93333,43.58333],"type":"Point"}
}