{
  "type": "Feature",
  "properties": {
    "gn:admin1_code":"57",
    "gn:asciiname":"Fabrika",
    "gn:country_code":"BG",
    "gn:dem":741,
    "gn:feature_class":"P",
    "gn:feature_code":"PPLL",
    "gn:name":"Fabrika",
    "gn:population":0,
    "gn:timezone":"Europe/Sofia",
    "iso:country":"BG",
    "name:bul_x_preferred":[
        "\u0413\u044e\u0434\u044e\u0440\u0441\u043a\u0430"
    ],
    "name:bul_x_variant":[
        "Fabrika",
        "\u0424\u0430\u0431\u0440\u0438\u043a\u0430"
    ],
    "name:deu_x_preferred":[
        "Fabrika"
    ],
    "name:fas_x_preferred":[
        "\u0641\u0627\u0628\u0631\u06cc\u06a9\u0627"
    ],
    "name:ita_x_preferred":[
        "Fabrika"
    ],
    "name:nld_x_preferred":[
        "Fabrika"
    ],
    "name:pol_x_preferred":[
        "Fabrika"
    ],
    "name:rus_x_preferred":[
        "\u0424\u0430\u0431\u0440\u0438\u043a\u0430"
    ],
    "name:ukr_x_preferred":[
        "\u0424\u0430\u0431\u0440\u0438\u043a\u0430"
    ],
    "name:und_x_variant":[
        "Gudurska",
        "Gudurskaya",
        "Gyudyurska",
        "Promishleno Selo Fabrika",
        "Promishleno Selo Laykov Chukar",
        "Laykov Chukar"
    ],
    "wof:name":"Fabrika",
    "wof:placetype":"locality"
},
  "geometry": {"coordinates":[25.00115,41.44125],"type":"Point"}
}