{
  "type": "Feature",
  "properties": {
    "gn:admin1_code":"44",
    "gn:asciiname":"Lopatar",
    "gn:country_code":"BG",
    "gn:dem":317,
    "gn:feature_class":"P",
    "gn:feature_code":"PPL",
    "gn:name":"Lopatar",
    "gn:population":0,
    "gn:timezone":"Europe/Sofia",
    "iso:country":"BG",
    "name:bul_x_preferred":[
        "Lopatar"
    ],
    "name:bul_x_variant":[
        "\u041b\u043e\u043f\u0430\u0442\u0430\u0440"
    ],
    "wof:name":"Lopatar",
    "wof:placetype":"locality"
},
  "geometry": {"coordinates":[25.65074,41.40107],"type":"Point"}
}