{
  "type": "Feature",
  "properties": {
    "gn:admin1_code":"44",
    "gn:asciiname":"Uchilishtna",
    "gn:country_code":"BG",
    "gn:dem":587,
    "gn:feature_class":"P",
    "gn:feature_code":"PPL",
    "gn:name":"Uchilishtna",
    "gn:population":0,
    "gn:timezone":"Europe/Sofia",
    "iso:country":"BG",
    "name:bul_x_preferred":[
        "Uchilishtna"
    ],
    "name:bul_x_variant":[
        "\u0423\u0447\u0438\u043b\u0438\u0449\u043d\u0430"
    ],
    "wof:name":"Uchilishtna",
    "wof:placetype":"locality"
},
  "geometry": {"coordinates":[25.76445,41.38731],"type":"Point"}
}