{
  "type": "Feature",
  "properties": {
    "gn:admin1_code":"46",
    "gn:admin2_code":"LOV18",
    "gn:admin3_code":"LOV18-30",
    "gn:asciiname":"Umarevtsi",
    "gn:cc2":"BG",
    "gn:country_code":"BG",
    "gn:dem":140,
    "gn:feature_class":"P",
    "gn:feature_code":"PPL",
    "gn:name":"Umarevtsi",
    "gn:population":0,
    "gn:timezone":"Europe/Sofia",
    "iso:country":"BG",
    "name:bul_x_preferred":[
        "\u0423\u043c\u0430\u0440\u0435\u0432\u0446\u0438"
    ],
    "name:ceb_x_preferred":[
        "Umarevci"
    ],
    "name:fas_x_preferred":[
        "\u0627\u0648\u0645\u0627\u0631\u0648\u062a\u0633\u06cc"
    ],
    "name:kaz_x_preferred":[
        "\u0423\u043c\u0430\u0440\u0435\u0432\u0446\u0438"
    ],
    "name:pol_x_preferred":[
        "Umarewci"
    ],
    "name:ron_x_preferred":[
        "Umarev\u021bi"
    ],
    "name:rus_x_preferred":[
        "\u0423\u043c\u0430\u0440\u0435\u0432\u0446\u0438"
    ],
    "name:swe_x_preferred":[
        "Umarevtsi"
    ],
    "name:ukr_x_preferred":[
        "\u0423\u043c\u0430\u0440\u0435\u0432\u0446\u0456"
    ],
    "name:und_x_variant":[
        "Umarewzi"
    ],
    "wof:name":"Umarevtsi",
    "wof:placetype":"locality"
},
  "geometry": {"coordinates":[24.78333,43.18333],"type":"Point"}
}