{
  "type": "Feature",
  "properties": {
    "gn:admin1_code":"39",
    "gn:admin2_code":"BGS06",
    "gn:asciiname":"Svetlina",
    "gn:country_code":"BG",
    "gn:dem":63,
    "gn:feature_class":"P",
    "gn:feature_code":"PPL",
    "gn:name":"Svetlina",
    "gn:population":0,
    "gn:timezone":"Europe/Sofia",
    "iso:country":"BG",
    "name:bul_x_preferred":[
        "\u0421\u0432\u0435\u0442\u043b\u0438\u043d\u0430"
    ],
    "name:und_x_variant":[
        "Gospodarewo",
        "Bey-Makhle",
        "Gospodarevo",
        "Bej Mahale",
        "Bei Mahle",
        "Svetlina"
    ],
    "wof:name":"Svetlina",
    "wof:placetype":"locality"
},
  "geometry": {"coordinates":[27.10502,42.37284],"type":"Point"}
}