{
  "type": "Feature",
  "properties": {
    "gn:admin1_code":"44",
    "gn:admin2_code":"KRZ02",
    "gn:admin3_code":"KRZ02-02",
    "gn:asciiname":"Bashevo",
    "gn:cc2":"BG",
    "gn:country_code":"BG",
    "gn:dem":392,
    "gn:feature_class":"P",
    "gn:feature_code":"PPL",
    "gn:name":"Bashevo",
    "gn:population":0,
    "gn:timezone":"Europe/Sofia",
    "iso:country":"BG",
    "name:bul_x_preferred":[
        "\u0411\u0430\u0448\u0435\u0432\u043e"
    ],
    "name:ceb_x_preferred":[
        "Bashevo"
    ],
    "name:fas_x_preferred":[
        "\u0628\u0627\u0634\u0648\u0648"
    ],
    "name:kat_x_preferred":[
        "\u10d1\u10d0\u10e8\u10d4\u10d5\u10dd"
    ],
    "name:kaz_x_preferred":[
        "\u0411\u0430\u0448\u0435\u0432\u043e"
    ],
    "name:ron_x_preferred":[
        "Ba\u0219evo"
    ],
    "name:rus_x_preferred":[
        "\u0411\u0430\u0448\u0435\u0432\u043e"
    ],
    "name:swe_x_preferred":[
        "Basjevo"
    ],
    "name:tur_x_preferred":[
        "Hallar"
    ],
    "name:ukr_x_preferred":[
        "\u0411\u0430\u0448\u0435\u0432\u043e"
    ],
    "name:und_x_variant":[
        "Bashtevo",
        "Bashevo"
    ],
    "wof:name":"Bashevo",
    "wof:placetype":"locality"
},
  "geometry": {"coordinates":[25.13333,41.66667],"type":"Point"}
}