{
  "type": "Feature",
  "properties": {
    "gn:admin1_code":"48",
    "gn:admin2_code":"PAZ14",
    "gn:admin3_code":"PAZ14-01",
    "gn:asciiname":"Borimechkovo",
    "gn:country_code":"BG",
    "gn:dem":547,
    "gn:feature_class":"P",
    "gn:feature_code":"PPL",
    "gn:name":"Borimechkovo",
    "gn:population":0,
    "gn:timezone":"Europe/Sofia",
    "iso:country":"BG",
    "name:bul_x_preferred":[
        "\u0411\u043e\u0440\u0438\u043c\u0435\u0447\u043a\u043e\u0432\u043e"
    ],
    "name:und_x_variant":[
        "Oruchlu",
        "Yurutsite",
        "Borimetschkowo",
        "Borimechkovo"
    ],
    "wof:name":"Borimechkovo",
    "wof:placetype":"locality"
},
  "geometry": {"coordinates":[24.12476,42.40172000000001],"type":"Point"}
}