{
  "type": "Feature",
  "properties": {
    "gn:admin1_code":"58",
    "gn:asciiname":"Giueshevo",
    "gn:country_code":"BG",
    "gn:dem":949,
    "gn:feature_class":"P",
    "gn:feature_code":"PPL",
    "gn:name":"Giueshevo",
    "gn:population":0,
    "gn:timezone":"Europe/Sofia",
    "iso:country":"BG",
    "wof:name":"Giueshevo",
    "wof:placetype":"locality"
},
  "geometry": {"coordinates":[22.4761,42.23624],"type":"Point"}
}