{
  "type": "Feature",
  "properties": {
    "gn:admin1_code":"40",
    "gn:admin2_code":"DOB12",
    "gn:asciiname":"Zograf",
    "gn:country_code":"BG",
    "gn:dem":205,
    "gn:feature_class":"P",
    "gn:feature_code":"PPL",
    "gn:name":"Zograf",
    "gn:population":0,
    "gn:timezone":"Europe/Sofia",
    "iso:country":"BG",
    "name:bul_x_preferred":[
        "\u0417\u043e\u0433\u0440\u0430\u0444"
    ],
    "name:deu_x_preferred":[
        "Sograf"
    ],
    "name:srp_x_preferred":[
        "Zograf"
    ],
    "name:und_x_variant":[
        "Casapli",
        "Zogra",
        "Kasaplii"
    ],
    "wof:name":"Zograf",
    "wof:placetype":"locality"
},
  "geometry": {"coordinates":[27.9349,43.74231],"type":"Point"}
}