{
  "type": "Feature",
  "properties": {
    "gn:admin1_code":"49",
    "gn:admin2_code":"PER51",
    "gn:asciiname":"Mramor",
    "gn:country_code":"BG",
    "gn:dem":820,
    "gn:feature_class":"P",
    "gn:feature_code":"PPL",
    "gn:name":"Mramor",
    "gn:population":0,
    "gn:timezone":"Europe/Sofia",
    "iso:country":"BG",
    "name:bos_x_preferred":[
        "Mramor"
    ],
    "name:bul_x_preferred":[
        "\u041c\u0430\u0440\u0430\u043c\u043e\u0440"
    ],
    "name:bul_x_variant":[
        "\u041c\u0440\u0430\u043c\u043e\u0440"
    ],
    "name:ceb_x_preferred":[
        "Mramor"
    ],
    "name:deu_x_preferred":[
        "Mramor"
    ],
    "name:fra_x_preferred":[
        "Mramor"
    ],
    "name:hrv_x_preferred":[
        "Mramor"
    ],
    "name:hye_x_preferred":[
        "\u0544\u0561\u0580\u0574\u0561\u0580"
    ],
    "name:pol_x_preferred":[
        "Mramor"
    ],
    "name:ron_x_preferred":[
        "Mramor"
    ],
    "name:rus_x_preferred":[
        "\u041c\u0440\u0430\u043c\u043e\u0440"
    ],
    "name:slv_x_preferred":[
        "Mramor"
    ],
    "name:srp_x_preferred":[
        "\u041c\u0440\u0430\u043c\u043e\u0440"
    ],
    "name:swe_x_preferred":[
        "Mramor"
    ],
    "wof:name":"Mramor",
    "wof:placetype":"locality"
},
  "geometry": {"coordinates":[22.61273,42.74825],"type":"Point"}
}