{
  "type": "Feature",
  "properties": {
    "gn:admin1_code":"63",
    "gn:admin2_code":"VID06",
    "gn:admin3_code":"VID06-01",
    "gn:asciiname":"Baley",
    "gn:cc2":"BG",
    "gn:country_code":"BG",
    "gn:dem":44,
    "gn:feature_class":"P",
    "gn:feature_code":"PPL",
    "gn:name":"Baley",
    "gn:population":0,
    "gn:timezone":"Europe/Sofia",
    "iso:country":"BG",
    "name:bul_x_preferred":[
        "\u0411\u0430\u043b\u0435\u0439"
    ],
    "name:ceb_x_preferred":[
        "Baley"
    ],
    "name:deu_x_preferred":[
        "Baley"
    ],
    "name:swe_x_preferred":[
        "Baley"
    ],
    "name:und_x_variant":[
        "Balej",
        "Baley"
    ],
    "wof:name":"Baley",
    "wof:placetype":"locality"
},
  "geometry": {"coordinates":[22.64611,44.18778],"type":"Point"}
}