{
  "type": "Feature",
  "properties": {
    "gn:admin1_code":"44",
    "gn:asciiname":"Kadilarka",
    "gn:country_code":"BG",
    "gn:dem":456,
    "gn:feature_class":"P",
    "gn:feature_code":"PPL",
    "gn:name":"Kadilarka",
    "gn:population":0,
    "gn:timezone":"Europe/Sofia",
    "iso:country":"BG",
    "name:bul_x_preferred":[
        "Kadilarka"
    ],
    "name:bul_x_variant":[
        "\u041a\u0430\u0434\u0438\u043b\u0430\u0440\u043a\u0430"
    ],
    "wof:name":"Kadilarka",
    "wof:placetype":"locality"
},
  "geometry": {"coordinates":[25.62638,41.36608],"type":"Point"}
}