{
  "type": "Feature",
  "properties": {
    "gn:admin1_code":"54",
    "gn:admin2_code":"SHU30",
    "gn:admin3_code":"SHU30-20",
    "gn:asciiname":"Struino",
    "gn:cc2":"BG",
    "gn:country_code":"BG",
    "gn:dem":282,
    "gn:feature_class":"P",
    "gn:feature_code":"PPL",
    "gn:name":"Struino",
    "gn:population":0,
    "gn:timezone":"Europe/Sofia",
    "iso:country":"BG",
    "name:bul_x_preferred":[
        "\u0421\u0442\u0440\u0443\u0439\u043d\u043e"
    ],
    "name:und_x_variant":[
        "Dere",
        "Struino"
    ],
    "wof:name":"Struino",
    "wof:placetype":"locality"
},
  "geometry": {"coordinates":[26.85,43.36667],"type":"Point"}
}