{
  "type": "Feature",
  "properties": {
    "gn:admin1_code":"39",
    "gn:admin2_code":"BGS21",
    "gn:admin3_code":"BGS21-14",
    "gn:asciiname":"Rosen",
    "gn:country_code":"BG",
    "gn:dem":2,
    "gn:feature_class":"P",
    "gn:feature_code":"PPL",
    "gn:name":"Rosen",
    "gn:population":0,
    "gn:timezone":"Europe/Sofia",
    "iso:country":"BG",
    "name:bul_x_preferred":[
        "\u0420\u043e\u0441\u0435\u043d"
    ],
    "wof:name":"Rosen",
    "wof:placetype":"locality"
},
  "geometry": {"coordinates":[27.41667,42.43333],"type":"Point"}
}