{
  "type": "Feature",
  "properties": {
    "gn:admin1_code":"57",
    "gn:admin2_code":"SML31",
    "gn:admin3_code":"SML31-24",
    "gn:asciiname":"Chuchur",
    "gn:cc2":"BG",
    "gn:country_code":"BG",
    "gn:dem":1118,
    "gn:feature_class":"P",
    "gn:feature_code":"PPL",
    "gn:name":"Chuchur",
    "gn:population":0,
    "gn:timezone":"Europe/Sofia",
    "iso:country":"BG",
    "name:bul_x_preferred":[
        "\u0427\u0443\u0447\u0443\u0440"
    ],
    "name:fas_x_preferred":[
        "\u0686\u0648\u0686\u0648\u0631"
    ],
    "name:kat_x_preferred":[
        "\u10e9\u10e3\u10e9\u10e3\u10e0\u10d8"
    ],
    "name:kaz_x_preferred":[
        "\u0427\u0443\u0447\u0443\u0440"
    ],
    "name:msa_x_preferred":[
        "Chuchur"
    ],
    "name:ron_x_preferred":[
        "Ciuciur"
    ],
    "name:rus_x_preferred":[
        "\u0427\u0443\u0447\u0443\u0440"
    ],
    "name:ukr_x_preferred":[
        "\u0427\u0443\u0447\u0443\u0440"
    ],
    "name:und_x_variant":[
        "Yuchur",
        "Tschutschura",
        "Chuchur"
    ],
    "wof:name":"Chuchur",
    "wof:placetype":"locality"
},
  "geometry": {"coordinates":[24.81667,41.53333],"type":"Point"}
}