{
  "type": "Feature",
  "properties": {
    "gn:admin1_code":"62",
    "gn:admin2_code":"VTR04",
    "gn:asciiname":"Doynovtsi",
    "gn:cc2":"BG",
    "gn:country_code":"BG",
    "gn:dem":431,
    "gn:feature_class":"P",
    "gn:feature_code":"PPL",
    "gn:name":"Doynovtsi",
    "gn:population":0,
    "gn:timezone":"Europe/Sofia",
    "iso:country":"BG",
    "name:bul_x_preferred":[
        "\u0414\u043e\u0439\u043d\u043e\u0432\u0446\u0438"
    ],
    "name:und_x_variant":[
        "Doynovts\u016d",
        "Doynovtsi"
    ],
    "wof:name":"Doynovtsi",
    "wof:placetype":"locality"
},
  "geometry": {"coordinates":[25.65,42.85],"type":"Point"}
}