{
  "type": "Feature",
  "properties": {
    "gn:admin1_code":"62",
    "gn:admin2_code":"VTR13",
    "gn:admin3_code":"VTR13-01",
    "gn:asciiname":"Petkovtsi",
    "gn:cc2":"BG",
    "gn:country_code":"BG",
    "gn:dem":418,
    "gn:feature_class":"P",
    "gn:feature_code":"PPL",
    "gn:name":"Petkovtsi",
    "gn:population":0,
    "gn:timezone":"Europe/Sofia",
    "iso:country":"BG",
    "name:bul_x_preferred":[
        "\u041f\u0435\u0442\u043a\u043e\u0432\u0446\u0438"
    ],
    "name:und_x_variant":[
        "Siyreni",
        "Petkovtsi"
    ],
    "wof:name":"Petkovtsi",
    "wof:placetype":"locality"
},
  "geometry": {"coordinates":[26.01667,42.95],"type":"Point"}
}