{
  "type": "Feature",
  "properties": {
    "gn:admin1_code":"45",
    "gn:asciiname":"Zhedilovo",
    "gn:cc2":"BG",
    "gn:country_code":"BG",
    "gn:dem":1112,
    "gn:feature_class":"P",
    "gn:feature_code":"PPL",
    "gn:name":"Zhedilovo",
    "gn:population":0,
    "gn:timezone":"Europe/Sofia",
    "iso:country":"BG",
    "name:bul_x_preferred":[
        "\u0416\u0435\u0434\u0438\u043b\u043e\u0432\u043e"
    ],
    "name:und_x_variant":[
        "Gedilovo",
        "Zhedilovo"
    ],
    "wof:name":"Zhedilovo",
    "wof:placetype":"locality"
},
  "geometry": {"coordinates":[22.43778,42.25806],"type":"Point"}
}