{
  "type": "Feature",
  "properties": {
    "gn:admin1_code":"44",
    "gn:asciiname":"Grapa",
    "gn:country_code":"BG",
    "gn:dem":401,
    "gn:feature_class":"P",
    "gn:feature_code":"PPL",
    "gn:name":"Grapa",
    "gn:population":0,
    "gn:timezone":"Europe/Sofia",
    "iso:country":"BG",
    "name:bul_x_preferred":[
        "Grapa"
    ],
    "name:bul_x_variant":[
        "\u0413\u0440\u0430\u043f\u0430"
    ],
    "name:cat_x_preferred":[
        "Grapa"
    ],
    "name:pol_x_preferred":[
        "Grapa"
    ],
    "name:slk_x_preferred":[
        "Grapa"
    ],
    "name:spa_x_preferred":[
        "Grapa"
    ],
    "name:vec_x_preferred":[
        "Grapa"
    ],
    "wof:name":"Grapa",
    "wof:placetype":"locality"
},
  "geometry": {"coordinates":[25.69756,41.46774],"type":"Point"}
}