{
  "type": "Feature",
  "properties": {
    "gn:admin1_code":"38",
    "gn:asciiname":"Prikrat",
    "gn:country_code":"BG",
    "gn:dem":891,
    "gn:feature_class":"P",
    "gn:feature_code":"PPL",
    "gn:name":"Prikrat",
    "gn:population":0,
    "gn:timezone":"Europe/Sofia",
    "iso:country":"BG",
    "name:bul_x_preferred":[
        "Prikrat"
    ],
    "name:bul_x_variant":[
        "\u041f\u0440\u0438\u043a\u0440\u0430\u0442"
    ],
    "wof:name":"Prikrat",
    "wof:placetype":"locality"
},
  "geometry": {"coordinates":[22.93434,41.92332],"type":"Point"}
}