{
  "type": "Feature",
  "properties": {
    "gn:admin1_code":"45",
    "gn:admin2_code":"KNL29",
    "gn:asciiname":"Kamenichka Skakavitsa",
    "gn:country_code":"BG",
    "gn:dem":994,
    "gn:feature_class":"P",
    "gn:feature_code":"PPL",
    "gn:name":"Kamenichka Skakavitsa",
    "gn:population":0,
    "gn:timezone":"Europe/Sofia",
    "iso:country":"BG",
    "name:bul_x_preferred":[
        "\u041a\u0430\u043c\u0435\u043d\u0438\u0448\u043a\u0430 \u0421\u043a\u0430\u043a\u0430\u0432\u0438\u0446\u0430"
    ],
    "name:bul_x_variant":[
        "\u041a\u0430\u043c\u0435\u043d\u0438\u0447\u043a\u0430 \u0421\u043a\u0430\u043a\u0430\u0432\u0438\u0446\u0430"
    ],
    "name:fas_x_preferred":[
        "\u06a9\u0627\u0645\u0646\u06cc\u0686\u06a9\u0627 \u0633\u06a9\u0627\u06a9\u0627\u0648\u06cc\u062a\u0633\u0627"
    ],
    "name:kaz_x_preferred":[
        "\u041a\u0430\u043c\u0435\u043d\u0438\u0447\u043a\u0430-\u0421\u043a\u0430\u043a\u0430\u0432\u0438\u0446\u0430"
    ],
    "name:ron_x_preferred":[
        "Kamenicika Skakavi\u021ba"
    ],
    "name:rus_x_preferred":[
        "\u041a\u0430\u043c\u0435\u043d\u0438\u0447\u043a\u0430-\u0421\u043a\u0430\u043a\u0430\u0432\u0438\u0446\u0430"
    ],
    "name:ukr_x_preferred":[
        "\u041a\u0430\u043c\u0435\u043d\u0438\u0447\u043a\u0430 \u0421\u043a\u0430\u043a\u0430\u0432\u0438\u0446\u044f"
    ],
    "name:und_x_variant":[
        "Skakavitsa-Kamenishka",
        "Kamenischka-Skakawiza",
        "Kamenishka Skakavitsa",
        "Kamenichka Skakavitsa"
    ],
    "wof:name":"Kamenichka Skakavitsa",
    "wof:placetype":"locality"
},
  "geometry": {"coordinates":[22.50289,42.235],"type":"Point"}
}