{
  "type": "Feature",
  "properties": {
    "gn:admin1_code":"45",
    "gn:admin2_code":"KNL31",
    "gn:admin3_code":"KNL31-01",
    "gn:asciiname":"Vaksevo",
    "gn:country_code":"BG",
    "gn:dem":554,
    "gn:feature_class":"P",
    "gn:feature_code":"PPL",
    "gn:name":"Vaksevo",
    "gn:population":0,
    "gn:timezone":"Europe/Sofia",
    "iso:country":"BG",
    "name:bul_x_preferred":[
        "\u0412\u0430\u043a\u0441\u0435\u0432\u043e"
    ],
    "name:bul_x_variant":[
        "Vaksevo"
    ],
    "name:und_x_variant":[
        "Waksewo"
    ],
    "wof:name":"Vaksevo",
    "wof:placetype":"locality"
},
  "geometry": {"coordinates":[22.85558,42.16038],"type":"Point"}
}