{
  "type": "Feature",
  "properties": {
    "gn:admin1_code":"62",
    "gn:asciiname":"Lokvata",
    "gn:cc2":"BG",
    "gn:country_code":"BG",
    "gn:dem":493,
    "gn:feature_class":"P",
    "gn:feature_code":"PPL",
    "gn:name":"Lokvata",
    "gn:population":0,
    "gn:timezone":"Europe/Sofia",
    "iso:country":"BG",
    "name:bul_x_preferred":[
        "\u041b\u043e\u043a\u0432\u0430\u0442\u0430"
    ],
    "name:und_x_variant":[
        "Lokwata",
        "Lokvata"
    ],
    "wof:name":"Lokvata",
    "wof:placetype":"locality"
},
  "geometry": {"coordinates":[26.05,43.03333],"type":"Point"}
}