{
  "type": "Feature",
  "properties": {
    "iso:country":"BG",
    "name:azb_x_preferred":[
        "\u0633\u062a\u06cc\u0626\u0627"
    ],
    "name:bos_x_preferred":[
        "Slatina"
    ],
    "name:bul_x_preferred":[
        "\u0421\u043b\u0430\u0442\u0438\u043d\u0430"
    ],
    "name:ceb_x_preferred":[
        "Slatina"
    ],
    "name:ces_x_preferred":[
        "Slatina"
    ],
    "name:deu_x_preferred":[
        "Slatina"
    ],
    "name:eng_x_preferred":[
        "Slatina"
    ],
    "name:epo_x_preferred":[
        "Slatina"
    ],
    "name:eus_x_preferred":[
        "Slatina"
    ],
    "name:fin_x_preferred":[
        "Slatina"
    ],
    "name:fra_x_preferred":[
        "Slatina"
    ],
    "name:hbs_x_preferred":[
        "Slatina"
    ],
    "name:heb_x_preferred":[
        "\u05e1\u05dc\u05d0\u05d8\u05d9\u05e0\u05d4"
    ],
    "name:hrv_x_preferred":[
        "Slatina"
    ],
    "name:hun_x_preferred":[
        "Slatina"
    ],
    "name:ita_x_preferred":[
        "Slatina"
    ],
    "name:jpn_x_preferred":[
        "\u30b9\u30e9\u30c6\u30a3\u30ca"
    ],
    "name:min_x_preferred":[
        "Slatina"
    ],
    "name:mkd_x_preferred":[
        "\u0421\u043b\u0430\u0442\u0438\u043d\u0430"
    ],
    "name:nld_x_preferred":[
        "Slatina"
    ],
    "name:pol_x_preferred":[
        "Slatina"
    ],
    "name:ron_x_preferred":[
        "Slatina"
    ],
    "name:rus_x_preferred":[
        "\u0421\u043b\u0430\u0442\u0438\u043d\u0430"
    ],
    "name:slk_x_preferred":[
        "Slatina"
    ],
    "name:slv_x_preferred":[
        "Slatina"
    ],
    "name:spa_x_preferred":[
        "Slatina"
    ],
    "name:sqi_x_preferred":[
        "Sllatina"
    ],
    "name:srp_x_preferred":[
        "\u0421\u043b\u0430\u0442\u0438\u043d\u0430"
    ],
    "name:swe_x_preferred":[
        "Slatina"
    ],
    "name:tat_x_preferred":[
        "\u0421\u043b\u0430\u0442\u0438\u043d\u0430"
    ],
    "name:ukr_x_preferred":[
        "\u0421\u043b\u0430\u0442\u0438\u043d\u0430"
    ],
    "name:unk_x_variant":[
        "Slatina"
    ],
    "qs:gn_adm0_cc":"BG",
    "qs:gn_fcode":"PPLX",
    "qs:gn_local":727011,
    "qs:gn_nam_loc":"Sofiya, Sofia, Sofiya-Grad, BG",
    "qs:gn_namadm1":"42",
    "qs:gn_name":"Slatina",
    "qs:local_max":4184,
    "qs:local_sum":18613,
    "qs:localhoods":26,
    "qs:name":"Slatina",
    "qs:name_adm0":"Bulgaria",
    "qs:name_adm1":"Sofiya-Grad",
    "qs:name_adm2":"Sofiya",
    "qs:name_local":"Sofia",
    "qs:photo_max":13,
    "qs:photo_sum":52,
    "qs:placetype":"Suburb",
    "qs:quad_count":13,
    "qs:woe_adm0":23424771,
    "qs:woe_adm1":20069794,
    "qs:woe_adm2":55873710,
    "qs:woe_lau":0,
    "qs:woe_local":839722,
    "qs:woe_ver":"7.10.0",
    "wof:lang":[
        "eng"
    ],
    "wof:name":"Slatina",
    "wof:placetype":"neighbourhood"
},
  "geometry": {"coordinates":[23.371019,42.682901],"type":"Point"}
}