{
  "type": "Feature",
  "properties": {
    "gn:admin1_code":"43",
    "gn:admin2_code":"HKV34",
    "gn:admin3_code":"HKV34-02",
    "gn:asciiname":"Bryagovo",
    "gn:cc2":"BG",
    "gn:country_code":"BG",
    "gn:dem":170,
    "gn:feature_class":"P",
    "gn:feature_code":"PPL",
    "gn:name":"Bryagovo",
    "gn:population":0,
    "gn:timezone":"Europe/Sofia",
    "iso:country":"BG",
    "name:bul_x_preferred":[
        "\u0411\u0440\u044f\u0433\u043e\u0432\u043e"
    ],
    "name:kat_x_preferred":[
        "\u10d1\u10e0\u10d8\u10d0\u10d2\u10dd\u10d5\u10dd"
    ],
    "name:kaz_x_preferred":[
        "\u0411\u0440\u044f\u0433\u043e\u0432\u043e"
    ],
    "name:msa_x_preferred":[
        "Bryagovo"
    ],
    "name:ron_x_preferred":[
        "Breagovo"
    ],
    "name:rus_x_preferred":[
        "\u0411\u0440\u044f\u0433\u043e\u0432\u043e"
    ],
    "name:ukr_x_preferred":[
        "\u0411\u0440\u044f\u0433\u043e\u0432\u043e"
    ],
    "name:und_x_variant":[
        "Tremezlii",
        "Bregowo"
    ],
    "wof:name":"Bryagovo",
    "wof:placetype":"locality"
},
  "geometry": {"coordinates":[25.78333,41.91667],"type":"Point"}
}