{
  "type": "Feature",
  "properties": {
    "gn:admin1_code":"43",
    "gn:admin2_code":"HKV34",
    "gn:admin3_code":"HKV34-02",
    "gn:asciiname":"Bryagovo",
    "gn:cc2":"BG",
    "gn:country_code":"BG",
    "gn:dem":170,
    "gn:feature_class":"P",
    "gn:feature_code":"PPL",
    "gn:name":"Bryagovo",
    "gn:population":0,
    "gn:timezone":"Europe/Sofia",
    "iso:country":"BG",
    "name:bul_x_preferred":[
        "\u0411\u0440\u044f\u0433\u043e\u0432\u043e"
    ],
    "name:und_x_variant":[
        "Tremezlii",
        "Bregowo",
        "Bryagovo"
    ],
    "wof:name":"Bryagovo",
    "wof:placetype":"locality"
},
  "geometry": {"coordinates":[25.78333,41.91667],"type":"Point"}
}