{
  "type": "Feature",
  "properties": {
    "gn:admin1_code":"39",
    "gn:admin2_code":"BGS06",
    "gn:asciiname":"Radoynovo",
    "gn:cc2":"BG",
    "gn:country_code":"BG",
    "gn:dem":113,
    "gn:feature_class":"P",
    "gn:feature_code":"PPL",
    "gn:name":"Radoynovo",
    "gn:population":0,
    "gn:timezone":"Europe/Sofia",
    "iso:country":"BG",
    "name:bul_x_preferred":[
        "\u0420\u0430\u0434\u043e\u0439\u043d\u043e\u0432\u043e"
    ],
    "name:fas_x_preferred":[
        "\u0631\u0627\u062f\u0648\u06cc\u0646\u0648\u0648\u0648"
    ],
    "name:kaz_x_preferred":[
        "\u0420\u0430\u0434\u043e\u0439\u043d\u043e\u0432\u043e"
    ],
    "name:ron_x_preferred":[
        "Radoinovo"
    ],
    "name:rus_x_preferred":[
        "\u0420\u0430\u0434\u043e\u0439\u043d\u043e\u0432\u043e"
    ],
    "name:ukr_x_preferred":[
        "\u0420\u0430\u0434\u043e\u0439\u043d\u043e\u0432\u043e"
    ],
    "name:und_x_variant":[
        "Kiril",
        "Bokludzha",
        "Radaynovo",
        "Radoinovo",
        "Radoynovo"
    ],
    "wof:name":"Radoynovo",
    "wof:placetype":"locality"
},
  "geometry": {"coordinates":[26.98333,42.38333],"type":"Point"}
}