{
  "type": "Feature",
  "properties": {
    "gn:admin1_code":"39",
    "gn:admin2_code":"BGS06",
    "gn:admin3_code":"BGS06-11",
    "gn:asciiname":"Zagortsi",
    "gn:country_code":"BG",
    "gn:dem":86,
    "gn:feature_class":"P",
    "gn:feature_code":"PPL",
    "gn:name":"Zagortsi",
    "gn:population":0,
    "gn:timezone":"Europe/Sofia",
    "iso:country":"BG",
    "name:bul_x_preferred":[
        "\u0417\u0430\u0433\u043e\u0440\u0446\u0438"
    ],
    "name:und_x_variant":[
        "Saban Kiri",
        "Harman Kiri",
        "Shaban-K\u016dr\u0103",
        "Kir Harman",
        "Sagorzi",
        "Zagortsi",
        "Zagortsy"
    ],
    "wof:name":"Zagortsi",
    "wof:placetype":"locality"
},
  "geometry": {"coordinates":[27.06021,42.39891],"type":"Point"}
}