{
  "type": "Feature",
  "properties": {
    "gn:admin1_code":"49",
    "gn:asciiname":"Kralevdol",
    "gn:country_code":"BG",
    "gn:dem":795,
    "gn:feature_class":"P",
    "gn:feature_code":"PPL",
    "gn:name":"Kralevdol",
    "gn:population":0,
    "gn:timezone":"Europe/Sofia",
    "iso:country":"BG",
    "name:bul_x_preferred":[
        "\u041a\u0440\u0430\u043b\u0435\u0432\u0434\u043e\u043b"
    ],
    "name:und_x_variant":[
        "Kralew-Dol",
        "Kralevdol"
    ],
    "wof:name":"Kralevdol",
    "wof:placetype":"locality"
},
  "geometry": {"coordinates":[23.09226,42.56204],"type":"Point"}
}