{
  "type": "Feature",
  "properties": {
    "gn:admin1_code":"48",
    "gn:admin2_code":"PAZ19",
    "gn:admin3_code":"PAZ19-22",
    "gn:asciiname":"Rosen",
    "gn:country_code":"BG",
    "gn:dem":270,
    "gn:feature_class":"P",
    "gn:feature_code":"PPL",
    "gn:name":"Rosen",
    "gn:population":0,
    "gn:timezone":"Europe/Sofia",
    "iso:country":"BG",
    "name:bul_x_preferred":[
        "\u0420\u043e\u0441\u0435\u043d"
    ],
    "name:deu_x_preferred":[
        "Rosen"
    ],
    "name:rus_x_preferred":[
        "\u0420\u043e\u0437\u0435\u043d"
    ],
    "name:ukr_x_preferred":[
        "\u0420\u043e\u0437\u0435\u043d"
    ],
    "name:und_x_variant":[
        "Baldevo",
        "Rossen"
    ],
    "wof:name":"Rosen",
    "wof:placetype":"locality"
},
  "geometry": {"coordinates":[24.36667000000001,42.31667],"type":"Point"}
}