{
  "type": "Feature",
  "properties": {
    "gn:admin1_code":"43",
    "gn:admin2_code":"HKV28",
    "gn:asciiname":"Mihalich",
    "gn:country_code":"BG",
    "gn:dem":354,
    "gn:feature_class":"P",
    "gn:feature_code":"PPL",
    "gn:name":"Mihalich",
    "gn:population":0,
    "gn:timezone":"Europe/Sofia",
    "iso:country":"BG",
    "name:bul_x_preferred":[
        "\u041c\u0438\u0445\u0430\u043b\u0438\u0447"
    ],
    "name:und_x_variant":[
        "Michalitsch",
        "Mikhalich"
    ],
    "wof:name":"Mihalich",
    "wof:placetype":"locality"
},
  "geometry": {"coordinates":[26.41811,41.85583],"type":"Point"}
}