{
  "type": "Feature",
  "properties": {
    "gn:admin1_code":"62",
    "gn:admin2_code":"VTR13",
    "gn:asciiname":"Darlevtsi",
    "gn:country_code":"BG",
    "gn:dem":465,
    "gn:feature_class":"P",
    "gn:feature_code":"PPL",
    "gn:name":"Darlevtsi",
    "gn:population":0,
    "gn:timezone":"Europe/Sofia",
    "iso:country":"BG",
    "name:bul_x_preferred":[
        "\u0414\u044a\u0440\u043b\u0435\u0432\u0446\u0438"
    ],
    "name:bul_x_variant":[
        "Darlevtsi"
    ],
    "name:und_x_variant":[
        "Derlevts\u016d",
        "D\u016drlevtsi"
    ],
    "wof:name":"Darlevtsi",
    "wof:placetype":"locality"
},
  "geometry": {"coordinates":[25.88333,42.96667],"type":"Point"}
}