{
  "type": "Feature",
  "properties": {
    "gn:admin1_code":"64",
    "gn:admin2_code":"VRC21",
    "gn:admin3_code":"VRC21-09",
    "gn:asciiname":"Lesura",
    "gn:cc2":"BG",
    "gn:country_code":"BG",
    "gn:dem":173,
    "gn:feature_class":"P",
    "gn:feature_code":"PPL",
    "gn:name":"Lesura",
    "gn:population":0,
    "gn:timezone":"Europe/Sofia",
    "iso:country":"BG",
    "name:bul_x_preferred":[
        "\u041b\u0435\u0441\u0443\u0440\u0430"
    ],
    "name:und_x_variant":[
        "Lessura",
        "Lesure",
        "Lesura"
    ],
    "wof:name":"Lesura",
    "wof:placetype":"locality"
},
  "geometry": {"coordinates":[23.56667,43.46667],"type":"Point"}
}