{
  "type": "Feature",
  "properties": {
    "gn:admin1_code":"59",
    "gn:admin2_code":"SZR36",
    "gn:asciiname":"Dimitrievo",
    "gn:cc2":"BG",
    "gn:country_code":"BG",
    "gn:dem":137,
    "gn:feature_class":"P",
    "gn:feature_code":"PPL",
    "gn:name":"Dimitrievo",
    "gn:population":0,
    "gn:timezone":"Europe/Sofia",
    "iso:country":"BG",
    "name:bul_x_preferred":[
        "\u0414\u0438\u043c\u0438\u0442\u0440\u0438\u0435\u0432\u043e"
    ],
    "name:und_x_variant":[
        "Dimitriewo",
        "Chikarlare",
        "Chak\u016drlari",
        "Dimitrievo"
    ],
    "wof:name":"Dimitrievo",
    "wof:placetype":"locality"
},
  "geometry": {"coordinates":[25.56667,42.18333],"type":"Point"}
}