{
  "type": "Feature",
  "properties": {
    "gn:admin1_code":"51",
    "gn:admin2_code":"PDV23",
    "gn:admin3_code":"PDV23-01",
    "gn:asciiname":"Bryagovo",
    "gn:cc2":"BG",
    "gn:country_code":"BG",
    "gn:dem":244,
    "gn:feature_class":"P",
    "gn:feature_code":"PPL",
    "gn:name":"Bryagovo",
    "gn:population":0,
    "gn:timezone":"Europe/Sofia",
    "iso:country":"BG",
    "name:bul_x_preferred":[
        "\u0411\u0440\u044f\u0433\u043e\u0432\u043e"
    ],
    "name:und_x_variant":[
        "Kara Alan",
        "Br\u011bgovo",
        "Bryegovo",
        "Brezovo",
        "Bregowo",
        "Bryagovo"
    ],
    "wof:name":"Bryagovo",
    "wof:placetype":"locality"
},
  "geometry": {"coordinates":[25.18333,41.98333],"type":"Point"}
}