{
  "type": "Feature",
  "properties": {
    "gn:admin1_code":"64",
    "gn:admin2_code":"VRC21",
    "gn:admin3_code":"VRC21-03",
    "gn:asciiname":"Galatin",
    "gn:country_code":"BG",
    "gn:dem":174,
    "gn:feature_class":"P",
    "gn:feature_code":"PPL",
    "gn:name":"Galatin",
    "gn:population":0,
    "gn:timezone":"Europe/Sofia",
    "iso:country":"BG",
    "name:bul_x_preferred":[
        "\u0413\u0430\u043b\u0430\u0442\u0438\u043d"
    ],
    "name:ceb_x_preferred":[
        "Galatin"
    ],
    "name:fas_x_preferred":[
        "\u06af\u0627\u0644\u0627\u062a\u06cc\u0646"
    ],
    "name:kat_x_preferred":[
        "\u10d2\u10d0\u10da\u10d0\u10e2\u10d8\u10dc\u10d8"
    ],
    "name:kaz_x_preferred":[
        "\u0413\u0430\u043b\u0430\u0442\u0438\u043d"
    ],
    "name:msa_x_preferred":[
        "Galatin"
    ],
    "name:ron_x_preferred":[
        "Galatin"
    ],
    "name:rus_x_preferred":[
        "\u0413\u0430\u043b\u0430\u0442\u0438\u043d"
    ],
    "name:swe_x_preferred":[
        "Galatin"
    ],
    "name:ukr_x_preferred":[
        "\u0413\u0430\u043b\u0430\u0442\u0438\u043d"
    ],
    "wof:name":"Galatin",
    "wof:placetype":"locality"
},
  "geometry": {"coordinates":[23.53333,43.41667],"type":"Point"}
}