{
  "type": "Feature",
  "properties": {
    "gn:admin1_code":"57",
    "gn:admin2_code":"SML16",
    "gn:asciiname":"Ravnil",
    "gn:cc2":"BG",
    "gn:country_code":"BG",
    "gn:dem":781,
    "gn:feature_class":"P",
    "gn:feature_code":"PPL",
    "gn:name":"Ravnil",
    "gn:population":0,
    "gn:timezone":"Europe/Sofia",
    "iso:country":"BG",
    "name:bul_x_preferred":[
        "\u0420\u0430\u0432\u043d\u0438\u043b"
    ],
    "name:und_x_variant":[
        "Rawnil",
        "Ravnil"
    ],
    "wof:name":"Ravnil",
    "wof:placetype":"locality"
},
  "geometry": {"coordinates":[24.98333,41.53333],"type":"Point"}
}