{
  "type": "Feature",
  "properties": {
    "gn:admin1_code":"57",
    "gn:admin2_code":"SML31",
    "gn:asciiname":"Chepleten",
    "gn:country_code":"BG",
    "gn:dem":1192,
    "gn:feature_class":"P",
    "gn:feature_code":"PPL",
    "gn:name":"Chepleten",
    "gn:population":0,
    "gn:timezone":"Europe/Sofia",
    "iso:country":"BG",
    "name:bul_x_preferred":[
        "\u0427\u0435\u043f\u043b\u0435\u0442\u0435\u043d"
    ],
    "name:fas_x_preferred":[
        "\u0686\u067e\u0644\u062a\u0646"
    ],
    "name:kat_x_preferred":[
        "\u10e9\u10d4\u10de\u10da\u10d4\u10e2\u10d4\u10dc\u10d8"
    ],
    "name:kaz_x_preferred":[
        "\u0427\u0435\u043f\u043b\u0435\u0442\u0435\u043d"
    ],
    "name:msa_x_preferred":[
        "Chepleten"
    ],
    "name:ron_x_preferred":[
        "Cepleten"
    ],
    "name:rus_x_preferred":[
        "\u0427\u0435\u043f\u043b\u0435\u0442\u0435\u043d"
    ],
    "name:ukr_x_preferred":[
        "\u0427\u0435\u043f\u043b\u0435\u0442\u0435\u043d"
    ],
    "name:und_x_variant":[
        "Bryagovo",
        "Chepleten"
    ],
    "wof:name":"Chepleten",
    "wof:placetype":"locality"
},
  "geometry": {"coordinates":[24.75391,41.46084000000001],"type":"Point"}
}