{
  "type": "Feature",
  "properties": {
    "gn:admin1_code":"44",
    "gn:admin2_code":"KRZ16",
    "gn:admin3_code":"KRZ16-13",
    "gn:asciiname":"Svatbare",
    "gn:cc2":"BG",
    "gn:country_code":"BG",
    "gn:dem":237,
    "gn:feature_class":"P",
    "gn:feature_code":"PPL",
    "gn:name":"Svatbare",
    "gn:population":0,
    "gn:timezone":"Europe/Sofia",
    "iso:country":"BG",
    "name:bul_x_preferred":[
        "\u0421\u0432\u0430\u0434\u0431\u0430\u0440\u0435"
    ],
    "name:bul_x_variant":[
        "\u0421\u0432\u0430\u0442\u0431\u0430\u0440\u0435"
    ],
    "name:fas_x_preferred":[
        "\u0633\u0648\u0627\u062a\u0628\u0627\u0631\u0647"
    ],
    "name:kat_x_preferred":[
        "\u10e1\u10d5\u10d0\u10e2\u10d1\u10d0\u10e0\u10d4"
    ],
    "name:kaz_x_preferred":[
        "\u0421\u0432\u0430\u0442\u0431\u0430\u0440\u0435"
    ],
    "name:ron_x_preferred":[
        "Svatbare"
    ],
    "name:rus_x_preferred":[
        "\u0421\u0432\u0430\u0442\u0431\u0430\u0440\u0435"
    ],
    "name:ukr_x_preferred":[
        "\u0421\u0432\u0430\u0442\u0431\u0430\u0440\u0435"
    ],
    "name:und_x_variant":[
        "Dyuyundzhiler"
    ],
    "wof:name":"Svatbare",
    "wof:placetype":"locality"
},
  "geometry": {"coordinates":[25.53333,41.66667],"type":"Point"}
}