{
  "type": "Feature",
  "properties": {
    "gn:admin1_code":"58",
    "gn:admin2_code":"SFO43",
    "gn:asciiname":"Manastirishte",
    "gn:cc2":"BG",
    "gn:country_code":"BG",
    "gn:dem":962,
    "gn:feature_class":"P",
    "gn:feature_code":"PPLL",
    "gn:name":"Manastirishte",
    "gn:population":0,
    "gn:timezone":"Europe/Sofia",
    "iso:country":"BG",
    "name:bul_x_preferred":[
        "\u041c\u0430\u043d\u0430\u0441\u0442\u0438\u0440\u0438\u0449\u0435"
    ],
    "name:und_x_variant":[
        "Manastirischte",
        "Manastirishte"
    ],
    "wof:name":"Manastirishte",
    "wof:placetype":"locality"
},
  "geometry": {"coordinates":[23.14278,43.00417],"type":"Point"}
}