{
  "type": "Feature",
  "properties": {
    "gn:admin1_code":"57",
    "gn:admin2_code":"SML16",
    "gn:admin3_code":"SML16-07",
    "gn:asciiname":"Staychin Dol",
    "gn:cc2":"BG",
    "gn:country_code":"BG",
    "gn:dem":986,
    "gn:feature_class":"P",
    "gn:feature_code":"PPL",
    "gn:name":"Staychin Dol",
    "gn:population":0,
    "gn:timezone":"Europe/Sofia",
    "iso:country":"BG",
    "name:bul_x_preferred":[
        "\u0421\u0442\u0430\u0439\u0447\u0438\u043d \u0414\u043e\u043b"
    ],
    "name:und_x_variant":[
        "Stantschin Dol",
        "Staychin Dol"
    ],
    "wof:name":"Staychin Dol",
    "wof:placetype":"locality"
},
  "geometry": {"coordinates":[24.98333,41.56667],"type":"Point"}
}