{
  "type": "Feature",
  "properties": {
    "gn:admin1_code":"44",
    "gn:admin2_code":"KRZ15",
    "gn:admin3_code":"KRZ15-27",
    "gn:asciiname":"Malak Devesil",
    "gn:country_code":"BG",
    "gn:dem":433,
    "gn:feature_class":"P",
    "gn:feature_code":"PPLL",
    "gn:name":"Malak Devesil",
    "gn:population":0,
    "gn:timezone":"Europe/Sofia",
    "iso:country":"BG",
    "name:bul_x_preferred":[
        "\u041c\u0430\u043b\u044a\u043a \u0414\u0435\u0432\u0435\u0441\u0438\u043b"
    ],
    "name:bul_x_variant":[
        "Malak Devesil"
    ],
    "name:und_x_variant":[
        "Dikili Kayrak",
        "Mal\u016dk Devesil"
    ],
    "wof:name":"Malak Devesil",
    "wof:placetype":"locality"
},
  "geometry": {"coordinates":[25.65551,41.37204000000001],"type":"Point"}
}