{
  "type": "Feature",
  "properties": {
    "gn:admin1_code":"41",
    "gn:admin2_code":"GAB12",
    "gn:asciiname":"Rusinovtsi",
    "gn:cc2":"BG",
    "gn:country_code":"BG",
    "gn:dem":537,
    "gn:feature_class":"P",
    "gn:feature_code":"PPL",
    "gn:name":"Rusinovtsi",
    "gn:population":0,
    "gn:timezone":"Europe/Sofia",
    "iso:country":"BG",
    "name:ara_x_preferred":[
        "\u0631\u0648\u0631\u064a\u0646\u0648\u0641\u062a\u0633\u064a"
    ],
    "name:bul_x_preferred":[
        "\u0420\u0443\u0441\u0438\u043d\u043e\u0432\u0446\u0438"
    ],
    "name:fas_x_preferred":[
        "\u0631\u0648\u0633\u06cc\u0646\u0648\u0648\u062a\u0633\u06cc"
    ],
    "name:kaz_x_preferred":[
        "\u0420\u0443\u0441\u0438\u043d\u043e\u0432\u0446\u0438"
    ],
    "name:pol_x_preferred":[
        "Rusinowci"
    ],
    "name:ron_x_preferred":[
        "Rusinov\u021bi"
    ],
    "name:rus_x_preferred":[
        "\u0420\u0443\u0441\u0438\u043d\u043e\u0432\u0446\u0438"
    ],
    "name:ukr_x_preferred":[
        "\u0420\u0443\u0441\u0438\u043d\u043e\u0432\u0446\u0456"
    ],
    "name:und_x_variant":[
        "Rusenovts\u016d",
        "Russenowzi",
        "Rusenovtsi",
        "Rusinovtsi"
    ],
    "wof:name":"Rusinovtsi",
    "wof:placetype":"locality"
},
  "geometry": {"coordinates":[25.51667,42.91667],"type":"Point"}
}