{
  "type": "Feature",
  "properties": {
    "gn:admin1_code":"59",
    "gn:admin2_code":"SZR31",
    "gn:admin3_code":"SZR31-39",
    "gn:asciiname":"Rakitnitsa",
    "gn:cc2":"BG",
    "gn:country_code":"BG",
    "gn:dem":206,
    "gn:feature_class":"P",
    "gn:feature_code":"PPL",
    "gn:name":"Rakitnitsa",
    "gn:population":0,
    "gn:timezone":"Europe/Sofia",
    "iso:country":"BG",
    "name:bul_x_preferred":[
        "\u0420\u0430\u043a\u0438\u0442\u043d\u0438\u0446\u0430"
    ],
    "name:und_x_variant":[
        "Byelchevo",
        "Bel\u010devo",
        "Biel\u010devo",
        "Belchevo",
        "Rakitnitsa"
    ],
    "wof:name":"Rakitnitsa",
    "wof:placetype":"locality"
},
  "geometry": {"coordinates":[25.51667,42.33333],"type":"Point"}
}