{
  "type": "Feature",
  "properties": {
    "gn:admin1_code":"60",
    "gn:admin2_code":"TGV22",
    "gn:admin3_code":"TGV22-05",
    "gn:asciiname":"Verentsi",
    "gn:cc2":"BG",
    "gn:country_code":"BG",
    "gn:dem":561,
    "gn:feature_class":"P",
    "gn:feature_code":"PPL",
    "gn:name":"Verentsi",
    "gn:population":0,
    "gn:timezone":"Europe/Sofia",
    "iso:country":"BG",
    "name:bul_x_preferred":[
        "\u0412\u0435\u0440\u0435\u043d\u0446\u0438"
    ],
    "name:und_x_variant":[
        "Sad\u016dklar",
        "Verintsi",
        "Sadiklar",
        "Werinzi",
        "Verentsi"
    ],
    "wof:name":"Verentsi",
    "wof:placetype":"locality"
},
  "geometry": {"coordinates":[26.45,43.06667],"type":"Point"}
}