{
  "type": "Feature",
  "properties": {
    "gn:admin1_code":"40",
    "gn:admin2_code":"DOB15",
    "gn:asciiname":"Malka Smolnitsa",
    "gn:country_code":"BG",
    "gn:dem":217,
    "gn:feature_class":"P",
    "gn:feature_code":"PPL",
    "gn:name":"Malka Smolnitsa",
    "gn:population":0,
    "gn:timezone":"Europe/Sofia",
    "iso:country":"BG",
    "name:bul_x_preferred":[
        "\u041c\u0430\u043b\u043a\u0430 \u0421\u043c\u043e\u043b\u043d\u0438\u0446\u0430"
    ],
    "name:und_x_variant":[
        "Ceamurlia Mic\u0103",
        "Malko Chamurlu",
        "Ceamurlia Mic",
        "Malko Tschamurlii",
        "Malko Chamurlii",
        "Mic Smolnica",
        "Malka Smolnitsa"
    ],
    "wof:name":"Malka Smolnitsa",
    "wof:placetype":"locality"
},
  "geometry": {"coordinates":[27.72934,43.60471],"type":"Point"}
}