{
  "type": "Feature",
  "properties": {
    "gn:admin1_code":"40",
    "gn:admin2_code":"DOB15",
    "gn:asciiname":"Malka Smolnitsa",
    "gn:country_code":"BG",
    "gn:dem":217,
    "gn:feature_class":"P",
    "gn:feature_code":"PPL",
    "gn:name":"Malka Smolnitsa",
    "gn:population":0,
    "gn:timezone":"Europe/Sofia",
    "iso:country":"BG",
    "name:bul_x_preferred":[
        "\u041c\u0430\u043b\u043a\u0430 \u0421\u043c\u043e\u043b\u043d\u0438\u0446\u0430"
    ],
    "name:fas_x_preferred":[
        "\u0645\u0627\u0644\u06a9\u0627 \u0633\u0645\u0648\u0644\u0646\u06cc\u062a\u0633\u0627"
    ],
    "name:kaz_x_preferred":[
        "\u041c\u0430\u043b\u043a\u0430-\u0421\u043c\u043e\u043b\u043d\u0438\u0446\u0430"
    ],
    "name:ron_x_preferred":[
        "Malka Smolni\u021ba"
    ],
    "name:rus_x_preferred":[
        "\u041c\u0430\u043b\u043a\u0430-\u0421\u043c\u043e\u043b\u043d\u0438\u0446\u0430"
    ],
    "name:ukr_x_preferred":[
        "\u041c\u0430\u043b\u043a\u0430 \u0421\u043c\u043e\u043b\u043d\u0438\u0446\u044f"
    ],
    "name:und_x_variant":[
        "Ceamurlia Mic\u0103",
        "Malko Chamurlu",
        "Ceamurlia Mic",
        "Malko Tschamurlii",
        "Malko Chamurlii",
        "Mic Smolnica",
        "Malka Smolnitsa"
    ],
    "wof:name":"Malka Smolnitsa",
    "wof:placetype":"locality"
},
  "geometry": {"coordinates":[27.72934,43.60471],"type":"Point"}
}