{
  "type": "Feature",
  "properties": {
    "gn:admin1_code":"39",
    "gn:admin2_code":"BGS04",
    "gn:asciiname":"Bryastovets",
    "gn:country_code":"BG",
    "gn:dem":260,
    "gn:feature_class":"P",
    "gn:feature_code":"PPL",
    "gn:name":"Bryastovets",
    "gn:population":0,
    "gn:timezone":"Europe/Sofia",
    "iso:country":"BG",
    "name:bul_x_preferred":[
        "\u0411\u0440\u044f\u0441\u0442\u043e\u0432\u0435\u0446"
    ],
    "name:und_x_variant":[
        "Kara Agach",
        "Brestovets",
        "Karaach",
        "Brestowez",
        "Bryestovets",
        "Bryastovets"
    ],
    "wof:name":"Bryastovets",
    "wof:placetype":"locality"
},
  "geometry": {"coordinates":[27.46464000000001,42.67224],"type":"Point"}
}