{
  "type": "Feature",
  "properties": {
    "gn:admin1_code":"39",
    "gn:admin2_code":"BGS09",
    "gn:asciiname":"San Stefano",
    "gn:cc2":"BG",
    "gn:country_code":"BG",
    "gn:dem":249,
    "gn:feature_class":"P",
    "gn:feature_code":"PPL",
    "gn:name":"San Stefano",
    "gn:population":0,
    "gn:timezone":"Europe/Sofia",
    "iso:country":"BG",
    "name:bul_x_preferred":[
        "\u0421\u0430\u043d \u0421\u0442\u0435\u0444\u0430\u043d\u043e"
    ],
    "name:und_x_variant":[
        "Ismayl-Fak",
        "Smel\u2019fak",
        "Ismail Faku",
        "San Stefano"
    ],
    "wof:name":"San Stefano",
    "wof:placetype":"locality"
},
  "geometry": {"coordinates":[26.88333,42.51667],"type":"Point"}
}