{
  "type": "Feature",
  "properties": {
    "gn:admin1_code":"39",
    "gn:admin2_code":"BGS04",
    "gn:admin3_code":"BGS04-06",
    "gn:asciiname":"Vetren",
    "gn:country_code":"BG",
    "gn:dem":42,
    "gn:feature_class":"P",
    "gn:feature_code":"PPL",
    "gn:name":"Vetren",
    "gn:population":0,
    "gn:timezone":"Europe/Sofia",
    "iso:country":"BG",
    "name:bul_x_preferred":[
        "\u0412\u0435\u0442\u0440\u0435\u043d"
    ],
    "name:und_x_variant":[
        "Tepl\u016deklyuchi L\u016ddzha",
        "Zhitarevo",
        "Vyetren",
        "Zhitarovo",
        "Wetren",
        "Vetren"
    ],
    "wof:name":"Vetren",
    "wof:placetype":"locality"
},
  "geometry": {"coordinates":[27.38455,42.60543],"type":"Point"}
}