{
  "type": "Feature",
  "properties": {
    "gn:gn_country":"BG",
    "gn:gn_fcode":"PPL",
    "gn:gn_pop":0,
    "iso:country":"BG",
    "name:bul_x_preferred":[
        "\u0413\u043e\u0440\u043d\u0430 \u041a\u0440\u0435\u043f\u043e\u0441\u0442"
    ],
    "name:eng_x_preferred":[
        "Gorna krepost"
    ],
    "name:geo_x_preferred":[
        "\u10d2\u10dd\u10e0\u10dc\u10d0-\u10d9\u10e0\u10d4\u10de\u10dd\u10e1\u10e2\u10d8"
    ],
    "name:kaz_x_preferred":[
        "\u0413\u043e\u0440\u043d\u0430-\u041a\u0440\u0435\u043f\u043e\u0441\u0442"
    ],
    "name:rum_x_preferred":[
        "Gorna Krepost"
    ],
    "name:rus_x_preferred":[
        "\u0413\u043e\u0440\u043d\u0430-\u041a\u0440\u0435\u043f\u043e\u0441\u0442"
    ],
    "name:swe_x_preferred":[
        "Gorna krepost"
    ],
    "name:ukr_x_preferred":[
        "\u0413\u043e\u0440\u0456\u0448\u043d\u044f \u041a\u0440\u0435\u043f\u043e\u0441\u0442"
    ],
    "name:unk_x_variant":[
        "Kara Alar"
    ],
    "qs_pg:aaroncc":"BG",
    "qs_pg:gn_country":"BG",
    "qs_pg:gn_fcode":"PPL",
    "qs_pg:gn_pop":0,
    "qs_pg:name":"Gorna Krepost",
    "qs_pg:name_adm0":"Bulgaria",
    "qs_pg:name_adm1":"Kurdzhali",
    "qs_pg:photos":154,
    "qs_pg:photos_1k":31,
    "qs_pg:photos_9k":1,
    "qs_pg:photos_9r":4,
    "qs_pg:photos_all":154,
    "qs_pg:photos_sr":4,
    "qs_pg:pop_sr":0,
    "qs_pg:qs_pg_placetype":"locality",
    "qs_pg:qs_pg_placetype_gp":"Town",
    "qs_pg:woe_adm0":23424771,
    "woe:adm0_id":23424771,
    "woe:name_adm0":"Bulgaria",
    "woe:name_adm1":"Kurdzhali",
    "woe:placetype":"Town",
    "wof:name":"Gorna Krepost",
    "wof:placetype":"locality"
},
  "geometry": {"coordinates":[25.46667,41.71667],"type":"Point"}
}