{
  "type": "Feature",
  "properties": {
    "gn:admin1_code":"44",
    "gn:asciiname":"Podvis",
    "gn:country_code":"BG",
    "gn:dem":385,
    "gn:feature_class":"P",
    "gn:feature_code":"PPL",
    "gn:name":"Podvis",
    "gn:population":0,
    "gn:timezone":"Europe/Sofia",
    "iso:country":"BG",
    "name:bul_x_preferred":[
        "Podvis"
    ],
    "name:bul_x_variant":[
        "\u041f\u043e\u0434\u0432\u0438\u0441"
    ],
    "wof:name":"Podvis",
    "wof:placetype":"locality"
},
  "geometry": {"coordinates":[25.33899,41.41508],"type":"Point"}
}