{
  "type": "Feature",
  "properties": {
    "gn:admin1_code":"55",
    "gn:admin2_code":"SLS07",
    "gn:admin3_code":"SLS07-10",
    "gn:asciiname":"Kalugerene",
    "gn:cc2":"BG",
    "gn:country_code":"BG",
    "gn:dem":140,
    "gn:feature_class":"P",
    "gn:feature_code":"PPL",
    "gn:name":"Kalugerene",
    "gn:population":0,
    "gn:timezone":"Europe/Sofia",
    "iso:country":"BG",
    "name:bul_x_preferred":[
        "\u041a\u0430\u043b\u0443\u0433\u0435\u0440\u0435\u043d\u0435"
    ],
    "name:und_x_variant":[
        "General Dobrev",
        "Hagifaclar",
        "Khadzhiolar",
        "Hagiolar",
        "Khadzhifaklar",
        "Kalugerene"
    ],
    "wof:name":"Kalugerene",
    "wof:placetype":"locality"
},
  "geometry": {"coordinates":[26.86667000000001,43.91667],"type":"Point"}
}