{
  "type": "Feature",
  "properties": {
    "gn:admin1_code":"40",
    "gn:admin2_code":"DOB15",
    "gn:asciiname":"Vrachantsi",
    "gn:country_code":"BG",
    "gn:dem":198,
    "gn:feature_class":"P",
    "gn:feature_code":"PPL",
    "gn:name":"Vrachantsi",
    "gn:population":0,
    "gn:timezone":"Europe/Sofia",
    "iso:country":"BG",
    "name:bul_x_preferred":[
        "\u0412\u0440\u0430\u0447\u0430\u043d\u0446\u0438"
    ],
    "name:fas_x_preferred":[
        "\u0648\u0631\u0627\u0686\u0627\u0646\u062a\u0633\u06cc"
    ],
    "name:kaz_x_preferred":[
        "\u0412\u0440\u0430\u0447\u0430\u043d\u0446\u0438"
    ],
    "name:ron_x_preferred":[
        "Vracean\u021bi"
    ],
    "name:rus_x_preferred":[
        "\u0412\u0440\u0430\u0447\u0430\u043d\u0446\u0438"
    ],
    "name:ukr_x_preferred":[
        "\u0412\u0440\u0430\u0447\u0430\u043d\u0446\u0456"
    ],
    "name:und_x_variant":[
        "Tschek\u0103rtscha",
        "Wra\u010danci",
        "Chek\u016drcha",
        "Ceacarcen",
        "Ceacarcia",
        "Chak\u016drcha",
        "Ceac\u00e2rcea",
        "Vrachantsi"
    ],
    "wof:name":"Vrachantsi",
    "wof:placetype":"locality"
},
  "geometry": {"coordinates":[27.78171,43.6159],"type":"Point"}
}