{
  "type": "Feature",
  "properties": {
    "gn:admin1_code":"44",
    "gn:admin2_code":"KRZ16",
    "gn:admin3_code":"KRZ16-45",
    "gn:asciiname":"Sokolyane",
    "gn:cc2":"BG",
    "gn:country_code":"BG",
    "gn:dem":370,
    "gn:feature_class":"P",
    "gn:feature_code":"PPL",
    "gn:name":"Sokolyane",
    "gn:population":0,
    "gn:timezone":"Europe/Sofia",
    "iso:country":"BG",
    "name:bul_x_preferred":[
        "\u0421\u043e\u043a\u043e\u043b\u044f\u043d\u0435"
    ],
    "name:fas_x_preferred":[
        "\u0633\u0648\u06a9\u0648\u0644\u06cc\u0627\u0646\u0647"
    ],
    "name:kat_x_preferred":[
        "\u10e1\u10dd\u10d9\u10dd\u10da\u10d8\u10d0\u10dc\u10d4"
    ],
    "name:kaz_x_preferred":[
        "\u0421\u043e\u043a\u043e\u043b\u044f\u043d\u0435"
    ],
    "name:ron_x_preferred":[
        "Sokoleane"
    ],
    "name:rus_x_preferred":[
        "\u0421\u043e\u043a\u043e\u043b\u044f\u043d\u0435"
    ],
    "name:ukr_x_preferred":[
        "\u0421\u043e\u043a\u043e\u043b\u044f\u043d\u0435"
    ],
    "name:und_x_variant":[
        "Duvandzhilar",
        "Sokoljane",
        "Sokolyane"
    ],
    "wof:name":"Sokolyane",
    "wof:placetype":"locality"
},
  "geometry": {"coordinates":[25.45,41.75],"type":"Point"}
}