{
  "type": "Feature",
  "properties": {
    "gn:admin1_code":"44",
    "gn:admin2_code":"KRZ16",
    "gn:admin3_code":"KRZ16-45",
    "gn:asciiname":"Sokolyane",
    "gn:cc2":"BG",
    "gn:country_code":"BG",
    "gn:dem":370,
    "gn:feature_class":"P",
    "gn:feature_code":"PPL",
    "gn:name":"Sokolyane",
    "gn:population":0,
    "gn:timezone":"Europe/Sofia",
    "iso:country":"BG",
    "name:bul_x_preferred":[
        "\u0421\u043e\u043a\u043e\u043b\u044f\u043d\u0435"
    ],
    "name:und_x_variant":[
        "Duvandzhilar",
        "Sokoljane",
        "Sokolyane"
    ],
    "wof:name":"Sokolyane",
    "wof:placetype":"locality"
},
  "geometry": {"coordinates":[25.45,41.75],"type":"Point"}
}