{
  "type": "Feature",
  "properties": {
    "gn:admin1_code":"49",
    "gn:admin2_code":"PER51",
    "gn:asciiname":"Slishovtsi",
    "gn:country_code":"BG",
    "gn:dem":829,
    "gn:feature_class":"P",
    "gn:feature_code":"PPL",
    "gn:name":"Slishovtsi",
    "gn:population":0,
    "gn:timezone":"Europe/Sofia",
    "iso:country":"BG",
    "name:bul_x_preferred":[
        "\u0421\u043b\u0438\u0448\u043e\u0432\u0446\u0438"
    ],
    "name:und_x_variant":[
        "Slischowzi",
        "Slishovtsi"
    ],
    "wof:name":"Slishovtsi",
    "wof:placetype":"locality"
},
  "geometry": {"coordinates":[22.46887000000001,42.8086],"type":"Point"}
}