{
  "type": "Feature",
  "properties": {
    "gn:admin1_code":"49",
    "gn:admin2_code":"PER36",
    "gn:asciiname":"Dragomirovo",
    "gn:country_code":"BG",
    "gn:dem":802,
    "gn:feature_class":"P",
    "gn:feature_code":"PPL",
    "gn:name":"Dragomirovo",
    "gn:population":0,
    "gn:timezone":"Europe/Sofia",
    "iso:country":"BG",
    "name:bul_x_preferred":[
        "\u0414\u0440\u0430\u0433\u043e\u043c\u0438\u0440\u043e\u0432\u043e"
    ],
    "name:und_x_variant":[
        "Novo Selo",
        "Nowo Selo",
        "Dragomirovo"
    ],
    "wof:name":"Dragomirovo",
    "wof:placetype":"locality"
},
  "geometry": {"coordinates":[22.84593,42.39336],"type":"Point"}
}