{
  "type": "Feature",
  "properties": {
    "gn:admin1_code":"44",
    "gn:admin2_code":"KRZ15",
    "gn:admin3_code":"KRZ15-41",
    "gn:asciiname":"Padalo",
    "gn:cc2":"BG",
    "gn:country_code":"BG",
    "gn:dem":547,
    "gn:feature_class":"P",
    "gn:feature_code":"PPL",
    "gn:name":"Padalo",
    "gn:population":0,
    "gn:timezone":"Europe/Sofia",
    "iso:country":"BG",
    "name:bul_x_preferred":[
        "\u041f\u0430\u0434\u0430\u043b\u043e"
    ],
    "name:fas_x_preferred":[
        "\u067e\u0627\u062f\u0627\u0644\u0648"
    ],
    "name:kaz_x_preferred":[
        "\u041f\u0430\u0434\u0430\u043b\u043e"
    ],
    "name:ron_x_preferred":[
        "Padalo"
    ],
    "name:rus_x_preferred":[
        "\u041f\u0430\u0434\u0430\u043b\u043e"
    ],
    "name:ukr_x_preferred":[
        "\u041f\u0430\u0434\u0430\u043b\u043e"
    ],
    "name:und_x_variant":[
        "Konadzhik",
        "Padalo"
    ],
    "wof:name":"Padalo",
    "wof:placetype":"locality"
},
  "geometry": {"coordinates":[25.76667,41.56667],"type":"Point"}
}