{
  "type": "Feature",
  "properties": {
    "gn:admin1_code":"44",
    "gn:asciiname":"Yamacha",
    "gn:country_code":"BG",
    "gn:dem":426,
    "gn:feature_class":"P",
    "gn:feature_code":"PPL",
    "gn:name":"Yamacha",
    "gn:population":0,
    "gn:timezone":"Europe/Sofia",
    "iso:country":"BG",
    "name:bul_x_preferred":[
        "Yamacha"
    ],
    "name:bul_x_variant":[
        "\u042f\u043c\u0430\u0447\u0430"
    ],
    "wof:name":"Yamacha",
    "wof:placetype":"locality"
},
  "geometry": {"coordinates":[25.5161,41.45458],"type":"Point"}
}