{
  "type": "Feature",
  "properties": {
    "gn:admin1_code":"62",
    "gn:admin2_code":"VTR14",
    "gn:admin3_code":"VTR14-07",
    "gn:asciiname":"Rodina",
    "gn:cc2":"BG",
    "gn:country_code":"BG",
    "gn:dem":144,
    "gn:feature_class":"P",
    "gn:feature_code":"PPL",
    "gn:name":"Rodina",
    "gn:population":0,
    "gn:timezone":"Europe/Sofia",
    "iso:country":"BG",
    "name:bul_x_preferred":[
        "\u0420\u043e\u0434\u0438\u043d\u0430"
    ],
    "name:ceb_x_preferred":[
        "Rodina"
    ],
    "name:ces_x_preferred":[
        "Rodina"
    ],
    "name:deu_x_preferred":[
        "Rodina"
    ],
    "name:fra_x_preferred":[
        "Rodina"
    ],
    "name:kaz_x_preferred":[
        "\u0420\u043e\u0434\u0438\u043d\u0430"
    ],
    "name:ron_x_preferred":[
        "Rodina"
    ],
    "name:rus_x_preferred":[
        "\u0420\u043e\u0434\u0438\u043d\u0430"
    ],
    "name:slk_x_preferred":[
        "Rodina"
    ],
    "name:swe_x_preferred":[
        "Rodina"
    ],
    "name:ukr_x_preferred":[
        "\u0420\u043e\u0434\u0438\u043d\u0430"
    ],
    "name:und_x_variant":[
        "Tanturi",
        "Rodina"
    ],
    "wof:name":"Rodina",
    "wof:placetype":"locality"
},
  "geometry": {"coordinates":[25.88333,43.08333],"type":"Point"}
}