{
  "type": "Feature",
  "properties": {
    "gn:admin1_code":"39",
    "gn:admin2_code":"BGS13",
    "gn:asciiname":"Izgrev",
    "gn:country_code":"BG",
    "gn:dem":143,
    "gn:feature_class":"P",
    "gn:feature_code":"PPL",
    "gn:name":"Izgrev",
    "gn:population":0,
    "gn:timezone":"Europe/Sofia",
    "iso:country":"BG",
    "name:bul_x_preferred":[
        "\u0418\u0437\u0433\u0440\u0435\u0432"
    ],
    "name:cat_x_preferred":[
        "Izgrev"
    ],
    "name:fas_x_preferred":[
        "\u0627\u06cc\u0632\u06af\u0631\u0648"
    ],
    "name:kaz_x_preferred":[
        "\u0418\u0437\u0433\u0440\u0435\u0432"
    ],
    "name:pol_x_preferred":[
        "Izgrew"
    ],
    "name:ron_x_preferred":[
        "Izgrev"
    ],
    "name:rus_x_preferred":[
        "\u0418\u0437\u0433\u0440\u0435\u0432"
    ],
    "name:spa_x_preferred":[
        "Izgrev"
    ],
    "name:ukr_x_preferred":[
        "\u0406\u0437\u0433\u0440\u0435\u0432"
    ],
    "name:und_x_variant":[
        "Lisovo",
        "Isgrew"
    ],
    "wof:name":"Izgrev",
    "wof:placetype":"locality"
},
  "geometry": {"coordinates":[27.80127,42.1443],"type":"Point"}
}