{
  "type": "Feature",
  "properties": {
    "gn:admin1_code":"40",
    "gn:admin2_code":"DOB15",
    "gn:admin3_code":"DOB15-44",
    "gn:asciiname":"Plachidol",
    "gn:country_code":"BG",
    "gn:dem":255,
    "gn:feature_class":"P",
    "gn:feature_code":"PPL",
    "gn:name":"Plachidol",
    "gn:population":0,
    "gn:timezone":"Europe/Sofia",
    "iso:country":"BG",
    "name:bul_x_preferred":[
        "\u041f\u043b\u0430\u0447\u0438\u0434\u043e\u043b"
    ],
    "name:fas_x_preferred":[
        "\u067e\u0644\u0627\u0686\u06cc \u062f\u0644"
    ],
    "name:hun_x_preferred":[
        "Placsidol"
    ],
    "name:kaz_x_preferred":[
        "\u041f\u043b\u0430\u0447\u0438\u0434\u043e\u043b"
    ],
    "name:ron_x_preferred":[
        "Placidol"
    ],
    "name:rus_x_preferred":[
        "\u041f\u043b\u0430\u0447\u0438\u0434\u043e\u043b"
    ],
    "name:ukr_x_preferred":[
        "\u041f\u043b\u0430\u0447\u0438\u0434\u043e\u043b"
    ],
    "name:und_x_variant":[
        "Golyam Al\u016dch K\u2019oy",
        "Aliciul-Mare",
        "Golem-Al\u0103tsch",
        "Pla\u010didol",
        "Plachidol"
    ],
    "wof:name":"Plachidol",
    "wof:placetype":"locality"
},
  "geometry": {"coordinates":[27.88291,43.53975],"type":"Point"}
}