{
  "type": "Feature",
  "properties": {
    "gn:admin1_code":"54",
    "gn:admin2_code":"SHU19",
    "gn:admin3_code":"SHU19-02",
    "gn:asciiname":"Zlatna Niva",
    "gn:cc2":"BG",
    "gn:country_code":"BG",
    "gn:dem":214,
    "gn:feature_class":"P",
    "gn:feature_code":"PPL",
    "gn:name":"Zlatna Niva",
    "gn:population":0,
    "gn:timezone":"Europe/Sofia",
    "iso:country":"BG",
    "name:bul_x_preferred":[
        "\u0417\u043b\u0430\u0442\u043d\u0430 \u041d\u0438\u0432\u0430"
    ],
    "name:und_x_variant":[
        "Slatna-Niwa",
        "Teker",
        "Zlatna Niva"
    ],
    "wof:name":"Zlatna Niva",
    "wof:placetype":"locality"
},
  "geometry": {"coordinates":[27.06667,43.38333],"type":"Point"}
}