{
  "type": "Feature",
  "properties": {
    "gn:admin1_code":"44",
    "gn:admin2_code":"KRZ21",
    "gn:admin3_code":"KRZ21-20",
    "gn:asciiname":"Sedefche",
    "gn:country_code":"BG",
    "gn:dem":478,
    "gn:feature_class":"P",
    "gn:feature_code":"PPL",
    "gn:name":"Sedefche",
    "gn:population":0,
    "gn:timezone":"Europe/Sofia",
    "iso:country":"BG",
    "name:bul_x_preferred":[
        "\u0421\u0435\u0434\u0435\u0444\u0447\u0435"
    ],
    "name:und_x_variant":[
        "Sedevche",
        "Sedeftsche",
        "Sarkhanl\u016d",
        "Sedefche"
    ],
    "wof:name":"Sedefche",
    "wof:placetype":"locality"
},
  "geometry": {"coordinates":[25.53446,41.42412],"type":"Point"}
}