{
  "type": "Feature",
  "properties": {
    "gn:admin1_code":"40",
    "gn:admin2_code":"DOB15",
    "gn:asciiname":"Polkovnik Sveshtarovo",
    "gn:country_code":"BG",
    "gn:dem":245,
    "gn:feature_class":"P",
    "gn:feature_code":"PPL",
    "gn:name":"Polkovnik Sveshtarovo",
    "gn:population":0,
    "gn:timezone":"Europe/Sofia",
    "iso:country":"BG",
    "name:bul_x_preferred":[
        "\u041f\u043e\u043b\u043a\u043e\u0432\u043d\u0438\u043a \u0421\u0432\u0435\u0449\u0430\u0440\u043e\u0432\u043e"
    ],
    "name:und_x_variant":[
        "Aidan-Ciufa",
        "Polkownik Swe\u0161tarowo",
        "Aid\u0103ntschucha",
        "Bash Bunar",
        "Baschbunar",
        "Bas-Bunar",
        "Polkovnik Sveshtarovo"
    ],
    "wof:name":"Polkovnik Sveshtarovo",
    "wof:placetype":"locality"
},
  "geometry": {"coordinates":[27.93444,43.55376],"type":"Point"}
}