{
  "type": "Feature",
  "properties": {
    "gn:admin1_code":"49",
    "gn:admin2_code":"PER08",
    "gn:asciiname":"Rezhantsi",
    "gn:country_code":"BG",
    "gn:dem":736,
    "gn:feature_class":"P",
    "gn:feature_code":"PPL",
    "gn:name":"Rezhantsi",
    "gn:population":0,
    "gn:timezone":"Europe/Sofia",
    "iso:country":"BG",
    "name:bul_x_preferred":[
        "\u0420\u0435\u0436\u0430\u043d\u0446\u0438"
    ],
    "name:und_x_variant":[
        "Ryezhantsi",
        "Reshanzi",
        "Rezhantsi"
    ],
    "wof:name":"Rezhantsi",
    "wof:placetype":"locality"
},
  "geometry": {"coordinates":[22.85017,42.71928],"type":"Point"}
}