{
  "type": "Feature",
  "properties": {
    "gn:admin1_code":"43",
    "gn:admin2_code":"HKV17",
    "gn:asciiname":"Vaskovo",
    "gn:country_code":"BG",
    "gn:dem":287,
    "gn:feature_class":"P",
    "gn:feature_code":"PPL",
    "gn:name":"Vaskovo",
    "gn:population":0,
    "gn:timezone":"Europe/Sofia",
    "iso:country":"BG",
    "name:bul_x_preferred":[
        "\u0412\u0435\u0441\u043a\u043e\u0432\u043e"
    ],
    "name:bul_x_variant":[
        "\u0412\u0430\u0441\u043a\u043e\u0432\u043e"
    ],
    "name:und_x_variant":[
        "Ishibeglii",
        "Vaskovo"
    ],
    "wof:name":"Vaskovo",
    "wof:placetype":"locality"
},
  "geometry": {"coordinates":[26.19865,41.91642],"type":"Point"}
}