{
  "type": "Feature",
  "properties": {
    "gn:admin1_code":"44",
    "gn:admin2_code":"KRZ15",
    "gn:admin3_code":"KRZ15-41",
    "gn:asciiname":"Strandzhevo",
    "gn:cc2":"BG",
    "gn:country_code":"BG",
    "gn:dem":197,
    "gn:feature_class":"P",
    "gn:feature_code":"PPL",
    "gn:name":"Strandzhevo",
    "gn:population":0,
    "gn:timezone":"Europe/Sofia",
    "iso:country":"BG",
    "name:bul_x_preferred":[
        "\u0421\u0442\u0440\u0430\u043d\u0434\u0436\u0435\u0432\u043e"
    ],
    "name:und_x_variant":[
        "Makhmutli",
        "Strandshewo",
        "Strandzhevo"
    ],
    "wof:name":"Strandzhevo",
    "wof:placetype":"locality"
},
  "geometry": {"coordinates":[25.76667,41.63333],"type":"Point"}
}