{
  "type": "Feature",
  "properties": {
    "gn:country":"BG",
    "gn:fcode":"PPL",
    "gn:population":0,
    "iso:country":"BG",
    "name:bul_x_preferred":[
        "\u041f\u0440\u043e\u0433\u043b\u0435\u0434"
    ],
    "name:che_x_preferred":[
        "\u041f\u0440\u043e\u0433\u043b\u0435\u0434"
    ],
    "name:eng_x_preferred":[
        "Progled"
    ],
    "name:fra_x_preferred":[
        "Progled"
    ],
    "name:kaz_x_preferred":[
        "\u041f\u0440\u043e\u0433\u043b\u0435\u0434"
    ],
    "name:nan_x_preferred":[
        "Progled"
    ],
    "name:ron_x_preferred":[
        "Progled"
    ],
    "name:rus_x_preferred":[
        "\u041f\u0440\u043e\u0433\u043b\u0435\u0434"
    ],
    "name:tat_x_preferred":[
        "\u041f\u0440\u043e\u0433\u043b\u0435\u0434"
    ],
    "name:ukr_x_preferred":[
        "\u041f\u0440\u043e\u0433\u043b\u0435\u0434"
    ],
    "qs_pg:aaroncc":"BG",
    "qs_pg:gn_country":"BG",
    "qs_pg:gn_fcode":"PPL",
    "qs_pg:gn_pop":0,
    "qs_pg:name":"Progled",
    "qs_pg:name_adm0":"Bulgaria",
    "qs_pg:name_adm1":"Smolyan",
    "qs_pg:photos":287,
    "qs_pg:photos_1k":58,
    "qs_pg:photos_9k":1,
    "qs_pg:photos_9r":4,
    "qs_pg:photos_all":287,
    "qs_pg:photos_sr":5,
    "qs_pg:pop_sr":0,
    "qs_pg:qs_pg_placetype":"locality",
    "qs_pg:qs_pg_placetype_gp":"Town",
    "qs_pg:woe_adm0":23424771,
    "woe:adm0_id":23424771,
    "woe:name_adm0":"Bulgaria",
    "woe:name_adm1":"Smolyan",
    "woe:placetype":"Town",
    "wof:name":"Progled",
    "wof:placetype":"locality"
},
  "geometry": {"coordinates":[24.71667,41.68333],"type":"Point"}
}