{
  "type": "Feature",
  "properties": {
    "gn:admin1_code":"62",
    "gn:admin2_code":"VTR13",
    "gn:admin3_code":"VTR13-01",
    "gn:asciiname":"Bosevtsi",
    "gn:cc2":"BG",
    "gn:country_code":"BG",
    "gn:dem":562,
    "gn:feature_class":"P",
    "gn:feature_code":"PPL",
    "gn:name":"Bosevtsi",
    "gn:population":0,
    "gn:timezone":"Europe/Sofia",
    "iso:country":"BG",
    "name:bul_x_preferred":[
        "\u0411\u043e\u0441\u0435\u0432\u0446\u0438"
    ],
    "name:und_x_variant":[
        "Bosevts\u016d",
        "Bossewzi",
        "Bosevtsi"
    ],
    "wof:name":"Bosevtsi",
    "wof:placetype":"locality"
},
  "geometry": {"coordinates":[25.95,42.96667],"type":"Point"}
}