{
  "type": "Feature",
  "properties": {
    "gn:admin1_code":"51",
    "gn:admin2_code":"PDV01",
    "gn:admin3_code":"PDV01-10",
    "gn:asciiname":"Kozanovo",
    "gn:cc2":"BG",
    "gn:country_code":"BG",
    "gn:dem":214,
    "gn:feature_class":"P",
    "gn:feature_code":"PPL",
    "gn:name":"Kozanovo",
    "gn:population":0,
    "gn:timezone":"Europe/Sofia",
    "iso:country":"BG",
    "name:bul_x_preferred":[
        "\u041a\u043e\u0437\u0430\u043d\u043e\u0432\u043e"
    ],
    "name:und_x_variant":[
        "Kosanowo",
        "Kozanovo"
    ],
    "wof:name":"Kozanovo",
    "wof:placetype":"locality"
},
  "geometry": {"coordinates":[24.96667,42.01667],"type":"Point"}
}