{
  "type": "Feature",
  "properties": {
    "gn:admin1_code":"62",
    "gn:asciiname":"Razvalatsi",
    "gn:cc2":"BG",
    "gn:country_code":"BG",
    "gn:dem":439,
    "gn:feature_class":"P",
    "gn:feature_code":"PPL",
    "gn:name":"Razvalatsi",
    "gn:population":0,
    "gn:timezone":"Europe/Sofia",
    "iso:country":"BG",
    "name:bul_x_preferred":[
        "\u0420\u0435\u0437\u0432\u0430\u043b\u0430\u0446\u0438"
    ],
    "name:und_x_variant":[
        "Nova Makhala",
        "Rozvalats\u016d",
        "Razvalatsi"
    ],
    "wof:name":"Razvalatsi",
    "wof:placetype":"locality"
},
  "geometry": {"coordinates":[25.76667,42.95],"type":"Point"}
}