{
  "type": "Feature",
  "properties": {
    "gn:admin1_code":"41",
    "gn:admin2_code":"GAB29",
    "gn:admin3_code":"GAB29-15",
    "gn:asciiname":"Kormyansko",
    "gn:country_code":"BG",
    "gn:dem":233,
    "gn:feature_class":"P",
    "gn:feature_code":"PPL",
    "gn:name":"Kormyansko",
    "gn:population":0,
    "gn:timezone":"Europe/Sofia",
    "iso:country":"BG",
    "name:ara_x_preferred":[
        "\u0643\u0648\u0631\u0645\u064a\u0627\u0646\u0633\u0643\u0648"
    ],
    "name:bul_x_preferred":[
        "\u041a\u043e\u0440\u043c\u044f\u043d\u0441\u043a\u043e"
    ],
    "name:ceb_x_preferred":[
        "Kormjansko"
    ],
    "name:fas_x_preferred":[
        "\u06a9\u0648\u0631\u0645\u06cc\u0627\u0646\u0633\u06a9\u0648"
    ],
    "name:kaz_x_preferred":[
        "\u041a\u043e\u0440\u043c\u044f\u043d\u0441\u043a\u043e"
    ],
    "name:pol_x_preferred":[
        "Kormjansko"
    ],
    "name:ron_x_preferred":[
        "Kormeansko"
    ],
    "name:rus_x_preferred":[
        "\u041a\u043e\u0440\u043c\u044f\u043d\u0441\u043a\u043e"
    ],
    "name:swe_x_preferred":[
        "Kormjansko"
    ],
    "name:ukr_x_preferred":[
        "\u041a\u043e\u0440\u043c\u044f\u043d\u0441\u044c\u043a\u043e"
    ],
    "wof:name":"Kormyansko",
    "wof:placetype":"locality"
},
  "geometry": {"coordinates":[25.03333,43.05],"type":"Point"}
}