{
  "type": "Feature",
  "properties": {
    "gn:admin1_code":"60",
    "gn:admin2_code":"TGV24",
    "gn:admin3_code":"TGV24-01",
    "gn:asciiname":"Aprilovo",
    "gn:cc2":"BG",
    "gn:country_code":"BG",
    "gn:dem":340,
    "gn:feature_class":"P",
    "gn:feature_code":"PPL",
    "gn:name":"Aprilovo",
    "gn:population":0,
    "gn:timezone":"Europe/Sofia",
    "iso:country":"BG",
    "name:bul_x_preferred":[
        "\u0410\u043f\u0440\u0438\u043b\u043e\u0432\u043e"
    ],
    "name:und_x_variant":[
        "Araplar",
        "Aprilowo",
        "Arablar",
        "Aprilovo"
    ],
    "wof:name":"Aprilovo",
    "wof:placetype":"locality"
},
  "geometry": {"coordinates":[26.28333,43.25],"type":"Point"}
}