{
  "type": "Feature",
  "properties": {
    "gn:admin1_code":"49",
    "gn:admin2_code":"PER08",
    "gn:asciiname":"Nepraznentsi",
    "gn:country_code":"BG",
    "gn:dem":750,
    "gn:feature_class":"P",
    "gn:feature_code":"PPL",
    "gn:name":"Nepraznentsi",
    "gn:population":0,
    "gn:timezone":"Europe/Sofia",
    "iso:country":"BG",
    "name:bul_x_preferred":[
        "\u041d\u0435\u043f\u0440\u0430\u0437\u043d\u0435\u043d\u0446\u0438"
    ],
    "wof:name":"Nepraznentsi",
    "wof:placetype":"locality"
},
  "geometry": {"coordinates":[22.84677000000001,42.67232],"type":"Point"}
}