{
  "type": "Feature",
  "properties": {
    "gn:admin1_code":"51",
    "gn:admin2_code":"PDV23",
    "gn:admin3_code":"PDV23-13",
    "gn:asciiname":"Krushevo",
    "gn:cc2":"BG",
    "gn:country_code":"BG",
    "gn:dem":124,
    "gn:feature_class":"P",
    "gn:feature_code":"PPL",
    "gn:name":"Krushevo",
    "gn:population":0,
    "gn:timezone":"Europe/Sofia",
    "iso:country":"BG",
    "name:bul_x_preferred":[
        "\u041a\u0440\u0443\u0448\u0435\u0432\u043e"
    ],
    "name:und_x_variant":[
        "Razvalini Khalatkioy",
        "Khal\u016dt K\u2019oy",
        "Kruschewo",
        "Krushevo"
    ],
    "wof:name":"Krushevo",
    "wof:placetype":"locality"
},
  "geometry": {"coordinates":[25.23333,42.13333],"type":"Point"}
}