{
  "type": "Feature",
  "properties": {
    "gn:admin1_code":"38",
    "gn:admin2_code":"BLG44",
    "gn:asciiname":"Suhostrel",
    "gn:country_code":"BG",
    "gn:dem":1133,
    "gn:feature_class":"P",
    "gn:feature_code":"PPLL",
    "gn:name":"Suhostrel",
    "gn:population":0,
    "gn:timezone":"Europe/Sofia",
    "iso:country":"BG",
    "name:bul_x_preferred":[
        "\u0421\u0443\u0445\u043e\u0441\u0442\u0440\u0435\u043b"
    ],
    "name:fas_x_preferred":[
        "\u0633\u0648\u062d\u0648\u0633\u062a\u0631\u0644"
    ],
    "name:kaz_x_preferred":[
        "\u0421\u0443\u0445\u043e\u0441\u0442\u0440\u0435\u043b"
    ],
    "name:mkd_x_preferred":[
        "\u0421\u0443\u0445\u043e\u0441\u0442\u0440\u0435\u043b"
    ],
    "name:pol_x_preferred":[
        "Suchostre\u0142"
    ],
    "name:ron_x_preferred":[
        "Suhostrel"
    ],
    "name:rus_x_preferred":[
        "\u0421\u0443\u0445\u043e\u0441\u0442\u0440\u0435\u043b"
    ],
    "name:ukr_x_preferred":[
        "\u0421\u0443\u0445\u043e\u0441\u0442\u0440\u0435\u043b"
    ],
    "name:und_x_variant":[
        "Suchostrel",
        "Suhostrel",
        "Sukhostrel"
    ],
    "wof:name":"Suhostrel",
    "wof:placetype":"locality"
},
  "geometry": {"coordinates":[22.96413,41.83557],"type":"Point"}
}