{
  "type": "Feature",
  "properties": {
    "gn:admin1_code":"60",
    "gn:admin2_code":"TGV22",
    "gn:admin3_code":"TGV22-42",
    "gn:asciiname":"Visok",
    "gn:cc2":"BG",
    "gn:country_code":"BG",
    "gn:dem":495,
    "gn:feature_class":"P",
    "gn:feature_code":"PPL",
    "gn:name":"Visok",
    "gn:population":0,
    "gn:timezone":"Europe/Sofia",
    "iso:country":"BG",
    "name:bul_x_preferred":[
        "\u0412\u0438\u0441\u043e\u043a"
    ],
    "name:und_x_variant":[
        "Osmanlar",
        "Wissok",
        "Visok"
    ],
    "wof:name":"Visok",
    "wof:placetype":"locality"
},
  "geometry": {"coordinates":[26.48333,43.05],"type":"Point"}
}