{
  "type": "Feature",
  "properties": {
    "gn:admin1_code":"38",
    "gn:admin2_code":"BLG03",
    "gn:admin3_code":"BLG03-17",
    "gn:asciiname":"Padesh",
    "gn:country_code":"BG",
    "gn:dem":561,
    "gn:feature_class":"P",
    "gn:feature_code":"PPL",
    "gn:name":"Padesh",
    "gn:population":0,
    "gn:timezone":"Europe/Sofia",
    "iso:country":"BG",
    "name:bul_x_preferred":[
        "\u041f\u0430\u0434\u0435\u0448"
    ],
    "name:und_x_variant":[
        "Padesch",
        "Pade\u0161",
        "Padesh"
    ],
    "wof:name":"Padesh",
    "wof:placetype":"locality"
},
  "geometry": {"coordinates":[23.00214,41.93076],"type":"Point"}
}