{
  "type": "Feature",
  "properties": {
    "gn:admin1_code":"44",
    "gn:admin2_code":"KRZ16",
    "gn:admin3_code":"KRZ16-28",
    "gn:asciiname":"Prileptsi",
    "gn:cc2":"BG",
    "gn:country_code":"BG",
    "gn:dem":309,
    "gn:feature_class":"P",
    "gn:feature_code":"PPL",
    "gn:name":"Prileptsi",
    "gn:population":0,
    "gn:timezone":"Europe/Sofia",
    "iso:country":"BG",
    "name:bul_x_preferred":[
        "\u041f\u0440\u0438\u043b\u0435\u043f\u0446\u0438"
    ],
    "name:und_x_variant":[
        "Salikhler",
        "Prilepzi",
        "Slikhler",
        "Prileptsi"
    ],
    "wof:name":"Prileptsi",
    "wof:placetype":"locality"
},
  "geometry": {"coordinates":[25.35,41.63333],"type":"Point"}
}