{
  "type": "Feature",
  "properties": {
    "gn:admin1_code":"44",
    "gn:admin2_code":"KRZ16",
    "gn:admin3_code":"KRZ16-28",
    "gn:asciiname":"Prileptsi",
    "gn:cc2":"BG",
    "gn:country_code":"BG",
    "gn:dem":309,
    "gn:feature_class":"P",
    "gn:feature_code":"PPL",
    "gn:name":"Prileptsi",
    "gn:population":0,
    "gn:timezone":"Europe/Sofia",
    "iso:country":"BG",
    "name:bul_x_preferred":[
        "\u041f\u0440\u0438\u043b\u0435\u043f\u0446\u0438"
    ],
    "name:ceb_x_preferred":[
        "Prilepci"
    ],
    "name:fas_x_preferred":[
        "\u067e\u0631\u06cc\u0644\u067e\u062a\u0633\u06cc"
    ],
    "name:kat_x_preferred":[
        "\u10de\u10e0\u10d8\u10da\u10d4\u10de\u10ea\u10d8"
    ],
    "name:kaz_x_preferred":[
        "\u041f\u0440\u0438\u043b\u0435\u043f\u0446\u0438"
    ],
    "name:ron_x_preferred":[
        "Prilep\u021bi"
    ],
    "name:rus_x_preferred":[
        "\u041f\u0440\u0438\u043b\u0435\u043f\u0446\u0438"
    ],
    "name:swe_x_preferred":[
        "Prileptsi"
    ],
    "name:ukr_x_preferred":[
        "\u041f\u0440\u0438\u043b\u0435\u043f\u0446\u0456"
    ],
    "name:und_x_variant":[
        "Salikhler",
        "Prilepzi",
        "Slikhler"
    ],
    "wof:name":"Prileptsi",
    "wof:placetype":"locality"
},
  "geometry": {"coordinates":[25.35,41.63333],"type":"Point"}
}