{
  "type": "Feature",
  "properties": {
    "gn:admin1_code":"61",
    "gn:admin2_code":"VAR01",
    "gn:admin3_code":"VAR01-01",
    "gn:asciiname":"Dobri Dol",
    "gn:country_code":"BG",
    "gn:dem":77,
    "gn:feature_class":"P",
    "gn:feature_code":"PPL",
    "gn:name":"Dobri Dol",
    "gn:population":0,
    "gn:timezone":"Europe/Sofia",
    "iso:country":"BG",
    "name:bul_x_preferred":[
        "\u0414\u043e\u0431\u0440\u0438 \u0414\u043e\u043b"
    ],
    "name:und_x_variant":[
        "Dede K\u2019oy",
        "Dere K\u2019oy",
        "Dedekioy",
        "Dobri Dol"
    ],
    "wof:name":"Dobri Dol",
    "wof:placetype":"locality"
},
  "geometry": {"coordinates":[27.75385,43.07178],"type":"Point"}
}