{
  "type": "Feature",
  "properties": {
    "iso:country":"BG",
    "name:bul_x_preferred":[
        "\u0415\u0440\u043c\u0430 \u0440\u0435\u043a\u0430"
    ],
    "name:bul_x_variant":[
        "\u0415\u0440\u043c\u0430 \u0420\u0435\u043a\u0430"
    ],
    "name:eng_x_preferred":[
        "Erma Reka"
    ],
    "name:eng_x_variant":[
        "Erma-Ryeka",
        "Irma Ryeka",
        "Promishleno Selo Erma Reka"
    ],
    "name:fra_x_preferred":[
        "Erma Reka"
    ],
    "name:kat_x_preferred":[
        "\u10d4\u10e0\u10db\u10d0-\u10e0\u10d4\u10d9\u10d0"
    ],
    "name:kaz_x_preferred":[
        "\u0415\u0440\u043c\u0430-\u0420\u0435\u043a\u0430"
    ],
    "name:ron_x_preferred":[
        "Erma Reka"
    ],
    "name:rus_x_preferred":[
        "\u0415\u0440\u043c\u0430-\u0420\u0435\u043a\u0430"
    ],
    "name:ukr_x_preferred":[
        "\u0404\u0440\u043c\u0430-\u0420\u0435\u043a\u0430"
    ],
    "qs:a0":"\u0411\u044a\u043b\u0433\u0430\u0440\u0438\u044f",
    "qs:a1":"*\u0421\u043c\u043e\u043b\u044f\u043d",
    "qs:a1_alt":"Smolyan",
    "qs:a1r":"0",
    "qs:adm0":"\u0411\u044a\u043b\u0433\u0430\u0440\u0438\u044f",
    "qs:la_lc":"*",
    "qs:level":"locality",
    "qs:loc":"\u0415\u0440\u043c\u0430 \u0440\u0435\u043a\u0430",
    "qs:loc_alt":"Erma reka",
    "qs:pop":0,
    "qs:type":"buffered point",
    "wd:wordcount":46,
    "wof:lang":[
        "eng"
    ],
    "wof:name":"\u0415\u0440\u043c\u0430 \u0440\u0435\u043a\u0430",
    "wof:placetype":"locality"
},
  "geometry": {"coordinates":[24.976261,41.417116],"type":"Point"}
}