{
  "type": "Feature",
  "properties": {
    "gn:admin1_code":"57",
    "gn:asciiname":"Angelovi Kolibi",
    "gn:country_code":"BG",
    "gn:dem":632,
    "gn:feature_class":"P",
    "gn:feature_code":"PPL",
    "gn:name":"Angelovi Kolibi",
    "gn:population":0,
    "gn:timezone":"Europe/Sofia",
    "iso:country":"BG",
    "name:bul_x_preferred":[
        "Angelovi Kolibi"
    ],
    "name:bul_x_variant":[
        "\u0410\u043d\u0433\u0435\u043b\u043e\u0432\u0438 \u041a\u043e\u043b\u0438\u0431\u0438"
    ],
    "wof:name":"Angelovi Kolibi",
    "wof:placetype":"locality"
},
  "geometry": {"coordinates":[25.14721,41.45052],"type":"Point"}
}