{
  "type": "Feature",
  "properties": {
    "iso:country":"BG",
    "qs_pg:aaroncc":"BG",
    "qs_pg:name":"Beklemeto",
    "qs_pg:name_adm0":"Bulgaria",
    "qs_pg:name_adm1":"Lovech",
    "qs_pg:photos":68,
    "qs_pg:photos_1k":14,
    "qs_pg:photos_9k":1,
    "qs_pg:photos_9r":2,
    "qs_pg:photos_all":68,
    "qs_pg:photos_sr":2,
    "qs_pg:pop_sr":0,
    "qs_pg:qs_pg_placetype":"locality",
    "qs_pg:qs_pg_placetype_gp":"Town",
    "qs_pg:woe_adm0":23424771,
    "woe:adm0_id":23424771,
    "woe:name_adm0":"Bulgaria",
    "woe:name_adm1":"Lovech",
    "woe:placetype":"Town",
    "wof:name":"Beklemeto",
    "wof:placetype":"locality"
},
  "geometry": {"coordinates":[24.64826,42.7905755],"type":"Point"}
}