{
  "type": "Feature",
  "properties": {
    "gn:admin1_code":"65",
    "gn:admin2_code":"JAM22",
    "gn:admin3_code":"JAM22-19",
    "gn:asciiname":"Parvenets",
    "gn:country_code":"BG",
    "gn:dem":142,
    "gn:feature_class":"P",
    "gn:feature_code":"PPL",
    "gn:name":"Parvenets",
    "gn:population":0,
    "gn:timezone":"Europe/Sofia",
    "iso:country":"BG",
    "name:bul_x_preferred":[
        "\u041f\u044a\u0440\u0432\u0435\u043d\u0435\u0446"
    ],
    "name:bul_x_variant":[
        "Parvenets"
    ],
    "name:und_x_variant":[
        "Bashalii",
        "P\u0103rwenez",
        "P\u016drvenets"
    ],
    "wof:name":"Parvenets",
    "wof:placetype":"locality"
},
  "geometry": {"coordinates":[26.85,42.43333],"type":"Point"}
}