{
  "type": "Feature",
  "properties": {
    "gn:admin1_code":"45",
    "gn:admin2_code":"KNL29",
    "gn:asciiname":"Bobeshino",
    "gn:cc2":"BG",
    "gn:country_code":"BG",
    "gn:dem":1036,
    "gn:feature_class":"P",
    "gn:feature_code":"PPLL",
    "gn:name":"Bobeshino",
    "gn:population":0,
    "gn:timezone":"Europe/Sofia",
    "iso:country":"BG",
    "name:bul_x_preferred":[
        "\u0411\u043e\u0431\u0435\u0448\u0438\u043d\u043e"
    ],
    "name:kaz_x_preferred":[
        "\u0411\u043e\u0431\u0435\u0448\u0438\u043d\u043e"
    ],
    "name:ron_x_preferred":[
        "Bobe\u0219ino"
    ],
    "name:rus_x_preferred":[
        "\u0411\u043e\u0431\u0435\u0448\u0438\u043d\u043e"
    ],
    "name:ukr_x_preferred":[
        "\u0411\u043e\u0431\u0435\u0448\u0438\u043d\u043e"
    ],
    "name:und_x_variant":[
        "Bobeschino",
        "Bobeshino"
    ],
    "wof:name":"Bobeshino",
    "wof:placetype":"locality"
},
  "geometry": {"coordinates":[22.4225,42.31444000000001],"type":"Point"}
}