{
  "type": "Feature",
  "properties": {
    "gn:admin1_code":"58",
    "gn:admin2_code":"SFO56",
    "gn:asciiname":"Hvarchil",
    "gn:country_code":"BG",
    "gn:dem":791,
    "gn:feature_class":"P",
    "gn:feature_code":"PPL",
    "gn:name":"Hvarchil",
    "gn:population":0,
    "gn:timezone":"Europe/Sofia",
    "iso:country":"BG",
    "name:bul_x_preferred":[
        "\u0425\u0432\u044a\u0440\u0447\u0438\u043b"
    ],
    "name:bul_x_variant":[
        "Hvarchil"
    ],
    "name:und_x_variant":[
        "F\u016drchil",
        "Khv\u016drchil"
    ],
    "wof:name":"Hvarchil",
    "wof:placetype":"locality"
},
  "geometry": {"coordinates":[23.93333,42.58333],"type":"Point"}
}