{
  "type": "Feature",
  "properties": {
    "gn:admin1_code":"45",
    "gn:admin2_code":"KNL29",
    "gn:asciiname":"Tsarvendol",
    "gn:country_code":"BG",
    "gn:dem":981,
    "gn:feature_class":"P",
    "gn:feature_code":"PPLL",
    "gn:name":"Tsarvendol",
    "gn:population":0,
    "gn:timezone":"Europe/Sofia",
    "iso:country":"BG",
    "name:bul_x_preferred":[
        "\u0426\u044a\u0440\u0432\u0435\u043d\u0434\u043e\u043b"
    ],
    "name:bul_x_variant":[
        "Tsarvendol",
        "\u0426\u044a\u0440\u0432\u0435\u043d\u044f\u043d\u043e"
    ],
    "name:fas_x_preferred":[
        "\u062a\u0633\u0627\u0631\u0648\u0646\u062f\u0648\u0644"
    ],
    "name:kaz_x_preferred":[
        "\u0426\u0435\u0440\u0432\u0435\u043d\u044f\u043d\u043e"
    ],
    "name:ron_x_preferred":[
        "\u021a\u0103rveneano"
    ],
    "name:rus_x_preferred":[
        "\u0426\u0435\u0440\u0432\u0435\u043d\u044f\u043d\u043e"
    ],
    "name:ukr_x_preferred":[
        "\u0426\u0438\u0440\u0432\u0435\u043d\u044f\u043d\u043e"
    ],
    "name:und_x_variant":[
        "Z\u0103rweni-Dol",
        "Ts\u016drveni Dol",
        "Ts\u016drveni Dol\u016d",
        "Ts\u016drvendol"
    ],
    "wof:name":"Tsarvendol",
    "wof:placetype":"locality"
},
  "geometry": {"coordinates":[22.45084,42.2828],"type":"Point"}
}