{
  "type": "Feature",
  "properties": {
    "gn:admin1_code":"44",
    "gn:admin2_code":"KRZ16",
    "gn:admin3_code":"KRZ16-42",
    "gn:asciiname":"Martino",
    "gn:cc2":"BG",
    "gn:country_code":"BG",
    "gn:dem":514,
    "gn:feature_class":"P",
    "gn:feature_code":"PPL",
    "gn:name":"Martino",
    "gn:population":0,
    "gn:timezone":"Europe/Sofia",
    "iso:country":"BG",
    "name:bul_x_preferred":[
        "\u041c\u0430\u0440\u0442\u0438\u043d\u043e"
    ],
    "name:und_x_variant":[
        "Apazlar",
        "Martino"
    ],
    "wof:name":"Martino",
    "wof:placetype":"locality"
},
  "geometry": {"coordinates":[25.26667,41.71667],"type":"Point"}
}