{
  "type": "Feature",
  "properties": {
    "gn:admin1_code":"38",
    "gn:asciiname":"Veselintsi",
    "gn:country_code":"BG",
    "gn:dem":663,
    "gn:feature_class":"P",
    "gn:feature_code":"PPL",
    "gn:name":"Veselintsi",
    "gn:population":0,
    "gn:timezone":"Europe/Sofia",
    "iso:country":"BG",
    "name:bul_x_preferred":[
        "Veselintsi"
    ],
    "name:bul_x_variant":[
        "\u0412\u0435\u0441\u0435\u043b\u0438\u043d\u0446\u0438"
    ],
    "wof:name":"Veselintsi",
    "wof:placetype":"locality"
},
  "geometry": {"coordinates":[23.01908,41.9645],"type":"Point"}
}