{
  "type": "Feature",
  "properties": {
    "gn:admin1_code":"41",
    "gn:admin2_code":"GAB35",
    "gn:asciiname":"Bardeni",
    "gn:country_code":"BG",
    "gn:dem":562,
    "gn:feature_class":"P",
    "gn:feature_code":"PPL",
    "gn:name":"Bardeni",
    "gn:population":0,
    "gn:timezone":"Europe/Sofia",
    "iso:country":"BG",
    "name:bul_x_preferred":[
        "\u0411\u044a\u0440\u0434\u0435\u043d\u0438"
    ],
    "name:bul_x_variant":[
        "Bardeni"
    ],
    "name:kaz_x_preferred":[
        "\u0411\u044b\u0440\u0434\u0435\u043d\u0438"
    ],
    "name:pol_x_preferred":[
        "Byrdeni"
    ],
    "name:ron_x_preferred":[
        "B\u0103rdeni"
    ],
    "name:rus_x_preferred":[
        "\u0411\u044b\u0440\u0434\u0435\u043d\u0438"
    ],
    "name:ukr_x_preferred":[
        "\u0411\u0438\u0440\u0434\u0435\u043d\u0438"
    ],
    "name:und_x_variant":[
        "Berdent\u016d",
        "B\u016drdenite",
        "B\u016drdeni"
    ],
    "wof:name":"Bardeni",
    "wof:placetype":"locality"
},
  "geometry": {"coordinates":[25.55,42.88333],"type":"Point"}
}