{
  "type": "Feature",
  "properties": {
    "gn:admin1_code":"40",
    "gn:admin2_code":"DOB20",
    "gn:admin3_code":"DOB20-11",
    "gn:asciiname":"Polkovnik Dyakovo",
    "gn:country_code":"BG",
    "gn:dem":173,
    "gn:feature_class":"P",
    "gn:feature_code":"PPL",
    "gn:name":"Polkovnik Dyakovo",
    "gn:population":0,
    "gn:timezone":"Europe/Sofia",
    "iso:country":"BG",
    "name:bul_x_preferred":[
        "\u041f\u043e\u043b\u043a\u043e\u0432\u043d\u0438\u043a-\u0414\u044f\u043a\u043e\u0432\u043e"
    ],
    "name:bul_x_variant":[
        "Polkovnik Dyakovo",
        "\u041f\u043e\u043b\u043a\u043e\u0432\u043d\u0438\u043a \u0414\u044f\u043a\u043e\u0432\u043e"
    ],
    "name:fas_x_preferred":[
        "\u067e\u0648\u0644\u06a9\u0648\u0648\u0646\u06cc\u06a9 \u062f\u06cc\u0627\u06a9\u0648\u0648\u0648"
    ],
    "name:kaz_x_preferred":[
        "\u041f\u043e\u043b\u043a\u043e\u0432\u043d\u0438\u043a-\u0414\u044f\u043a\u043e\u0432\u043e"
    ],
    "name:ron_x_preferred":[
        "Polkovnik Deakovo"
    ],
    "name:rus_x_preferred":[
        "\u041f\u043e\u043b\u043a\u043e\u0432\u043d\u0438\u043a-\u0414\u044f\u043a\u043e\u0432\u043e"
    ],
    "name:ukr_x_preferred":[
        "\u041f\u043e\u043b\u043a\u043e\u0432\u043d\u0438\u043a-\u0414\u044f\u043a\u043e\u0432\u043e"
    ],
    "name:und_x_variant":[
        "Azarplar",
        "Polkownik Djakovo",
        "Azaplar"
    ],
    "wof:name":"Polkovnik Dyakovo",
    "wof:placetype":"locality"
},
  "geometry": {"coordinates":[27.78845,43.84472],"type":"Point"}
}