{
  "type": "Feature",
  "properties": {
    "gn:admin1_code":"58",
    "gn:admin2_code":"SFO18",
    "gn:admin3_code":"SFO18-05",
    "gn:asciiname":"Malki Iskar",
    "gn:country_code":"BG",
    "gn:dem":443,
    "gn:feature_class":"P",
    "gn:feature_code":"PPL",
    "gn:name":"Malki Iskar",
    "gn:population":0,
    "gn:timezone":"Europe/Sofia",
    "iso:country":"BG",
    "name:bul_x_preferred":[
        "\u041c\u0430\u043b\u043a\u0438 \u0418\u0441\u043a\u044a\u0440"
    ],
    "name:bul_x_variant":[
        "Malki Iskar"
    ],
    "name:und_x_variant":[
        "Malki Isk\u016dr"
    ],
    "wof:name":"Malki Iskar",
    "wof:placetype":"locality"
},
  "geometry": {"coordinates":[24.08333,42.91667],"type":"Point"}
}