{
  "type": "Feature",
  "properties": {
    "gn:admin1_code":"65",
    "gn:admin2_code":"JAM25",
    "gn:admin3_code":"JAM25-41",
    "gn:asciiname":"Hanovo",
    "gn:country_code":"BG",
    "gn:dem":120,
    "gn:feature_class":"P",
    "gn:feature_code":"PPL",
    "gn:name":"Hanovo",
    "gn:population":0,
    "gn:timezone":"Europe/Sofia",
    "iso:country":"BG",
    "name:bul_x_preferred":[
        "\u0425\u0430\u043d\u043e\u0432\u043e"
    ],
    "name:bul_x_variant":[
        "Hanovo"
    ],
    "name:und_x_variant":[
        "Chanowo",
        "Karga K\u2019oy",
        "Khanevo",
        "Khanovo"
    ],
    "wof:name":"Hanovo",
    "wof:placetype":"locality"
},
  "geometry": {"coordinates":[26.51667,42.38333],"type":"Point"}
}