{
  "type": "Feature",
  "properties": {
    "gn:admin1_code":"46",
    "gn:admin2_code":"LOV34",
    "gn:asciiname":"Patreshko",
    "gn:cc2":"BG",
    "gn:country_code":"BG",
    "gn:dem":644,
    "gn:feature_class":"P",
    "gn:feature_code":"PPL",
    "gn:name":"Patreshko",
    "gn:population":0,
    "gn:timezone":"Europe/Sofia",
    "iso:country":"BG",
    "name:bul_x_preferred":[
        "\u041f\u0430\u0442\u0440\u0448\u043a\u043e"
    ],
    "name:bul_x_variant":[
        "\u041f\u0430\u0442\u0440\u0435\u0448\u043a\u043e"
    ],
    "name:fas_x_preferred":[
        "\u067e\u0627\u062a\u0631\u0634\u06a9\u0648"
    ],
    "name:kaz_x_preferred":[
        "\u041f\u0430\u0442\u0440\u0435\u0448\u043a\u043e"
    ],
    "name:pol_x_preferred":[
        "Patreszko"
    ],
    "name:ron_x_preferred":[
        "Patre\u0219ko"
    ],
    "name:rus_x_preferred":[
        "\u041f\u0430\u0442\u0440\u0435\u0448\u043a\u043e"
    ],
    "name:ukr_x_preferred":[
        "\u041f\u0430\u0442\u0440\u0435\u0448\u043a\u043e"
    ],
    "name:und_x_variant":[
        "Patreschko",
        "Patreshko"
    ],
    "wof:name":"Patreshko",
    "wof:placetype":"locality"
},
  "geometry": {"coordinates":[24.76667,42.91667],"type":"Point"}
}