{
  "type": "Feature",
  "properties": {
    "gn:admin1_code":"43",
    "gn:admin2_code":"HKV18",
    "gn:asciiname":"Razhenovo",
    "gn:country_code":"BG",
    "gn:dem":207,
    "gn:feature_class":"P",
    "gn:feature_code":"PPL",
    "gn:name":"Razhenovo",
    "gn:population":0,
    "gn:timezone":"Europe/Sofia",
    "iso:country":"BG",
    "name:bul_x_preferred":[
        "\u0420\u044a\u0436\u0435\u043d\u043e\u0432\u043e"
    ],
    "name:bul_x_variant":[
        "Razhenovo"
    ],
    "name:fas_x_preferred":[
        "\u0631\u0627\u0698\u0646\u0648\u0648\u0648"
    ],
    "name:kaz_x_preferred":[
        "\u0420\u044b\u0436\u0435\u043d\u043e\u0432\u043e"
    ],
    "name:pol_x_preferred":[
        "Ry\u017cenowo"
    ],
    "name:ron_x_preferred":[
        "R\u0103jenovo"
    ],
    "name:rus_x_preferred":[
        "\u0420\u044b\u0436\u0435\u043d\u043e\u0432\u043e"
    ],
    "name:ukr_x_preferred":[
        "\u0420\u0438\u0436\u0435\u043d\u043e\u0432\u043e"
    ],
    "name:und_x_variant":[
        "Belenlii",
        "R\u0103shenowo",
        "R\u016dzhenovo"
    ],
    "wof:name":"Razhenovo",
    "wof:placetype":"locality"
},
  "geometry": {"coordinates":[25.76667,41.68333],"type":"Point"}
}