{
  "type": "Feature",
  "properties": {
    "gn:admin1_code":"63",
    "gn:admin2_code":"VID25",
    "gn:admin3_code":"VID25-02",
    "gn:asciiname":"Kireevo",
    "gn:country_code":"BG",
    "gn:dem":381,
    "gn:feature_class":"P",
    "gn:feature_code":"PPL",
    "gn:name":"Kireevo",
    "gn:population":0,
    "gn:timezone":"Europe/Sofia",
    "iso:country":"BG",
    "name:bul_x_preferred":[
        "\u041a\u0438\u0440\u0435\u0435\u0432\u043e"
    ],
    "name:und_x_variant":[
        "Prerdelina",
        "Kireewo",
        "Kiryeevo",
        "Kiryaevo",
        "Kireevo"
    ],
    "wof:name":"Kireevo",
    "wof:placetype":"locality"
},
  "geometry": {"coordinates":[22.39469,43.79488],"type":"Point"}
}