{
  "type": "Feature",
  "properties": {
    "gn:admin1_code":"65",
    "gn:admin2_code":"JAM07",
    "gn:admin3_code":"JAM07-02",
    "gn:asciiname":"Boyanovo",
    "gn:cc2":"BG",
    "gn:country_code":"BG",
    "gn:dem":178,
    "gn:feature_class":"P",
    "gn:feature_code":"PPL",
    "gn:name":"Boyanovo",
    "gn:population":0,
    "gn:timezone":"Europe/Sofia",
    "iso:country":"BG",
    "name:bul_x_preferred":[
        "\u0411\u043e\u044f\u043d\u043e\u0432\u043e"
    ],
    "name:che_x_preferred":[
        "\u0411\u043e\u044f\u043d\u043e\u0432\u043e"
    ],
    "name:rus_x_preferred":[
        "\u0411\u043e\u044f\u043d\u043e\u0432\u043e"
    ],
    "name:und_x_variant":[
        "Moursatlii",
        "Bojanowo",
        "Mursatliy",
        "Mursatlii",
        "Mursatli",
        "Boyanovo"
    ],
    "wof:name":"Boyanovo",
    "wof:placetype":"locality"
},
  "geometry": {"coordinates":[26.63333,42.25],"type":"Point"}
}