{
  "type": "Feature",
  "properties": {
    "gn:admin1_code":"44",
    "gn:asciiname":"Balchovtsi",
    "gn:country_code":"BG",
    "gn:dem":408,
    "gn:feature_class":"P",
    "gn:feature_code":"PPL",
    "gn:name":"Balchovtsi",
    "gn:population":0,
    "gn:timezone":"Europe/Sofia",
    "iso:country":"BG",
    "name:bul_x_preferred":[
        "Balchovtsi"
    ],
    "name:bul_x_variant":[
        "\u0411\u0430\u043b\u0447\u043e\u0432\u0446\u0438"
    ],
    "wof:name":"Balchovtsi",
    "wof:placetype":"locality"
},
  "geometry": {"coordinates":[25.57343,41.40788],"type":"Point"}
}