{
  "type": "Feature",
  "properties": {
    "iso:country":"BG",
    "name:bul_x_variant":[
        "Starijat grad"
    ],
    "name:eng_x_preferred":[
        "\u0421\u0442\u0430\u0440\u0438\u044f\u0442 \u0433\u0440\u0430\u0434"
    ],
    "wof:name":"Old Town",
    "wof:placetype":"neighbourhood"
},
  "geometry": {"coordinates":[24.75300793050726,42.14931677289402],"type":"Point"}
}