{
  "type": "Feature",
  "properties": {
    "gn:admin1_code":"45",
    "gn:admin2_code":"KNL48",
    "gn:asciiname":"Gramade",
    "gn:country_code":"BG",
    "gn:dem":482,
    "gn:feature_class":"P",
    "gn:feature_code":"PPL",
    "gn:name":"Gramade",
    "gn:population":0,
    "gn:timezone":"Europe/Sofia",
    "iso:country":"BG",
    "name:bul_x_preferred":[
        "\u0413\u0440\u0430\u043c\u0430\u0434\u0435"
    ],
    "name:ceb_x_preferred":[
        "Gramade"
    ],
    "name:fra_x_preferred":[
        "Gramade"
    ],
    "name:ron_x_preferred":[
        "Gramade"
    ],
    "name:rus_x_preferred":[
        "\u0413\u0440\u0430\u043c\u0430\u0434\u0435"
    ],
    "name:swe_x_preferred":[
        "Gramade"
    ],
    "name:ukr_x_preferred":[
        "\u0413\u0440\u0430\u043c\u0430\u0434\u0435"
    ],
    "name:und_x_variant":[
        "Gramada"
    ],
    "wof:name":"Gramade",
    "wof:placetype":"locality"
},
  "geometry": {"coordinates":[23.03832,42.21747],"type":"Point"}
}