{
  "type": "Feature",
  "properties": {
    "gn:admin1_code":"45",
    "gn:asciiname":"Gelchina Mahala",
    "gn:country_code":"BG",
    "gn:dem":1229,
    "gn:feature_class":"P",
    "gn:feature_code":"PPL",
    "gn:name":"Gelchina Mahala",
    "gn:population":0,
    "gn:timezone":"Europe/Sofia",
    "iso:country":"BG",
    "name:bul_x_preferred":[
        "\u0413\u0435\u043b\u0447\u0438\u043d\u0430 \u043c\u0430\u0445\u0430\u043b\u0430"
    ],
    "name:bul_x_variant":[
        "Gelchina Mahala",
        "\u0413\u0435\u043b\u0447\u0438\u043d\u0430 \u041c\u0430\u0445\u0430\u043b\u0430"
    ],
    "name:und_x_variant":[
        "Gelchina",
        "Gheltchina Mahala",
        "Gelchina Makhala"
    ],
    "wof:name":"Gelchina Mahala",
    "wof:placetype":"locality"
},
  "geometry": {"coordinates":[22.47944,42.55722],"type":"Point"}
}