{
  "type": "Feature",
  "properties": {
    "gn:admin1_code":"53",
    "gn:admin2_code":"RSE27",
    "gn:admin3_code":"RSE27-13",
    "gn:asciiname":"Yastrebovo",
    "gn:country_code":"BG",
    "gn:dem":151,
    "gn:feature_class":"P",
    "gn:feature_code":"PPL",
    "gn:name":"Yastrebovo",
    "gn:population":0,
    "gn:timezone":"Europe/Sofia",
    "iso:country":"BG",
    "name:bul_x_preferred":[
        "\u042f\u0441\u0442\u0440\u0435\u0431\u043e\u0432\u043e"
    ],
    "name:und_x_variant":[
        "Enidzhekioy",
        "Yastrebetz",
        "Endzhek\u2019oy",
        "Yastrebets",
        "Gyuvemli Enidzhe",
        "Gyuvemli Endzhek\u2019oy",
        "Jastrebez",
        "Yastrebovo"
    ],
    "wof:name":"Yastrebovo",
    "wof:placetype":"locality"
},
  "geometry": {"coordinates":[26.12531,43.75835],"type":"Point"}
}