{
  "type": "Feature",
  "properties": {
    "gn:admin1_code":"45",
    "gn:admin2_code":"KNL29",
    "gn:asciiname":"Sazhdenik",
    "gn:country_code":"BG",
    "gn:dem":1190,
    "gn:feature_class":"P",
    "gn:feature_code":"PPL",
    "gn:name":"Sazhdenik",
    "gn:population":0,
    "gn:timezone":"Europe/Sofia",
    "iso:country":"BG",
    "name:bul_x_preferred":[
        "\u0421\u0430\u0436\u0434\u0435\u043d\u0438\u043a"
    ],
    "name:fas_x_preferred":[
        "\u0633\u0627\u0698\u062f\u0646\u06cc\u06a9"
    ],
    "name:kaz_x_preferred":[
        "\u0421\u0430\u0436\u0434\u0435\u043d\u0438\u043a"
    ],
    "name:ron_x_preferred":[
        "Sajdenik"
    ],
    "name:rus_x_preferred":[
        "\u0421\u0430\u0436\u0434\u0435\u043d\u0438\u043a"
    ],
    "name:ukr_x_preferred":[
        "\u0421\u0430\u0436\u0434\u0435\u043d\u0438\u043a"
    ],
    "name:und_x_variant":[
        "Sashdenik",
        "Sazhdenik"
    ],
    "wof:name":"Sazhdenik",
    "wof:placetype":"locality"
},
  "geometry": {"coordinates":[22.5785,42.13121],"type":"Point"}
}