{
  "type": "Feature",
  "properties": {
    "gn:admin1_code":"38",
    "gn:admin2_code":"BLG49",
    "gn:admin3_code":"BLG49-06",
    "gn:asciiname":"Igralishte",
    "gn:cc2":"BG",
    "gn:country_code":"BG",
    "gn:dem":880,
    "gn:feature_class":"P",
    "gn:feature_code":"PPL",
    "gn:name":"Igralishte",
    "gn:population":0,
    "gn:timezone":"Europe/Sofia",
    "iso:country":"BG",
    "name:bul_x_preferred":[
        "\u0418\u0433\u0440\u0430\u043b\u0438\u0449\u0435"
    ],
    "name:fas_x_preferred":[
        "\u0627\u06cc\u06af\u0631\u0627\u0644\u06cc\u0634\u062a\u0647"
    ],
    "name:kaz_x_preferred":[
        "\u0418\u0433\u0440\u0430\u043b\u0438\u0448\u0442\u0435"
    ],
    "name:mkd_x_preferred":[
        "\u0418\u0433\u0440\u0430\u043b\u0438\u0448\u0442\u0430"
    ],
    "name:ron_x_preferred":[
        "Igrali\u0219te"
    ],
    "name:rus_x_preferred":[
        "\u0418\u0433\u0440\u0430\u043b\u0438\u0448\u0442\u0435"
    ],
    "name:ukr_x_preferred":[
        "\u0406\u0433\u0440\u0430\u043b\u0438\u0448\u0442\u0435"
    ],
    "name:und_x_variant":[
        "Igralishta",
        "Igralischte",
        "Igralitsa",
        "Igralishte"
    ],
    "wof:name":"Igralishte",
    "wof:placetype":"locality"
},
  "geometry": {"coordinates":[23.13333,41.56667],"type":"Point"}
}