{
  "type": "Feature",
  "properties": {
    "gn:admin1_code":"44",
    "gn:asciiname":"Vishna",
    "gn:country_code":"BG",
    "gn:dem":623,
    "gn:feature_class":"P",
    "gn:feature_code":"PPL",
    "gn:name":"Vishna",
    "gn:population":0,
    "gn:timezone":"Europe/Sofia",
    "iso:country":"BG",
    "name:bul_x_preferred":[
        "\u0412\u0438\u0448\u043d\u0430"
    ],
    "name:ceb_x_preferred":[
        "Vishna"
    ],
    "name:fas_x_preferred":[
        "\u0648\u06cc\u0634\u0646\u0627"
    ],
    "name:kaz_x_preferred":[
        "\u0412\u0438\u0448\u043d\u0430"
    ],
    "name:ron_x_preferred":[
        "Vi\u0219na"
    ],
    "name:rus_x_preferred":[
        "\u0412\u0438\u0448\u043d\u0430"
    ],
    "name:swe_x_preferred":[
        "Visjna"
    ],
    "name:ukr_x_preferred":[
        "\u0412\u0438\u0448\u043d\u0430"
    ],
    "wof:name":"Vishna",
    "wof:placetype":"locality"
},
  "geometry": {"coordinates":[25.11667000000001,41.65],"type":"Point"}
}