{
  "type": "Feature",
  "properties": {
    "gn:admin1_code":"54",
    "gn:admin2_code":"SHU19",
    "gn:admin3_code":"SHU19-05",
    "gn:asciiname":"Kyulevcha",
    "gn:cc2":"BG",
    "gn:country_code":"BG",
    "gn:dem":199,
    "gn:feature_class":"P",
    "gn:feature_code":"PPL",
    "gn:name":"Kyulevcha",
    "gn:population":0,
    "gn:timezone":"Europe/Sofia",
    "iso:country":"BG",
    "name:bul_x_preferred":[
        "\u041a\u044e\u043b\u0435\u0432\u0447\u0430"
    ],
    "name:und_x_variant":[
        "Kulefche",
        "Kiulev\u010da",
        "Kjulef\u010da",
        "Kyulefcha",
        "Kjulewtscha",
        "Kyulevcha"
    ],
    "wof:name":"Kyulevcha",
    "wof:placetype":"locality"
},
  "geometry": {"coordinates":[27.11667000000001,43.25],"type":"Point"}
}