{
  "type": "Feature",
  "properties": {
    "iso:country":"BG",
    "name:bul_x_preferred":[
        "\u0418\u0441\u043a\u0440\u0435\u0446"
    ],
    "name:ceb_x_preferred":[
        "Iskrec"
    ],
    "name:eng_x_preferred":[
        "Iskrets"
    ],
    "name:eng_x_variant":[
        "Iskrec",
        "Isskrez"
    ],
    "name:fas_x_preferred":[
        "\u0627\u06cc\u0633\u06a9\u0631\u062a\u0633"
    ],
    "name:fra_x_preferred":[
        "Iskrets"
    ],
    "name:hye_x_preferred":[
        "\u053b\u057d\u056f\u0580\u0565\u0581"
    ],
    "name:jpn_x_preferred":[
        "\u30a4\u30b9\u30af\u30ec\u30c4"
    ],
    "name:kaz_x_preferred":[
        "\u0418\u0441\u043a\u0440\u0435\u0446"
    ],
    "name:pol_x_preferred":[
        "Iskrec"
    ],
    "name:ron_x_preferred":[
        "Iskre\u021b"
    ],
    "name:rus_x_preferred":[
        "\u0418\u0441\u043a\u0440\u0435\u0446"
    ],
    "name:swe_x_preferred":[
        "Iskrets"
    ],
    "name:ukr_x_preferred":[
        "\u0406\u0441\u043a\u0440\u0435\u0446\u044c"
    ],
    "name:unk_x_variant":[
        "Isskrez"
    ],
    "qs:a0":"\u0411\u044a\u043b\u0433\u0430\u0440\u0438\u044f",
    "qs:a1":"*\u0421\u043e\u0444\u0438\u044f",
    "qs:a1_alt":"Sofia",
    "qs:a1r":"0",
    "qs:adm0":"\u0411\u044a\u043b\u0433\u0430\u0440\u0438\u044f",
    "qs:la_lc":"*",
    "qs:level":"locality",
    "qs:loc":"\u0418\u0441\u043a\u0440\u0435\u0446",
    "qs:loc_alt":"Iskrets",
    "qs:pop":0,
    "qs:type":"buffered point",
    "wd:wordcount":144,
    "wof:name":"\u0418\u0441\u043a\u0440\u0435\u0446",
    "wof:placetype":"locality"
},
  "geometry": {"coordinates":[23.212884,42.985554],"type":"Point"}
}