{
  "type": "Feature",
  "properties": {
    "gn:admin1_code":"44",
    "gn:asciiname":"Redova",
    "gn:country_code":"BG",
    "gn:dem":383,
    "gn:feature_class":"P",
    "gn:feature_code":"PPL",
    "gn:name":"Redova",
    "gn:population":0,
    "gn:timezone":"Europe/Sofia",
    "iso:country":"BG",
    "name:bul_x_preferred":[
        "\u0420\u0435\u0434\u043e\u0432\u0430"
    ],
    "wof:name":"Redova",
    "wof:placetype":"locality"
},
  "geometry": {"coordinates":[25.56667,41.43333],"type":"Point"}
}