{
  "type": "Feature",
  "properties": {
    "gn:admin1_code":"61",
    "gn:admin2_code":"VAR01",
    "gn:admin3_code":"VAR01-11",
    "gn:asciiname":"Sadovo",
    "gn:cc2":"BG",
    "gn:country_code":"BG",
    "gn:dem":91,
    "gn:feature_class":"P",
    "gn:feature_code":"PPL",
    "gn:name":"Sadovo",
    "gn:population":0,
    "gn:timezone":"Europe/Sofia",
    "iso:country":"BG",
    "name:bul_x_preferred":[
        "\u0421\u0430\u0434\u043e\u0432\u043e"
    ],
    "name:und_x_variant":[
        "Sadowo",
        "Suludzha-Al\u016d",
        "Suludzhal\u016d",
        "Suludzha Ala",
        "Sadovo"
    ],
    "wof:name":"Sadovo",
    "wof:placetype":"locality"
},
  "geometry": {"coordinates":[27.71667,43.06667],"type":"Point"}
}