{
  "type": "Feature",
  "properties": {
    "gn:admin1_code":"61",
    "gn:admin2_code":"VAR01",
    "gn:admin3_code":"VAR01-11",
    "gn:asciiname":"Sadovo",
    "gn:cc2":"BG",
    "gn:country_code":"BG",
    "gn:dem":91,
    "gn:feature_class":"P",
    "gn:feature_code":"PPL",
    "gn:name":"Sadovo",
    "gn:population":0,
    "gn:timezone":"Europe/Sofia",
    "iso:country":"BG",
    "name:azb_x_preferred":[
        "\u0633\u0627\u062f\u0648\u0648"
    ],
    "name:bul_x_preferred":[
        "\u0421\u0430\u0434\u043e\u0432\u043e"
    ],
    "name:ceb_x_preferred":[
        "Sadovo"
    ],
    "name:ces_x_preferred":[
        "Sadovo"
    ],
    "name:ckb_x_preferred":[
        "\u0633\u0627\u062f\u06c6\u06a4\u06c6"
    ],
    "name:deu_x_preferred":[
        "Sadowo"
    ],
    "name:fas_x_preferred":[
        "\u0633\u0627\u062f\u0648\u0641\u0648"
    ],
    "name:kaz_x_preferred":[
        "\u0421\u0430\u0434\u043e\u0432\u043e"
    ],
    "name:pol_x_preferred":[
        "Sadowo"
    ],
    "name:por_x_preferred":[
        "Sadovo"
    ],
    "name:ron_x_preferred":[
        "Sadovo"
    ],
    "name:rus_x_preferred":[
        "\u0421\u0430\u0434\u043e\u0432\u043e"
    ],
    "name:spa_x_preferred":[
        "Sadovo"
    ],
    "name:srp_x_preferred":[
        "\u0421\u0430\u0434\u043e\u0432\u043e"
    ],
    "name:tur_x_preferred":[
        "Sadovo"
    ],
    "name:ukr_x_preferred":[
        "\u0421\u0430\u0434\u043e\u0432\u043e"
    ],
    "name:und_x_variant":[
        "Suludzha-Al\u016d",
        "Suludzhal\u016d",
        "Suludzha Ala"
    ],
    "name:vie_x_preferred":[
        "Sadovo"
    ],
    "name:war_x_preferred":[
        "Sadovo"
    ],
    "name:zho_x_preferred":[
        "\u85a9\u591a\u6c83"
    ],
    "wof:name":"Sadovo",
    "wof:placetype":"locality"
},
  "geometry": {"coordinates":[27.71667,43.06667],"type":"Point"}
}