{
  "type": "Feature",
  "properties": {
    "gn:admin1_code":"41",
    "gn:admin2_code":"GAB35",
    "gn:asciiname":"Golemi Stanchovtsi",
    "gn:cc2":"BG",
    "gn:country_code":"BG",
    "gn:dem":501,
    "gn:feature_class":"P",
    "gn:feature_code":"PPL",
    "gn:name":"Golemi Stanchovtsi",
    "gn:population":0,
    "gn:timezone":"Europe/Sofia",
    "iso:country":"BG",
    "name:ara_x_preferred":[
        "\u062c\u0648\u0644\u064a\u0645\u064a \u0633\u062a\u0627\u0646\u062a\u0634\u0648\u0641\u062a\u0633\u064a"
    ],
    "name:bul_x_preferred":[
        "\u0413\u043e\u043b\u0435\u043c\u0438 \u0441\u0442\u0430\u043d\u0447\u043e\u0432\u0446\u0438"
    ],
    "name:bul_x_variant":[
        "\u0413\u043e\u043b\u0435\u043c\u0438 \u0421\u0442\u0430\u043d\u0447\u043e\u0432\u0446\u0438"
    ],
    "name:pol_x_preferred":[
        "Golemi Stanczowci"
    ],
    "name:ukr_x_preferred":[
        "\u0413\u043e\u043b\u0435\u043c\u0456 \u0421\u0442\u0430\u043d\u0447\u043e\u0432\u0446\u0456"
    ],
    "name:und_x_variant":[
        "Stanchevts\u016d Bol\u016dsh",
        "Golemi Stanchovtsi"
    ],
    "wof:name":"Golemi Stanchovtsi",
    "wof:placetype":"locality"
},
  "geometry": {"coordinates":[25.53333,42.91667],"type":"Point"}
}