{
  "type": "Feature",
  "properties": {
    "gn:admin1_code":"63",
    "gn:admin2_code":"VID09",
    "gn:asciiname":"Vartop",
    "gn:country_code":"BG",
    "gn:dem":209,
    "gn:feature_class":"P",
    "gn:feature_code":"PPL",
    "gn:name":"Vartop",
    "gn:population":0,
    "gn:timezone":"Europe/Sofia",
    "iso:country":"BG",
    "name:bul_x_preferred":[
        "\u0412\u044a\u0440\u0442\u043e\u043f"
    ],
    "name:bul_x_variant":[
        "Vartop"
    ],
    "name:und_x_variant":[
        "W\u0103rtop",
        "V\u016drtop"
    ],
    "wof:name":"Vartop",
    "wof:placetype":"locality"
},
  "geometry": {"coordinates":[22.79011,43.80245],"type":"Point"}
}