{
  "type": "Feature",
  "properties": {
    "gn:admin1_code":"40",
    "gn:admin2_code":"DOB15",
    "gn:asciiname":"Popgrigorovo",
    "gn:country_code":"BG",
    "gn:dem":231,
    "gn:feature_class":"P",
    "gn:feature_code":"PPL",
    "gn:name":"Popgrigorovo",
    "gn:population":0,
    "gn:timezone":"Europe/Sofia",
    "iso:country":"BG",
    "name:bul_x_preferred":[
        "\u041f\u043e\u043f\u0433\u0440\u0438\u0433\u043e\u0440\u043e\u0432\u043e"
    ],
    "name:fas_x_preferred":[
        "\u067e\u0648\u067e\u06af\u0631\u06cc\u06af\u0648\u0631\u0648\u0648\u0648"
    ],
    "name:kaz_x_preferred":[
        "\u041f\u043e\u043f\u0433\u0440\u0438\u0433\u043e\u0440\u043e\u0432\u043e"
    ],
    "name:ron_x_preferred":[
        "Popgrigorovo"
    ],
    "name:rus_x_preferred":[
        "\u041f\u043e\u043f\u0433\u0440\u0438\u0433\u043e\u0440\u043e\u0432\u043e"
    ],
    "name:ukr_x_preferred":[
        "\u041f\u043e\u043f\u0433\u0440\u0438\u0433\u043e\u0440\u043e\u0432\u043e"
    ],
    "name:und_x_variant":[
        "Veli Fak\u016d",
        "Popgrigorowo",
        "Velifaca"
    ],
    "wof:name":"Popgrigorovo",
    "wof:placetype":"locality"
},
  "geometry": {"coordinates":[27.93083,43.52219],"type":"Point"}
}