{
  "type": "Feature",
  "properties": {
    "gn:admin1_code":"41",
    "gn:admin2_code":"GAB35",
    "gn:asciiname":"Krastec",
    "gn:country_code":"BG",
    "gn:dem":992,
    "gn:feature_class":"P",
    "gn:feature_code":"PPL",
    "gn:name":"Krastec",
    "gn:population":0,
    "gn:timezone":"Europe/Sofia",
    "iso:country":"BG",
    "name:ara_x_preferred":[
        "\u0643\u0631\u0648\u0633\u062a\u064a\u062a\u0633"
    ],
    "name:bul_x_preferred":[
        "\u041a\u0440\u044a\u0441\u0442\u0435\u0446"
    ],
    "name:bul_x_variant":[
        "Krastec"
    ],
    "name:fas_x_preferred":[
        "\u06a9\u0631\u0648\u0633\u062a\u062a\u0633"
    ],
    "name:kaz_x_preferred":[
        "\u041a\u0440\u044b\u0441\u0442\u0435\u0446"
    ],
    "name:pol_x_preferred":[
        "Krystec"
    ],
    "name:ron_x_preferred":[
        "Kr\u0103ste\u021b"
    ],
    "name:rus_x_preferred":[
        "\u041a\u0440\u044b\u0441\u0442\u0435\u0446"
    ],
    "name:ukr_x_preferred":[
        "\u041a\u0440\u0438\u0441\u0442\u0435\u0446\u044c"
    ],
    "name:und_x_variant":[
        "Kr\u0103stec",
        "Kr\u0103stez",
        "Krastetz",
        "Krestets",
        "Kr\u016dstets"
    ],
    "wof:name":"Krastec",
    "wof:placetype":"locality"
},
  "geometry": {"coordinates":[25.56667,42.76667],"type":"Point"}
}