{
  "type": "Feature",
  "properties": {
    "gn:admin1_code":"41",
    "gn:admin2_code":"GAB35",
    "gn:asciiname":"Krastec",
    "gn:country_code":"BG",
    "gn:dem":992,
    "gn:feature_class":"P",
    "gn:feature_code":"PPL",
    "gn:name":"Krastec",
    "gn:population":0,
    "gn:timezone":"Europe/Sofia",
    "iso:country":"BG",
    "name:bul_x_preferred":[
        "\u041a\u0440\u044a\u0441\u0442\u0435\u0446"
    ],
    "name:bul_x_variant":[
        "Krastec"
    ],
    "name:und_x_variant":[
        "Kr\u0103stec",
        "Kr\u0103stez",
        "Krastetz",
        "Krestets",
        "Kr\u016dstets"
    ],
    "wof:name":"Krastec",
    "wof:placetype":"locality"
},
  "geometry": {"coordinates":[25.56667,42.76667],"type":"Point"}
}