{
  "type": "Feature",
  "properties": {
    "gn:admin1_code":"54",
    "gn:admin2_code":"SHU22",
    "gn:admin3_code":"SHU22-06",
    "gn:asciiname":"Izbul",
    "gn:cc2":"BG",
    "gn:country_code":"BG",
    "gn:dem":320,
    "gn:feature_class":"P",
    "gn:feature_code":"PPL",
    "gn:name":"Izbul",
    "gn:population":0,
    "gn:timezone":"Europe/Sofia",
    "iso:country":"BG",
    "name:bul_x_preferred":[
        "\u0418\u0437\u0431\u0443\u043b"
    ],
    "name:und_x_variant":[
        "Teke Kozludzha",
        "Kozludzha-Teke",
        "Isbul",
        "Izbul"
    ],
    "wof:name":"Izbul",
    "wof:placetype":"locality"
},
  "geometry": {"coordinates":[27.11667000000001,43.43333],"type":"Point"}
}