{
  "type": "Feature",
  "properties": {
    "iso:country":"BG",
    "name:bul_x_preferred":[
        "\u0418\u043b\u0438\u043d\u0434\u0435\u043d"
    ],
    "name:eng_x_preferred":[
        "Ilinden"
    ],
    "name:eng_x_variant":[
        "FK Ilinden"
    ],
    "name:fra_x_preferred":[
        "FK Ilinden"
    ],
    "name:heb_x_preferred":[
        "\u05d0\u05d9\u05dc\u05d9\u05e0\u05d3\u05df"
    ],
    "name:hun_x_preferred":[
        "Ilinden"
    ],
    "name:mkd_x_preferred":[
        "\u0424\u041a \u0418\u043b\u0438\u043d\u0434\u0435\u043d"
    ],
    "name:nld_x_preferred":[
        "FK Ilinden"
    ],
    "name:spa_x_preferred":[
        "FK Ilinden"
    ],
    "name:und_x_variant":[
        "Nenovi Koshari"
    ],
    "qs:gn_adm0_cc":"BG",
    "qs:gn_fcode":"PPL",
    "qs:gn_local":727011,
    "qs:gn_nam_loc":"Sofiya, Sofia, Sofiya-Grad, BG",
    "qs:gn_namadm1":"58",
    "qs:gn_name":"Ilinden",
    "qs:local_max":4184,
    "qs:local_sum":18613,
    "qs:localhoods":26,
    "qs:name":"Ilinden",
    "qs:name_adm0":"Bulgaria",
    "qs:name_adm1":"Sofiya-Grad",
    "qs:name_adm2":"Sofiya",
    "qs:name_local":"Sofia",
    "qs:photo_max":186,
    "qs:photo_sum":359,
    "qs:placetype":"Suburb",
    "qs:quad_count":21,
    "qs:woe_adm0":23424771,
    "qs:woe_adm1":20069794,
    "qs:woe_adm2":55873710,
    "qs:woe_lau":0,
    "qs:woe_local":839722,
    "qs:woe_ver":"7.10.0",
    "wd:wordcount":151,
    "wof:lang":[
        "eng"
    ],
    "wof:name":"Ilinden",
    "wof:placetype":"neighbourhood"
},
  "geometry": {"coordinates":[23.289072,42.711176],"type":"Point"}
}