{
  "type": "Feature",
  "properties": {
    "gn:admin1_code":"58",
    "gn:admin2_code":"SFO16",
    "gn:asciiname":"Kambelevtsi",
    "gn:country_code":"BG",
    "gn:dem":606,
    "gn:feature_class":"P",
    "gn:feature_code":"PPL",
    "gn:name":"Kambelevtsi",
    "gn:population":0,
    "gn:timezone":"Europe/Sofia",
    "iso:country":"BG",
    "name:bul_x_preferred":[
        "\u041a\u0430\u043c\u0431\u0435\u043b\u0435\u0432\u0446\u0438"
    ],
    "name:und_x_variant":[
        "Kambelewzi",
        "Kambelevtsi"
    ],
    "wof:name":"Kambelevtsi",
    "wof:placetype":"locality"
},
  "geometry": {"coordinates":[22.8837,42.89162],"type":"Point"}
}