{
  "type": "Feature",
  "properties": {
    "gn:admin1_code":"38",
    "gn:asciiname":"Kraykovtsi",
    "gn:country_code":"BG",
    "gn:dem":918,
    "gn:feature_class":"P",
    "gn:feature_code":"PPL",
    "gn:name":"Kraykovtsi",
    "gn:population":0,
    "gn:timezone":"Europe/Sofia",
    "iso:country":"BG",
    "name:bul_x_preferred":[
        "Kraykovtsi"
    ],
    "name:bul_x_variant":[
        "\u041a\u0440\u0430\u0439\u043a\u043e\u0432\u0446\u0438"
    ],
    "wof:name":"Kraykovtsi",
    "wof:placetype":"locality"
},
  "geometry": {"coordinates":[22.88921,41.95743],"type":"Point"}
}