{
  "type": "Feature",
  "properties": {
    "gn:admin1_code":"43",
    "gn:admin2_code":"HKV33",
    "gn:asciiname":"Bogomil",
    "gn:cc2":"BG",
    "gn:country_code":"BG",
    "gn:dem":292,
    "gn:feature_class":"P",
    "gn:feature_code":"PPL",
    "gn:name":"Bogomil",
    "gn:population":0,
    "gn:timezone":"Europe/Sofia",
    "iso:country":"BG",
    "name:bul_x_preferred":[
        "\u0411\u043e\u0433\u043e\u043c\u0438\u043b"
    ],
    "name:und_x_variant":[
        "Teke",
        "Bogomil"
    ],
    "wof:name":"Bogomil",
    "wof:placetype":"locality"
},
  "geometry": {"coordinates":[26.01667,41.98333],"type":"Point"}
}