{
  "type": "Feature",
  "properties": {
    "gn:admin1_code":"40",
    "gn:admin2_code":"DOB15",
    "gn:admin3_code":"DOB15-55",
    "gn:asciiname":"Smolnitsa",
    "gn:country_code":"BG",
    "gn:dem":240,
    "gn:feature_class":"P",
    "gn:feature_code":"PPL",
    "gn:name":"Smolnitsa",
    "gn:population":0,
    "gn:timezone":"Europe/Sofia",
    "iso:country":"BG",
    "name:bul_x_preferred":[
        "\u0421\u043c\u043e\u043b\u043d\u0438\u0446\u0430"
    ],
    "name:und_x_variant":[
        "Ceamurlia de Mijloc",
        "Smolnica",
        "Sredna Chamurlu",
        "Sredno Chamurlii",
        "Smolnitsa",
        "Golyamo Chamurlii",
        "Golyama Smolnitsa",
        "Golyama Smolnica",
        "Golyama Chamurlu",
        "Golemo Tschamurlii",
        "Ceamurlia Mare"
    ],
    "wof:name":"Smolnitsa",
    "wof:placetype":"locality"
},
  "geometry": {"coordinates":[27.70842,43.63005],"type":"Point"}
}