{
  "type": "Feature",
  "properties": {
    "gn:admin1_code":"49",
    "gn:admin2_code":"PER08",
    "gn:asciiname":"Gigintsi",
    "gn:country_code":"BG",
    "gn:dem":777,
    "gn:feature_class":"P",
    "gn:feature_code":"PPL",
    "gn:name":"Gigintsi",
    "gn:population":0,
    "gn:timezone":"Europe/Sofia",
    "iso:country":"BG",
    "name:bul_x_preferred":[
        "\u0413\u0438\u0433\u0438\u043d\u0446\u0438"
    ],
    "name:und_x_variant":[
        "Giginzi",
        "Gigintsi"
    ],
    "wof:name":"Gigintsi",
    "wof:placetype":"locality"
},
  "geometry": {"coordinates":[22.81411,42.66224],"type":"Point"}
}