{
  "type": "Feature",
  "properties": {
    "gn:admin1_code":"41",
    "gn:admin2_code":"GAB29",
    "gn:asciiname":"Shopite",
    "gn:country_code":"BG",
    "gn:dem":582,
    "gn:feature_class":"P",
    "gn:feature_code":"PPL",
    "gn:name":"Shopite",
    "gn:population":0,
    "gn:timezone":"Europe/Sofia",
    "iso:country":"BG",
    "name:ara_x_preferred":[
        "\u0634\u0648\u0633\u064a\u062a"
    ],
    "name:bul_x_preferred":[
        "\u0428\u043e\u043f\u0438\u0442\u0435"
    ],
    "name:fas_x_preferred":[
        "\u0634\u0648\u067e\u06cc\u062a\u0647"
    ],
    "name:kaz_x_preferred":[
        "\u0428\u043e\u043f\u0438\u0442\u0435"
    ],
    "name:pol_x_preferred":[
        "Szopite"
    ],
    "name:ron_x_preferred":[
        "\u0218opite"
    ],
    "name:rus_x_preferred":[
        "\u0428\u043e\u043f\u0438\u0442\u0435"
    ],
    "name:ukr_x_preferred":[
        "\u0428\u043e\u043f\u0438\u0442\u0435"
    ],
    "wof:name":"Shopite",
    "wof:placetype":"locality"
},
  "geometry": {"coordinates":[24.98333,42.85],"type":"Point"}
}