{
  "type": "Feature",
  "properties": {
    "gn:admin1_code":"62",
    "gn:admin2_code":"VTR04",
    "gn:asciiname":"Pozhernik",
    "gn:cc2":"BG",
    "gn:country_code":"BG",
    "gn:dem":319,
    "gn:feature_class":"P",
    "gn:feature_code":"PPL",
    "gn:name":"Pozhernik",
    "gn:population":0,
    "gn:timezone":"Europe/Sofia",
    "iso:country":"BG",
    "name:bul_x_preferred":[
        "\u041f\u043e\u0436\u0435\u0440\u043d\u0438\u043a"
    ],
    "name:und_x_variant":[
        "Pozhernek",
        "Pozhernik"
    ],
    "wof:name":"Pozhernik",
    "wof:placetype":"locality"
},
  "geometry": {"coordinates":[25.63333,42.93333],"type":"Point"}
}