{
  "type": "Feature",
  "properties": {
    "gn:admin1_code":"52",
    "gn:admin2_code":"RAZ16",
    "gn:admin3_code":"RAZ16-09",
    "gn:asciiname":"Savin",
    "gn:country_code":"BG",
    "gn:dem":200,
    "gn:feature_class":"P",
    "gn:feature_code":"PPL",
    "gn:name":"Savin",
    "gn:population":0,
    "gn:timezone":"Europe/Sofia",
    "iso:country":"BG",
    "name:bul_x_preferred":[
        "\u0421\u0430\u0432\u0438\u043d"
    ],
    "name:ceb_x_preferred":[
        "Savin"
    ],
    "name:deu_x_preferred":[
        "Savin"
    ],
    "name:fra_x_preferred":[
        "Savin"
    ],
    "name:ron_x_preferred":[
        "Savin"
    ],
    "name:slv_x_preferred":[
        "Savin"
    ],
    "name:swe_x_preferred":[
        "Savin"
    ],
    "name:und_x_variant":[
        "Dzhaferovo",
        "Sawin",
        "Dzheferovo",
        "Savin"
    ],
    "wof:name":"Savin",
    "wof:placetype":"locality"
},
  "geometry": {"coordinates":[26.54761,43.80986],"type":"Point"}
}