{
  "type": "Feature",
  "properties": {
    "gn:admin1_code":"47",
    "gn:admin2_code":"MON02",
    "gn:admin3_code":"MON02-04",
    "gn:asciiname":"Borovtsi",
    "gn:cc2":"BG",
    "gn:country_code":"BG",
    "gn:dem":220,
    "gn:feature_class":"P",
    "gn:feature_code":"PPL",
    "gn:name":"Borovtsi",
    "gn:population":0,
    "gn:timezone":"Europe/Sofia",
    "iso:country":"BG",
    "name:bul_x_preferred":[
        "\u0411\u043e\u0440\u043e\u0432\u0446\u0438"
    ],
    "name:ceb_x_preferred":[
        "Borovci"
    ],
    "name:kaz_x_preferred":[
        "\u0411\u043e\u0440\u043e\u0432\u0446\u0438"
    ],
    "name:msa_x_preferred":[
        "Borovtsi"
    ],
    "name:ron_x_preferred":[
        "Borov\u021bi"
    ],
    "name:rus_x_preferred":[
        "\u0411\u043e\u0440\u043e\u0432\u0446\u0438"
    ],
    "name:swe_x_preferred":[
        "Borovtsi"
    ],
    "name:ukr_x_preferred":[
        "\u0411\u043e\u0440\u043e\u0432\u0446\u0456"
    ],
    "name:und_x_variant":[
        "Borowzi",
        "Borovtsi"
    ],
    "wof:name":"Borovtsi",
    "wof:placetype":"locality"
},
  "geometry": {"coordinates":[23.17722,43.32333],"type":"Point"}
}