{
  "type": "Feature",
  "properties": {
    "iso:country":"BG",
    "name:bul_x_preferred":[
        "\u0421\u0435\u0440\u0434\u0438\u043a\u0430"
    ],
    "name:bul_x_variant":[
        "Malaschewzi",
        "\u041c\u0430\u043b\u0430\u0448\u0435\u0432\u0446\u0438"
    ],
    "name:ceb_x_preferred":[
        "Rayon Serdika"
    ],
    "name:eng_x_preferred":[
        "Malashevtsi"
    ],
    "name:eng_x_variant":[
        "Malaschewzi"
    ],
    "name:pol_x_preferred":[
        "Rejon Serdika"
    ],
    "name:swe_x_preferred":[
        "Rajon Serdika"
    ],
    "name:unk_x_variant":[
        "Malaschewzi",
        "Malashevtsi"
    ],
    "qs:gn_adm0_cc":"BG",
    "qs:gn_fcode":"PPLX",
    "qs:gn_local":727011,
    "qs:gn_nam_loc":"Sofiya, Sofia, Sofiya-Grad, BG",
    "qs:gn_namadm1":"42",
    "qs:gn_name":"Malashevtsi",
    "qs:local_max":4184,
    "qs:local_sum":18613,
    "qs:localhoods":26,
    "qs:name":"Malashevtsi",
    "qs:name_adm0":"Bulgaria",
    "qs:name_adm1":"Sofiya-Grad",
    "qs:name_adm2":"Sofiya",
    "qs:name_local":"Sofia",
    "qs:photo_max":2,
    "qs:photo_sum":4,
    "qs:placetype":"Suburb",
    "qs:quad_count":2,
    "qs:woe_adm0":23424771,
    "qs:woe_adm1":20069794,
    "qs:woe_adm2":55873710,
    "qs:woe_lau":0,
    "qs:woe_local":839722,
    "qs:woe_ver":"7.10.0",
    "wd:wordcount":139,
    "wof:lang":[
        "eng"
    ],
    "wof:name":"Malashevtsi",
    "wof:placetype":"neighbourhood"
},
  "geometry": {"coordinates":[23.35041,42.707081],"type":"Point"}
}