{
  "type": "Feature",
  "properties": {
    "gn:admin1_code":"44",
    "gn:admin2_code":"KRZ08",
    "gn:admin3_code":"KRZ08-15",
    "gn:asciiname":"Mrezhichko",
    "gn:country_code":"BG",
    "gn:dem":470,
    "gn:feature_class":"P",
    "gn:feature_code":"PPL",
    "gn:name":"Mrezhichko",
    "gn:population":0,
    "gn:timezone":"Europe/Sofia",
    "iso:country":"BG",
    "name:bul_x_preferred":[
        "\u041c\u0440\u0435\u0436\u0438\u0447\u043a\u043e"
    ],
    "name:fra_x_preferred":[
        "Mrejitchko"
    ],
    "name:ron_x_preferred":[
        "Mrejiciko"
    ],
    "name:rus_x_preferred":[
        "\u041c\u0440\u0435\u0436\u0438\u0447\u043a\u043e"
    ],
    "name:ukr_x_preferred":[
        "\u041c\u0440\u0435\u0436\u0438\u0447\u043a\u043e"
    ],
    "name:und_x_variant":[
        "Tyule",
        "Mreshitschko",
        "Mrezhichko"
    ],
    "wof:name":"Mrezhichko",
    "wof:placetype":"locality"
},
  "geometry": {"coordinates":[25.26872,41.4622],"type":"Point"}
}