{
  "type": "Feature",
  "properties": {
    "gn:admin1_code":"38",
    "gn:asciiname":"Malinovska Mahala",
    "gn:country_code":"BG",
    "gn:dem":837,
    "gn:feature_class":"P",
    "gn:feature_code":"PPL",
    "gn:name":"Malinovska Mahala",
    "gn:population":0,
    "gn:timezone":"Europe/Sofia",
    "iso:country":"BG",
    "name:bul_x_preferred":[
        "Malinovska Mahala"
    ],
    "name:bul_x_variant":[
        "\u041c\u0430\u043b\u0438\u043d\u043e\u0432\u0441\u043a\u0430 \u041c\u0430\u0445\u0430\u043b\u0430"
    ],
    "name:und_x_variant":[
        "Malinovska Makhala"
    ],
    "wof:name":"Malinovska Mahala",
    "wof:placetype":"locality"
},
  "geometry": {"coordinates":[22.96468,41.89125],"type":"Point"}
}