{
  "type": "Feature",
  "properties": {
    "gn:admin1_code":"45",
    "gn:admin2_code":"KNL31",
    "gn:asciiname":"Dolna Koznitsa",
    "gn:country_code":"BG",
    "gn:dem":542,
    "gn:feature_class":"P",
    "gn:feature_code":"PPL",
    "gn:name":"Dolna Koznitsa",
    "gn:population":0,
    "gn:timezone":"Europe/Sofia",
    "iso:country":"BG",
    "name:bul_x_preferred":[
        "\u0414\u043e\u043b\u043d\u0430 \u041a\u043e\u0437\u043d\u0438\u0446\u0430"
    ],
    "name:fas_x_preferred":[
        "\u062f\u0648\u0644\u0646\u0627 \u06a9\u0648\u0632\u0646\u06cc\u062a\u0633\u0627"
    ],
    "name:kaz_x_preferred":[
        "\u0414\u043e\u043b\u043d\u0430-\u041a\u043e\u0437\u043d\u0438\u0446\u0430"
    ],
    "name:ron_x_preferred":[
        "Dolna Kozni\u021ba"
    ],
    "name:rus_x_preferred":[
        "\u0414\u043e\u043b\u043d\u0430-\u041a\u043e\u0437\u043d\u0438\u0446\u0430"
    ],
    "name:ukr_x_preferred":[
        "\u0414\u043e\u043b\u0456\u0448\u043d\u044f \u041a\u043e\u0437\u043d\u0438\u0446\u044f"
    ],
    "name:und_x_variant":[
        "Dolna-Kosniza",
        "Dolna Koznitsa"
    ],
    "wof:name":"Dolna Koznitsa",
    "wof:placetype":"locality"
},
  "geometry": {"coordinates":[22.90986,42.2668],"type":"Point"}
}