{
  "type": "Feature",
  "properties": {
    "gn:admin1_code":"41",
    "gn:admin2_code":"GAB35",
    "gn:asciiname":"Ralevtsi",
    "gn:cc2":"BG",
    "gn:country_code":"BG",
    "gn:dem":548,
    "gn:feature_class":"P",
    "gn:feature_code":"PPL",
    "gn:name":"Ralevtsi",
    "gn:population":0,
    "gn:timezone":"Europe/Sofia",
    "iso:country":"BG",
    "name:ara_x_preferred":[
        "\u0631\u0627\u0641\u0631\u064a\u062a\u0633\u064a"
    ],
    "name:bul_x_preferred":[
        "\u0420\u0430\u043b\u0435\u0432\u0446\u0438"
    ],
    "name:fas_x_preferred":[
        "\u0631\u0627\u0644\u0648\u062a\u0633\u06cc"
    ],
    "name:kaz_x_preferred":[
        "\u0420\u0430\u043b\u0435\u0432\u0446\u0438"
    ],
    "name:pol_x_preferred":[
        "Ralewci"
    ],
    "name:ron_x_preferred":[
        "Ralev\u021bi"
    ],
    "name:rus_x_preferred":[
        "\u0420\u0430\u043b\u0435\u0432\u0446\u0438"
    ],
    "name:ukr_x_preferred":[
        "\u0420\u0430\u043b\u0435\u0432\u0446\u0456"
    ],
    "name:und_x_variant":[
        "Ralevts\u016d",
        "Ralevtsi"
    ],
    "wof:name":"Ralevtsi",
    "wof:placetype":"locality"
},
  "geometry": {"coordinates":[25.56667,42.83333],"type":"Point"}
}