{
  "type": "Feature",
  "properties": {
    "gn:admin1_code":"41",
    "gn:admin2_code":"GAB35",
    "gn:asciiname":"Ralevtsi",
    "gn:cc2":"BG",
    "gn:country_code":"BG",
    "gn:dem":548,
    "gn:feature_class":"P",
    "gn:feature_code":"PPL",
    "gn:name":"Ralevtsi",
    "gn:population":0,
    "gn:timezone":"Europe/Sofia",
    "iso:country":"BG",
    "name:bul_x_preferred":[
        "\u0420\u0430\u043b\u0435\u0432\u0446\u0438"
    ],
    "name:und_x_variant":[
        "Ralevts\u016d",
        "Ralevtsi"
    ],
    "wof:name":"Ralevtsi",
    "wof:placetype":"locality"
},
  "geometry": {"coordinates":[25.56667,42.83333],"type":"Point"}
}