{
  "type": "Feature",
  "properties": {
    "gn:admin1_code":"60",
    "gn:asciiname":"Zahari-Stoyanovo",
    "gn:country_code":"BG",
    "gn:dem":170,
    "gn:feature_class":"P",
    "gn:feature_code":"PPL",
    "gn:name":"Zahari-Stoyanovo",
    "gn:population":0,
    "gn:timezone":"Europe/Sofia",
    "iso:country":"BG",
    "name:bul_x_preferred":[
        "\u0417\u0430\u0445\u0430\u0440\u0438-\u0421\u0442\u043e\u044f\u043d\u043e\u0432\u043e"
    ],
    "name:bul_x_variant":[
        "Zahari-Stoyanovo"
    ],
    "name:und_x_variant":[
        "Omur Bey",
        "Sachari-Stojanowo",
        "Zakhari-Stoyanovo"
    ],
    "wof:name":"Zahari-Stoyanovo",
    "wof:placetype":"locality"
},
  "geometry": {"coordinates":[26.25,43.53333],"type":"Point"}
}