{
  "type": "Feature",
  "properties": {
    "gn:admin1_code":"38",
    "gn:admin2_code":"BLG33",
    "gn:asciiname":"Drenovo",
    "gn:cc2":"BG",
    "gn:country_code":"BG",
    "gn:dem":715,
    "gn:feature_class":"P",
    "gn:feature_code":"PPL",
    "gn:name":"Drenovo",
    "gn:population":0,
    "gn:timezone":"Europe/Sofia",
    "iso:country":"BG",
    "name:bul_x_preferred":[
        "\u0414\u0440\u0435\u043d\u043e\u0432\u043e"
    ],
    "name:ceb_x_preferred":[
        "Drenovo"
    ],
    "name:mkd_x_preferred":[
        "\u0414\u0440\u0435\u043d\u043e\u0432\u043e"
    ],
    "name:pol_x_preferred":[
        "Drenowo"
    ],
    "name:ron_x_preferred":[
        "Drenovo"
    ],
    "name:rus_x_preferred":[
        "\u0414\u0440\u0435\u043d\u043e\u0432\u043e"
    ],
    "name:srp_x_preferred":[
        "\u0414\u0440\u0435\u043d\u043e\u0432\u043e"
    ],
    "name:swe_x_preferred":[
        "Drenovo"
    ],
    "name:ukr_x_preferred":[
        "\u0414\u0440\u0435\u043d\u043e\u0432\u043e"
    ],
    "wof:name":"Drenovo",
    "wof:placetype":"locality"
},
  "geometry": {"coordinates":[23.16667,41.51667],"type":"Point"}
}