{
  "type": "Feature",
  "properties": {
    "gn:admin1_code":"44",
    "gn:asciiname":"Sulitsa",
    "gn:country_code":"BG",
    "gn:dem":416,
    "gn:feature_class":"P",
    "gn:feature_code":"PPL",
    "gn:name":"Sulitsa",
    "gn:population":0,
    "gn:timezone":"Europe/Sofia",
    "iso:country":"BG",
    "name:bul_x_preferred":[
        "Sulitsa"
    ],
    "name:bul_x_variant":[
        "\u0421\u0443\u043b\u0438\u0446\u0430"
    ],
    "wof:name":"Sulitsa",
    "wof:placetype":"locality"
},
  "geometry": {"coordinates":[25.54186,41.45924],"type":"Point"}
}