{
  "type": "Feature",
  "properties": {
    "gn:admin1_code":"52",
    "gn:admin2_code":"RAZ16",
    "gn:asciiname":"Terter",
    "gn:country_code":"BG",
    "gn:dem":97,
    "gn:feature_class":"P",
    "gn:feature_code":"PPL",
    "gn:name":"Terter",
    "gn:population":0,
    "gn:timezone":"Europe/Sofia",
    "iso:country":"BG",
    "name:bul_x_preferred":[
        "\u0422\u0435\u0440\u0442\u0435\u0440"
    ],
    "name:und_x_variant":[
        "K\u016dwandshilar",
        "Covangilar",
        "Kovandzhilar",
        "Terter",
        "Khadzhi Faklar",
        "Hagi Faclar",
        "General-Dobrero",
        "Chadshi Faklar"
    ],
    "wof:name":"Terter",
    "wof:placetype":"locality"
},
  "geometry": {"coordinates":[26.55775,43.89],"type":"Point"}
}