{
  "type": "Feature",
  "properties": {
    "iso:country":"BG",
    "name:eng_x_preferred":[
        "\u0425\u0430\u0440\u043c\u0430\u043d \u043c\u0430\u0445\u0430\u043b\u0430"
    ],
    "wof:name":"Harman Mahala",
    "wof:placetype":"neighbourhood"
},
  "geometry": {"coordinates":[24.74646854214268,42.16725345158317],"type":"Point"}
}