{
  "type": "Feature",
  "properties": {
    "gn:admin1_code":"44",
    "gn:asciiname":"Kukovtsi",
    "gn:country_code":"BG",
    "gn:dem":867,
    "gn:feature_class":"P",
    "gn:feature_code":"PPL",
    "gn:name":"Kukovtsi",
    "gn:population":0,
    "gn:timezone":"Europe/Sofia",
    "iso:country":"BG",
    "name:bul_x_preferred":[
        "\u041a\u0443\u043a\u043e\u0432\u0446\u0438"
    ],
    "wof:name":"Kukovtsi",
    "wof:placetype":"locality"
},
  "geometry": {"coordinates":[25.18333,41.58333],"type":"Point"}
}