{
  "type": "Feature",
  "properties": {
    "gn:admin1_code":"58",
    "gn:asciiname":"Gradishte",
    "gn:cc2":"BG",
    "gn:country_code":"BG",
    "gn:dem":666,
    "gn:feature_class":"P",
    "gn:feature_code":"PPL",
    "gn:name":"Gradishte",
    "gn:population":0,
    "gn:timezone":"Europe/Sofia",
    "iso:country":"BG",
    "name:bul_x_preferred":[
        "\u0413\u0440\u0430\u0434\u0438\u0449\u0435 \u043f\u043b\u0430\u043d\u0438\u043d\u0430"
    ],
    "name:und_x_variant":[
        "Gradischte",
        "Gradishte"
    ],
    "wof:name":"Gradishte",
    "wof:placetype":"locality"
},
  "geometry": {"coordinates":[23.96667,43.01667],"type":"Point"}
}