{
  "type": "Feature",
  "properties": {
    "gn:admin1_code":"45",
    "gn:admin2_code":"KNL31",
    "gn:asciiname":"Stradalovo",
    "gn:cc2":"BG",
    "gn:country_code":"BG",
    "gn:dem":718,
    "gn:feature_class":"P",
    "gn:feature_code":"PPL",
    "gn:name":"Stradalovo",
    "gn:population":0,
    "gn:timezone":"Europe/Sofia",
    "iso:country":"BG",
    "name:bul_x_preferred":[
        "\u0421\u0442\u0440\u0430\u0434\u0430\u043b\u043e\u0432\u043e"
    ],
    "name:fas_x_preferred":[
        "\u0633\u062a\u0631\u0627\u062f\u0627\u0644\u0648\u0648\u0648"
    ],
    "name:kaz_x_preferred":[
        "\u0421\u0442\u0440\u0430\u0434\u0430\u043b\u043e\u0432\u043e"
    ],
    "name:ron_x_preferred":[
        "Stradalovo"
    ],
    "name:rus_x_preferred":[
        "\u0421\u0442\u0440\u0430\u0434\u0430\u043b\u043e\u0432\u043e"
    ],
    "name:ukr_x_preferred":[
        "\u0421\u0442\u0440\u0430\u0434\u0430\u043b\u043e\u0432\u043e"
    ],
    "name:und_x_variant":[
        "Stradalowo"
    ],
    "wof:name":"Stradalovo",
    "wof:placetype":"locality"
},
  "geometry": {"coordinates":[22.75667,42.1275],"type":"Point"}
}