{
  "type": "Feature",
  "properties": {
    "gn:admin1_code":"44",
    "gn:asciiname":"Barzia",
    "gn:country_code":"BG",
    "gn:dem":313,
    "gn:feature_class":"P",
    "gn:feature_code":"PPL",
    "gn:name":"Barzia",
    "gn:population":0,
    "gn:timezone":"Europe/Sofia",
    "iso:country":"BG",
    "name:bul_x_preferred":[
        "\u0411\u044a\u0440\u0437\u0438\u044f"
    ],
    "name:bul_x_variant":[
        "Barzia"
    ],
    "name:und_x_variant":[
        "Sap Dere",
        "Barsija",
        "B\u016drziya",
        "B\u016drzeya"
    ],
    "wof:name":"Barzia",
    "wof:placetype":"locality"
},
  "geometry": {"coordinates":[25.32282,41.34819],"type":"Point"}
}