{
  "type": "Feature",
  "properties": {
    "gn:admin1_code":"54",
    "gn:admin2_code":"SHU18",
    "gn:admin3_code":"SHU18-10",
    "gn:asciiname":"Sini Vir",
    "gn:cc2":"BG",
    "gn:country_code":"BG",
    "gn:dem":282,
    "gn:feature_class":"P",
    "gn:feature_code":"PPL",
    "gn:name":"Sini Vir",
    "gn:population":0,
    "gn:timezone":"Europe/Sofia",
    "iso:country":"BG",
    "name:bul_x_preferred":[
        "\u0421\u0438\u043d \u0412\u0438\u0440"
    ],
    "name:und_x_variant":[
        "Senebir",
        "Senebirtik",
        "Seneberlik",
        "Siniwir",
        "Sini Vir"
    ],
    "wof:name":"Sini Vir",
    "wof:placetype":"locality"
},
  "geometry": {"coordinates":[27.05,43.55],"type":"Point"}
}