{
  "type": "Feature",
  "properties": {
    "gn:admin1_code":"47",
    "gn:admin2_code":"MON29",
    "gn:admin3_code":"MON29-19",
    "gn:asciiname":"Stubel",
    "gn:country_code":"BG",
    "gn:dem":212,
    "gn:feature_class":"P",
    "gn:feature_code":"PPL",
    "gn:name":"Stubel",
    "gn:population":0,
    "gn:timezone":"Europe/Sofia",
    "iso:country":"BG",
    "name:bul_x_preferred":[
        "\u0421\u0442\u0443\u0431\u0435\u043b"
    ],
    "name:fas_x_preferred":[
        "\u0633\u062a\u0648\u0628\u0644"
    ],
    "name:kaz_x_preferred":[
        "\u0421\u0442\u0443\u0431\u0435\u043b"
    ],
    "name:msa_x_preferred":[
        "Stubel"
    ],
    "name:ron_x_preferred":[
        "Stubel"
    ],
    "name:rus_x_preferred":[
        "\u0421\u0442\u0443\u0431\u0435\u043b"
    ],
    "name:ukr_x_preferred":[
        "\u0421\u0442\u0443\u0431\u0435\u043b"
    ],
    "wof:name":"Stubel",
    "wof:placetype":"locality"
},
  "geometry": {"coordinates":[23.35028,43.38944],"type":"Point"}
}