{
  "type": "Feature",
  "properties": {
    "gn:admin1_code":"64",
    "gn:admin2_code":"PVN39",
    "gn:admin3_code":"PVN39-03",
    "gn:asciiname":"Lazarovo",
    "gn:country_code":"BG",
    "gn:dem":149,
    "gn:feature_class":"P",
    "gn:feature_code":"PPL",
    "gn:name":"Lazarovo",
    "gn:population":0,
    "gn:timezone":"Europe/Sofia",
    "iso:country":"BG",
    "name:bul_x_preferred":[
        "\u041b\u0430\u0437\u0430\u0440\u043e\u0432\u043e"
    ],
    "name:und_x_variant":[
        "Strupen",
        "Lazarovo"
    ],
    "wof:name":"Lazarovo",
    "wof:placetype":"locality"
},
  "geometry": {"coordinates":[24.08333,43.41667],"type":"Point"}
}