{
  "type": "Feature",
  "properties": {
    "gn:admin1_code":"45",
    "gn:asciiname":"Dryanov Dolska Mahala",
    "gn:country_code":"BG",
    "gn:dem":903,
    "gn:feature_class":"P",
    "gn:feature_code":"PPL",
    "gn:name":"Dryanov Dolska Mahala",
    "gn:population":0,
    "gn:timezone":"Europe/Sofia",
    "iso:country":"BG",
    "name:bul_x_preferred":[
        "\u0414\u0440\u044f\u043d\u043e\u0432 \u0434\u043e\u043b\u0441\u043a\u0430 \u043c\u0430\u0445\u0430\u043b\u0430"
    ],
    "name:bul_x_variant":[
        "Dryanov Dolska Mahala",
        "\u0414\u0440\u044f\u043d\u043e\u0432 \u0414\u043e\u043b\u0441\u043a\u0430 \u041c\u0430\u0445\u0430\u043b\u0430"
    ],
    "name:und_x_variant":[
        "Dryanov Dolska Makhala"
    ],
    "wof:name":"Dryanov Dolska Mahala",
    "wof:placetype":"locality"
},
  "geometry": {"coordinates":[22.47639,42.29194],"type":"Point"}
}