{
  "type": "Feature",
  "properties": {
    "gn:admin1_code":"42",
    "gn:admin2_code":"SOF46",
    "gn:admin3_code":"SOF46-34",
    "gn:asciiname":"Malo Buchino",
    "gn:cc2":"BG",
    "gn:country_code":"BG",
    "gn:dem":760,
    "gn:feature_class":"P",
    "gn:feature_code":"PPL",
    "gn:name":"Malo Buchino",
    "gn:population":0,
    "gn:timezone":"Europe/Sofia",
    "iso:country":"BG",
    "name:bul_x_preferred":[
        "\u041c\u0430\u043b\u043e \u0411\u0443\u0447\u0438\u043d\u043e"
    ],
    "name:und_x_variant":[
        "Malo Butschino",
        "Malo Buchino"
    ],
    "wof:name":"Malo Buchino",
    "wof:placetype":"locality"
},
  "geometry": {"coordinates":[23.16667,42.68333],"type":"Point"}
}