{
  "type": "Feature",
  "properties": {
    "gn:admin1_code":"44",
    "gn:admin2_code":"KRZ02",
    "gn:asciiname":"Spoluka",
    "gn:cc2":"BG",
    "gn:country_code":"BG",
    "gn:dem":1032,
    "gn:feature_class":"P",
    "gn:feature_code":"PPL",
    "gn:name":"Spoluka",
    "gn:population":0,
    "gn:timezone":"Europe/Sofia",
    "iso:country":"BG",
    "name:bul_x_preferred":[
        "\u0421\u043f\u043e\u043b\u0443\u043a\u0430"
    ],
    "name:fas_x_preferred":[
        "\u0633\u067e\u0648\u0644\u0648\u06a9\u0627"
    ],
    "name:kat_x_preferred":[
        "\u10e1\u10de\u10dd\u10da\u10e3\u10d9\u10d0"
    ],
    "name:kaz_x_preferred":[
        "\u0421\u043f\u043e\u043b\u0443\u043a\u0430"
    ],
    "name:ron_x_preferred":[
        "Spoluka"
    ],
    "name:rus_x_preferred":[
        "\u0421\u043f\u043e\u043b\u0443\u043a\u0430"
    ],
    "name:ukr_x_preferred":[
        "\u0421\u043f\u043e\u043b\u0443\u043a\u0430"
    ],
    "name:und_x_variant":[
        "Oladzhak",
        "Spoluka"
    ],
    "wof:name":"Spoluka",
    "wof:placetype":"locality"
},
  "geometry": {"coordinates":[25.11667000000001,41.71667],"type":"Point"}
}