{
  "type": "Feature",
  "properties": {
    "gn:admin1_code":"49",
    "gn:admin2_code":"PER51",
    "gn:asciiname":"Staychovtsi",
    "gn:country_code":"BG",
    "gn:dem":830,
    "gn:feature_class":"P",
    "gn:feature_code":"PPL",
    "gn:name":"Staychovtsi",
    "gn:population":0,
    "gn:timezone":"Europe/Sofia",
    "iso:country":"BG",
    "name:bul_x_preferred":[
        "\u0421\u0442\u0430\u0439\u0447\u043e\u0432\u0446\u0438"
    ],
    "name:und_x_variant":[
        "Staitschowzi",
        "Staychovtsi"
    ],
    "wof:name":"Staychovtsi",
    "wof:placetype":"locality"
},
  "geometry": {"coordinates":[22.53902,42.76069],"type":"Point"}
}