{
  "type": "Feature",
  "properties": {
    "gn:admin1_code":"44",
    "gn:admin2_code":"KRZ08",
    "gn:admin3_code":"KRZ08-11",
    "gn:asciiname":"Tsvyatovo",
    "gn:cc2":"BG",
    "gn:country_code":"BG",
    "gn:dem":408,
    "gn:feature_class":"P",
    "gn:feature_code":"PPL",
    "gn:name":"Tsvyatovo",
    "gn:population":0,
    "gn:timezone":"Europe/Sofia",
    "iso:country":"BG",
    "name:bul_x_preferred":[
        "\u0426\u0432\u044f\u0442\u043e\u0432\u043e"
    ],
    "name:ron_x_preferred":[
        "\u021aveatovo"
    ],
    "name:rus_x_preferred":[
        "\u0426\u0432\u044f\u0442\u043e\u0432\u043e"
    ],
    "name:ukr_x_preferred":[
        "\u0426\u0432\u044f\u0442\u043e\u0432\u043e"
    ],
    "name:und_x_variant":[
        "Zwetewo",
        "Al K\u2019oy",
        "Tsvyatovo"
    ],
    "wof:name":"Tsvyatovo",
    "wof:placetype":"locality"
},
  "geometry": {"coordinates":[25.28333,41.53333],"type":"Point"}
}