{
  "type": "Feature",
  "properties": {
    "gn:admin1_code":"51",
    "gn:admin2_code":"PDV17",
    "gn:admin3_code":"PDV17-12",
    "gn:asciiname":"Radinovo",
    "gn:cc2":"BG",
    "gn:country_code":"BG",
    "gn:dem":175,
    "gn:feature_class":"P",
    "gn:feature_code":"PPL",
    "gn:name":"Radinovo",
    "gn:population":0,
    "gn:timezone":"Europe/Sofia",
    "iso:country":"BG",
    "name:bul_x_preferred":[
        "\u0420\u0430\u0434\u0438\u043d\u043e\u0432\u043e"
    ],
    "name:und_x_variant":[
        "Radinowo",
        "Radinovo"
    ],
    "wof:name":"Radinovo",
    "wof:placetype":"locality"
},
  "geometry": {"coordinates":[24.63333,42.18333],"type":"Point"}
}