{
  "type": "Feature",
  "properties": {
    "gn:admin1_code":"51",
    "gn:admin2_code":"PDV17",
    "gn:admin3_code":"PDV17-12",
    "gn:asciiname":"Radinovo",
    "gn:cc2":"BG",
    "gn:country_code":"BG",
    "gn:dem":175,
    "gn:feature_class":"P",
    "gn:feature_code":"PPL",
    "gn:name":"Radinovo",
    "gn:population":0,
    "gn:timezone":"Europe/Sofia",
    "iso:country":"BG",
    "name:bul_x_preferred":[
        "\u0420\u0430\u0434\u0438\u043d\u043e\u0432\u043e"
    ],
    "name:ceb_x_preferred":[
        "Radinovo"
    ],
    "name:fas_x_preferred":[
        "\u0631\u0627\u062f\u06cc\u0646\u0648\u0648\u0648"
    ],
    "name:kat_x_preferred":[
        "\u10e0\u10d0\u10d3\u10d8\u10dc\u10dd\u10d5\u10dd"
    ],
    "name:kaz_x_preferred":[
        "\u0420\u0430\u0434\u0438\u043d\u043e\u0432\u043e"
    ],
    "name:msa_x_preferred":[
        "Radinovo"
    ],
    "name:pol_x_preferred":[
        "Radinowo"
    ],
    "name:ron_x_preferred":[
        "Radinovo"
    ],
    "name:rus_x_preferred":[
        "\u0420\u0430\u0434\u0438\u043d\u043e\u0432\u043e"
    ],
    "name:swe_x_preferred":[
        "Radinovo"
    ],
    "name:ukr_x_preferred":[
        "\u0420\u0430\u0434\u0438\u043d\u043e\u0432\u043e"
    ],
    "wof:name":"Radinovo",
    "wof:placetype":"locality"
},
  "geometry": {"coordinates":[24.63333,42.18333],"type":"Point"}
}