{
  "type": "Feature",
  "properties": {
    "gn:admin1_code":"63",
    "gn:admin2_code":"VID06",
    "gn:admin3_code":"VID06-02",
    "gn:asciiname":"Vrav",
    "gn:country_code":"BG",
    "gn:dem":51,
    "gn:feature_class":"P",
    "gn:feature_code":"PPL",
    "gn:name":"Vrav",
    "gn:population":0,
    "gn:timezone":"Europe/Sofia",
    "iso:country":"BG",
    "name:bul_x_preferred":[
        "\u0412\u0440\u044a\u0432"
    ],
    "name:bul_x_variant":[
        "Vrav"
    ],
    "name:und_x_variant":[
        "V\u016drv",
        "Vr\u0103v",
        "Vrv",
        "W\u0103rw",
        "Vrf",
        "Vr\u016dv"
    ],
    "wof:name":"Vrav",
    "wof:placetype":"locality"
},
  "geometry": {"coordinates":[22.73426,44.19161],"type":"Point"}
}