{
  "type": "Feature",
  "properties": {
    "gn:admin1_code":"54",
    "gn:admin2_code":"SHU11",
    "gn:admin3_code":"SHU11-07",
    "gn:asciiname":"Dobri Voynikovo",
    "gn:cc2":"BG",
    "gn:country_code":"BG",
    "gn:dem":349,
    "gn:feature_class":"P",
    "gn:feature_code":"PPL",
    "gn:name":"Dobri Voynikovo",
    "gn:population":0,
    "gn:timezone":"Europe/Sofia",
    "iso:country":"BG",
    "name:bul_x_preferred":[
        "\u0414\u043e\u0431\u0440\u0438 \u0412\u043e\u0439\u043d\u0438\u043a\u043e\u0432\u043e"
    ],
    "name:und_x_variant":[
        "Khass\u016d",
        "Dobri Voynikovo"
    ],
    "wof:name":"Dobri Voynikovo",
    "wof:placetype":"locality"
},
  "geometry": {"coordinates":[26.85,43.43333],"type":"Point"}
}