{
  "type": "Feature",
  "properties": {
    "gn:admin1_code":"54",
    "gn:admin2_code":"SHU11",
    "gn:admin3_code":"SHU11-16",
    "gn:asciiname":"Studenitsa",
    "gn:cc2":"BG",
    "gn:country_code":"BG",
    "gn:dem":360,
    "gn:feature_class":"P",
    "gn:feature_code":"PPL",
    "gn:name":"Studenitsa",
    "gn:population":0,
    "gn:timezone":"Europe/Sofia",
    "iso:country":"BG",
    "name:bul_x_preferred":[
        "\u0421\u0442\u0443\u0434\u0435\u043d\u0438\u0446\u0430"
    ],
    "name:und_x_variant":[
        "Sudzhas",
        "Studeniza",
        "Studenitsa"
    ],
    "wof:name":"Studenitsa",
    "wof:placetype":"locality"
},
  "geometry": {"coordinates":[26.75,43.45],"type":"Point"}
}