{
  "type": "Feature",
  "properties": {
    "gn:admin1_code":"62",
    "gn:admin2_code":"VTR22",
    "gn:admin3_code":"VTR22-14",
    "gn:asciiname":"Paskalevets",
    "gn:cc2":"BG",
    "gn:country_code":"BG",
    "gn:dem":207,
    "gn:feature_class":"P",
    "gn:feature_code":"PPL",
    "gn:name":"Paskalevets",
    "gn:population":0,
    "gn:timezone":"Europe/Sofia",
    "iso:country":"BG",
    "name:bul_x_preferred":[
        "\u041f\u0430\u0441\u043a\u0430\u043b\u0435\u0432\u0435\u0446"
    ],
    "name:und_x_variant":[
        "Paskalewez",
        "Paskalevec",
        "Paskalevets"
    ],
    "wof:name":"Paskalevets",
    "wof:placetype":"locality"
},
  "geometry": {"coordinates":[25.48333,43.25],"type":"Point"}
}