{
  "type": "Feature",
  "properties": {
    "gn:admin1_code":"41",
    "gn:admin2_code":"GAB12",
    "gn:asciiname":"Ritya",
    "gn:cc2":"BG",
    "gn:country_code":"BG",
    "gn:dem":406,
    "gn:feature_class":"P",
    "gn:feature_code":"PPL",
    "gn:name":"Ritya",
    "gn:population":0,
    "gn:timezone":"Europe/Sofia",
    "iso:country":"BG",
    "name:ara_x_preferred":[
        "\u0631\u064a\u062a\u064a\u0627"
    ],
    "name:bul_x_preferred":[
        "\u0420\u0438\u0442\u044f"
    ],
    "name:fas_x_preferred":[
        "\u0631\u06cc\u062a\u06cc\u0627"
    ],
    "name:kaz_x_preferred":[
        "\u0420\u0438\u0442\u044f"
    ],
    "name:pol_x_preferred":[
        "Ritja"
    ],
    "name:rus_x_preferred":[
        "\u0420\u0438\u0442\u044f"
    ],
    "name:ukr_x_preferred":[
        "\u0420\u0438\u0442\u044f"
    ],
    "name:und_x_variant":[
        "R\u016dtya",
        "Ritya"
    ],
    "wof:name":"Ritya",
    "wof:placetype":"locality"
},
  "geometry": {"coordinates":[25.41667,42.98333],"type":"Point"}
}