{
  "type": "Feature",
  "properties": {
    "gn:admin1_code":"54",
    "gn:admin2_code":"SHU30",
    "gn:admin3_code":"SHU30-04",
    "gn:asciiname":"Vehtovo",
    "gn:country_code":"BG",
    "gn:dem":119,
    "gn:feature_class":"P",
    "gn:feature_code":"PPL",
    "gn:name":"Vehtovo",
    "gn:population":0,
    "gn:timezone":"Europe/Sofia",
    "iso:country":"BG",
    "name:bul_x_preferred":[
        "\u0412\u0435\u0445\u0442\u043e\u0432\u043e"
    ],
    "name:bul_x_variant":[
        "Vehtovo"
    ],
    "name:und_x_variant":[
        "Eski K\u2019oy",
        "Vekhto",
        "Wechto",
        "Vekhtovo"
    ],
    "wof:name":"Vehtovo",
    "wof:placetype":"locality"
},
  "geometry": {"coordinates":[27.08333,43.16667],"type":"Point"}
}