{
  "type": "Feature",
  "properties": {
    "gn:admin1_code":"41",
    "gn:admin2_code":"GAB29",
    "gn:admin3_code":"GAB29-18",
    "gn:asciiname":"Kravenik",
    "gn:country_code":"BG",
    "gn:dem":515,
    "gn:feature_class":"P",
    "gn:feature_code":"PPL",
    "gn:name":"Kravenik",
    "gn:population":0,
    "gn:timezone":"Europe/Sofia",
    "iso:country":"BG",
    "name:bul_x_preferred":[
        "\u041a\u0440\u044a\u0432\u0435\u043d\u0438\u043a"
    ],
    "name:und_x_variant":[
        "Kr\u0103wenik",
        "Krivenik",
        "Krevenik",
        "Kravjanik",
        "Kravenik",
        "Kr\u016dvenik"
    ],
    "wof:name":"Kravenik",
    "wof:placetype":"locality"
},
  "geometry": {"coordinates":[25.01667,42.85],"type":"Point"}
}