{
  "type": "Feature",
  "properties": {
    "gn:admin1_code":"49",
    "gn:admin2_code":"PER36",
    "gn:admin3_code":"PER36-26",
    "gn:asciiname":"Galabnik",
    "gn:country_code":"BG",
    "gn:dem":692,
    "gn:feature_class":"P",
    "gn:feature_code":"PPL",
    "gn:name":"Galabnik",
    "gn:population":0,
    "gn:timezone":"Europe/Sofia",
    "iso:country":"BG",
    "name:bul_x_preferred":[
        "\u0413\u044a\u043b\u044a\u0431\u043d\u0438\u043a"
    ],
    "name:bul_x_variant":[
        "Galabnik"
    ],
    "name:und_x_variant":[
        "G\u0103l\u0103bnik",
        "Musi Bey",
        "G\u016dl\u016dbnik"
    ],
    "wof:name":"Galabnik",
    "wof:placetype":"locality"
},
  "geometry": {"coordinates":[23.07898,42.40134000000001],"type":"Point"}
}