{
  "type": "Feature",
  "properties": {
    "gn:admin1_code":"44",
    "gn:asciiname":"Merdzhenik",
    "gn:country_code":"BG",
    "gn:dem":332,
    "gn:feature_class":"P",
    "gn:feature_code":"PPL",
    "gn:name":"Merdzhenik",
    "gn:population":0,
    "gn:timezone":"Europe/Sofia",
    "iso:country":"BG",
    "name:bul_x_preferred":[
        "Merdzhenik"
    ],
    "name:bul_x_variant":[
        "\u041c\u0435\u0440\u0434\u0436\u0435\u043d\u0438\u043a"
    ],
    "wof:name":"Merdzhenik",
    "wof:placetype":"locality"
},
  "geometry": {"coordinates":[25.34748,41.43939],"type":"Point"}
}