{
  "type": "Feature",
  "properties": {
    "gn:admin1_code":"51",
    "gn:admin2_code":"PDV37",
    "gn:asciiname":"Malo Krushevo",
    "gn:cc2":"BG",
    "gn:country_code":"BG",
    "gn:dem":338,
    "gn:feature_class":"P",
    "gn:feature_code":"PPL",
    "gn:name":"Malo Krushevo",
    "gn:population":0,
    "gn:timezone":"Europe/Sofia",
    "iso:country":"BG",
    "name:bul_x_preferred":[
        "\u041c\u0430\u043b\u043e \u041a\u0440\u0443\u0448\u0435\u0432\u043e"
    ],
    "name:und_x_variant":[
        "Armutlii",
        "Krushovo",
        "Germotliy",
        "Krushevo",
        "Armutliy",
        "Kruschowo",
        "Malo Krushevo"
    ],
    "wof:name":"Malo Krushevo",
    "wof:placetype":"locality"
},
  "geometry": {"coordinates":[24.48333,42.41667],"type":"Point"}
}