{
  "type": "Feature",
  "properties": {
    "gn:admin1_code":"63",
    "gn:admin2_code":"VID30",
    "gn:admin3_code":"VID30-04",
    "gn:asciiname":"Yasen",
    "gn:country_code":"BG",
    "gn:dem":92,
    "gn:feature_class":"P",
    "gn:feature_code":"PPL",
    "gn:name":"Yasen",
    "gn:population":0,
    "gn:timezone":"Europe/Sofia",
    "iso:country":"BG",
    "name:bul_x_preferred":[
        "\u042f\u0441\u0435\u043d"
    ],
    "name:und_x_variant":[
        "Jassen",
        "Yasen"
    ],
    "wof:name":"Yasen",
    "wof:placetype":"locality"
},
  "geometry": {"coordinates":[22.87844,44.118],"type":"Point"}
}