{
  "type": "Feature",
  "properties": {
    "gn:admin1_code":"55",
    "gn:admin2_code":"SLS32",
    "gn:admin3_code":"SLS32-06",
    "gn:asciiname":"Yastrebna",
    "gn:cc2":"BG",
    "gn:country_code":"BG",
    "gn:dem":88,
    "gn:feature_class":"P",
    "gn:feature_code":"PPL",
    "gn:name":"Yastrebna",
    "gn:population":0,
    "gn:timezone":"Europe/Sofia",
    "iso:country":"BG",
    "name:bul_x_preferred":[
        "\u042f\u0441\u0442\u0440\u0435\u0431\u043d\u0430"
    ],
    "name:kaz_x_preferred":[
        "\u042f\u0441\u0442\u0440\u0435\u0431\u043d\u0430"
    ],
    "name:ron_x_preferred":[
        "Iastrebna"
    ],
    "name:rus_x_preferred":[
        "\u042f\u0441\u0442\u0440\u0435\u0431\u043d\u0430"
    ],
    "name:ukr_x_preferred":[
        "\u042f\u0441\u0442\u0440\u0435\u0431\u043d\u0430"
    ],
    "name:und_x_variant":[
        "Atmagea",
        "Jastrebna",
        "Atmadsha",
        "Golebina Atmadzha",
        "Yastrebna"
    ],
    "wof:name":"Yastrebna",
    "wof:placetype":"locality"
},
  "geometry": {"coordinates":[27.06667,43.96667],"type":"Point"}
}