{
  "type": "Feature",
  "properties": {
    "gn:admin1_code":"41",
    "gn:asciiname":"Dragievtsi",
    "gn:cc2":"BG",
    "gn:country_code":"BG",
    "gn:dem":275,
    "gn:feature_class":"P",
    "gn:feature_code":"PPL",
    "gn:name":"Dragievtsi",
    "gn:population":0,
    "gn:timezone":"Europe/Sofia",
    "iso:country":"BG",
    "name:ara_x_preferred":[
        "\u062f\u0631\u0627\u064a\u064a\u0641\u062a\u0633\u064a"
    ],
    "name:bul_x_preferred":[
        "\u0414\u0440\u0430\u0433\u0438\u0435\u0432\u0446\u0438"
    ],
    "name:fas_x_preferred":[
        "\u062f\u0631\u0627\u06af\u06cc\u0648\u062a\u0633\u06cc"
    ],
    "name:kaz_x_preferred":[
        "\u0414\u0440\u0430\u0433\u0438\u0435\u0432\u0446\u0438"
    ],
    "name:pol_x_preferred":[
        "Dragiewci"
    ],
    "name:ron_x_preferred":[
        "Draghiev\u021bi"
    ],
    "name:rus_x_preferred":[
        "\u0414\u0440\u0430\u0433\u0438\u0435\u0432\u0446\u0438"
    ],
    "name:ukr_x_preferred":[
        "\u0414\u0440\u0430\u0433\u0456\u0454\u0432\u0446\u0456"
    ],
    "name:und_x_variant":[
        "Dragiewzi",
        "Dragievts\u016d",
        "Dragnevtsi",
        "Dragievtsi"
    ],
    "wof:name":"Dragievtsi",
    "wof:placetype":"locality"
},
  "geometry": {"coordinates":[25.18333,42.93333],"type":"Point"}
}