{
  "type": "Feature",
  "properties": {
    "gn:admin1_code":"59",
    "gn:admin2_code":"SZR31",
    "gn:asciiname":"Pryaporets",
    "gn:cc2":"BG",
    "gn:country_code":"BG",
    "gn:dem":506,
    "gn:feature_class":"P",
    "gn:feature_code":"PPL",
    "gn:name":"Pryaporets",
    "gn:population":0,
    "gn:timezone":"Europe/Sofia",
    "iso:country":"BG",
    "name:bul_x_preferred":[
        "\u041f\u0440\u044f\u043f\u043e\u0440\u0435\u0446"
    ],
    "name:und_x_variant":[
        "Baraklari",
        "Preporez",
        "Baraklarit",
        "Pryaporets"
    ],
    "wof:name":"Pryaporets",
    "wof:placetype":"locality"
},
  "geometry": {"coordinates":[25.53333,42.46667],"type":"Point"}
}