{
  "type": "Feature",
  "properties": {
    "gn:admin1_code":"58",
    "gn:admin2_code":"SFO56",
    "gn:asciiname":"Kamenitsa",
    "gn:cc2":"BG",
    "gn:country_code":"BG",
    "gn:dem":791,
    "gn:feature_class":"P",
    "gn:feature_code":"PPL",
    "gn:name":"Kamenitsa",
    "gn:population":0,
    "gn:timezone":"Europe/Sofia",
    "iso:country":"BG",
    "name:bul_x_preferred":[
        "\u041a\u0430\u043c\u0435\u043d\u0438\u0446\u0430"
    ],
    "name:ceb_x_preferred":[
        "Kamenitsa"
    ],
    "name:fra_x_preferred":[
        "Kamenitsa"
    ],
    "name:swe_x_preferred":[
        "Kamenitsa"
    ],
    "name:und_x_variant":[
        "Kameniza"
    ],
    "wof:name":"Kamenitsa",
    "wof:placetype":"locality"
},
  "geometry": {"coordinates":[23.93333,42.58333],"type":"Point"}
}