{
  "type": "Feature",
  "properties": {
    "gn:admin1_code":"49",
    "gn:asciiname":"Chuypetlovo",
    "gn:cc2":"BG",
    "gn:country_code":"BG",
    "gn:dem":1377,
    "gn:feature_class":"P",
    "gn:feature_code":"PPL",
    "gn:name":"Chuypetlovo",
    "gn:population":0,
    "gn:timezone":"Europe/Sofia",
    "iso:country":"BG",
    "name:bul_x_preferred":[
        "\u0427\u0443\u0439\u043f\u0435\u0442\u043b\u044c\u043e\u0432\u043e"
    ],
    "name:und_x_variant":[
        "Tschupetlowo",
        "Chuiletlevo",
        "Chupetlovo",
        "Chuypetlovo"
    ],
    "wof:name":"Chuypetlovo",
    "wof:placetype":"locality"
},
  "geometry": {"coordinates":[23.25,42.51667],"type":"Point"}
}