{
  "type": "Feature",
  "properties": {
    "iso:country":"BG",
    "name:bul_x_preferred":[
        "\u041d\u0430\u0434\u0435\u0436\u0434\u0430"
    ],
    "name:bul_x_variant":[
        "Nadejda",
        "Kvartal Nadezhda"
    ],
    "name:eng_x_preferred":[
        "Nadezhda"
    ],
    "name:eng_x_variant":[
        "Kvartal Nadezhda",
        "Nadejda",
        "Nadezhda District"
    ],
    "name:hye_x_preferred":[
        "\u0546\u0561\u0564\u0565\u056a\u0564\u0561"
    ],
    "name:pol_x_preferred":[
        "Rejon Nade\u017cda"
    ],
    "qs:gn_adm0_cc":"BG",
    "qs:gn_fcode":"PPLX",
    "qs:gn_local":727011,
    "qs:gn_nam_loc":"Sofiya, Sofia, Sofiya-Grad, BG",
    "qs:gn_namadm1":"42",
    "qs:gn_name":"Nadezhda",
    "qs:local_max":4184,
    "qs:local_sum":18613,
    "qs:localhoods":26,
    "qs:name":"Nadezhda",
    "qs:name_adm0":"Bulgaria",
    "qs:name_adm1":"Sofiya-Grad",
    "qs:name_adm2":"Sofiya",
    "qs:name_local":"Sofia",
    "qs:photo_max":38,
    "qs:photo_sum":104,
    "qs:placetype":"Suburb",
    "qs:quad_count":23,
    "qs:woe_adm0":23424771,
    "qs:woe_adm1":20069794,
    "qs:woe_adm2":55873710,
    "qs:woe_lau":0,
    "qs:woe_local":839722,
    "qs:woe_ver":"7.10.0",
    "wd:wordcount":203,
    "wof:lang":[
        "eng"
    ],
    "wof:name":"Nadezhda",
    "wof:placetype":"neighbourhood"
},
  "geometry": {"coordinates":[23.309399,42.742795],"type":"Point"}
}