{
  "type": "Feature",
  "properties": {
    "gn:admin1_code":"44",
    "gn:asciiname":"Frandak Mahala",
    "gn:country_code":"BG",
    "gn:dem":1024,
    "gn:feature_class":"P",
    "gn:feature_code":"PPL",
    "gn:name":"Frandak Mahala",
    "gn:population":0,
    "gn:timezone":"Europe/Sofia",
    "iso:country":"BG",
    "name:bul_x_preferred":[
        "\u0424\u0440\u0430\u043d\u0434\u044a\u043a \u043c\u0430\u0445\u0430\u043b\u0430"
    ],
    "name:bul_x_variant":[
        "Frandak Mahala"
    ],
    "name:und_x_variant":[
        "Frand\u016dk Makhala"
    ],
    "wof:name":"Frandak Mahala",
    "wof:placetype":"locality"
},
  "geometry": {"coordinates":[25.08333,41.76667],"type":"Point"}
}