{
  "type": "Feature",
  "properties": {
    "gn:admin1_code":"38",
    "gn:admin2_code":"BLG33",
    "gn:asciiname":"Dragush",
    "gn:cc2":"BG",
    "gn:country_code":"BG",
    "gn:dem":844,
    "gn:feature_class":"P",
    "gn:feature_code":"PPL",
    "gn:name":"Dragush",
    "gn:population":0,
    "gn:timezone":"Europe/Sofia",
    "iso:country":"BG",
    "name:bul_x_preferred":[
        "\u0414\u0440\u0430\u0433\u0443\u0448"
    ],
    "name:fas_x_preferred":[
        "\u062f\u0631\u0627\u06af\u0648\u0634"
    ],
    "name:kaz_x_preferred":[
        "\u0414\u0440\u0430\u0433\u0443\u0448"
    ],
    "name:mkd_x_preferred":[
        "\u0414\u0440\u0430\u0433\u0443\u0448"
    ],
    "name:ron_x_preferred":[
        "Dragu\u0219"
    ],
    "name:rus_x_preferred":[
        "\u0414\u0440\u0430\u0433\u0443\u0448"
    ],
    "name:ukr_x_preferred":[
        "\u0414\u0440\u0430\u0433\u0443\u0448"
    ],
    "name:und_x_variant":[
        "Dragusch",
        "Dragush"
    ],
    "wof:name":"Dragush",
    "wof:placetype":"locality"
},
  "geometry": {"coordinates":[23.09245,41.51738],"type":"Point"}
}