{
  "type": "Feature",
  "properties": {
    "gn:admin1_code":"58",
    "gn:admin2_code":"SFO16",
    "gn:asciiname":"Gorno Selo",
    "gn:country_code":"BG",
    "gn:dem":712,
    "gn:feature_class":"P",
    "gn:feature_code":"PPL",
    "gn:name":"Gorno Selo",
    "gn:population":0,
    "gn:timezone":"Europe/Sofia",
    "iso:country":"BG",
    "name:bul_x_preferred":[
        "\u0413\u043e\u0440\u043d\u043e \u0421\u0435\u043b\u043e"
    ],
    "name:und_x_variant":[
        "Novo Selo",
        "Gorno Novo Selo",
        "Nowo Selo",
        "Gorno Selo"
    ],
    "wof:name":"Gorno Selo",
    "wof:placetype":"locality"
},
  "geometry": {"coordinates":[22.78026,42.86917],"type":"Point"}
}