{
  "type": "Feature",
  "properties": {
    "gn:admin1_code":"44",
    "gn:asciiname":"Ruy",
    "gn:country_code":"BG",
    "gn:dem":303,
    "gn:feature_class":"P",
    "gn:feature_code":"PPL",
    "gn:name":"Ruy",
    "gn:population":0,
    "gn:timezone":"Europe/Sofia",
    "iso:country":"BG",
    "name:bul_x_preferred":[
        "Ruy"
    ],
    "name:bul_x_variant":[
        "\u0420\u0443\u0439"
    ],
    "name:ceb_x_preferred":[
        "Ruy"
    ],
    "name:deu_x_preferred":[
        "Ruy"
    ],
    "name:fra_x_preferred":[
        "Ruy"
    ],
    "name:nld_x_preferred":[
        "Ruy"
    ],
    "name:por_x_preferred":[
        "Ruy"
    ],
    "name:rus_x_preferred":[
        "\u0420\u0443\u0439"
    ],
    "name:swe_x_preferred":[
        "Ruy"
    ],
    "name:ukr_x_preferred":[
        "\u0420\u0443\u0439"
    ],
    "wof:name":"Ruy",
    "wof:placetype":"locality"
},
  "geometry": {"coordinates":[25.5777,41.42781],"type":"Point"}
}