{
  "type": "Feature",
  "properties": {
    "gn:admin1_code":"44",
    "gn:asciiname":"Chukur",
    "gn:country_code":"BG",
    "gn:dem":452,
    "gn:feature_class":"P",
    "gn:feature_code":"PPL",
    "gn:name":"Chukur",
    "gn:population":0,
    "gn:timezone":"Europe/Sofia",
    "iso:country":"BG",
    "name:bul_x_preferred":[
        "Chukur"
    ],
    "name:bul_x_variant":[
        "\u0427\u0443\u043a\u0443\u0440"
    ],
    "wof:name":"Chukur",
    "wof:placetype":"locality"
},
  "geometry": {"coordinates":[25.51257,41.46119],"type":"Point"}
}