{
  "type": "Feature",
  "properties": {
    "gn:admin1_code":"38",
    "gn:asciiname":"Stopanska Mahala",
    "gn:country_code":"BG",
    "gn:dem":876,
    "gn:feature_class":"P",
    "gn:feature_code":"PPL",
    "gn:name":"Stopanska Mahala",
    "gn:population":0,
    "gn:timezone":"Europe/Sofia",
    "iso:country":"BG",
    "name:bul_x_preferred":[
        "Stopanska Mahala"
    ],
    "name:bul_x_variant":[
        "\u0421\u0442\u043e\u043f\u0430\u043d\u0441\u043a\u0430 \u041c\u0430\u0445\u0430\u043b\u0430"
    ],
    "name:und_x_variant":[
        "Stopanska Makhala"
    ],
    "wof:name":"Stopanska Mahala",
    "wof:placetype":"locality"
},
  "geometry": {"coordinates":[22.94495,41.88288],"type":"Point"}
}