{
  "type": "Feature",
  "properties": {
    "gn:admin1_code":"62",
    "gn:admin2_code":"VTR13",
    "gn:asciiname":"Gorni Tanchevtsi",
    "gn:cc2":"BG",
    "gn:country_code":"BG",
    "gn:dem":611,
    "gn:feature_class":"P",
    "gn:feature_code":"PPL",
    "gn:name":"Gorni Tanchevtsi",
    "gn:population":0,
    "gn:timezone":"Europe/Sofia",
    "iso:country":"BG",
    "name:bul_x_preferred":[
        "\u0413\u043e\u0440\u043d\u0438 \u0422\u0430\u043d\u0447\u0435\u0432\u0446\u0438"
    ],
    "name:und_x_variant":[
        "Tanchovtsi",
        "Gorni Tanchovtsi",
        "Gorni Tanchevtsi"
    ],
    "wof:name":"Gorni Tanchevtsi",
    "wof:placetype":"locality"
},
  "geometry": {"coordinates":[25.91667,42.83333],"type":"Point"}
}