{
  "type": "Feature",
  "properties": {
    "gn:gn_country":"BG",
    "gn:gn_fcode":"PPL",
    "gn:gn_pop":0,
    "iso:country":"BG",
    "name:bul_x_preferred":[
        "\u0420\u0430\u0431\u043e\u0432\u043e"
    ],
    "name:eng_x_preferred":[
        "Rabovo"
    ],
    "name:kaz_x_preferred":[
        "\u0420\u0430\u0431\u043e\u0432\u043e"
    ],
    "name:ron_x_preferred":[
        "Rabovo"
    ],
    "name:rus_x_preferred":[
        "\u0420\u0430\u0431\u043e\u0432\u043e"
    ],
    "name:swe_x_preferred":[
        "Rabovo"
    ],
    "name:ukr_x_preferred":[
        "\u0420\u0430\u0431\u043e\u0432\u043e"
    ],
    "name:unk_x_variant":[
        "Abdul Kadir"
    ],
    "qs_pg:aaroncc":"BG",
    "qs_pg:gn_country":"BG",
    "qs_pg:gn_fcode":"PPL",
    "qs_pg:gn_pop":0,
    "qs_pg:name":"Rabovo",
    "qs_pg:name_adm0":"Bulgaria",
    "qs_pg:name_adm1":"Khaskovo",
    "qs_pg:photos":4,
    "qs_pg:photos_1k":1,
    "qs_pg:photos_9k":1,
    "qs_pg:photos_9r":1,
    "qs_pg:photos_all":4,
    "qs_pg:photos_sr":1,
    "qs_pg:pop_sr":0,
    "qs_pg:qs_pg_placetype":"locality",
    "qs_pg:qs_pg_placetype_gp":"Town",
    "qs_pg:woe_adm0":23424771,
    "woe:adm0_id":23424771,
    "woe:name_adm0":"Bulgaria",
    "woe:name_adm1":"Khaskovo",
    "woe:placetype":"Town",
    "wof:name":"Rabovo",
    "wof:placetype":"locality"
},
  "geometry": {"coordinates":[25.66667,41.61667],"type":"Point"}
}