{
  "type": "Feature",
  "properties": {
    "gn:admin1_code":"41",
    "gn:admin2_code":"VTR04",
    "gn:asciiname":"Dolen Enevets",
    "gn:country_code":"BG",
    "gn:dem":428,
    "gn:feature_class":"P",
    "gn:feature_code":"PPL",
    "gn:name":"Dolen Enevets",
    "gn:population":0,
    "gn:timezone":"Europe/Sofia",
    "iso:country":"BG",
    "name:bul_x_preferred":[
        "\u0414\u043e\u043b\u0435\u043d \u0415\u043d\u0435\u0432\u0435\u0446"
    ],
    "name:und_x_variant":[
        "Dolni Evenets",
        "Dolni Enovets",
        "Dolni Enevets",
        "Dolen Enevets"
    ],
    "wof:name":"Dolen Enevets",
    "wof:placetype":"locality"
},
  "geometry": {"coordinates":[25.56667,42.93333],"type":"Point"}
}