{
  "type": "Feature",
  "properties": {
    "gn:admin1_code":"63",
    "gn:admin2_code":"VID22",
    "gn:asciiname":"Golemanovo",
    "gn:cc2":"BG",
    "gn:country_code":"BG",
    "gn:dem":299,
    "gn:feature_class":"P",
    "gn:feature_code":"PPL",
    "gn:name":"Golemanovo",
    "gn:population":0,
    "gn:timezone":"Europe/Sofia",
    "iso:country":"BG",
    "name:bul_x_preferred":[
        "\u0413\u043e\u043b\u0435\u043c\u0430\u043d\u043e\u0432\u043e"
    ],
    "name:und_x_variant":[
        "Golemanowo",
        "Goljemanovo",
        "Golyemanovo",
        "Golemanovo"
    ],
    "wof:name":"Golemanovo",
    "wof:placetype":"locality"
},
  "geometry": {"coordinates":[22.44611,43.92222],"type":"Point"}
}