{
  "type": "Feature",
  "properties": {
    "gn:admin1_code":"52",
    "gn:admin2_code":"SFO06",
    "gn:asciiname":"Mala Rakovitsa",
    "gn:country_code":"BG",
    "gn:dem":900,
    "gn:feature_class":"P",
    "gn:feature_code":"PPL",
    "gn:name":"Mala Rakovitsa",
    "gn:population":0,
    "gn:timezone":"Europe/Sofia",
    "iso:country":"BG",
    "name:bul_x_preferred":[
        "\u041c\u0430\u043b\u0430 \u0420\u0430\u043a\u043e\u0432\u0438\u0446\u0430"
    ],
    "name:und_x_variant":[
        "Mala Rakovshta",
        "Mala Rakowiza",
        "Mala Rakovitsa"
    ],
    "wof:name":"Mala Rakovitsa",
    "wof:placetype":"locality"
},
  "geometry": {"coordinates":[23.05793,42.72945],"type":"Point"}
}