{
  "type": "Feature",
  "properties": {
    "gn:admin1_code":"41",
    "gn:asciiname":"Dalboki",
    "gn:country_code":"BG",
    "gn:dem":485,
    "gn:feature_class":"P",
    "gn:feature_code":"PPL",
    "gn:name":"Dalboki",
    "gn:population":0,
    "gn:timezone":"Europe/Sofia",
    "iso:country":"BG",
    "name:bul_x_preferred":[
        "\u0414\u044a\u043b\u0431\u043e\u043a\u0438"
    ],
    "name:bul_x_variant":[
        "Dalboki"
    ],
    "name:und_x_variant":[
        "D\u016dlboki"
    ],
    "wof:name":"Dalboki",
    "wof:placetype":"locality"
},
  "geometry": {"coordinates":[24.96667,42.88333],"type":"Point"}
}