{
  "type": "Feature",
  "properties": {
    "gn:admin1_code":"47",
    "gn:admin2_code":"MON04",
    "gn:admin3_code":"MON04-09",
    "gn:asciiname":"Marchevo",
    "gn:country_code":"BG",
    "gn:dem":115,
    "gn:feature_class":"P",
    "gn:feature_code":"PPL",
    "gn:name":"Marchevo",
    "gn:population":0,
    "gn:timezone":"Europe/Sofia",
    "iso:country":"BG",
    "name:bul_x_preferred":[
        "\u041c\u044a\u0440\u0447\u0435\u0432\u043e"
    ],
    "name:bul_x_variant":[
        "Marchevo"
    ],
    "name:und_x_variant":[
        "Golemo M\u0103rtschewo",
        "M\u0103r\u0107evo",
        "Malko M\u0103rtschewo",
        "Merchevo",
        "Martchevo",
        "M\u016drchevo"
    ],
    "wof:name":"Marchevo",
    "wof:placetype":"locality"
},
  "geometry": {"coordinates":[23.3479,43.51373],"type":"Point"}
}