{
  "type": "Feature",
  "properties": {
    "gn:admin1_code":"49",
    "gn:admin2_code":"PER51",
    "gn:asciiname":"Glogovitsa",
    "gn:cc2":"BG",
    "gn:country_code":"BG",
    "gn:dem":768,
    "gn:feature_class":"P",
    "gn:feature_code":"PPL",
    "gn:name":"Glogovitsa",
    "gn:population":0,
    "gn:timezone":"Europe/Sofia",
    "iso:country":"BG",
    "name:bul_x_preferred":[
        "\u0413\u043b\u043e\u0433\u043e\u0432\u0438\u0446\u0430"
    ],
    "name:und_x_variant":[
        "Glogowiza",
        "Glogovitsa"
    ],
    "wof:name":"Glogovitsa",
    "wof:placetype":"locality"
},
  "geometry": {"coordinates":[22.6675,42.79194],"type":"Point"}
}