{
  "type": "Feature",
  "properties": {
    "gn:admin1_code":"51",
    "gn:asciiname":"Krushevo",
    "gn:country_code":"BG",
    "gn:dem":1541,
    "gn:feature_class":"P",
    "gn:feature_code":"PPL",
    "gn:name":"Krushevo",
    "gn:population":0,
    "gn:timezone":"Europe/Sofia",
    "iso:country":"BG",
    "name:bul_x_preferred":[
        "\u041a\u0440\u0443\u0448\u0435\u0432\u043e"
    ],
    "wof:name":"Krushevo",
    "wof:placetype":"locality"
},
  "geometry": {"coordinates":[24.93333,41.75],"type":"Point"}
}