{
  "type": "Feature",
  "properties": {
    "gn:admin1_code":"44",
    "gn:asciiname":"Progres",
    "gn:country_code":"BG",
    "gn:dem":311,
    "gn:feature_class":"P",
    "gn:feature_code":"PPL",
    "gn:name":"Progres",
    "gn:population":0,
    "gn:timezone":"Europe/Sofia",
    "iso:country":"BG",
    "name:bul_x_preferred":[
        "Progres"
    ],
    "name:bul_x_variant":[
        "\u041f\u0440\u043e\u0433\u0440\u0435\u0441"
    ],
    "wof:name":"Progres",
    "wof:placetype":"locality"
},
  "geometry": {"coordinates":[25.4102,41.49453],"type":"Point"}
}