{
  "type": "Feature",
  "properties": {
    "gn:admin1_code":"43",
    "gn:admin2_code":"HKV11",
    "gn:admin3_code":"HKV11-04",
    "gn:asciiname":"Gugutka",
    "gn:country_code":"BG",
    "gn:dem":194,
    "gn:feature_class":"P",
    "gn:feature_code":"PPL",
    "gn:name":"Gugutka",
    "gn:population":0,
    "gn:timezone":"Europe/Sofia",
    "iso:country":"BG",
    "name:bul_x_preferred":[
        "\u0413\u0443\u0433\u0443\u0442\u043a\u0430"
    ],
    "name:und_x_variant":[
        "Arnaut-Kjoj",
        "Anaut-K\u2019oy",
        "Arnaut-K\u2019oy",
        "Gugutka",
        "Gukutka"
    ],
    "wof:name":"Gugutka",
    "wof:placetype":"locality"
},
  "geometry": {"coordinates":[25.92206,41.41683],"type":"Point"}
}