{
  "type": "Feature",
  "properties": {
    "gn:admin1_code":"43",
    "gn:admin2_code":"HKV11",
    "gn:admin3_code":"HKV11-04",
    "gn:asciiname":"Gugutka",
    "gn:country_code":"BG",
    "gn:dem":194,
    "gn:feature_class":"P",
    "gn:feature_code":"PPL",
    "gn:name":"Gugutka",
    "gn:population":0,
    "gn:timezone":"Europe/Sofia",
    "iso:country":"BG",
    "name:bul_x_preferred":[
        "\u0413\u0443\u0433\u0443\u0442\u043a\u0430"
    ],
    "name:ceb_x_preferred":[
        "Gugutka"
    ],
    "name:fas_x_preferred":[
        "\u06af\u0648\u06af\u0648\u062a\u06a9\u0627"
    ],
    "name:kat_x_preferred":[
        "\u10d2\u10e3\u10d2\u10e3\u10e2\u10d9\u10d0"
    ],
    "name:kaz_x_preferred":[
        "\u0413\u0443\u0433\u0443\u0442\u043a\u0430"
    ],
    "name:msa_x_preferred":[
        "Gugutka"
    ],
    "name:pol_x_preferred":[
        "Gugutka"
    ],
    "name:ron_x_preferred":[
        "Gugutka"
    ],
    "name:rus_x_preferred":[
        "\u0413\u0443\u0433\u0443\u0442\u043a\u0430"
    ],
    "name:swe_x_preferred":[
        "Gugutka"
    ],
    "name:ukr_x_preferred":[
        "\u0413\u0443\u0433\u0443\u0442\u043a\u0430"
    ],
    "name:und_x_variant":[
        "Arnaut-Kjoj",
        "Anaut-K\u2019oy",
        "Arnaut-K\u2019oy",
        "Gugutka",
        "Gukutka"
    ],
    "wof:name":"Gugutka",
    "wof:placetype":"locality"
},
  "geometry": {"coordinates":[25.92206,41.41683],"type":"Point"}
}