{
  "type": "Feature",
  "properties": {
    "gn:admin1_code":"45",
    "gn:admin2_code":"KNL31",
    "gn:asciiname":"Lilyach",
    "gn:country_code":"BG",
    "gn:dem":586,
    "gn:feature_class":"P",
    "gn:feature_code":"PPL",
    "gn:name":"Lilyach",
    "gn:population":0,
    "gn:timezone":"Europe/Sofia",
    "iso:country":"BG",
    "name:bul_x_preferred":[
        "\u041b\u0438\u043b\u044f\u0447"
    ],
    "name:fas_x_preferred":[
        "\u0644\u06cc\u0644\u06cc\u0627\u0686"
    ],
    "name:kaz_x_preferred":[
        "\u041b\u0438\u043b\u044f\u0447"
    ],
    "name:ron_x_preferred":[
        "Lileaci"
    ],
    "name:rus_x_preferred":[
        "\u041b\u0438\u043b\u044f\u0447"
    ],
    "name:ukr_x_preferred":[
        "\u041b\u0438\u043b\u044f\u0447"
    ],
    "name:und_x_variant":[
        "Liljatsch",
        "Lilyach"
    ],
    "wof:name":"Lilyach",
    "wof:placetype":"locality"
},
  "geometry": {"coordinates":[22.86701,42.2929],"type":"Point"}
}