{
  "type": "Feature",
  "properties": {
    "gn:admin1_code":"47",
    "gn:admin2_code":"MON29",
    "gn:admin3_code":"MON29-04",
    "gn:asciiname":"Blagovo",
    "gn:cc2":"BG",
    "gn:country_code":"BG",
    "gn:dem":244,
    "gn:feature_class":"P",
    "gn:feature_code":"PPL",
    "gn:name":"Blagovo",
    "gn:population":0,
    "gn:timezone":"Europe/Sofia",
    "iso:country":"BG",
    "name:bul_x_preferred":[
        "\u0411\u043b\u0430\u0433\u043e\u0432\u043e"
    ],
    "name:ceb_x_preferred":[
        "Blagovo"
    ],
    "name:fra_x_preferred":[
        "Blagovo"
    ],
    "name:ron_x_preferred":[
        "Blagovo"
    ],
    "name:rus_x_preferred":[
        "\u0411\u043b\u0430\u0433\u043e\u0432\u043e"
    ],
    "name:swe_x_preferred":[
        "Blagovo"
    ],
    "name:ukr_x_preferred":[
        "\u0411\u043b\u0430\u0433\u043e\u0432\u043e"
    ],
    "name:und_x_variant":[
        "Novo Selo",
        "Nowo Selo"
    ],
    "wof:name":"Blagovo",
    "wof:placetype":"locality"
},
  "geometry": {"coordinates":[23.22056,43.35139],"type":"Point"}
}