{
  "type": "Feature",
  "properties": {
    "gn:admin1_code":"60",
    "gn:admin2_code":"TGV35",
    "gn:admin3_code":"TGV35-05",
    "gn:asciiname":"Bozhurka",
    "gn:cc2":"BG",
    "gn:country_code":"BG",
    "gn:dem":253,
    "gn:feature_class":"P",
    "gn:feature_code":"PPL",
    "gn:name":"Bozhurka",
    "gn:population":0,
    "gn:timezone":"Europe/Sofia",
    "iso:country":"BG",
    "name:bul_x_preferred":[
        "\u0411\u043e\u0436\u0443\u0440\u043a\u0430"
    ],
    "name:und_x_variant":[
        "Orchenlar",
        "Bozhurka"
    ],
    "wof:name":"Bozhurka",
    "wof:placetype":"locality"
},
  "geometry": {"coordinates":[26.48333,43.23333],"type":"Point"}
}