{
  "type": "Feature",
  "properties": {
    "gn:admin1_code":"38",
    "gn:admin2_code":"BLG40",
    "gn:asciiname":"Debrene",
    "gn:country_code":"BG",
    "gn:dem":528,
    "gn:feature_class":"P",
    "gn:feature_code":"PPL",
    "gn:name":"Debrene",
    "gn:population":0,
    "gn:timezone":"Europe/Sofia",
    "iso:country":"BG",
    "name:bul_x_preferred":[
        "\u0414\u0435\u0431\u0440\u0435\u043d\u0435"
    ],
    "wof:name":"Debrene",
    "wof:placetype":"locality"
},
  "geometry": {"coordinates":[23.31667,41.58333],"type":"Point"}
}