{
  "type": "Feature",
  "properties": {
    "gn:admin1_code":"44",
    "gn:asciiname":"Selyanka",
    "gn:country_code":"BG",
    "gn:dem":593,
    "gn:feature_class":"P",
    "gn:feature_code":"PPL",
    "gn:name":"Selyanka",
    "gn:population":0,
    "gn:timezone":"Europe/Sofia",
    "iso:country":"BG",
    "name:bul_x_preferred":[
        "\u0421\u0435\u043b\u044f\u043d\u043a"
    ],
    "name:bul_x_variant":[
        "Selyanka",
        "\u0421\u0435\u043b\u044f\u043d\u043a\u0430"
    ],
    "name:und_x_variant":[
        "Selyank"
    ],
    "wof:name":"Selyanka",
    "wof:placetype":"locality"
},
  "geometry": {"coordinates":[25.20373,41.49079],"type":"Point"}
}