{
  "type": "Feature",
  "properties": {
    "gn:admin1_code":"61",
    "gn:admin2_code":"VAR02",
    "gn:asciiname":"Zornitsa",
    "gn:country_code":"BG",
    "gn:dem":319,
    "gn:feature_class":"P",
    "gn:feature_code":"PPL",
    "gn:name":"Zornitsa",
    "gn:population":0,
    "gn:timezone":"Europe/Sofia",
    "iso:country":"BG",
    "name:bul_x_preferred":[
        "\u0417\u043e\u0440\u043d\u0438\u0446\u0430"
    ],
    "name:und_x_variant":[
        "Doudzha",
        "Sorniza",
        "Zornitsa"
    ],
    "wof:name":"Zornitsa",
    "wof:placetype":"locality"
},
  "geometry": {"coordinates":[27.73201,43.33006],"type":"Point"}
}