{
  "type": "Feature",
  "properties": {
    "iso:country":"BG",
    "name:eng_x_preferred":[
        "\u0418\u043d\u0434\u0443\u0441\u0442\u0440\u0438\u0430\u043b\u043d\u0430 \u0437\u043e\u043d\u0430 \u0422\u0440\u0430\u043a\u0438\u044f"
    ],
    "wof:name":"Trakia Industrial Zone",
    "wof:placetype":"neighbourhood"
},
  "geometry": {"coordinates":[24.78386516864309,42.12045405649894],"type":"Point"}
}