{
  "type": "Feature",
  "properties": {
    "gn:admin1_code":"65",
    "gn:admin2_code":"JAM07",
    "gn:asciiname":"Golyam Dervent",
    "gn:country_code":"BG",
    "gn:dem":365,
    "gn:feature_class":"P",
    "gn:feature_code":"PPL",
    "gn:name":"Golyam Dervent",
    "gn:population":0,
    "gn:timezone":"Europe/Sofia",
    "iso:country":"BG",
    "name:bul_x_preferred":[
        "\u0413\u043e\u043b\u044f\u043c \u0414\u0435\u0440\u0432\u0435\u043d\u0442"
    ],
    "name:und_x_variant":[
        "B\u00f6j\u00fck Dervent",
        "Beuyuk Dervent",
        "Golyam",
        "Golem Derwent",
        "Gol\u011bm Dervent",
        "Golyem-Dervent",
        "Golyam Dervent"
    ],
    "wof:name":"Golyam Dervent",
    "wof:placetype":"locality"
},
  "geometry": {"coordinates":[26.74661,41.98415],"type":"Point"}
}