{
  "type": "Feature",
  "properties": {
    "gn:admin1_code":"41",
    "gn:admin2_code":"GAB35",
    "gn:admin3_code":"GAB35-04",
    "gn:asciiname":"Dolni Marentsi",
    "gn:country_code":"BG",
    "gn:dem":788,
    "gn:feature_class":"P",
    "gn:feature_code":"PPL",
    "gn:name":"Dolni Marentsi",
    "gn:population":0,
    "gn:timezone":"Europe/Sofia",
    "iso:country":"BG",
    "name:bul_x_preferred":[
        "\u0414\u043e\u043b\u043d\u0438 \u041c\u0430\u0440\u0435\u043d\u0446\u0438"
    ],
    "wof:name":"Dolni Marentsi",
    "wof:placetype":"locality"
},
  "geometry": {"coordinates":[25.41667,42.83333],"type":"Point"}
}