{
  "type": "Feature",
  "properties": {
    "gn:admin1_code":"38",
    "gn:admin2_code":"BLG44",
    "gn:admin3_code":"BLG44-07",
    "gn:asciiname":"Polena",
    "gn:country_code":"BG",
    "gn:dem":386,
    "gn:feature_class":"P",
    "gn:feature_code":"PPL",
    "gn:name":"Polena",
    "gn:population":0,
    "gn:timezone":"Europe/Sofia",
    "iso:country":"BG",
    "name:bul_x_preferred":[
        "\u041f\u043e\u043b\u0435\u043d\u0430"
    ],
    "name:und_x_variant":[
        "Dolna Sushitsa",
        "Polena"
    ],
    "wof:name":"Polena",
    "wof:placetype":"locality"
},
  "geometry": {"coordinates":[23.09582,41.83926],"type":"Point"}
}