{
  "type": "Feature",
  "properties": {
    "gn:admin1_code":"40",
    "gn:admin2_code":"DOB15",
    "gn:admin3_code":"DOB15-29",
    "gn:asciiname":"Kotlentsi",
    "gn:country_code":"BG",
    "gn:dem":226,
    "gn:feature_class":"P",
    "gn:feature_code":"PPL",
    "gn:name":"Kotlentsi",
    "gn:population":0,
    "gn:timezone":"Europe/Sofia",
    "iso:country":"BG",
    "name:bul_x_preferred":[
        "\u041a\u043e\u0442\u043b\u0435\u043d\u0446\u0438"
    ],
    "name:ceb_x_preferred":[
        "Kotlenci"
    ],
    "name:fas_x_preferred":[
        "\u06a9\u0648\u062a\u0644\u0646\u062a\u0633\u06cc"
    ],
    "name:kaz_x_preferred":[
        "\u041a\u043e\u0442\u043b\u0435\u043d\u0446\u0438"
    ],
    "name:ron_x_preferred":[
        "Kotlen\u021bi"
    ],
    "name:rus_x_preferred":[
        "\u041a\u043e\u0442\u043b\u0435\u043d\u0446\u0438"
    ],
    "name:swe_x_preferred":[
        "Kotlentsi"
    ],
    "name:ukr_x_preferred":[
        "\u041a\u043e\u0442\u043b\u0435\u043d\u0446\u0456"
    ],
    "name:und_x_variant":[
        "Choschkadem",
        "Khosh Kadem",
        "Bucureni"
    ],
    "wof:name":"Kotlentsi",
    "wof:placetype":"locality"
},
  "geometry": {"coordinates":[27.91862,43.57144],"type":"Point"}
}