{
  "type": "Feature",
  "properties": {
    "gn:admin1_code":"41",
    "gn:admin2_code":"GAB05",
    "gn:asciiname":"Bobevtsi",
    "gn:cc2":"BG",
    "gn:country_code":"BG",
    "gn:dem":367,
    "gn:feature_class":"P",
    "gn:feature_code":"PPL",
    "gn:name":"Bobevtsi",
    "gn:population":0,
    "gn:timezone":"Europe/Sofia",
    "iso:country":"BG",
    "name:bul_x_preferred":[
        "\u0411\u043e\u0431\u0435\u0432\u0446\u0438"
    ],
    "name:und_x_variant":[
        "Kolibi Bobevtsi",
        "Bobevts\u016d",
        "Boevtsi",
        "Bobevtsi"
    ],
    "wof:name":"Bobevtsi",
    "wof:placetype":"locality"
},
  "geometry": {"coordinates":[25.31667,42.95],"type":"Point"}
}