{
  "type": "Feature",
  "properties": {
    "gn:admin1_code":"44",
    "gn:asciiname":"Godomanska Mahala",
    "gn:country_code":"BG",
    "gn:dem":545,
    "gn:feature_class":"P",
    "gn:feature_code":"PPL",
    "gn:name":"Godomanska Mahala",
    "gn:population":0,
    "gn:timezone":"Europe/Sofia",
    "iso:country":"BG",
    "name:bul_x_preferred":[
        "Godomanska Mahala"
    ],
    "name:bul_x_variant":[
        "\u0413\u043e\u0434\u043e\u043c\u0430\u043d\u0441\u043a\u0430 \u041c\u0430\u0445\u0430\u043b\u0430"
    ],
    "name:und_x_variant":[
        "Godomanska Makhala"
    ],
    "wof:name":"Godomanska Mahala",
    "wof:placetype":"locality"
},
  "geometry": {"coordinates":[25.25491,41.32341],"type":"Point"}
}