{
  "type": "Feature",
  "properties": {
    "gn:admin1_code":"63",
    "gn:admin2_code":"VID09",
    "gn:admin3_code":"VID09-32",
    "gn:asciiname":"Mayor Uzunovo",
    "gn:country_code":"BG",
    "gn:dem":96,
    "gn:feature_class":"P",
    "gn:feature_code":"PPL",
    "gn:name":"Mayor Uzunovo",
    "gn:population":0,
    "gn:timezone":"Europe/Sofia",
    "iso:country":"BG",
    "name:bul_x_preferred":[
        "\u041c\u0430\u0439\u043e\u0440 \u0423\u0437\u0443\u043d\u043e\u0432\u043e"
    ],
    "name:und_x_variant":[
        "Khalvadzhi",
        "Major Usunowo",
        "Mayor Uzunovo"
    ],
    "wof:name":"Mayor Uzunovo",
    "wof:placetype":"locality"
},
  "geometry": {"coordinates":[22.82353,44.0731],"type":"Point"}
}