{
  "type": "Feature",
  "properties": {
    "gn:admin1_code":"49",
    "gn:asciiname":"Mahala Polomska",
    "gn:country_code":"BG",
    "gn:dem":1240,
    "gn:feature_class":"P",
    "gn:feature_code":"PPL",
    "gn:name":"Mahala Polomska",
    "gn:population":0,
    "gn:timezone":"Europe/Sofia",
    "iso:country":"BG",
    "name:bul_x_preferred":[
        "\u041c\u0430\u0445\u0430\u043b\u0430 \u041f\u043e\u043b\u043e\u043c\u0441\u043a\u0430"
    ],
    "name:bul_x_variant":[
        "Mahala Polomska"
    ],
    "name:und_x_variant":[
        "Makhala Polomska"
    ],
    "wof:name":"Mahala Polomska",
    "wof:placetype":"locality"
},
  "geometry": {"coordinates":[22.49153,42.68983],"type":"Point"}
}