{
  "type": "Feature",
  "properties": {
    "gn:admin1_code":"62",
    "gn:asciiname":"Bochkovtsi",
    "gn:cc2":"BG",
    "gn:country_code":"BG",
    "gn:dem":618,
    "gn:feature_class":"P",
    "gn:feature_code":"PPL",
    "gn:name":"Bochkovtsi",
    "gn:population":0,
    "gn:timezone":"Europe/Sofia",
    "iso:country":"BG",
    "name:bul_x_preferred":[
        "\u0411\u043e\u0448\u043a\u043e\u0432\u0446\u0438"
    ],
    "name:und_x_variant":[
        "Bochkovts\u016d",
        "Bochkovtsi"
    ],
    "wof:name":"Bochkovtsi",
    "wof:placetype":"locality"
},
  "geometry": {"coordinates":[25.66667,42.83333],"type":"Point"}
}