{
  "type": "Feature",
  "properties": {
    "gn:admin1_code":"56",
    "gn:asciiname":"Kozin Dol",
    "gn:cc2":"BG",
    "gn:country_code":"BG",
    "gn:dem":638,
    "gn:feature_class":"P",
    "gn:feature_code":"PPL",
    "gn:name":"Kozin Dol",
    "gn:population":0,
    "gn:timezone":"Europe/Sofia",
    "iso:country":"BG",
    "name:bul_x_preferred":[
        "\u041a\u043e\u0437\u0438\u043d \u0414\u043e\u043b"
    ],
    "name:und_x_variant":[
        "Kosin-Dol",
        "Kechi Dere",
        "Kozin Dol"
    ],
    "wof:name":"Kozin Dol",
    "wof:placetype":"locality"
},
  "geometry": {"coordinates":[26.08333,42.86667],"type":"Point"}
}