{
  "type": "Feature",
  "properties": {
    "gn:admin1_code":"45",
    "gn:asciiname":"Varoshka Mahala",
    "gn:country_code":"BG",
    "gn:dem":924,
    "gn:feature_class":"P",
    "gn:feature_code":"PPL",
    "gn:name":"Varoshka Mahala",
    "gn:population":0,
    "gn:timezone":"Europe/Sofia",
    "iso:country":"BG",
    "name:bul_x_preferred":[
        "\u0412\u0430\u0440\u043e\u0448\u043a\u0430 \u043c\u0430\u0445\u0430\u043b\u0430"
    ],
    "name:bul_x_variant":[
        "Varoshka Mahala",
        "\u0412\u0430\u0440\u043e\u0448\u043a\u0430 \u041c\u0430\u0445\u0430\u043b\u0430"
    ],
    "name:und_x_variant":[
        "Varoshka Makhala"
    ],
    "wof:name":"Varoshka Mahala",
    "wof:placetype":"locality"
},
  "geometry": {"coordinates":[22.47944,42.2734],"type":"Point"}
}