{
  "type": "Feature",
  "properties": {
    "gn:admin1_code":"58",
    "gn:asciiname":"Mlechanovtsi",
    "gn:cc2":"BG",
    "gn:country_code":"BG",
    "gn:dem":796,
    "gn:feature_class":"P",
    "gn:feature_code":"PPL",
    "gn:name":"Mlechanovtsi",
    "gn:population":0,
    "gn:timezone":"Europe/Sofia",
    "iso:country":"BG",
    "name:bul_x_preferred":[
        "\u041c\u043b\u0435\u0447\u0430\u043d\u043e\u0432\u0446\u0438"
    ],
    "name:und_x_variant":[
        "Mlyechanovtsi",
        "Mlechanovtsi"
    ],
    "wof:name":"Mlechanovtsi",
    "wof:placetype":"locality"
},
  "geometry": {"coordinates":[23.66667,42.56667],"type":"Point"}
}