{
  "type": "Feature",
  "properties": {
    "gn:admin1_code":"57",
    "gn:asciiname":"Selishteto",
    "gn:country_code":"BG",
    "gn:dem":931,
    "gn:feature_class":"P",
    "gn:feature_code":"PPL",
    "gn:name":"Selishteto",
    "gn:population":0,
    "gn:timezone":"Europe/Sofia",
    "iso:country":"BG",
    "name:bul_x_preferred":[
        "Selishteto"
    ],
    "name:bul_x_variant":[
        "\u0421\u0435\u043b\u0438\u0449\u0435\u0442\u043e"
    ],
    "wof:name":"Selishteto",
    "wof:placetype":"locality"
},
  "geometry": {"coordinates":[24.9675,41.42349],"type":"Point"}
}