{
  "type": "Feature",
  "properties": {
    "gn:admin1_code":"58",
    "gn:admin2_code":"SFO16",
    "gn:admin3_code":"SFO16-08",
    "gn:asciiname":"Lipintsi",
    "gn:country_code":"BG",
    "gn:dem":685,
    "gn:feature_class":"P",
    "gn:feature_code":"PPL",
    "gn:name":"Lipintsi",
    "gn:population":0,
    "gn:timezone":"Europe/Sofia",
    "iso:country":"BG",
    "name:bul_x_preferred":[
        "\u041b\u0438\u043f\u0438\u043d\u0446\u0438"
    ],
    "name:und_x_variant":[
        "Lipinzi",
        "Lipints\u016d",
        "Lipintsi"
    ],
    "wof:name":"Lipintsi",
    "wof:placetype":"locality"
},
  "geometry": {"coordinates":[22.86709,43.01247],"type":"Point"}
}