{
  "type": "Feature",
  "properties": {
    "gn:admin1_code":"40",
    "gn:admin2_code":"DOB12",
    "gn:admin3_code":"DOB12-18",
    "gn:asciiname":"Krasen",
    "gn:country_code":"BG",
    "gn:dem":160,
    "gn:feature_class":"P",
    "gn:feature_code":"PPL",
    "gn:name":"Krasen",
    "gn:population":0,
    "gn:timezone":"Europe/Sofia",
    "iso:country":"BG",
    "name:ara_x_preferred":[
        "\u0643\u0627\u0631\u0627\u0644\u064a"
    ],
    "name:bul_x_preferred":[
        "\u041a\u0440\u0430\u0441\u0435\u043d"
    ],
    "name:bul_x_variant":[
        "\u041a\u0430\u0440\u0430\u043b\u0438"
    ],
    "name:fas_x_preferred":[
        "\u06a9\u0627\u0631\u0627\u0644\u06cc"
    ],
    "name:fra_x_preferred":[
        "Famille Karali"
    ],
    "name:kaz_x_preferred":[
        "\u041a\u0430\u0440\u0430\u043b\u0438"
    ],
    "name:pol_x_preferred":[
        "Karali"
    ],
    "name:ron_x_preferred":[
        "Karali"
    ],
    "name:rus_x_preferred":[
        "\u041a\u0430\u0440\u0430\u043b\u0438"
    ],
    "name:ukr_x_preferred":[
        "\u041a\u0430\u0440\u0430\u043b\u0438"
    ],
    "name:und_x_variant":[
        "Carali",
        "Karal\u0103",
        "Kvasen",
        "Karali",
        "Karalii",
        "Krasen",
        "Munidere",
        "Buideri",
        "Bogdaylii",
        "Bogdali",
        "Beloklas"
    ],
    "wof:name":"Krasen",
    "wof:placetype":"locality"
},
  "geometry": {"coordinates":[27.92733,43.83976],"type":"Point"}
}