{
  "type": "Feature",
  "properties": {
    "gn:admin1_code":"40",
    "gn:admin2_code":"DOB27",
    "gn:admin3_code":"DOB27-20",
    "gn:asciiname":"Voynikovo",
    "gn:cc2":"BG",
    "gn:country_code":"BG",
    "gn:dem":223,
    "gn:feature_class":"P",
    "gn:feature_code":"PPL",
    "gn:name":"Voynikovo",
    "gn:population":0,
    "gn:timezone":"Europe/Sofia",
    "iso:country":"BG",
    "name:bul_x_preferred":[
        "\u0412\u043e\u0439\u043d\u0438\u043a\u043e\u0432\u043e"
    ],
    "name:und_x_variant":[
        "Kavurga",
        "Voinikovo",
        "Bej\u00fck Machala",
        "Biuiuk",
        "Voynikovo"
    ],
    "wof:name":"Voynikovo",
    "wof:placetype":"locality"
},
  "geometry": {"coordinates":[27.36667000000001,43.68333],"type":"Point"}
}