{
  "type": "Feature",
  "properties": {
    "gn:admin1_code":"65",
    "gn:admin2_code":"JAM07",
    "gn:admin3_code":"JAM07-17",
    "gn:asciiname":"Razdel",
    "gn:cc2":"BG",
    "gn:country_code":"BG",
    "gn:dem":224,
    "gn:feature_class":"P",
    "gn:feature_code":"PPL",
    "gn:name":"Razdel",
    "gn:population":0,
    "gn:timezone":"Europe/Sofia",
    "iso:country":"BG",
    "name:bul_x_preferred":[
        "\u0420\u0430\u0437\u0434\u0435\u043b"
    ],
    "name:und_x_variant":[
        "Chitalovo",
        "Rasdel",
        "Chatalovo",
        "Razdyel",
        "\u010citalovo",
        "Razdel"
    ],
    "wof:name":"Razdel",
    "wof:placetype":"locality"
},
  "geometry": {"coordinates":[26.65,42.08333],"type":"Point"}
}