{
  "type": "Feature",
  "properties": {
    "gn:admin1_code":"40",
    "gn:admin2_code":"DOB29",
    "gn:admin3_code":"DOB29-06",
    "gn:asciiname":"Staevtsi",
    "gn:country_code":"BG",
    "gn:dem":33,
    "gn:feature_class":"P",
    "gn:feature_code":"PPL",
    "gn:name":"Staevtsi",
    "gn:population":0,
    "gn:timezone":"Europe/Sofia",
    "iso:country":"BG",
    "name:bul_x_preferred":[
        "\u0421\u0442\u0430\u0435\u0432\u0446\u0438"
    ],
    "name:und_x_variant":[
        "Khotalere",
        "Staevci",
        "Hotarele",
        "Staevsti",
        "Kalichior",
        "Kal\u016dkchii",
        "Staevtsi"
    ],
    "wof:name":"Staevtsi",
    "wof:placetype":"locality"
},
  "geometry": {"coordinates":[28.49658,43.68828],"type":"Point"}
}