{
  "type": "Feature",
  "properties": {
    "gn:admin1_code":"45",
    "gn:admin2_code":"KNL31",
    "gn:asciiname":"Tsarvaritsa",
    "gn:country_code":"BG",
    "gn:dem":732,
    "gn:feature_class":"P",
    "gn:feature_code":"PPL",
    "gn:name":"Tsarvaritsa",
    "gn:population":0,
    "gn:timezone":"Europe/Sofia",
    "iso:country":"BG",
    "name:bul_x_preferred":[
        "\u0426\u044a\u0440\u0432\u0430\u0440\u0438\u0446\u0430"
    ],
    "name:bul_x_variant":[
        "Tsarvaritsa"
    ],
    "name:fas_x_preferred":[
        "\u062a\u0633\u0627\u0631\u0648\u0627\u0631\u06cc\u062a\u0633\u0627"
    ],
    "name:kaz_x_preferred":[
        "\u0426\u0435\u0440\u0432\u0430\u0440\u0438\u0446\u0430"
    ],
    "name:ron_x_preferred":[
        "\u021a\u0103rvari\u021ba"
    ],
    "name:rus_x_preferred":[
        "\u0426\u0435\u0440\u0432\u0430\u0440\u0438\u0446\u0430"
    ],
    "name:ukr_x_preferred":[
        "\u0426\u0438\u0440\u0432\u0430\u0440\u0438\u0446\u044f"
    ],
    "name:und_x_variant":[
        "Zarwariza",
        "Crvarica",
        "Ts\u016drvaritsa"
    ],
    "wof:name":"Tsarvaritsa",
    "wof:placetype":"locality"
},
  "geometry": {"coordinates":[22.8307,42.06676],"type":"Point"}
}