{
  "type": "Feature",
  "properties": {
    "gn:admin1_code":"45",
    "gn:asciiname":"Selo",
    "gn:country_code":"BG",
    "gn:dem":1165,
    "gn:feature_class":"P",
    "gn:feature_code":"PPL",
    "gn:name":"Selo",
    "gn:population":0,
    "gn:timezone":"Europe/Sofia",
    "iso:country":"BG",
    "name:bel_x_preferred":[
        "\u0421\u044f\u043b\u043e"
    ],
    "name:bos_x_preferred":[
        "Selo"
    ],
    "name:bul_x_preferred":[
        "\u043c\u0430\u0445\u0430\u043b\u0430 \u0421\u0435\u043b\u043e"
    ],
    "name:bul_x_variant":[
        "Mahala Selo",
        "Selo",
        "\u0421\u0435\u043b\u043e"
    ],
    "name:ceb_x_preferred":[
        "Selo"
    ],
    "name:ces_x_preferred":[
        "Selo"
    ],
    "name:deu_x_preferred":[
        "Selo"
    ],
    "name:fin_x_preferred":[
        "Selo"
    ],
    "name:fra_x_preferred":[
        "Selo"
    ],
    "name:glg_x_preferred":[
        "Selo"
    ],
    "name:hun_x_preferred":[
        "Selo"
    ],
    "name:ido_x_preferred":[
        "Selo"
    ],
    "name:ind_x_preferred":[
        "Selo"
    ],
    "name:nld_x_preferred":[
        "Selo"
    ],
    "name:pol_x_preferred":[
        "Selo"
    ],
    "name:por_x_preferred":[
        "Selo"
    ],
    "name:ron_x_preferred":[
        "Selo"
    ],
    "name:rus_x_preferred":[
        "\u0421\u0435\u043b\u043e"
    ],
    "name:sco_x_preferred":[
        "Selo"
    ],
    "name:slk_x_preferred":[
        "Selo"
    ],
    "name:slv_x_preferred":[
        "Selo"
    ],
    "name:spa_x_preferred":[
        "Sel\u00f3"
    ],
    "name:srp_x_preferred":[
        "\u0421\u0435\u043b\u043e"
    ],
    "name:swe_x_preferred":[
        "Selo"
    ],
    "name:ukr_x_preferred":[
        "\u0421\u0435\u043b\u043e"
    ],
    "name:und_x_variant":[
        "Makhala Selo"
    ],
    "wof:name":"Selo",
    "wof:placetype":"locality"
},
  "geometry": {"coordinates":[22.48985,42.57987],"type":"Point"}
}