{
  "type": "Feature",
  "properties": {
    "gn:admin1_code":"49",
    "gn:admin2_code":"PER08",
    "gn:asciiname":"Zavala",
    "gn:country_code":"BG",
    "gn:dem":1010,
    "gn:feature_class":"P",
    "gn:feature_code":"PPL",
    "gn:name":"Zavala",
    "gn:population":0,
    "gn:timezone":"Europe/Sofia",
    "iso:country":"BG",
    "name:bos_x_preferred":[
        "Zavala"
    ],
    "name:bul_x_preferred":[
        "\u0417\u0430\u0432\u0430\u043b\u0430"
    ],
    "name:ceb_x_preferred":[
        "Zavala"
    ],
    "name:deu_x_preferred":[
        "Zavala"
    ],
    "name:est_x_preferred":[
        "Zavala"
    ],
    "name:fra_x_preferred":[
        "Zavala"
    ],
    "name:hrv_x_preferred":[
        "Zavala"
    ],
    "name:hun_x_preferred":[
        "Zavala"
    ],
    "name:ita_x_preferred":[
        "Zavala"
    ],
    "name:nld_x_preferred":[
        "Zavala"
    ],
    "name:rus_x_preferred":[
        "\u0417\u0430\u0432\u0430\u043b\u0430"
    ],
    "name:slv_x_preferred":[
        "Zavala"
    ],
    "name:spa_x_preferred":[
        "Zavala"
    ],
    "name:srp_x_preferred":[
        "\u0417\u0430\u0432\u0430\u043b\u0430"
    ],
    "name:swe_x_preferred":[
        "Zavala"
    ],
    "name:ukr_x_preferred":[
        "\u0417\u0430\u0432\u0430\u043b\u0430"
    ],
    "name:und_x_variant":[
        "Sawala"
    ],
    "wof:name":"Zavala",
    "wof:placetype":"locality"
},
  "geometry": {"coordinates":[22.79712,42.82505],"type":"Point"}
}