{
  "type": "Feature",
  "properties": {
    "gn:admin1_code":"50",
    "gn:admin2_code":"PVN27",
    "gn:asciiname":"Borislav",
    "gn:cc2":"BG",
    "gn:country_code":"BG",
    "gn:dem":129,
    "gn:feature_class":"P",
    "gn:feature_code":"PPL",
    "gn:name":"Borislav",
    "gn:population":0,
    "gn:timezone":"Europe/Sofia",
    "iso:country":"BG",
    "name:bul_x_preferred":[
        "\u0411\u043e\u0440\u0438\u0441\u043b\u0430\u0432"
    ],
    "name:ces_x_preferred":[
        "Borislav"
    ],
    "name:fra_x_preferred":[
        "Borislav"
    ],
    "name:ita_x_preferred":[
        "Borislav"
    ],
    "name:slv_x_preferred":[
        "Borislav"
    ],
    "name:und_x_variant":[
        "Sm\u016drdekhcha",
        "Borislaw"
    ],
    "wof:name":"Borislav",
    "wof:placetype":"locality"
},
  "geometry": {"coordinates":[24.96667,43.31667],"type":"Point"}
}