{
  "type": "Feature",
  "properties": {
    "gn:admin1_code":"62",
    "gn:asciiname":"Yovkovtsi",
    "gn:cc2":"BG",
    "gn:country_code":"BG",
    "gn:dem":439,
    "gn:feature_class":"P",
    "gn:feature_code":"PPL",
    "gn:name":"Yovkovtsi",
    "gn:population":0,
    "gn:timezone":"Europe/Sofia",
    "iso:country":"BG",
    "name:bul_x_preferred":[
        "\u0419\u043e\u0432\u043a\u043e\u0432\u0446\u0438"
    ],
    "name:und_x_variant":[
        "Evkovts\u016d",
        "Iovkovtsi",
        "Yovkovtsi"
    ],
    "name:zho_x_preferred":[
        "\u7d04\u592b\u79d1\u592b\u9f4a\u6c34\u5eab"
    ],
    "wof:name":"Yovkovtsi",
    "wof:placetype":"locality"
},
  "geometry": {"coordinates":[25.76667,42.95],"type":"Point"}
}