{
  "type": "Feature",
  "properties": {
    "gn:admin1_code":"58",
    "gn:admin2_code":"SFO16",
    "gn:asciiname":"Chorul",
    "gn:country_code":"BG",
    "gn:dem":675,
    "gn:feature_class":"P",
    "gn:feature_code":"PPL",
    "gn:name":"Chorul",
    "gn:population":0,
    "gn:timezone":"Europe/Sofia",
    "iso:country":"BG",
    "name:bul_x_preferred":[
        "\u0427\u043e\u0440\u0443\u043b"
    ],
    "name:fas_x_preferred":[
        "\u0686\u0648\u0631\u0648\u0644"
    ],
    "name:kaz_x_preferred":[
        "\u0427\u043e\u0440\u0443\u043b"
    ],
    "name:ron_x_preferred":[
        "Ciorul"
    ],
    "name:rus_x_preferred":[
        "\u0427\u043e\u0440\u0443\u043b"
    ],
    "name:ukr_x_preferred":[
        "\u0427\u043e\u0440\u0443\u043b"
    ],
    "name:und_x_variant":[
        "Tschorul",
        "Chorul"
    ],
    "wof:name":"Chorul",
    "wof:placetype":"locality"
},
  "geometry": {"coordinates":[22.8635,42.91868],"type":"Point"}
}