{
  "type": "Feature",
  "properties": {
    "gn:admin1_code":"45",
    "gn:admin2_code":"KNL48",
    "gn:asciiname":"Krayni Dol",
    "gn:country_code":"BG",
    "gn:dem":536,
    "gn:feature_class":"P",
    "gn:feature_code":"PPL",
    "gn:name":"Krayni Dol",
    "gn:population":0,
    "gn:timezone":"Europe/Sofia",
    "iso:country":"BG",
    "name:bul_x_preferred":[
        "\u041a\u0440\u0430\u0439\u043d\u0438 \u0434\u043e\u043b"
    ],
    "name:bul_x_variant":[
        "\u041a\u0440\u0430\u0439\u043d\u0438 \u0414\u043e\u043b"
    ],
    "name:und_x_variant":[
        "Kraini Dol",
        "Krayni Dol"
    ],
    "wof:name":"Krayni Dol",
    "wof:placetype":"locality"
},
  "geometry": {"coordinates":[23.08872,42.19852],"type":"Point"}
}