{
  "type": "Feature",
  "properties": {
    "gn:admin1_code":"63",
    "gn:admin2_code":"VID16",
    "gn:asciiname":"Kostichovtsi",
    "gn:cc2":"BG",
    "gn:country_code":"BG",
    "gn:dem":253,
    "gn:feature_class":"P",
    "gn:feature_code":"PPL",
    "gn:name":"Kostichovtsi",
    "gn:population":0,
    "gn:timezone":"Europe/Sofia",
    "iso:country":"BG",
    "name:bul_x_preferred":[
        "\u041a\u043e\u0441\u0442\u0438\u0447\u043e\u0432\u0446\u0438"
    ],
    "name:und_x_variant":[
        "Kostitschowzi",
        "Kostichovtsi"
    ],
    "wof:name":"Kostichovtsi",
    "wof:placetype":"locality"
},
  "geometry": {"coordinates":[22.77917,43.71528],"type":"Point"}
}