{
  "type": "Feature",
  "properties": {
    "gn:admin1_code":"45",
    "gn:asciiname":"Ridare Mahala",
    "gn:country_code":"BG",
    "gn:dem":1014,
    "gn:feature_class":"P",
    "gn:feature_code":"PPL",
    "gn:name":"Ridare Mahala",
    "gn:population":0,
    "gn:timezone":"Europe/Sofia",
    "iso:country":"BG",
    "name:bul_x_preferred":[
        "\u0420\u0438\u0434\u0430\u0440\u0435"
    ],
    "name:bul_x_variant":[
        "Ridare Mahala",
        "\u0420\u0438\u0434\u0430\u0440\u0435 \u041c\u0430\u0445\u0430\u043b\u0430"
    ],
    "name:und_x_variant":[
        "Ridare Makhala"
    ],
    "wof:name":"Ridare Mahala",
    "wof:placetype":"locality"
},
  "geometry": {"coordinates":[22.45167,42.28778],"type":"Point"}
}