{
  "type": "Feature",
  "properties": {
    "gn:admin1_code":"42",
    "gn:admin2_code":"SFO06",
    "gn:admin3_code":"SFO06-01",
    "gn:asciiname":"Gurmazovo",
    "gn:country_code":"BG",
    "gn:dem":655,
    "gn:feature_class":"P",
    "gn:feature_code":"PPL",
    "gn:name":"Gurmazovo",
    "gn:population":0,
    "gn:timezone":"Europe/Sofia",
    "iso:country":"BG",
    "name:bul_x_preferred":[
        "\u0413\u0443\u0440\u043c\u0430\u0437\u043e\u0432\u043e"
    ],
    "name:und_x_variant":[
        "Gurmasowo",
        "Gurmazovo"
    ],
    "wof:name":"Gurmazovo",
    "wof:placetype":"locality"
},
  "geometry": {"coordinates":[23.16667,42.73333],"type":"Point"}
}