{
  "type": "Feature",
  "properties": {
    "gn:admin1_code":"41",
    "gn:admin2_code":"GAB29",
    "gn:admin3_code":"GAB29-26",
    "gn:asciiname":"Stokite",
    "gn:cc2":"BG",
    "gn:country_code":"BG",
    "gn:dem":489,
    "gn:feature_class":"P",
    "gn:feature_code":"PPL",
    "gn:name":"Stokite",
    "gn:population":0,
    "gn:timezone":"Europe/Sofia",
    "iso:country":"BG",
    "name:ara_x_preferred":[
        "\u0633\u062a\u0648\u0643\u0627\u064a\u062a"
    ],
    "name:bul_x_preferred":[
        "\u0421\u0442\u043e\u043a\u0438\u0442\u0435"
    ],
    "name:ceb_x_preferred":[
        "Stokite"
    ],
    "name:fas_x_preferred":[
        "\u0633\u062a\u0648\u06a9\u06cc\u062a\u0647"
    ],
    "name:kaz_x_preferred":[
        "\u0421\u0442\u043e\u043a\u0438\u0442\u0435"
    ],
    "name:pol_x_preferred":[
        "Stokite"
    ],
    "name:ron_x_preferred":[
        "Stokite"
    ],
    "name:rus_x_preferred":[
        "\u0421\u0442\u043e\u043a\u0438\u0442\u0435"
    ],
    "name:swe_x_preferred":[
        "Stokite"
    ],
    "name:ukr_x_preferred":[
        "\u0421\u0442\u043e\u043a\u0438\u0442\u0435"
    ],
    "name:und_x_variant":[
        "Selishteto",
        "Stoki",
        "Stokito",
        "Stokitye",
        "Stokite"
    ],
    "wof:name":"Stokite",
    "wof:placetype":"locality"
},
  "geometry": {"coordinates":[25.06667,42.86667],"type":"Point"}
}