{
  "type": "Feature",
  "properties": {
    "gn:admin1_code":"57",
    "gn:asciiname":"Sadakovtsi",
    "gn:country_code":"BG",
    "gn:dem":1277,
    "gn:feature_class":"P",
    "gn:feature_code":"PPL",
    "gn:name":"Sadakovtsi",
    "gn:population":0,
    "gn:timezone":"Europe/Sofia",
    "iso:country":"BG",
    "name:bul_x_preferred":[
        "\u0421\u0430\u0434\u044a\u043a\u043e\u0432\u0446\u0438"
    ],
    "name:bul_x_variant":[
        "Sadakovtsi"
    ],
    "name:und_x_variant":[
        "Sad\u016dkovtsi"
    ],
    "wof:name":"Sadakovtsi",
    "wof:placetype":"locality"
},
  "geometry": {"coordinates":[24.83333,41.65],"type":"Point"}
}