{
  "type": "Feature",
  "properties": {
    "gn:admin1_code":"60",
    "gn:asciiname":"Bozhitsa",
    "gn:cc2":"BG",
    "gn:country_code":"BG",
    "gn:dem":448,
    "gn:feature_class":"P",
    "gn:feature_code":"PPL",
    "gn:name":"Bozhitsa",
    "gn:population":0,
    "gn:timezone":"Europe/Sofia",
    "iso:country":"BG",
    "name:bul_x_preferred":[
        "\u0411\u043e\u0436\u0438\u0446\u0430"
    ],
    "name:und_x_variant":[
        "Khoranlari",
        "Boshiza",
        "Bozhitsa"
    ],
    "wof:name":"Bozhitsa",
    "wof:placetype":"locality"
},
  "geometry": {"coordinates":[26.25,43.13333],"type":"Point"}
}