{
  "type": "Feature",
  "properties": {
    "gn:admin1_code":"40",
    "gn:admin2_code":"DOB03",
    "gn:asciiname":"Prespa",
    "gn:country_code":"BG",
    "gn:dem":249,
    "gn:feature_class":"P",
    "gn:feature_code":"PPL",
    "gn:name":"Prespa",
    "gn:population":0,
    "gn:timezone":"Europe/Sofia",
    "iso:country":"BG",
    "name:bul_x_preferred":[
        "\u041f\u0440\u0435\u0441\u043f\u0430"
    ],
    "name:und_x_variant":[
        "Karla Bay",
        "Carlabeichioi",
        "Pryespa",
        "Carabeichioi",
        "Prespa"
    ],
    "wof:name":"Prespa",
    "wof:placetype":"locality"
},
  "geometry": {"coordinates":[28.0379,43.55427],"type":"Point"}
}