{
  "type": "Feature",
  "properties": {
    "gn:admin1_code":"60",
    "gn:admin2_code":"TGV02",
    "gn:asciiname":"Stara Rechka",
    "gn:cc2":"BG",
    "gn:country_code":"BG",
    "gn:dem":171,
    "gn:feature_class":"P",
    "gn:feature_code":"PPL",
    "gn:name":"Stara Rechka",
    "gn:population":0,
    "gn:timezone":"Europe/Sofia",
    "iso:country":"BG",
    "name:bul_x_preferred":[
        "\u0421\u0442\u0430\u0440\u0430 \u0420\u0435\u0447\u043a\u0430"
    ],
    "name:und_x_variant":[
        "Avlankioi",
        "Stara Retschka",
        "Avlan K\u2019oy",
        "Stara Rechka"
    ],
    "wof:name":"Stara Rechka",
    "wof:placetype":"locality"
},
  "geometry": {"coordinates":[26.08333,43.08333],"type":"Point"}
}