{
  "type": "Feature",
  "properties": {
    "gn:admin1_code":"51",
    "gn:asciiname":"Srebroto",
    "gn:country_code":"BG",
    "gn:dem":1354,
    "gn:feature_class":"P",
    "gn:feature_code":"PPL",
    "gn:name":"Srebroto",
    "gn:population":0,
    "gn:timezone":"Europe/Sofia",
    "iso:country":"BG",
    "name:bul_x_preferred":[
        "\u0421\u0440\u0435\u0431\u0440\u043e\u0442\u043e"
    ],
    "wof:name":"Srebroto",
    "wof:placetype":"locality"
},
  "geometry": {"coordinates":[24.83333,41.75],"type":"Point"}
}