{
  "type": "Feature",
  "properties": {
    "gn:admin1_code":"60",
    "gn:admin2_code":"TGV02",
    "gn:asciiname":"Malka Cherkovna",
    "gn:cc2":"BG",
    "gn:country_code":"BG",
    "gn:dem":420,
    "gn:feature_class":"P",
    "gn:feature_code":"PPL",
    "gn:name":"Malka Cherkovna",
    "gn:population":0,
    "gn:timezone":"Europe/Sofia",
    "iso:country":"BG",
    "name:bul_x_preferred":[
        "\u041c\u0430\u043b\u043a\u0430 \u0427\u0435\u0440\u043a\u043e\u0432\u043d\u0430"
    ],
    "name:und_x_variant":[
        "Chikr\u016dkchilari",
        "Malka Tscherkowna",
        "Chekrikcheler",
        "Malka Cherkovna"
    ],
    "wof:name":"Malka Cherkovna",
    "wof:placetype":"locality"
},
  "geometry": {"coordinates":[26.18333,43.08333],"type":"Point"}
}