{
  "type": "Feature",
  "properties": {
    "gn:admin1_code":"59",
    "gn:admin2_code":"SZR04",
    "gn:asciiname":"Pravoslav",
    "gn:cc2":"BG",
    "gn:country_code":"BG",
    "gn:dem":264,
    "gn:feature_class":"P",
    "gn:feature_code":"PPL",
    "gn:name":"Pravoslav",
    "gn:population":0,
    "gn:timezone":"Europe/Sofia",
    "iso:country":"BG",
    "name:bul_x_preferred":[
        "\u041f\u0440\u0430\u0432\u043e\u0441\u043b\u0430\u0432"
    ],
    "name:und_x_variant":[
        "Misilim",
        "Pravoslaven",
        "Misilii",
        "Prawoslawen",
        "Pravoslav"
    ],
    "wof:name":"Pravoslav",
    "wof:placetype":"locality"
},
  "geometry": {"coordinates":[25.15,42.33333],"type":"Point"}
}