{
  "type": "Feature",
  "properties": {
    "gn:admin1_code":"62",
    "gn:admin2_code":"VTR28",
    "gn:admin3_code":"VTR28-01",
    "gn:asciiname":"Alekovo",
    "gn:cc2":"BG",
    "gn:country_code":"BG",
    "gn:dem":70,
    "gn:feature_class":"P",
    "gn:feature_code":"PPL",
    "gn:name":"Alekovo",
    "gn:population":0,
    "gn:timezone":"Europe/Sofia",
    "iso:country":"BG",
    "name:bul_x_preferred":[
        "\u0410\u043b\u0435\u043a\u043e\u0432\u043e"
    ],
    "name:und_x_variant":[
        "Ak\u010dar",
        "Akchar",
        "Aktchar",
        "Akchayar",
        "Akchaer",
        "Alekowo",
        "Alekovo"
    ],
    "wof:name":"Alekovo",
    "wof:placetype":"locality"
},
  "geometry": {"coordinates":[25.41667,43.46667],"type":"Point"}
}