{
  "type": "Feature",
  "properties": {
    "gn:admin1_code":"46",
    "gn:admin2_code":"LOV18",
    "gn:admin3_code":"LOV18-15",
    "gn:asciiname":"Kazachevo",
    "gn:cc2":"BG",
    "gn:country_code":"BG",
    "gn:dem":225,
    "gn:feature_class":"P",
    "gn:feature_code":"PPL",
    "gn:name":"Kazachevo",
    "gn:population":0,
    "gn:timezone":"Europe/Sofia",
    "iso:country":"BG",
    "name:bul_x_preferred":[
        "\u041a\u0430\u0437\u0430\u0447\u0435\u0432\u043e"
    ],
    "name:ceb_x_preferred":[
        "Kazachevo"
    ],
    "name:fas_x_preferred":[
        "\u06a9\u0627\u0632\u0627\u0686\u0648\u0648"
    ],
    "name:kaz_x_preferred":[
        "\u041a\u0430\u0437\u0430\u0447\u0435\u0432\u043e"
    ],
    "name:pol_x_preferred":[
        "Kazaczewo"
    ],
    "name:ron_x_preferred":[
        "Kazacevo"
    ],
    "name:rus_x_preferred":[
        "\u041a\u0430\u0437\u0430\u0447\u0435\u0432\u043e"
    ],
    "name:swe_x_preferred":[
        "Kazatjevo"
    ],
    "name:ukr_x_preferred":[
        "\u041a\u0430\u0437\u0430\u0447\u0435\u0432\u043e"
    ],
    "name:und_x_variant":[
        "Tatareto",
        "Kaza\u010devo",
        "Tatarito",
        "Kasatschewo"
    ],
    "wof:name":"Kazachevo",
    "wof:placetype":"locality"
},
  "geometry": {"coordinates":[24.75,43.08333],"type":"Point"}
}