{
  "type": "Feature",
  "properties": {
    "gn:admin1_code":"44",
    "gn:asciiname":"Katino",
    "gn:country_code":"BG",
    "gn:dem":395,
    "gn:feature_class":"P",
    "gn:feature_code":"PPL",
    "gn:name":"Katino",
    "gn:population":0,
    "gn:timezone":"Europe/Sofia",
    "iso:country":"BG",
    "name:bul_x_preferred":[
        "\u041a\u044a\u0442\u0438\u043d\u043e"
    ],
    "name:bul_x_variant":[
        "Katino"
    ],
    "name:und_x_variant":[
        "Egri-Budzhak",
        "K\u0103tino",
        "K\u016dtino"
    ],
    "wof:name":"Katino",
    "wof:placetype":"locality"
},
  "geometry": {"coordinates":[25.16667,41.68333],"type":"Point"}
}