{
  "type": "Feature",
  "properties": {
    "gn:admin1_code":"38",
    "gn:asciiname":"Demichina Mahala",
    "gn:country_code":"BG",
    "gn:dem":378,
    "gn:feature_class":"P",
    "gn:feature_code":"PPL",
    "gn:name":"Demichina Mahala",
    "gn:population":0,
    "gn:timezone":"Europe/Sofia",
    "iso:country":"BG",
    "name:bul_x_preferred":[
        "\u0414\u0435\u043c\u0438\u0447\u0438\u043d\u0430 \u043c\u0430\u0445\u0430\u043b\u0430"
    ],
    "name:bul_x_variant":[
        "Demichina Mahala"
    ],
    "name:und_x_variant":[
        "Demichina Makhala"
    ],
    "wof:name":"Demichina Mahala",
    "wof:placetype":"locality"
},
  "geometry": {"coordinates":[23.13333,41.88333],"type":"Point"}
}