{
  "type": "Feature",
  "properties": {
    "gn:admin1_code":"53",
    "gn:admin2_code":"RSE03",
    "gn:admin3_code":"RSE03-01",
    "gn:asciiname":"Batin",
    "gn:country_code":"BG",
    "gn:dem":71,
    "gn:feature_class":"P",
    "gn:feature_code":"PPL",
    "gn:name":"Batin",
    "gn:population":0,
    "gn:timezone":"Europe/Sofia",
    "iso:country":"BG",
    "name:bul_x_preferred":[
        "\u0411\u0430\u0442\u0438\u043d"
    ],
    "name:ceb_x_preferred":[
        "Batin"
    ],
    "name:deu_x_preferred":[
        "Batin"
    ],
    "name:ita_x_preferred":[
        "Batin"
    ],
    "name:rus_x_preferred":[
        "\u0411\u0430\u0442\u0438\u043d"
    ],
    "name:swe_x_preferred":[
        "Batin"
    ],
    "wof:name":"Batin",
    "wof:placetype":"locality"
},
  "geometry": {"coordinates":[25.67785,43.6581],"type":"Point"}
}