{
  "type": "Feature",
  "properties": {
    "gn:admin1_code":"57",
    "gn:admin2_code":"SML18",
    "gn:asciiname":"Tanka Bara",
    "gn:country_code":"BG",
    "gn:dem":665,
    "gn:feature_class":"P",
    "gn:feature_code":"PPL",
    "gn:name":"Tanka Bara",
    "gn:population":0,
    "gn:timezone":"Europe/Sofia",
    "iso:country":"BG",
    "name:bul_x_preferred":[
        "\u0422\u044a\u043d\u043a\u0430 \u0411\u0430\u0440\u0430"
    ],
    "name:bul_x_variant":[
        "Tanka Bara"
    ],
    "name:und_x_variant":[
        "T\u016dnka Bara"
    ],
    "wof:name":"Tanka Bara",
    "wof:placetype":"locality"
},
  "geometry": {"coordinates":[25.14374,41.47321],"type":"Point"}
}