{
  "type": "Feature",
  "properties": {
    "gn:admin1_code":"45",
    "gn:asciiname":"Kosharinska",
    "gn:country_code":"BG",
    "gn:dem":961,
    "gn:feature_class":"P",
    "gn:feature_code":"PPL",
    "gn:name":"Kosharinska",
    "gn:population":0,
    "gn:timezone":"Europe/Sofia",
    "iso:country":"BG",
    "name:bul_x_preferred":[
        "\u041a\u043e\u0448\u0430\u0440\u0438\u043d\u0441\u043a\u0430"
    ],
    "wof:name":"Kosharinska",
    "wof:placetype":"locality"
},
  "geometry": {"coordinates":[22.46666,42.30323],"type":"Point"}
}