{
  "type": "Feature",
  "properties": {
    "gn:admin1_code":"44",
    "gn:asciiname":"Kremenik",
    "gn:country_code":"BG",
    "gn:dem":342,
    "gn:feature_class":"P",
    "gn:feature_code":"PPL",
    "gn:name":"Kremenik",
    "gn:population":0,
    "gn:timezone":"Europe/Sofia",
    "iso:country":"BG",
    "name:bos_x_preferred":[
        "Kremenik"
    ],
    "name:bul_x_preferred":[
        "Kremenik"
    ],
    "name:bul_x_variant":[
        "\u041a\u0440\u0435\u043c\u0435\u043d\u0438\u043a"
    ],
    "name:hrv_x_preferred":[
        "Kremenik"
    ],
    "name:nld_x_preferred":[
        "Kremenik"
    ],
    "name:pol_x_preferred":[
        "Kremenik"
    ],
    "name:ron_x_preferred":[
        "Kremenik"
    ],
    "name:slv_x_preferred":[
        "Kremenik"
    ],
    "name:ukr_x_preferred":[
        "\u041a\u0440\u0435\u043c\u0435\u043d\u0438\u043a"
    ],
    "wof:name":"Kremenik",
    "wof:placetype":"locality"
},
  "geometry": {"coordinates":[25.63423,41.43294],"type":"Point"}
}