{
  "type": "Feature",
  "properties": {
    "gn:admin1_code":"40",
    "gn:asciiname":"Lyaskovo",
    "gn:country_code":"BG",
    "gn:dem":209,
    "gn:feature_class":"P",
    "gn:feature_code":"PPL",
    "gn:name":"Lyaskovo",
    "gn:population":0,
    "gn:timezone":"Europe/Sofia",
    "iso:country":"BG",
    "name:bul_x_preferred":[
        "\u041b\u0435\u0441\u043a\u043e\u0432\u043e"
    ],
    "name:bul_x_variant":[
        "Lyaskovo",
        "\u041b\u044f\u0441\u043a\u043e\u0432\u043e"
    ],
    "name:und_x_variant":[
        "F\u00e2ndacli",
        "F\u016dndaklii",
        "Leskovo"
    ],
    "wof:name":"Lyaskovo",
    "wof:placetype":"locality"
},
  "geometry": {"coordinates":[27.68676,43.71769000000001],"type":"Point"}
}