{
  "type": "Feature",
  "properties": {
    "gn:admin1_code":"45",
    "gn:admin2_code":"KNL29",
    "gn:admin3_code":"KNL29-40",
    "gn:asciiname":"Sovolyano",
    "gn:cc2":"BG",
    "gn:country_code":"BG",
    "gn:dem":550,
    "gn:feature_class":"P",
    "gn:feature_code":"PPL",
    "gn:name":"Sovolyano",
    "gn:population":0,
    "gn:timezone":"Europe/Sofia",
    "iso:country":"BG",
    "name:bul_x_preferred":[
        "\u0421\u043e\u0432\u043e\u043b\u044f\u043d\u043e\u0432\u043e"
    ],
    "name:bul_x_variant":[
        "\u0421\u043e\u0432\u043e\u043b\u044f\u043d\u043e"
    ],
    "name:fas_x_preferred":[
        "\u0633\u0648\u0648\u0648\u0644\u06cc\u0627\u0646\u0648"
    ],
    "name:kaz_x_preferred":[
        "\u0421\u043e\u0432\u043e\u043b\u044f\u043d\u043e"
    ],
    "name:ron_x_preferred":[
        "Sovoleano"
    ],
    "name:rus_x_preferred":[
        "\u0421\u043e\u0432\u043e\u043b\u044f\u043d\u043e"
    ],
    "name:ukr_x_preferred":[
        "\u0421\u043e\u0432\u043e\u043b\u044f\u043d\u043e"
    ],
    "name:und_x_variant":[
        "Sovoljano",
        "Sowoljano",
        "Sabolino",
        "Savoljano",
        "Sovolyano"
    ],
    "wof:name":"Sovolyano",
    "wof:placetype":"locality"
},
  "geometry": {"coordinates":[22.66028,42.33111],"type":"Point"}
}