{
  "type": "Feature",
  "properties": {
    "gn:admin1_code":"49",
    "gn:admin2_code":"PER51",
    "gn:asciiname":"Zabel",
    "gn:country_code":"BG",
    "gn:dem":845,
    "gn:feature_class":"P",
    "gn:feature_code":"PPL",
    "gn:name":"Zabel",
    "gn:population":0,
    "gn:timezone":"Europe/Sofia",
    "iso:country":"BG",
    "name:bul_x_preferred":[
        "\u0417\u0430\u0431\u0435\u043b"
    ],
    "name:und_x_variant":[
        "Sabol",
        "Zabyel",
        "Zabel"
    ],
    "wof:name":"Zabel",
    "wof:placetype":"locality"
},
  "geometry": {"coordinates":[22.58347,42.83293],"type":"Point"}
}