{
  "type": "Feature",
  "properties": {
    "gn:admin1_code":"54",
    "gn:admin2_code":"SHU11",
    "gn:admin3_code":"SHU11-20",
    "gn:asciiname":"Cherna",
    "gn:cc2":"BG",
    "gn:country_code":"BG",
    "gn:dem":405,
    "gn:feature_class":"P",
    "gn:feature_code":"PPL",
    "gn:name":"Cherna",
    "gn:population":0,
    "gn:timezone":"Europe/Sofia",
    "iso:country":"BG",
    "name:bul_x_preferred":[
        "\u0427\u0435\u0440\u043d\u0430"
    ],
    "name:und_x_variant":[
        "Karalar",
        "Tscherna",
        "Chorna",
        "Cherna"
    ],
    "wof:name":"Cherna",
    "wof:placetype":"locality"
},
  "geometry": {"coordinates":[26.88333,43.46667],"type":"Point"}
}