{
  "type": "Feature",
  "properties": {
    "gn:admin1_code":"38",
    "gn:asciiname":"Bogdantsi",
    "gn:country_code":"BG",
    "gn:dem":984,
    "gn:feature_class":"P",
    "gn:feature_code":"PPL",
    "gn:name":"Bogdantsi",
    "gn:population":0,
    "gn:timezone":"Europe/Sofia",
    "iso:country":"BG",
    "name:bul_x_preferred":[
        "Bogdantsi"
    ],
    "name:bul_x_variant":[
        "\u0411\u043e\u0433\u0434\u0430\u043d\u0446\u0438"
    ],
    "wof:name":"Bogdantsi",
    "wof:placetype":"locality"
},
  "geometry": {"coordinates":[22.9385,41.87984],"type":"Point"}
}