{
  "type": "Feature",
  "properties": {
    "gn:admin1_code":"38",
    "gn:asciiname":"Rolevtsi",
    "gn:country_code":"BG",
    "gn:dem":703,
    "gn:feature_class":"P",
    "gn:feature_code":"PPL",
    "gn:name":"Rolevtsi",
    "gn:population":0,
    "gn:timezone":"Europe/Sofia",
    "iso:country":"BG",
    "name:bul_x_preferred":[
        "Rolevtsi"
    ],
    "name:bul_x_variant":[
        "\u0420\u043e\u043b\u0435\u0432\u0446\u0438"
    ],
    "wof:name":"Rolevtsi",
    "wof:placetype":"locality"
},
  "geometry": {"coordinates":[22.96526,41.91902],"type":"Point"}
}