{
  "type": "Feature",
  "properties": {
    "gn:admin1_code":"53",
    "gn:admin2_code":"RSE37",
    "gn:admin3_code":"RSE37-04",
    "gn:asciiname":"Dolna Studena",
    "gn:country_code":"BG",
    "gn:dem":34,
    "gn:feature_class":"P",
    "gn:feature_code":"PPL",
    "gn:name":"Dolna Studena",
    "gn:population":0,
    "gn:timezone":"Europe/Sofia",
    "iso:country":"BG",
    "name:bul_x_preferred":[
        "\u0414\u043e\u043b\u043d\u0430 \u0421\u0442\u0443\u0434\u0435\u043d\u0430"
    ],
    "wof:name":"Dolna Studena",
    "wof:placetype":"locality"
},
  "geometry": {"coordinates":[25.69348,43.52859],"type":"Point"}
}