{
  "type": "Feature",
  "properties": {
    "gn:admin1_code":"65",
    "gn:admin2_code":"JAM22",
    "gn:admin3_code":"JAM22-24",
    "gn:asciiname":"Tamarino",
    "gn:cc2":"BG",
    "gn:country_code":"BG",
    "gn:dem":256,
    "gn:feature_class":"P",
    "gn:feature_code":"PPL",
    "gn:name":"Tamarino",
    "gn:population":0,
    "gn:timezone":"Europe/Sofia",
    "iso:country":"BG",
    "name:bul_x_preferred":[
        "\u0422\u0430\u043c\u0430\u0440\u0438\u043d\u043e"
    ],
    "name:und_x_variant":[
        "Tyurkmeni",
        "Tamarino"
    ],
    "wof:name":"Tamarino",
    "wof:placetype":"locality"
},
  "geometry": {"coordinates":[26.75,42.38333],"type":"Point"}
}