{
  "type": "Feature",
  "properties": {
    "gn:admin1_code":"44",
    "gn:asciiname":"Ayvadzhik",
    "gn:country_code":"BG",
    "gn:dem":697,
    "gn:feature_class":"P",
    "gn:feature_code":"PPL",
    "gn:name":"Ayvadzhik",
    "gn:population":0,
    "gn:timezone":"Europe/Sofia",
    "iso:country":"BG",
    "name:bul_x_preferred":[
        "Ayvadzhik"
    ],
    "name:bul_x_variant":[
        "\u0410\u0439\u0432\u0430\u0434\u0436\u0438\u043a"
    ],
    "wof:name":"Ayvadzhik",
    "wof:placetype":"locality"
},
  "geometry": {"coordinates":[25.19645,41.41262],"type":"Point"}
}