{
  "type": "Feature",
  "properties": {
    "gn:admin1_code":"60",
    "gn:admin2_code":"TGV24",
    "gn:admin3_code":"TGV24-10",
    "gn:asciiname":"Dolna Kabda",
    "gn:cc2":"BG",
    "gn:country_code":"BG",
    "gn:dem":335,
    "gn:feature_class":"P",
    "gn:feature_code":"PPL",
    "gn:name":"Dolna Kabda",
    "gn:population":0,
    "gn:timezone":"Europe/Sofia",
    "iso:country":"BG",
    "name:bul_x_preferred":[
        "\u0414\u043e\u043b\u043d\u0430 \u041a\u0430\u0431\u0434\u0430"
    ],
    "name:und_x_variant":[
        "Ashakikabda",
        "Dolna Kabda"
    ],
    "wof:name":"Dolna Kabda",
    "wof:placetype":"locality"
},
  "geometry": {"coordinates":[26.33333,43.23333],"type":"Point"}
}