{
  "type": "Feature",
  "properties": {
    "gn:admin1_code":"44",
    "gn:asciiname":"Plovdina",
    "gn:country_code":"BG",
    "gn:dem":667,
    "gn:feature_class":"P",
    "gn:feature_code":"PPL",
    "gn:name":"Plovdina",
    "gn:population":0,
    "gn:timezone":"Europe/Sofia",
    "iso:country":"BG",
    "name:bul_x_preferred":[
        "Plovdina"
    ],
    "name:bul_x_variant":[
        "\u041f\u043b\u043e\u0432\u0434\u0438\u043d\u0430"
    ],
    "wof:name":"Plovdina",
    "wof:placetype":"locality"
},
  "geometry": {"coordinates":[25.23517,41.48255],"type":"Point"}
}