{
  "type": "Feature",
  "properties": {
    "gn:admin1_code":"47",
    "gn:admin2_code":"MON11",
    "gn:admin3_code":"MON11-09",
    "gn:asciiname":"Razgrad",
    "gn:country_code":"BG",
    "gn:dem":87,
    "gn:feature_class":"P",
    "gn:feature_code":"PPL",
    "gn:name":"Razgrad",
    "gn:population":0,
    "gn:timezone":"Europe/Sofia",
    "iso:country":"BG",
    "name:ara_x_preferred":[
        "\u0631\u0627\u0632\u063a\u0631\u0627\u062f"
    ],
    "name:azb_x_preferred":[
        "\u0631\u0627\u0632\u06af\u0631\u0627\u062f"
    ],
    "name:bak_x_preferred":[
        "\u0420\u0430\u0437\u0433\u0440\u0430\u0434"
    ],
    "name:bel_x_preferred":[
        "\u0420\u0430\u0437\u0433\u0440\u0430\u0434"
    ],
    "name:bul_x_preferred":[
        "\u0420\u0430\u0437\u0433\u0440\u0430\u0434"
    ],
    "name:cat_x_preferred":[
        "R\u00e0zgrad"
    ],
    "name:ceb_x_preferred":[
        "Razgrad"
    ],
    "name:ces_x_preferred":[
        "Razgrad"
    ],
    "name:chu_x_preferred":[
        "\u0420\u0430\ua641\u0433\u0440\u0430\u0434\u044a"
    ],
    "name:dan_x_preferred":[
        "Razgrad"
    ],
    "name:deu_x_preferred":[
        "Rasgrad"
    ],
    "name:ell_x_preferred":[
        "\u03a1\u03b1\u03b6\u03b3\u03ba\u03c1\u03ac\u03bd\u03c4"
    ],
    "name:epo_x_preferred":[
        "Razgrad"
    ],
    "name:fas_x_preferred":[
        "\u0631\u0627\u0632\u06af\u0631\u0627\u062f"
    ],
    "name:fin_x_preferred":[
        "Razgrad"
    ],
    "name:fra_x_preferred":[
        "Razgrad"
    ],
    "name:frr_x_preferred":[
        "Rasgrad"
    ],
    "name:heb_x_preferred":[
        "\u05e8\u05d0\u05d6\u05d2\u05e8\u05d3"
    ],
    "name:hrv_x_preferred":[
        "Razgrad"
    ],
    "name:ile_x_preferred":[
        "Razgrad"
    ],
    "name:jpn_x_preferred":[
        "\u30e9\u30ba\u30b0\u30e9\u30c8"
    ],
    "name:kat_x_preferred":[
        "\u10e0\u10d0\u10d6\u10d2\u10e0\u10d0\u10d3\u10d8"
    ],
    "name:kaz_x_preferred":[
        "\u0420\u0430\u0437\u0433\u0440\u0430\u0434"
    ],
    "name:kor_x_preferred":[
        "\ub77c\uc988\uadf8\ub77c\ub4dc"
    ],
    "name:lit_x_preferred":[
        "Razgradas"
    ],
    "name:mkd_x_preferred":[
        "\u0420\u0430\u0437\u0433\u0440\u0430\u0434"
    ],
    "name:nld_x_preferred":[
        "Razgrad"
    ],
    "name:nor_x_preferred":[
        "Razgrad"
    ],
    "name:oss_x_preferred":[
        "\u0420\u0430\u0437\u0433\u0440\u0430\u0434"
    ],
    "name:pnb_x_preferred":[
        "\u0631\u0627\u0632\u06af\u0631\u0627\u062f"
    ],
    "name:pol_x_preferred":[
        "Razgrad"
    ],
    "name:por_x_preferred":[
        "Razgrad"
    ],
    "name:ron_x_preferred":[
        "Razgrad"
    ],
    "name:rus_x_preferred":[
        "\u0420\u0430\u0437\u0433\u0440\u0430\u0434"
    ],
    "name:slk_x_preferred":[
        "Razgrad"
    ],
    "name:spa_x_preferred":[
        "Razgrad"
    ],
    "name:srp_x_preferred":[
        "\u0420\u0430\u0437\u0433\u0440\u0430\u0434"
    ],
    "name:tur_x_preferred":[
        "Razgrad"
    ],
    "name:ukr_x_preferred":[
        "\u0420\u0430\u0437\u0433\u0440\u0430\u0434"
    ],
    "name:und_x_variant":[
        "Krumovo",
        "Razgrad Makhala",
        "Masgrad Machala",
        "Razgrad"
    ],
    "name:urd_x_preferred":[
        "\u0631\u0627\u0632\u06af\u0631\u0627\u0688"
    ],
    "name:vie_x_preferred":[
        "Razgrad"
    ],
    "name:war_x_preferred":[
        "Razgrad"
    ],
    "name:zho_x_preferred":[
        "\u62c9\u8332\u683c\u52d2"
    ],
    "wof:name":"Razgrad",
    "wof:placetype":"locality"
},
  "geometry": {"coordinates":[23.49719,43.75092],"type":"Point"}
}