{
  "type": "Feature",
  "properties": {
    "gn:admin1_code":"47",
    "gn:admin2_code":"MON11",
    "gn:admin3_code":"MON11-09",
    "gn:asciiname":"Razgrad",
    "gn:country_code":"BG",
    "gn:dem":87,
    "gn:feature_class":"P",
    "gn:feature_code":"PPL",
    "gn:name":"Razgrad",
    "gn:population":0,
    "gn:timezone":"Europe/Sofia",
    "iso:country":"BG",
    "name:bul_x_preferred":[
        "\u0420\u0430\u0437\u0433\u0440\u0430\u0434"
    ],
    "name:und_x_variant":[
        "Krumovo",
        "Razgrad Makhala",
        "Masgrad Machala",
        "Razgrad"
    ],
    "wof:name":"Razgrad",
    "wof:placetype":"locality"
},
  "geometry": {"coordinates":[23.49719,43.75092],"type":"Point"}
}