{
  "type": "Feature",
  "properties": {
    "gn:admin1_code":"49",
    "gn:admin2_code":"PER51",
    "gn:asciiname":"Dalga Luka",
    "gn:country_code":"BG",
    "gn:dem":863,
    "gn:feature_class":"P",
    "gn:feature_code":"PPL",
    "gn:name":"Dalga Luka",
    "gn:population":0,
    "gn:timezone":"Europe/Sofia",
    "iso:country":"BG",
    "name:bul_x_preferred":[
        "\u0414\u044a\u043b\u0433\u0430 \u043b\u044a\u043a\u0430"
    ],
    "name:bul_x_variant":[
        "Dalga Luka",
        "\u0414\u044a\u043b\u0433\u0430 \u041b\u0443\u043a\u0430",
        "\u0414\u044a\u043b\u0433\u0430 \u043b\u0443\u043a\u0430"
    ],
    "name:kaz_x_preferred":[
        "\u0414\u044b\u043b\u0433\u0430-\u041b\u0443\u043a\u0430"
    ],
    "name:ron_x_preferred":[
        "D\u0103lga Luka"
    ],
    "name:rus_x_preferred":[
        "\u0414\u044b\u043b\u0433\u0430-\u041b\u0443\u043a\u0430"
    ],
    "name:ukr_x_preferred":[
        "\u0414\u0438\u043b\u0433\u0430 \u041b\u0443\u043a\u0430"
    ],
    "name:und_x_variant":[
        "D\u016dlga Luka"
    ],
    "wof:name":"Dalga Luka",
    "wof:placetype":"locality"
},
  "geometry": {"coordinates":[22.55524,42.63841],"type":"Point"}
}