{
  "type": "Feature",
  "properties": {
    "gn:admin1_code":"57",
    "gn:asciiname":"Leskovi Kolibi",
    "gn:country_code":"BG",
    "gn:dem":627,
    "gn:feature_class":"P",
    "gn:feature_code":"PPL",
    "gn:name":"Leskovi Kolibi",
    "gn:population":0,
    "gn:timezone":"Europe/Sofia",
    "iso:country":"BG",
    "name:bul_x_preferred":[
        "\u041b\u0435\u0441\u043a\u043e\u0432\u0438 \u041a\u043e\u043b\u0438\u0431\u0438"
    ],
    "wof:name":"Leskovi Kolibi",
    "wof:placetype":"locality"
},
  "geometry": {"coordinates":[25.05262,41.4092],"type":"Point"}
}