{
  "type": "Feature",
  "properties": {
    "gn:admin1_code":"41",
    "gn:admin2_code":"GAB05",
    "gn:asciiname":"Petrovtsi",
    "gn:cc2":"BG",
    "gn:country_code":"BG",
    "gn:dem":332,
    "gn:feature_class":"P",
    "gn:feature_code":"PPL",
    "gn:name":"Petrovtsi",
    "gn:population":0,
    "gn:timezone":"Europe/Sofia",
    "iso:country":"BG",
    "name:ara_x_preferred":[
        "\u0628\u064a\u062a\u0631\u0648\u0641\u062a\u0633\u064a"
    ],
    "name:bul_x_preferred":[
        "\u041f\u0435\u0442\u0440\u043e\u0432\u0446\u0438"
    ],
    "name:fas_x_preferred":[
        "\u067e\u062a\u0631\u0648\u0648\u062a\u0633\u06cc"
    ],
    "name:kaz_x_preferred":[
        "\u041f\u0435\u0442\u0440\u043e\u0432\u0446\u0438"
    ],
    "name:pol_x_preferred":[
        "Petrowci"
    ],
    "name:ron_x_preferred":[
        "Petrov\u021bi"
    ],
    "name:rus_x_preferred":[
        "\u041f\u0435\u0442\u0440\u043e\u0432\u0446\u0438"
    ],
    "name:ukr_x_preferred":[
        "\u041f\u0435\u0442\u0440\u043e\u0432\u0446\u0456"
    ],
    "name:und_x_variant":[
        "Petrowzi",
        "Petrovts\u016d",
        "Petrovtsi"
    ],
    "wof:name":"Petrovtsi",
    "wof:placetype":"locality"
},
  "geometry": {"coordinates":[25.23333,42.91667],"type":"Point"}
}