{
  "type": "Feature",
  "properties": {
    "gn:admin1_code":"38",
    "gn:asciiname":"Yurutsite",
    "gn:country_code":"BG",
    "gn:dem":1054,
    "gn:feature_class":"P",
    "gn:feature_code":"PPL",
    "gn:name":"Yurutsite",
    "gn:population":0,
    "gn:timezone":"Europe/Sofia",
    "iso:country":"BG",
    "name:bul_x_preferred":[
        "Yurutsite"
    ],
    "name:bul_x_variant":[
        "\u042e\u0440\u0443\u0446\u0438\u0442\u0435"
    ],
    "wof:name":"Yurutsite",
    "wof:placetype":"locality"
},
  "geometry": {"coordinates":[22.90395,41.97644],"type":"Point"}
}