{
  "type": "Feature",
  "properties": {
    "gn:admin1_code":"57",
    "gn:asciiname":"Selinska Reka",
    "gn:country_code":"BG",
    "gn:dem":992,
    "gn:feature_class":"P",
    "gn:feature_code":"PPL",
    "gn:name":"Selinska Reka",
    "gn:population":0,
    "gn:timezone":"Europe/Sofia",
    "iso:country":"BG",
    "name:bul_x_preferred":[
        "Selinska Reka"
    ],
    "name:bul_x_variant":[
        "\u0421\u0435\u043b\u0438\u043d\u0441\u043a\u0430 \u0420\u0435\u043a\u0430"
    ],
    "wof:name":"Selinska Reka",
    "wof:placetype":"locality"
},
  "geometry": {"coordinates":[24.66216,41.48063],"type":"Point"}
}