{
  "type": "Feature",
  "properties": {
    "gn:admin1_code":"45",
    "gn:admin2_code":"KNL04",
    "gn:asciiname":"Babinska Reka",
    "gn:country_code":"BG",
    "gn:dem":538,
    "gn:feature_class":"P",
    "gn:feature_code":"PPL",
    "gn:name":"Babinska Reka",
    "gn:population":0,
    "gn:timezone":"Europe/Sofia",
    "iso:country":"BG",
    "name:bul_x_preferred":[
        "\u0411\u0430\u0431\u0438\u043d\u0441\u043a\u0430 \u0440\u0435\u043a\u0430"
    ],
    "name:bul_x_variant":[
        "\u0411\u0430\u0431\u0438\u043d\u0441\u043a\u0430 \u0420\u0435\u043a\u0430"
    ],
    "name:fas_x_preferred":[
        "\u0628\u0627\u0628\u06cc\u0646\u0633\u06a9\u0627 \u0631\u06a9\u0627"
    ],
    "name:kaz_x_preferred":[
        "\u0411\u0430\u0431\u0438\u043d\u0441\u043a\u0430-\u0420\u0435\u043a\u0430"
    ],
    "name:ron_x_preferred":[
        "Babinska Reka"
    ],
    "name:rus_x_preferred":[
        "\u0411\u0430\u0431\u0438\u043d\u0441\u043a\u0430-\u0420\u0435\u043a\u0430"
    ],
    "name:ukr_x_preferred":[
        "\u0411\u0430\u0431\u0438\u043d\u0441\u044c\u043a\u0430 \u0420\u0435\u043a\u0430"
    ],
    "name:und_x_variant":[
        "Makhala Babinska Reka",
        "Babinska",
        "Babinoka Reka",
        "Babinska Reka"
    ],
    "wof:name":"Babinska Reka",
    "wof:placetype":"locality"
},
  "geometry": {"coordinates":[22.99628,42.33032],"type":"Point"}
}