{
  "type": "Feature",
  "properties": {
    "gn:admin1_code":"57",
    "gn:admin2_code":"SML31",
    "gn:admin3_code":"SML31-38",
    "gn:asciiname":"Elenska",
    "gn:cc2":"BG",
    "gn:country_code":"BG",
    "gn:dem":689,
    "gn:feature_class":"P",
    "gn:feature_code":"PPL",
    "gn:name":"Elenska",
    "gn:population":0,
    "gn:timezone":"Europe/Sofia",
    "iso:country":"BG",
    "name:bul_x_preferred":[
        "\u0415\u043b\u0435\u043d\u0441\u043a\u0430"
    ],
    "name:und_x_variant":[
        "Ukhlovitsa",
        "Elenska"
    ],
    "wof:name":"Elenska",
    "wof:placetype":"locality"
},
  "geometry": {"coordinates":[24.88333,41.55],"type":"Point"}
}