{
  "type": "Feature",
  "properties": {
    "gn:admin1_code":"51",
    "gn:admin2_code":"PDV23",
    "gn:admin3_code":"PDV23-02",
    "gn:asciiname":"Byala Reka",
    "gn:cc2":"BG",
    "gn:country_code":"BG",
    "gn:dem":151,
    "gn:feature_class":"P",
    "gn:feature_code":"PPL",
    "gn:name":"Byala Reka",
    "gn:population":0,
    "gn:timezone":"Europe/Sofia",
    "iso:country":"BG",
    "name:bul_x_preferred":[
        "\u0411\u044f\u043b\u0430 \u0440\u0435\u043a\u0430"
    ],
    "name:ceb_x_preferred":[
        "Byala Reka"
    ],
    "name:fra_x_preferred":[
        "Byala reka"
    ],
    "name:pol_x_preferred":[
        "Bja\u0142a reka"
    ],
    "name:ron_x_preferred":[
        "Beala Reka"
    ],
    "name:rus_x_preferred":[
        "\u0411\u044f\u043b\u0430-\u0420\u0435\u043a\u0430"
    ],
    "name:swe_x_preferred":[
        "Byala Reka"
    ],
    "name:und_x_variant":[
        "Bela-Reka",
        "Byela-Ryeka",
        "Chitak"
    ],
    "wof:name":"Byala Reka",
    "wof:placetype":"locality"
},
  "geometry": {"coordinates":[25.26667,42.05],"type":"Point"}
}