{
  "type": "Feature",
  "properties": {
    "gn:admin1_code":"44",
    "gn:asciiname":"Veslets",
    "gn:country_code":"BG",
    "gn:dem":449,
    "gn:feature_class":"P",
    "gn:feature_code":"PPL",
    "gn:name":"Veslets",
    "gn:population":0,
    "gn:timezone":"Europe/Sofia",
    "iso:country":"BG",
    "name:bul_x_preferred":[
        "Veslets"
    ],
    "name:bul_x_variant":[
        "\u0412\u0435\u0441\u043b\u0435\u0446"
    ],
    "wof:name":"Veslets",
    "wof:placetype":"locality"
},
  "geometry": {"coordinates":[25.68975,41.38007],"type":"Point"}
}