{
  "type": "Feature",
  "properties": {
    "gn:admin1_code":"40",
    "gn:admin2_code":"DOB12",
    "gn:asciiname":"Plenimir",
    "gn:country_code":"BG",
    "gn:dem":242,
    "gn:feature_class":"P",
    "gn:feature_code":"PPL",
    "gn:name":"Plenimir",
    "gn:population":0,
    "gn:timezone":"Europe/Sofia",
    "iso:country":"BG",
    "name:bul_x_preferred":[
        "\u041f\u043b\u0435\u043d\u0438\u043c\u0438\u0440"
    ],
    "name:fas_x_preferred":[
        "\u067e\u0644\u0646\u06cc\u0645\u06cc\u0631"
    ],
    "name:kaz_x_preferred":[
        "\u041f\u043b\u0435\u043d\u0438\u043c\u0438\u0440"
    ],
    "name:ron_x_preferred":[
        "Plenimir"
    ],
    "name:rus_x_preferred":[
        "\u041f\u043b\u0435\u043d\u0438\u043c\u0438\u0440"
    ],
    "name:ukr_x_preferred":[
        "\u041f\u043b\u0435\u043d\u0438\u043c\u0438\u0440"
    ],
    "name:und_x_variant":[
        "Salaman",
        "Plenimiv",
        "Salman"
    ],
    "wof:name":"Plenimir",
    "wof:placetype":"locality"
},
  "geometry": {"coordinates":[27.98253,43.65403],"type":"Point"}
}