{
  "type": "Feature",
  "properties": {
    "gn:admin1_code":"44",
    "gn:admin2_code":"KRZ16",
    "gn:admin3_code":"KRZ16-33",
    "gn:asciiname":"Byalka",
    "gn:cc2":"BG",
    "gn:country_code":"BG",
    "gn:dem":373,
    "gn:feature_class":"P",
    "gn:feature_code":"PPL",
    "gn:name":"Byalka",
    "gn:population":0,
    "gn:timezone":"Europe/Sofia",
    "iso:country":"BG",
    "name:bul_x_preferred":[
        "\u0411\u044f\u043b\u043a\u0430"
    ],
    "name:fas_x_preferred":[
        "\u0628\u06cc\u0627\u0644\u06a9\u0627"
    ],
    "name:kat_x_preferred":[
        "\u10d1\u10d8\u10d0\u10da\u10d9\u10d0"
    ],
    "name:kaz_x_preferred":[
        "\u0411\u044f\u043b\u043a\u0430"
    ],
    "name:pol_x_preferred":[
        "Bja\u0142ka"
    ],
    "name:ron_x_preferred":[
        "Bealka"
    ],
    "name:rus_x_preferred":[
        "\u0411\u044f\u043b\u043a\u0430"
    ],
    "name:ukr_x_preferred":[
        "\u0411\u044f\u043b\u043a\u0430"
    ],
    "name:und_x_variant":[
        "Belka",
        "Dutludzha",
        "Byalka"
    ],
    "wof:name":"Byalka",
    "wof:placetype":"locality"
},
  "geometry": {"coordinates":[25.41667,41.66667],"type":"Point"}
}