{
  "type": "Feature",
  "properties": {
    "gn:admin1_code":"44",
    "gn:admin2_code":"KRZ16",
    "gn:admin3_code":"KRZ16-33",
    "gn:asciiname":"Byalka",
    "gn:cc2":"BG",
    "gn:country_code":"BG",
    "gn:dem":373,
    "gn:feature_class":"P",
    "gn:feature_code":"PPL",
    "gn:name":"Byalka",
    "gn:population":0,
    "gn:timezone":"Europe/Sofia",
    "iso:country":"BG",
    "name:bul_x_preferred":[
        "\u0411\u044f\u043b\u043a\u0430"
    ],
    "name:und_x_variant":[
        "Belka",
        "Dutludzha",
        "Byalka"
    ],
    "wof:name":"Byalka",
    "wof:placetype":"locality"
},
  "geometry": {"coordinates":[25.41667,41.66667],"type":"Point"}
}