{
  "type": "Feature",
  "properties": {
    "gn:admin1_code":"38",
    "gn:asciiname":"Kovachka",
    "gn:country_code":"BG",
    "gn:dem":732,
    "gn:feature_class":"P",
    "gn:feature_code":"PPL",
    "gn:name":"Kovachka",
    "gn:population":0,
    "gn:timezone":"Europe/Sofia",
    "iso:country":"BG",
    "name:bul_x_preferred":[
        "Kovachka"
    ],
    "name:bul_x_variant":[
        "\u041a\u043e\u0432\u0430\u0447\u043a\u0430"
    ],
    "wof:name":"Kovachka",
    "wof:placetype":"locality"
},
  "geometry": {"coordinates":[22.97091,41.90135],"type":"Point"}
}