{
  "type": "Feature",
  "properties": {
    "gn:admin1_code":"39",
    "gn:admin2_code":"BGS23",
    "gn:asciiname":"Balabanchevo",
    "gn:cc2":"BG",
    "gn:country_code":"BG",
    "gn:dem":329,
    "gn:feature_class":"P",
    "gn:feature_code":"PPL",
    "gn:name":"Balabanchevo",
    "gn:population":0,
    "gn:timezone":"Europe/Sofia",
    "iso:country":"BG",
    "name:bul_x_preferred":[
        "\u0411\u0430\u043b\u0430\u0431\u0430\u043d\u0447\u0435\u0432\u043e"
    ],
    "name:und_x_variant":[
        "Balabash",
        "Balabantschewo",
        "Balabanchevo"
    ],
    "wof:name":"Balabanchevo",
    "wof:placetype":"locality"
},
  "geometry": {"coordinates":[26.78333,42.78333],"type":"Point"}
}