{
  "type": "Feature",
  "properties": {
    "gn:gn_country":"BG",
    "gn:gn_fcode":"PPL",
    "gn:gn_pop":0,
    "iso:country":"BG",
    "name:bul_x_preferred":[
        "\u0421\u0442\u0438\u043a\u044a\u043b"
    ],
    "name:bul_x_variant":[
        "Stikal"
    ],
    "name:eng_x_preferred":[
        "Stikal"
    ],
    "name:kaz_x_preferred":[
        "\u0421\u0442\u0438\u043a\u044b\u043b"
    ],
    "name:ron_x_preferred":[
        "Stik\u0103l"
    ],
    "name:rus_x_preferred":[
        "\u0421\u0442\u0438\u043a\u044b\u043b"
    ],
    "name:ukr_x_preferred":[
        "\u0421\u0442\u0438\u043a\u0438\u043b"
    ],
    "name:unk_x_variant":[
        "Stik\u016dl"
    ],
    "qs_pg:aaroncc":"BG",
    "qs_pg:gn_country":"BG",
    "qs_pg:gn_fcode":"PPL",
    "qs_pg:gn_pop":0,
    "qs_pg:name":"Stikul",
    "qs_pg:name_adm0":"Bulgaria",
    "qs_pg:name_adm1":"Smolyan",
    "qs_pg:photos":92,
    "qs_pg:photos_1k":19,
    "qs_pg:photos_9k":1,
    "qs_pg:photos_9r":3,
    "qs_pg:photos_all":92,
    "qs_pg:photos_sr":3,
    "qs_pg:pop_sr":0,
    "qs_pg:qs_pg_placetype":"locality",
    "qs_pg:qs_pg_placetype_gp":"Town",
    "qs_pg:woe_adm0":23424771,
    "woe:adm0_id":23424771,
    "woe:name_adm0":"Bulgaria",
    "woe:name_adm1":"Smolyan",
    "woe:placetype":"Town",
    "wof:name":"Stikul",
    "wof:placetype":"locality"
},
  "geometry": {"coordinates":[24.58333,41.68333],"type":"Point"}
}