{
  "type": "Feature",
  "properties": {
    "gn:admin1_code":"48",
    "gn:admin2_code":"PAZ03",
    "gn:admin3_code":"PAZ03-02",
    "gn:asciiname":"Fotinovo",
    "gn:cc2":"BG",
    "gn:country_code":"BG",
    "gn:dem":1124,
    "gn:feature_class":"P",
    "gn:feature_code":"PPL",
    "gn:name":"Fotinovo",
    "gn:population":0,
    "gn:timezone":"Europe/Sofia",
    "iso:country":"BG",
    "name:bul_x_preferred":[
        "\u0424\u043e\u0442\u0438\u043d\u043e\u0432\u043e"
    ],
    "name:ron_x_preferred":[
        "Fotinovo"
    ],
    "name:rus_x_preferred":[
        "\u0424\u043e\u0442\u0438\u043d\u043e\u0432\u043e"
    ],
    "name:ukr_x_preferred":[
        "\u0424\u043e\u0442\u0438\u043d\u043e\u0432\u043e"
    ],
    "name:und_x_variant":[
        "Potinovo",
        "Foten",
        "Fotin"
    ],
    "wof:name":"Fotinovo",
    "wof:placetype":"locality"
},
  "geometry": {"coordinates":[24.35,41.88333],"type":"Point"}
}