{
  "type": "Feature",
  "properties": {
    "gn:admin1_code":"62",
    "gn:admin2_code":"VTR04",
    "gn:asciiname":"Kutsarovtsi",
    "gn:cc2":"BG",
    "gn:country_code":"BG",
    "gn:dem":531,
    "gn:feature_class":"P",
    "gn:feature_code":"PPL",
    "gn:name":"Kutsarovtsi",
    "gn:population":0,
    "gn:timezone":"Europe/Sofia",
    "iso:country":"BG",
    "name:bul_x_preferred":[
        "\u041a\u0443\u0446\u0430\u0440\u043e\u0432\u0446\u0438"
    ],
    "name:und_x_variant":[
        "Kutserovts\u016d",
        "Kutsarovtsi"
    ],
    "wof:name":"Kutsarovtsi",
    "wof:placetype":"locality"
},
  "geometry": {"coordinates":[25.71667,42.93333],"type":"Point"}
}