{
  "type": "Feature",
  "properties": {
    "gn:admin1_code":"38",
    "gn:asciiname":"Korianska",
    "gn:country_code":"BG",
    "gn:dem":780,
    "gn:feature_class":"P",
    "gn:feature_code":"PPL",
    "gn:name":"Korianska",
    "gn:population":0,
    "gn:timezone":"Europe/Sofia",
    "iso:country":"BG",
    "name:bul_x_preferred":[
        "Korianska"
    ],
    "name:bul_x_variant":[
        "\u041a\u043e\u0440\u0438\u044f\u043d\u0441\u043a\u0430"
    ],
    "wof:name":"Korianska",
    "wof:placetype":"locality"
},
  "geometry": {"coordinates":[22.94216,41.93274],"type":"Point"}
}