{
  "type": "Feature",
  "properties": {
    "gn:admin1_code":"44",
    "gn:asciiname":"Hadzhievtsi",
    "gn:country_code":"BG",
    "gn:dem":343,
    "gn:feature_class":"P",
    "gn:feature_code":"PPL",
    "gn:name":"Hadzhievtsi",
    "gn:population":0,
    "gn:timezone":"Europe/Sofia",
    "iso:country":"BG",
    "name:bul_x_preferred":[
        "\u0425\u0430\u0434\u0436\u0438\u0435\u0432\u0446\u0438"
    ],
    "name:bul_x_variant":[
        "Hadzhievtsi"
    ],
    "name:und_x_variant":[
        "Chadshiewzi",
        "Khadzhi Oglular",
        "Khadzhievtsi"
    ],
    "wof:name":"Hadzhievtsi",
    "wof:placetype":"locality"
},
  "geometry": {"coordinates":[25.21667,41.68333],"type":"Point"}
}