{
  "type": "Feature",
  "properties": {
    "gn:admin1_code":"45",
    "gn:asciiname":"Chergarska Mahala",
    "gn:country_code":"BG",
    "gn:dem":1158,
    "gn:feature_class":"P",
    "gn:feature_code":"PPL",
    "gn:name":"Chergarska Mahala",
    "gn:population":0,
    "gn:timezone":"Europe/Sofia",
    "iso:country":"BG",
    "name:bul_x_preferred":[
        "\u0427\u0435\u0440\u0433\u0430\u0440\u0441\u043a\u0430 \u043c\u0430\u0445\u0430\u043b\u0430"
    ],
    "name:bul_x_variant":[
        "Chergarska Mahala",
        "\u0427\u0435\u0440\u0433\u0430\u0440\u0441\u043a\u0430 \u041c\u0430\u0445\u0430\u043b\u0430"
    ],
    "name:und_x_variant":[
        "Tchergarska mahala",
        "Chergarska Makhala"
    ],
    "wof:name":"Chergarska Mahala",
    "wof:placetype":"locality"
},
  "geometry": {"coordinates":[22.37833,42.31139],"type":"Point"}
}