{
  "type": "Feature",
  "properties": {
    "gn:admin1_code":"59",
    "gn:admin2_code":"SZR23",
    "gn:admin3_code":"SZR23-12",
    "gn:asciiname":"Yastrebovo",
    "gn:cc2":"BG",
    "gn:country_code":"BG",
    "gn:dem":166,
    "gn:feature_class":"P",
    "gn:feature_code":"PPL",
    "gn:name":"Yastrebovo",
    "gn:population":0,
    "gn:timezone":"Europe/Sofia",
    "iso:country":"BG",
    "name:bul_x_preferred":[
        "\u042f\u0441\u0442\u0440\u0435\u0431\u043e\u0432\u043e"
    ],
    "name:und_x_variant":[
        "Jastrebowo",
        "Shakhpazliy",
        "Shakhpazlii",
        "Yastrebovo"
    ],
    "wof:name":"Yastrebovo",
    "wof:placetype":"locality"
},
  "geometry": {"coordinates":[25.66667,42.28333],"type":"Point"}
}