{
  "type": "Feature",
  "properties": {
    "gn:admin1_code":"65",
    "gn:asciiname":"Stroyno",
    "gn:cc2":"BG",
    "gn:country_code":"BG",
    "gn:dem":178,
    "gn:feature_class":"P",
    "gn:feature_code":"PPL",
    "gn:name":"Stroyno",
    "gn:population":0,
    "gn:timezone":"Europe/Sofia",
    "iso:country":"BG",
    "name:bul_x_preferred":[
        "\u0421\u0442\u043e\u0439\u043d\u043e"
    ],
    "name:und_x_variant":[
        "Indzheklii",
        "Sveti Iliya",
        "Stroyno"
    ],
    "wof:name":"Stroyno",
    "wof:placetype":"locality"
},
  "geometry": {"coordinates":[26.63333,42.25],"type":"Point"}
}