{
  "type": "Feature",
  "properties": {
    "gn:admin1_code":"49",
    "gn:admin2_code":"PER08",
    "gn:admin3_code":"PER08-16",
    "gn:asciiname":"Dolna Sekirna",
    "gn:country_code":"BG",
    "gn:dem":811,
    "gn:feature_class":"P",
    "gn:feature_code":"PPL",
    "gn:name":"Dolna Sekirna",
    "gn:population":0,
    "gn:timezone":"Europe/Sofia",
    "iso:country":"BG",
    "name:bul_x_preferred":[
        "\u0414\u043e\u043b\u043d\u0430 \u0421\u0435\u043a\u0438\u0440\u043d\u0430"
    ],
    "name:und_x_variant":[
        "Syekirna Dolna",
        "Dolna-Syekirna",
        "Dolna Sekirna"
    ],
    "wof:name":"Dolna Sekirna",
    "wof:placetype":"locality"
},
  "geometry": {"coordinates":[22.72454,42.67146],"type":"Point"}
}