{
  "type": "Feature",
  "properties": {
    "gn:admin1_code":"51",
    "gn:admin2_code":"PDV26",
    "gn:admin3_code":"PDV26-21",
    "gn:asciiname":"Orizari",
    "gn:cc2":"BG",
    "gn:country_code":"BG",
    "gn:dem":169,
    "gn:feature_class":"P",
    "gn:feature_code":"PPL",
    "gn:name":"Orizari",
    "gn:population":0,
    "gn:timezone":"Europe/Sofia",
    "iso:country":"BG",
    "name:bul_x_preferred":[
        "\u041e\u0440\u0438\u0437\u0430\u0440\u0438"
    ],
    "name:ceb_x_preferred":[
        "Orizari"
    ],
    "name:fra_x_preferred":[
        "Orizari"
    ],
    "name:kaz_x_preferred":[
        "\u041e\u0440\u0438\u0437\u0430\u0440\u0438"
    ],
    "name:pol_x_preferred":[
        "Orizari"
    ],
    "name:ron_x_preferred":[
        "Orizari"
    ],
    "name:rus_x_preferred":[
        "\u041e\u0440\u0438\u0437\u0430\u0440\u0438"
    ],
    "name:sqi_x_preferred":[
        "Orizari"
    ],
    "name:srp_x_preferred":[
        "\u041e\u0440\u0438\u0437\u0430\u0440\u0438"
    ],
    "name:swe_x_preferred":[
        "Orizari"
    ],
    "name:ukr_x_preferred":[
        "\u041e\u0440\u0438\u0437\u0430\u0440\u0438"
    ],
    "name:und_x_variant":[
        "Ayrene",
        "Orizare",
        "Orisari",
        "Orizari"
    ],
    "wof:name":"Orizari",
    "wof:placetype":"locality"
},
  "geometry": {"coordinates":[24.65,42.15],"type":"Point"}
}