{
  "type": "Feature",
  "properties": {
    "gn:admin1_code":"40",
    "gn:admin2_code":"DOB12",
    "gn:asciiname":"Loznitsa",
    "gn:country_code":"BG",
    "gn:dem":117,
    "gn:feature_class":"P",
    "gn:feature_code":"PPL",
    "gn:name":"Loznitsa",
    "gn:population":0,
    "gn:timezone":"Europe/Sofia",
    "iso:country":"BG",
    "name:azb_x_preferred":[
        "\u0644\u0648\u0632\u0646\u06cc\u062a\u0633\u0627"
    ],
    "name:bul_x_preferred":[
        "\u041b\u043e\u0437\u043d\u0438\u0446\u0430"
    ],
    "name:ceb_x_preferred":[
        "Loznitsa"
    ],
    "name:ckb_x_preferred":[
        "\u0644\u06c6\u0632\u0646\u06cc\u062a\u0633\u0627"
    ],
    "name:fas_x_preferred":[
        "\u0644\u0648\u0632\u0646\u06cc\u062a\u0633\u0627"
    ],
    "name:ita_x_preferred":[
        "Loznica"
    ],
    "name:nld_x_preferred":[
        "Loznitsa"
    ],
    "name:pol_x_preferred":[
        "\u0141oznica"
    ],
    "name:por_x_preferred":[
        "Loznica"
    ],
    "name:ron_x_preferred":[
        "Lozni\u021ba"
    ],
    "name:rus_x_preferred":[
        "\u041b\u043e\u0437\u043d\u0438\u0446\u0430"
    ],
    "name:spa_x_preferred":[
        "Loznitsa"
    ],
    "name:srp_x_preferred":[
        "\u041b\u043e\u0437\u043d\u0438\u0446\u0430"
    ],
    "name:tur_x_preferred":[
        "Loznitsa"
    ],
    "name:ukr_x_preferred":[
        "\u041b\u043e\u0437\u043d\u0438\u0446\u044f"
    ],
    "name:und_x_variant":[
        "Deli Yusuf Kuyusu",
        "P\u0103dureni",
        "Deliyusufkoyusu",
        "Deli-J\u00fcssufkuj\u00fcssu"
    ],
    "name:vie_x_preferred":[
        "Loznitsa"
    ],
    "name:war_x_preferred":[
        "Loznitsa"
    ],
    "name:zho_x_preferred":[
        "\u6d1b\u8332\u5c3c\u5bdf"
    ],
    "wof:name":"Loznitsa",
    "wof:placetype":"locality"
},
  "geometry": {"coordinates":[27.91623,43.96879000000001],"type":"Point"}
}