{
  "type": "Feature",
  "properties": {
    "gn:admin1_code":"40",
    "gn:admin2_code":"DOB12",
    "gn:asciiname":"Loznitsa",
    "gn:country_code":"BG",
    "gn:dem":117,
    "gn:feature_class":"P",
    "gn:feature_code":"PPL",
    "gn:name":"Loznitsa",
    "gn:population":0,
    "gn:timezone":"Europe/Sofia",
    "iso:country":"BG",
    "name:bul_x_preferred":[
        "\u041b\u043e\u0437\u043d\u0438\u0446\u0430"
    ],
    "name:und_x_variant":[
        "Deli Yusuf Kuyusu",
        "P\u0103dureni",
        "Deliyusufkoyusu",
        "Loznica",
        "Deli-J\u00fcssufkuj\u00fcssu",
        "Loznitsa"
    ],
    "wof:name":"Loznitsa",
    "wof:placetype":"locality"
},
  "geometry": {"coordinates":[27.91623,43.96879000000001],"type":"Point"}
}