{
  "type": "Feature",
  "properties": {
    "gn:admin1_code":"41",
    "gn:admin2_code":"GAB12",
    "gn:asciiname":"Slaveykovo",
    "gn:cc2":"BG",
    "gn:country_code":"BG",
    "gn:dem":262,
    "gn:feature_class":"P",
    "gn:feature_code":"PPL",
    "gn:name":"Slaveykovo",
    "gn:population":0,
    "gn:timezone":"Europe/Sofia",
    "iso:country":"BG",
    "name:bul_x_preferred":[
        "\u0421\u043b\u0430\u0432\u0435\u0439\u043a\u043e\u0432\u043e"
    ],
    "name:und_x_variant":[
        "Yalari",
        "Slaweikowo",
        "Slaveykovo"
    ],
    "wof:name":"Slaveykovo",
    "wof:placetype":"locality"
},
  "geometry": {"coordinates":[25.36667000000001,42.98333],"type":"Point"}
}