{
  "type": "Feature",
  "properties": {
    "gn:admin1_code":"49",
    "gn:asciiname":"Razhavets",
    "gn:country_code":"BG",
    "gn:dem":860,
    "gn:feature_class":"P",
    "gn:feature_code":"PPL",
    "gn:name":"Razhavets",
    "gn:population":0,
    "gn:timezone":"Europe/Sofia",
    "iso:country":"BG",
    "name:bul_x_preferred":[
        "\u0420\u044a\u0436\u0430\u0432\u0435\u0446"
    ],
    "name:bul_x_variant":[
        "Razhavets"
    ],
    "name:und_x_variant":[
        "R\u0103shawez",
        "R\u016dzhavets"
    ],
    "wof:name":"Razhavets",
    "wof:placetype":"locality"
},
  "geometry": {"coordinates":[22.72898,42.71201],"type":"Point"}
}