{
  "type": "Feature",
  "properties": {
    "gn:admin1_code":"56",
    "gn:admin2_code":"SLV20",
    "gn:admin3_code":"SLV20-39",
    "gn:asciiname":"Staro Selo",
    "gn:cc2":"BG",
    "gn:country_code":"BG",
    "gn:dem":302,
    "gn:feature_class":"P",
    "gn:feature_code":"PPL",
    "gn:name":"Staro Selo",
    "gn:population":0,
    "gn:timezone":"Europe/Sofia",
    "iso:country":"BG",
    "name:bel_x_preferred":[
        "\u0421\u0442\u0430\u0440\u043e\u0435 \u0421\u044f\u043b\u043e"
    ],
    "name:bos_x_preferred":[
        "Staro Selo"
    ],
    "name:bul_x_preferred":[
        "\u0421\u0442\u0430\u0440\u043e \u0421\u0435\u043b\u043e"
    ],
    "name:bul_x_variant":[
        "\u0421\u0442\u0430\u0440\u043e \u0441\u0435\u043b\u043e"
    ],
    "name:ceb_x_preferred":[
        "Staro Selo"
    ],
    "name:deu_x_preferred":[
        "Staro Selo"
    ],
    "name:fra_x_preferred":[
        "Staro selo"
    ],
    "name:hrv_x_preferred":[
        "Staro Selo"
    ],
    "name:hun_x_preferred":[
        "Staro Selo"
    ],
    "name:nld_x_preferred":[
        "Staro Selo"
    ],
    "name:ron_x_preferred":[
        "Staro Selo"
    ],
    "name:rus_x_preferred":[
        "\u0421\u0442\u0430\u0440\u043e\u0435 \u0421\u0435\u043b\u043e"
    ],
    "name:slv_x_preferred":[
        "Staro Selo"
    ],
    "name:srp_x_preferred":[
        "\u0421\u0442\u0430\u0440\u043e \u0421\u0435\u043b\u043e"
    ],
    "name:swe_x_preferred":[
        "Staro Selo"
    ],
    "name:und_x_variant":[
        "Mekhrem Bey"
    ],
    "wof:name":"Staro Selo",
    "wof:placetype":"locality"
},
  "geometry": {"coordinates":[26.15,42.58333],"type":"Point"}
}