{
  "type": "Feature",
  "properties": {
    "gn:admin1_code":"43",
    "gn:admin2_code":"HKV30",
    "gn:admin3_code":"HKV30-22",
    "gn:asciiname":"Svetoslav",
    "gn:cc2":"BG",
    "gn:country_code":"BG",
    "gn:dem":361,
    "gn:feature_class":"P",
    "gn:feature_code":"PPL",
    "gn:name":"Svetoslav",
    "gn:population":0,
    "gn:timezone":"Europe/Sofia",
    "iso:country":"BG",
    "name:bul_x_preferred":[
        "\u0421\u0432\u0435\u0442\u043e\u0441\u043b\u0430\u0432"
    ],
    "name:ron_x_preferred":[
        "Svetoslav"
    ],
    "name:rus_x_preferred":[
        "\u0421\u0432\u0435\u0442\u043e\u0441\u043b\u0430\u0432"
    ],
    "name:ukr_x_preferred":[
        "\u0421\u0432\u0435\u0442\u043e\u0441\u043b\u0430\u0432"
    ],
    "name:und_x_variant":[
        "Ayledin",
        "Swetoslaw",
        "Svetoslav"
    ],
    "wof:name":"Svetoslav",
    "wof:placetype":"locality"
},
  "geometry": {"coordinates":[25.65,41.65],"type":"Point"}
}