{
  "type": "Feature",
  "properties": {
    "gn:admin1_code":"57",
    "gn:admin2_code":"SML31",
    "gn:asciiname":"Sredok",
    "gn:country_code":"BG",
    "gn:dem":1072,
    "gn:feature_class":"P",
    "gn:feature_code":"PPL",
    "gn:name":"Sredok",
    "gn:population":0,
    "gn:timezone":"Europe/Sofia",
    "iso:country":"BG",
    "name:bul_x_preferred":[
        "\u0421\u0440\u0435\u0434\u043e\u043a"
    ],
    "wof:name":"Sredok",
    "wof:placetype":"locality"
},
  "geometry": {"coordinates":[24.60768,41.45605],"type":"Point"}
}