{
  "type": "Feature",
  "properties": {
    "gn:admin1_code":"61",
    "gn:asciiname":"Petrovdol",
    "gn:cc2":"BG",
    "gn:country_code":"BG",
    "gn:dem":191,
    "gn:feature_class":"P",
    "gn:feature_code":"PPL",
    "gn:name":"Petrovdol",
    "gn:population":0,
    "gn:timezone":"Europe/Sofia",
    "iso:country":"BG",
    "name:bul_x_preferred":[
        "\u041f\u0435\u0442\u0440\u043e\u0432\u0434\u043e\u043b"
    ],
    "name:und_x_variant":[
        "Dere Kioi",
        "Petrow-Dol",
        "Dere-Kjoj",
        "Dere-Kyoy",
        "Dereki\u00f6j",
        "Dere-K\u2019oy",
        "Petrovdol"
    ],
    "wof:name":"Petrovdol",
    "wof:placetype":"locality"
},
  "geometry": {"coordinates":[27.46667,43.21667],"type":"Point"}
}