{
  "type": "Feature",
  "properties": {
    "gn:admin1_code":"57",
    "gn:admin2_code":"SML16",
    "gn:asciiname":"Ravno Nivishte",
    "gn:country_code":"BG",
    "gn:dem":859,
    "gn:feature_class":"P",
    "gn:feature_code":"PPL",
    "gn:name":"Ravno Nivishte",
    "gn:population":0,
    "gn:timezone":"Europe/Sofia",
    "iso:country":"BG",
    "name:bul_x_preferred":[
        "\u0420\u0430\u0432\u043d\u043e \u041d\u0438\u0432\u0438\u0449\u0435"
    ],
    "name:und_x_variant":[
        "Rawno Niwischte",
        "Ravno Nivishte"
    ],
    "wof:name":"Ravno Nivishte",
    "wof:placetype":"locality"
},
  "geometry": {"coordinates":[24.95733,41.49536],"type":"Point"}
}