{
  "type": "Feature",
  "properties": {
    "gn:admin1_code":"38",
    "gn:asciiname":"Todorovska",
    "gn:country_code":"BG",
    "gn:dem":887,
    "gn:feature_class":"P",
    "gn:feature_code":"PPL",
    "gn:name":"Todorovska",
    "gn:population":0,
    "gn:timezone":"Europe/Sofia",
    "iso:country":"BG",
    "name:bul_x_preferred":[
        "Todorovska"
    ],
    "name:bul_x_variant":[
        "\u0422\u043e\u0434\u043e\u0440\u043e\u0432\u0441\u043a\u0430"
    ],
    "wof:name":"Todorovska",
    "wof:placetype":"locality"
},
  "geometry": {"coordinates":[22.95957000000001,41.87336],"type":"Point"}
}