{
  "type": "Feature",
  "properties": {
    "gn:admin1_code":"53",
    "gn:admin2_code":"RSE33",
    "gn:admin3_code":"RSE33-09",
    "gn:asciiname":"Stambolovo",
    "gn:country_code":"BG",
    "gn:dem":111,
    "gn:feature_class":"P",
    "gn:feature_code":"PPL",
    "gn:name":"Stambolovo",
    "gn:population":0,
    "gn:timezone":"Europe/Sofia",
    "iso:country":"BG",
    "name:bul_x_preferred":[
        "\u0421\u0442\u0430\u043c\u0431\u043e\u043b\u043e\u0432\u043e"
    ],
    "name:und_x_variant":[
        "Garvan",
        "Stefan-Stambolowo",
        "Stefan Stambolovo",
        "Stambolovo"
    ],
    "wof:name":"Stambolovo",
    "wof:placetype":"locality"
},
  "geometry": {"coordinates":[26.30024,43.89944000000001],"type":"Point"}
}