{
  "type": "Feature",
  "properties": {
    "gn:admin1_code":"58",
    "gn:admin2_code":"SFO43",
    "gn:asciiname":"Zhelen",
    "gn:cc2":"BG",
    "gn:country_code":"BG",
    "gn:dem":935,
    "gn:feature_class":"P",
    "gn:feature_code":"PPL",
    "gn:name":"Zhelen",
    "gn:population":0,
    "gn:timezone":"Europe/Sofia",
    "iso:country":"BG",
    "name:bul_x_preferred":[
        "\u0416\u0435\u043b\u0435\u043d"
    ],
    "name:fas_x_preferred":[
        "\u0698\u0644\u0646"
    ],
    "name:kaz_x_preferred":[
        "\u0416\u0435\u043b\u0435\u043d"
    ],
    "name:ron_x_preferred":[
        "Jelen"
    ],
    "name:rus_x_preferred":[
        "\u0416\u0435\u043b\u0435\u043d"
    ],
    "name:ukr_x_preferred":[
        "\u0416\u0435\u043b\u0435\u043d"
    ],
    "name:und_x_variant":[
        "Shelen",
        "Zhelen"
    ],
    "wof:name":"Zhelen",
    "wof:placetype":"locality"
},
  "geometry": {"coordinates":[23.38333,42.98333],"type":"Point"}
}