{
  "type": "Feature",
  "properties": {
    "gn:admin1_code":"41",
    "gn:admin2_code":"GAB12",
    "gn:asciiname":"Kosarka",
    "gn:cc2":"BG",
    "gn:country_code":"BG",
    "gn:dem":270,
    "gn:feature_class":"P",
    "gn:feature_code":"PPL",
    "gn:name":"Kosarka",
    "gn:population":0,
    "gn:timezone":"Europe/Sofia",
    "iso:country":"BG",
    "name:bul_x_preferred":[
        "\u041a\u043e\u0441\u0430\u0440\u043a\u0430"
    ],
    "name:und_x_variant":[
        "Kossarka",
        "Kosarka"
    ],
    "wof:name":"Kosarka",
    "wof:placetype":"locality"
},
  "geometry": {"coordinates":[25.55,43.01667],"type":"Point"}
}