{
  "type": "Feature",
  "properties": {
    "gn:admin1_code":"59",
    "gn:admin2_code":"SZR04",
    "gn:asciiname":"Naydenovo",
    "gn:cc2":"BG",
    "gn:country_code":"BG",
    "gn:dem":368,
    "gn:feature_class":"P",
    "gn:feature_code":"PPL",
    "gn:name":"Naydenovo",
    "gn:population":0,
    "gn:timezone":"Europe/Sofia",
    "iso:country":"BG",
    "name:bul_x_preferred":[
        "\u041d\u0430\u0439\u0434\u0435\u043d\u043e\u0432\u043e"
    ],
    "name:und_x_variant":[
        "Nova Makhla",
        "Nowa Machla",
        "Naydenovo"
    ],
    "wof:name":"Naydenovo",
    "wof:placetype":"locality"
},
  "geometry": {"coordinates":[25.26667,42.38333],"type":"Point"}
}