{
  "type": "Feature",
  "properties": {
    "gn:admin1_code":"39",
    "gn:admin2_code":"BGS23",
    "gn:asciiname":"Velislav",
    "gn:cc2":"BG",
    "gn:country_code":"BG",
    "gn:dem":335,
    "gn:feature_class":"P",
    "gn:feature_code":"PPL",
    "gn:name":"Velislav",
    "gn:population":0,
    "gn:timezone":"Europe/Sofia",
    "iso:country":"BG",
    "name:bul_x_preferred":[
        "\u0412\u0435\u043b\u0438\u0441\u043b\u0430\u0432"
    ],
    "name:fas_x_preferred":[
        "\u0648\u0644\u06cc\u0633\u0644\u0648"
    ],
    "name:kaz_x_preferred":[
        "\u0412\u0435\u043b\u0438\u0441\u043b\u0430\u0432"
    ],
    "name:ron_x_preferred":[
        "Velislav"
    ],
    "name:rus_x_preferred":[
        "\u0412\u0435\u043b\u0438\u0441\u043b\u0430\u0432"
    ],
    "name:ukr_x_preferred":[
        "\u0412\u0435\u043b\u0438\u0441\u043b\u0430\u0432"
    ],
    "name:und_x_variant":[
        "Feklach",
        "Vekil\u2019agach",
        "Feklatsch",
        "Velislav"
    ],
    "wof:name":"Velislav",
    "wof:placetype":"locality"
},
  "geometry": {"coordinates":[26.76667,42.86667],"type":"Point"}
}