{
  "type": "Feature",
  "properties": {
    "gn:admin1_code":"62",
    "gn:admin2_code":"VTR13",
    "gn:asciiname":"Hanevtsi",
    "gn:country_code":"BG",
    "gn:dem":407,
    "gn:feature_class":"P",
    "gn:feature_code":"PPL",
    "gn:name":"Hanevtsi",
    "gn:population":0,
    "gn:timezone":"Europe/Sofia",
    "iso:country":"BG",
    "name:bul_x_preferred":[
        "\u0425\u044a\u043d\u0435\u0432\u0446\u0438"
    ],
    "name:bul_x_variant":[
        "Hanevtsi"
    ],
    "name:und_x_variant":[
        "Chanewzi",
        "Khanevts\u016d",
        "Kh\u016dnevtsi"
    ],
    "wof:name":"Hanevtsi",
    "wof:placetype":"locality"
},
  "geometry": {"coordinates":[25.91667,42.88333],"type":"Point"}
}