{
  "type": "Feature",
  "properties": {
    "gn:admin1_code":"65",
    "gn:admin2_code":"JAM03",
    "gn:asciiname":"Sitovo",
    "gn:country_code":"BG",
    "gn:dem":308,
    "gn:feature_class":"P",
    "gn:feature_code":"PPL",
    "gn:name":"Sitovo",
    "gn:population":0,
    "gn:timezone":"Europe/Sofia",
    "iso:country":"BG",
    "name:bul_x_preferred":[
        "\u0421\u0438\u0442\u043e\u0432\u043e"
    ],
    "name:und_x_variant":[
        "Elemenliy",
        "Elemenlii",
        "Sitovo"
    ],
    "wof:name":"Sitovo",
    "wof:placetype":"locality"
},
  "geometry": {"coordinates":[26.77113,42.06154],"type":"Point"}
}