{
  "type": "Feature",
  "properties": {
    "gn:admin1_code":"62",
    "gn:admin2_code":"VTR13",
    "gn:asciiname":"Valchovtsi",
    "gn:country_code":"BG",
    "gn:dem":448,
    "gn:feature_class":"P",
    "gn:feature_code":"PPL",
    "gn:name":"Valchovtsi",
    "gn:population":0,
    "gn:timezone":"Europe/Sofia",
    "iso:country":"BG",
    "name:bul_x_preferred":[
        "\u0412\u044a\u043b\u0447\u043e\u0432\u0446\u0438"
    ],
    "name:bul_x_variant":[
        "Valchovtsi"
    ],
    "name:und_x_variant":[
        "Vel\u2019chovts\u016d",
        "W\u0103ltschowzi",
        "V\u016dlchovtsi"
    ],
    "wof:name":"Valchovtsi",
    "wof:placetype":"locality"
},
  "geometry": {"coordinates":[25.81667,42.95],"type":"Point"}
}