{
  "type": "Feature",
  "properties": {
    "gn:admin1_code":"43",
    "gn:admin2_code":"HKV11",
    "gn:asciiname":"Karlovsko",
    "gn:country_code":"BG",
    "gn:dem":511,
    "gn:feature_class":"P",
    "gn:feature_code":"PPL",
    "gn:name":"Karlovsko",
    "gn:population":0,
    "gn:timezone":"Europe/Sofia",
    "iso:country":"BG",
    "name:bul_x_preferred":[
        "\u041a\u0430\u0440\u043b\u043e\u0432\u0441\u043a\u043e"
    ],
    "name:und_x_variant":[
        "Karlowsko",
        "Karlovo",
        "Karlovsko"
    ],
    "wof:name":"Karlovsko",
    "wof:placetype":"locality"
},
  "geometry": {"coordinates":[25.92968,41.52792],"type":"Point"}
}