{
  "type": "Feature",
  "properties": {
    "gn:admin1_code":"46",
    "gn:admin2_code":"LOV34",
    "gn:asciiname":"Raykovska",
    "gn:country_code":"BG",
    "gn:dem":458,
    "gn:feature_class":"P",
    "gn:feature_code":"PPL",
    "gn:name":"Raykovska",
    "gn:population":0,
    "gn:timezone":"Europe/Sofia",
    "iso:country":"BG",
    "name:bul_x_preferred":[
        "\u0420\u0430\u0439\u043a\u043e\u0432\u0441\u043a\u0430"
    ],
    "wof:name":"Raykovska",
    "wof:placetype":"locality"
},
  "geometry": {"coordinates":[24.71667,42.88333],"type":"Point"}
}