{
  "type": "Feature",
  "properties": {
    "iso:country":"BG",
    "name:eng_x_preferred":[
        "\u041c\u0430\u0440\u0430\u0448\u0430"
    ],
    "wof:name":"Marasha",
    "wof:placetype":"neighbourhood"
},
  "geometry": {"coordinates":[24.73508375596763,42.15062149994724],"type":"Point"}
}