{
  "type": "Feature",
  "properties": {
    "gn:admin1_code":"43",
    "gn:admin2_code":"HKV33",
    "gn:admin3_code":"HKV33-04",
    "gn:asciiname":"Balgarin",
    "gn:country_code":"BG",
    "gn:dem":183,
    "gn:feature_class":"P",
    "gn:feature_code":"PPL",
    "gn:name":"Balgarin",
    "gn:population":0,
    "gn:timezone":"Europe/Sofia",
    "iso:country":"BG",
    "name:bul_x_preferred":[
        "\u0411\u044a\u043b\u0433\u0430\u0440\u0438\u043d"
    ],
    "name:bul_x_variant":[
        "Balgarin"
    ],
    "name:kaz_x_preferred":[
        "\u0411\u043e\u043b\u0433\u0430\u0440\u0438\u043d"
    ],
    "name:pol_x_preferred":[
        "By\u0142garin"
    ],
    "name:ron_x_preferred":[
        "B\u0103lgarin"
    ],
    "name:rus_x_preferred":[
        "\u0411\u043e\u043b\u0433\u0430\u0440\u0438\u043d"
    ],
    "name:ukr_x_preferred":[
        "\u0411\u0438\u043b\u0433\u0430\u0440\u0438\u043d"
    ],
    "name:und_x_variant":[
        "Syulemenchevo",
        "Belgarin",
        "Blgarin",
        "B\u016dlgarin"
    ],
    "wof:name":"Balgarin",
    "wof:placetype":"locality"
},
  "geometry": {"coordinates":[25.95,41.95],"type":"Point"}
}