{
  "type": "Feature",
  "properties": {
    "gn:admin1_code":"38",
    "gn:asciiname":"Yanchovtsi",
    "gn:country_code":"BG",
    "gn:dem":540,
    "gn:feature_class":"P",
    "gn:feature_code":"PPL",
    "gn:name":"Yanchovtsi",
    "gn:population":0,
    "gn:timezone":"Europe/Sofia",
    "iso:country":"BG",
    "name:bul_x_preferred":[
        "Yanchovtsi"
    ],
    "name:bul_x_variant":[
        "\u042f\u043d\u0447\u043e\u0432\u0446\u0438"
    ],
    "wof:name":"Yanchovtsi",
    "wof:placetype":"locality"
},
  "geometry": {"coordinates":[23.03848,41.97093],"type":"Point"}
}