{
  "type": "Feature",
  "properties": {
    "gn:admin1_code":"63",
    "gn:admin2_code":"VID09",
    "gn:asciiname":"Ruptsi",
    "gn:country_code":"BG",
    "gn:dem":50,
    "gn:feature_class":"P",
    "gn:feature_code":"PPL",
    "gn:name":"Ruptsi",
    "gn:population":0,
    "gn:timezone":"Europe/Sofia",
    "iso:country":"BG",
    "name:bul_x_preferred":[
        "\u0420\u0443\u043f\u0446\u0438"
    ],
    "name:und_x_variant":[
        "Rupzi",
        "Ruptsi"
    ],
    "wof:name":"Ruptsi",
    "wof:placetype":"locality"
},
  "geometry": {"coordinates":[22.80097,44.00413],"type":"Point"}
}