{
  "type": "Feature",
  "properties": {
    "gn:admin1_code":"40",
    "gn:admin2_code":"DOB12",
    "gn:asciiname":"Pisarovo",
    "gn:country_code":"BG",
    "gn:dem":184,
    "gn:feature_class":"P",
    "gn:feature_code":"PPL",
    "gn:name":"Pisarovo",
    "gn:population":0,
    "gn:timezone":"Europe/Sofia",
    "iso:country":"BG",
    "name:bul_x_preferred":[
        "\u041f\u0438\u0441\u0430\u0440\u043e\u0432\u043e"
    ],
    "name:und_x_variant":[
        "Karajas\u0103dshi",
        "Pisarava",
        "Pisarovo"
    ],
    "wof:name":"Pisarovo",
    "wof:placetype":"locality"
},
  "geometry": {"coordinates":[28.10605,43.7002],"type":"Point"}
}