{
  "type": "Feature",
  "properties": {
    "gn:admin1_code":"44",
    "gn:admin2_code":"KRZ15",
    "gn:admin3_code":"KRZ15-23",
    "gn:asciiname":"Leshtarka",
    "gn:country_code":"BG",
    "gn:dem":542,
    "gn:feature_class":"P",
    "gn:feature_code":"PPL",
    "gn:name":"Leshtarka",
    "gn:population":0,
    "gn:timezone":"Europe/Sofia",
    "iso:country":"BG",
    "name:bul_x_preferred":[
        "\u041b\u0435\u0449\u0430\u0440\u043a\u0430"
    ],
    "name:und_x_variant":[
        "Leshterka",
        "Kodzha Musalar",
        "Leschtarka",
        "Leshtarka"
    ],
    "wof:name":"Leshtarka",
    "wof:placetype":"locality"
},
  "geometry": {"coordinates":[25.54958,41.37992],"type":"Point"}
}