{
  "type": "Feature",
  "properties": {
    "gn:admin1_code":"45",
    "gn:admin2_code":"KNL05",
    "gn:asciiname":"Skrino",
    "gn:country_code":"BG",
    "gn:dem":601,
    "gn:feature_class":"P",
    "gn:feature_code":"PPL",
    "gn:name":"Skrino",
    "gn:population":0,
    "gn:timezone":"Europe/Sofia",
    "iso:country":"BG",
    "name:bul_x_preferred":[
        "\u0421\u043a\u0440\u0438\u043d\u043e"
    ],
    "name:fas_x_preferred":[
        "\u0627\u0633\u06a9\u0631\u06cc\u0646\u0648"
    ],
    "name:kat_x_preferred":[
        "\u10e1\u10d9\u10e0\u10d8\u10dc\u10dd"
    ],
    "name:kaz_x_preferred":[
        "\u0421\u043a\u0440\u0438\u043d\u043e"
    ],
    "name:msa_x_preferred":[
        "Skrino"
    ],
    "name:ron_x_preferred":[
        "Skrino"
    ],
    "name:rus_x_preferred":[
        "\u0421\u043a\u0440\u0438\u043d\u043e"
    ],
    "name:ukr_x_preferred":[
        "\u0421\u043a\u0440\u0438\u043d\u043e"
    ],
    "name:und_x_variant":[
        "Skino"
    ],
    "wof:name":"Skrino",
    "wof:placetype":"locality"
},
  "geometry": {"coordinates":[22.95573,42.18195],"type":"Point"}
}