{
  "type": "Feature",
  "properties": {
    "gn:admin1_code":"44",
    "gn:asciiname":"Zimnitsa",
    "gn:country_code":"BG",
    "gn:dem":550,
    "gn:feature_class":"P",
    "gn:feature_code":"PPL",
    "gn:name":"Zimnitsa",
    "gn:population":0,
    "gn:timezone":"Europe/Sofia",
    "iso:country":"BG",
    "name:bul_x_preferred":[
        "\u0417\u0438\u043c\u043d\u0438\u0446\u0430"
    ],
    "wof:name":"Zimnitsa",
    "wof:placetype":"locality"
},
  "geometry": {"coordinates":[25.08333,41.68333],"type":"Point"}
}