{
  "type": "Feature",
  "properties": {
    "gn:admin1_code":"64",
    "gn:admin2_code":"VRC27",
    "gn:admin3_code":"VRC27-05",
    "gn:asciiname":"Gorna Kremena",
    "gn:cc2":"BG",
    "gn:country_code":"BG",
    "gn:dem":295,
    "gn:feature_class":"P",
    "gn:feature_code":"PPL",
    "gn:name":"Gorna Kremena",
    "gn:population":0,
    "gn:timezone":"Europe/Sofia",
    "iso:country":"BG",
    "name:bul_x_preferred":[
        "\u0413\u043e\u0440\u043d\u0430 \u041a\u0440\u0435\u043c\u0435\u043d\u0430"
    ],
    "name:und_x_variant":[
        "Kremena",
        "Gorna Kremena"
    ],
    "wof:name":"Gorna Kremena",
    "wof:placetype":"locality"
},
  "geometry": {"coordinates":[23.73333,43.18333],"type":"Point"}
}