{
  "type": "Feature",
  "properties": {
    "gn:admin1_code":"61",
    "gn:asciiname":"General-Kolevo",
    "gn:cc2":"BG",
    "gn:country_code":"BG",
    "gn:dem":277,
    "gn:feature_class":"P",
    "gn:feature_code":"PPL",
    "gn:name":"General-Kolevo",
    "gn:population":0,
    "gn:timezone":"Europe/Sofia",
    "iso:country":"BG",
    "name:bul_x_preferred":[
        "\u0413\u0435\u043d\u0435\u0440\u0430\u043b-\u041a\u043e\u043b\u0435\u0432\u043e"
    ],
    "name:und_x_variant":[
        "Arablar",
        "General Kolewo",
        "Araplar",
        "General-Kolevo"
    ],
    "wof:name":"General-Kolevo",
    "wof:placetype":"locality"
},
  "geometry": {"coordinates":[27.36667000000001,43.51667],"type":"Point"}
}