{
  "type": "Feature",
  "properties": {
    "gn:admin1_code":"48",
    "gn:admin2_code":"PAZ08",
    "gn:asciiname":"Tsvetino",
    "gn:cc2":"BG",
    "gn:country_code":"BG",
    "gn:dem":1179,
    "gn:feature_class":"P",
    "gn:feature_code":"PPL",
    "gn:name":"Tsvetino",
    "gn:population":0,
    "gn:timezone":"Europe/Sofia",
    "iso:country":"BG",
    "name:bul_x_preferred":[
        "\u0446\u0432\u0435\u0442\u0438\u043d\u043e"
    ],
    "name:und_x_variant":[
        "Zwetino",
        "Florovo",
        "Tsvyetino",
        "Tsvetino"
    ],
    "wof:name":"Tsvetino",
    "wof:placetype":"locality"
},
  "geometry": {"coordinates":[23.85,41.98333],"type":"Point"}
}