{
  "type": "Feature",
  "properties": {
    "gn:admin1_code":"58",
    "gn:admin2_code":"SFO20",
    "gn:asciiname":"Bogdanovtsi",
    "gn:cc2":"BG",
    "gn:country_code":"BG",
    "gn:dem":932,
    "gn:feature_class":"P",
    "gn:feature_code":"PPL",
    "gn:name":"Bogdanovtsi",
    "gn:population":0,
    "gn:timezone":"Europe/Sofia",
    "iso:country":"BG",
    "name:bul_x_preferred":[
        "\u0411\u043e\u0433\u0434\u0430\u043d\u043e\u0432\u0446\u0438"
    ],
    "name:und_x_variant":[
        "Bogdanowzi",
        "Bogdanovtsi"
    ],
    "wof:name":"Bogdanovtsi",
    "wof:placetype":"locality"
},
  "geometry": {"coordinates":[23.78333,42.53333],"type":"Point"}
}