{
  "type": "Feature",
  "properties": {
    "gn:admin1_code":"41",
    "gn:admin2_code":"GAB29",
    "gn:admin3_code":"GAB29-25",
    "gn:asciiname":"Sennik",
    "gn:cc2":"BG",
    "gn:country_code":"BG",
    "gn:dem":269,
    "gn:feature_class":"P",
    "gn:feature_code":"PPL",
    "gn:name":"Sennik",
    "gn:population":0,
    "gn:timezone":"Europe/Sofia",
    "iso:country":"BG",
    "name:bul_x_preferred":[
        "\u0421\u0435\u043d\u043d\u0438\u043a"
    ],
    "name:ceb_x_preferred":[
        "Sennik"
    ],
    "name:fas_x_preferred":[
        "\u0633\u0646\u0646\u06cc\u06a9"
    ],
    "name:kaz_x_preferred":[
        "\u0421\u0435\u043d\u043d\u0438\u043a"
    ],
    "name:pol_x_preferred":[
        "Sennik"
    ],
    "name:ron_x_preferred":[
        "Sennik"
    ],
    "name:rus_x_preferred":[
        "\u0421\u0435\u043d\u043d\u0438\u043a"
    ],
    "name:swe_x_preferred":[
        "Sennik"
    ],
    "name:ukr_x_preferred":[
        "\u0421\u0435\u043d\u043d\u0438\u043a"
    ],
    "name:und_x_variant":[
        "Chad\u016drlii",
        "Syennik",
        "Chad\u016drl\u016d",
        "Chad\u0103rlii",
        "\u010cadirli",
        "Sennik"
    ],
    "wof:name":"Sennik",
    "wof:placetype":"locality"
},
  "geometry": {"coordinates":[25.05,42.98333],"type":"Point"}
}