{
  "type": "Feature",
  "properties": {
    "gn:admin1_code":"60",
    "gn:admin2_code":"TGV35",
    "gn:admin3_code":"TGV35-26",
    "gn:asciiname":"Paydushko",
    "gn:cc2":"BG",
    "gn:country_code":"BG",
    "gn:dem":509,
    "gn:feature_class":"P",
    "gn:feature_code":"PPL",
    "gn:name":"Paydushko",
    "gn:population":0,
    "gn:timezone":"Europe/Sofia",
    "iso:country":"BG",
    "name:bul_x_preferred":[
        "\u041f\u0430\u0439\u0434\u0443\u0448\u043a\u043e"
    ],
    "name:und_x_variant":[
        "K\u2019ochekler",
        "Paiduschko",
        "Kirtirle Makhle",
        "Paydushko"
    ],
    "wof:name":"Paydushko",
    "wof:placetype":"locality"
},
  "geometry": {"coordinates":[26.45,43.18333],"type":"Point"}
}