{
  "type": "Feature",
  "properties": {
    "gn:admin1_code":"47",
    "gn:admin2_code":"MON26",
    "gn:admin3_code":"MON26-01",
    "gn:asciiname":"Asparuhovo",
    "gn:country_code":"BG",
    "gn:dem":136,
    "gn:feature_class":"P",
    "gn:feature_code":"PPL",
    "gn:name":"Asparuhovo",
    "gn:population":0,
    "gn:timezone":"Europe/Sofia",
    "iso:country":"BG",
    "name:bul_x_preferred":[
        "\u0410\u0441\u043f\u0430\u0440\u0443\u0445\u043e\u0432\u043e"
    ],
    "name:bul_x_variant":[
        "Asparuhovo"
    ],
    "name:und_x_variant":[
        "K\u016drki Zhaba",
        "Asparuchowo",
        "Asparukhovo"
    ],
    "wof:name":"Asparuhovo",
    "wof:placetype":"locality"
},
  "geometry": {"coordinates":[23.21367,43.70418],"type":"Point"}
}