{
  "type": "Feature",
  "properties": {
    "gn:admin1_code":"44",
    "gn:admin2_code":"KRZ16",
    "gn:admin3_code":"KRZ16-04",
    "gn:asciiname":"Veleshani",
    "gn:cc2":"BG",
    "gn:country_code":"BG",
    "gn:dem":563,
    "gn:feature_class":"P",
    "gn:feature_code":"PPL",
    "gn:name":"Veleshani",
    "gn:population":0,
    "gn:timezone":"Europe/Sofia",
    "iso:country":"BG",
    "name:bul_x_preferred":[
        "\u0412\u0435\u043b\u0435\u0448\u0430\u043d\u0438"
    ],
    "name:und_x_variant":[
        "Tyurk Kabaach",
        "Weleschani",
        "Veleshani"
    ],
    "wof:name":"Veleshani",
    "wof:placetype":"locality"
},
  "geometry": {"coordinates":[25.28333,41.58333],"type":"Point"}
}