{
  "type": "Feature",
  "properties": {
    "gn:admin1_code":"44",
    "gn:admin2_code":"KRZ16",
    "gn:admin3_code":"KRZ16-04",
    "gn:asciiname":"Veleshani",
    "gn:cc2":"BG",
    "gn:country_code":"BG",
    "gn:dem":563,
    "gn:feature_class":"P",
    "gn:feature_code":"PPL",
    "gn:name":"Veleshani",
    "gn:population":0,
    "gn:timezone":"Europe/Sofia",
    "iso:country":"BG",
    "name:bul_x_preferred":[
        "\u0412\u0435\u043b\u0435\u0448\u0430\u043d\u0438"
    ],
    "name:ceb_x_preferred":[
        "Veleshani"
    ],
    "name:fas_x_preferred":[
        "\u0648\u0644\u0634\u0627\u0646\u06cc"
    ],
    "name:kat_x_preferred":[
        "\u10d5\u10d4\u10da\u10d4\u10e8\u10d0\u10dc\u10d8"
    ],
    "name:kaz_x_preferred":[
        "\u0412\u0435\u043b\u0435\u0448\u0430\u043d\u0438"
    ],
    "name:ron_x_preferred":[
        "Vele\u0219ani"
    ],
    "name:rus_x_preferred":[
        "\u0412\u0435\u043b\u0435\u0448\u0430\u043d\u0438"
    ],
    "name:swe_x_preferred":[
        "Velesjani"
    ],
    "name:ukr_x_preferred":[
        "\u0412\u0435\u043b\u0435\u0448\u0430\u043d\u0438"
    ],
    "name:und_x_variant":[
        "Tyurk Kabaach",
        "Weleschani",
        "Veleshani"
    ],
    "wof:name":"Veleshani",
    "wof:placetype":"locality"
},
  "geometry": {"coordinates":[25.28333,41.58333],"type":"Point"}
}