{
  "type": "Feature",
  "properties": {
    "gn:admin1_code":"44",
    "gn:asciiname":"Drazhintsi",
    "gn:country_code":"BG",
    "gn:dem":360,
    "gn:feature_class":"P",
    "gn:feature_code":"PPL",
    "gn:name":"Drazhintsi",
    "gn:population":0,
    "gn:timezone":"Europe/Sofia",
    "iso:country":"BG",
    "name:bul_x_preferred":[
        "Drazhintsi"
    ],
    "name:bul_x_variant":[
        "\u0414\u0440\u0430\u0436\u0438\u043d\u0446\u0438"
    ],
    "wof:name":"Drazhintsi",
    "wof:placetype":"locality"
},
  "geometry": {"coordinates":[25.54484,41.40184],"type":"Point"}
}