{
  "type": "Feature",
  "properties": {
    "gn:admin1_code":"38",
    "gn:asciiname":"Dimovtsi",
    "gn:country_code":"BG",
    "gn:dem":996,
    "gn:feature_class":"P",
    "gn:feature_code":"PPL",
    "gn:name":"Dimovtsi",
    "gn:population":0,
    "gn:timezone":"Europe/Sofia",
    "iso:country":"BG",
    "name:bul_x_preferred":[
        "Dimovtsi"
    ],
    "name:bul_x_variant":[
        "\u0414\u0438\u043c\u043e\u0432\u0446\u0438"
    ],
    "wof:name":"Dimovtsi",
    "wof:placetype":"locality"
},
  "geometry": {"coordinates":[22.9716,41.83976],"type":"Point"}
}