{
  "type": "Feature",
  "properties": {
    "gn:admin1_code":"46",
    "gn:admin2_code":"LOV18",
    "gn:asciiname":"Prelom",
    "gn:cc2":"BG",
    "gn:country_code":"BG",
    "gn:dem":560,
    "gn:feature_class":"P",
    "gn:feature_code":"PPL",
    "gn:name":"Prelom",
    "gn:population":0,
    "gn:timezone":"Europe/Sofia",
    "iso:country":"BG",
    "name:bul_x_preferred":[
        "\u041f\u0440\u0435\u043b\u043e\u043c"
    ],
    "name:fas_x_preferred":[
        "\u067e\u0631\u0644\u0648\u0645"
    ],
    "name:kaz_x_preferred":[
        "\u041f\u0440\u0435\u043b\u043e\u043c"
    ],
    "name:pol_x_preferred":[
        "Pre\u0142om"
    ],
    "name:ron_x_preferred":[
        "Prelom"
    ],
    "name:rus_x_preferred":[
        "\u041f\u0440\u0435\u043b\u043e\u043c"
    ],
    "name:ukr_x_preferred":[
        "\u041f\u0440\u0435\u043b\u043e\u043c"
    ],
    "name:und_x_variant":[
        "Dolni Bivol",
        "Wassilewo",
        "Vasilevo"
    ],
    "wof:name":"Prelom",
    "wof:placetype":"locality"
},
  "geometry": {"coordinates":[24.85,43.06667],"type":"Point"}
}