{
  "type": "Feature",
  "properties": {
    "gn:admin1_code":"44",
    "gn:admin2_code":"KRZ02",
    "gn:asciiname":"Pesnopoy",
    "gn:cc2":"BG",
    "gn:country_code":"BG",
    "gn:dem":558,
    "gn:feature_class":"P",
    "gn:feature_code":"PPL",
    "gn:name":"Pesnopoy",
    "gn:population":0,
    "gn:timezone":"Europe/Sofia",
    "iso:country":"BG",
    "name:bul_x_preferred":[
        "\u041f\u0435\u0441\u043d\u043e\u043f\u043e\u0439"
    ],
    "name:und_x_variant":[
        "Ashiklar",
        "Pesnopoj",
        "Pesnopoy"
    ],
    "wof:name":"Pesnopoy",
    "wof:placetype":"locality"
},
  "geometry": {"coordinates":[25.11667000000001,41.68333],"type":"Point"}
}