{
  "type": "Feature",
  "properties": {
    "gn:admin1_code":"57",
    "gn:asciiname":"Mahmutovtsi",
    "gn:country_code":"BG",
    "gn:dem":995,
    "gn:feature_class":"P",
    "gn:feature_code":"PPL",
    "gn:name":"Mahmutovtsi",
    "gn:population":0,
    "gn:timezone":"Europe/Sofia",
    "iso:country":"BG",
    "name:bul_x_preferred":[
        "\u041c\u0430\u0445\u043c\u0443\u0442\u043e\u0432\u0446\u0438"
    ],
    "name:bul_x_variant":[
        "Mahmutovtsi"
    ],
    "name:und_x_variant":[
        "Makhmutovtsi"
    ],
    "wof:name":"Mahmutovtsi",
    "wof:placetype":"locality"
},
  "geometry": {"coordinates":[24.88333,41.56667],"type":"Point"}
}