{
  "type": "Feature",
  "properties": {
    "gn:admin1_code":"38",
    "gn:asciiname":"Mizhevtsi",
    "gn:country_code":"BG",
    "gn:dem":574,
    "gn:feature_class":"P",
    "gn:feature_code":"PPL",
    "gn:name":"Mizhevtsi",
    "gn:population":0,
    "gn:timezone":"Europe/Sofia",
    "iso:country":"BG",
    "name:bul_x_preferred":[
        "Mizhevtsi"
    ],
    "name:bul_x_variant":[
        "\u041c\u0438\u0436\u0435\u0432\u0446\u0438"
    ],
    "wof:name":"Mizhevtsi",
    "wof:placetype":"locality"
},
  "geometry": {"coordinates":[22.988,41.93774000000001],"type":"Point"}
}