{
  "type": "Feature",
  "properties": {
    "gn:admin1_code":"59",
    "gn:admin2_code":"SZR31",
    "gn:admin3_code":"SZR31-24",
    "gn:asciiname":"Madzherito",
    "gn:cc2":"BG",
    "gn:country_code":"BG",
    "gn:dem":160,
    "gn:feature_class":"P",
    "gn:feature_code":"PPL",
    "gn:name":"Madzherito",
    "gn:population":0,
    "gn:timezone":"Europe/Sofia",
    "iso:country":"BG",
    "name:bul_x_preferred":[
        "\u041c\u0430\u0434\u0436\u0435\u0440\u0438\u0442\u043e"
    ],
    "name:und_x_variant":[
        "Madsherito",
        "Madzherito"
    ],
    "wof:name":"Madzherito",
    "wof:placetype":"locality"
},
  "geometry": {"coordinates":[25.65,42.36667],"type":"Point"}
}