{
  "type": "Feature",
  "properties": {
    "gn:admin1_code":"63",
    "gn:admin2_code":"VID22",
    "gn:asciiname":"Kosta Perchevo",
    "gn:country_code":"BG",
    "gn:dem":183,
    "gn:feature_class":"P",
    "gn:feature_code":"PPL",
    "gn:name":"Kosta Perchevo",
    "gn:population":0,
    "gn:timezone":"Europe/Sofia",
    "iso:country":"BG",
    "name:bul_x_preferred":[
        "\u041a\u043e\u0441\u0442\u0430 \u041f\u0435\u0440\u0447\u0435\u0432\u043e"
    ],
    "name:und_x_variant":[
        "Psederzi",
        "Kostaperchovo",
        "Psedertsi",
        "Kosta Perchevo"
    ],
    "wof:name":"Kosta Perchevo",
    "wof:placetype":"locality"
},
  "geometry": {"coordinates":[22.5929,43.8537],"type":"Point"}
}