{
  "type": "Feature",
  "properties": {
    "gn:admin1_code":"43",
    "gn:admin2_code":"HKV11",
    "gn:asciiname":"Plevun",
    "gn:country_code":"BG",
    "gn:dem":404,
    "gn:feature_class":"P",
    "gn:feature_code":"PPL",
    "gn:name":"Plevun",
    "gn:population":0,
    "gn:timezone":"Europe/Sofia",
    "iso:country":"BG",
    "name:bul_x_preferred":[
        "\u041f\u043b\u0435\u0432\u0443\u043d"
    ],
    "name:und_x_variant":[
        "Peliwun",
        "Pelevun",
        "Pelivun",
        "Plevun"
    ],
    "wof:name":"Plevun",
    "wof:placetype":"locality"
},
  "geometry": {"coordinates":[26.01873,41.45547],"type":"Point"}
}