{
  "type": "Feature",
  "properties": {
    "gn:admin1_code":"40",
    "gn:admin2_code":"DOB03",
    "gn:admin3_code":"DOB03-14",
    "gn:asciiname":"Karvuna",
    "gn:country_code":"BG",
    "gn:dem":256,
    "gn:feature_class":"P",
    "gn:feature_code":"PPL",
    "gn:name":"Karvuna",
    "gn:population":0,
    "gn:timezone":"Europe/Sofia",
    "iso:country":"BG",
    "name:bul_x_preferred":[
        "\u041a\u0430\u0440\u0432\u0443\u043d\u0430"
    ],
    "name:fas_x_preferred":[
        "\u06a9\u0627\u0631\u0648\u0648\u0646\u0627"
    ],
    "name:kaz_x_preferred":[
        "\u041a\u0430\u0440\u0432\u0443\u043d\u0430"
    ],
    "name:pol_x_preferred":[
        "Karwuna"
    ],
    "name:ron_x_preferred":[
        "Karvuna"
    ],
    "name:rus_x_preferred":[
        "\u041a\u0430\u0440\u0432\u0443\u043d\u0430"
    ],
    "name:ukr_x_preferred":[
        "\u041a\u0430\u0440\u0432\u0443\u043d\u0430"
    ],
    "name:und_x_variant":[
        "Kujukioj",
        "Karwina",
        "Kuyu K\u2019oy"
    ],
    "wof:name":"Karvuna",
    "wof:placetype":"locality"
},
  "geometry": {"coordinates":[28.02134,43.47314],"type":"Point"}
}