{
  "type": "Feature",
  "properties": {
    "gn:admin1_code":"39",
    "gn:admin2_code":"BGS08",
    "gn:asciiname":"Livada",
    "gn:country_code":"BG",
    "gn:dem":10,
    "gn:feature_class":"P",
    "gn:feature_code":"PPL",
    "gn:name":"Livada",
    "gn:population":0,
    "gn:timezone":"Europe/Sofia",
    "iso:country":"BG",
    "name:bul_x_preferred":[
        "\u041b\u0438\u0432\u0430\u0434\u0430"
    ],
    "name:ceb_x_preferred":[
        "Livada"
    ],
    "name:deu_x_preferred":[
        "Livada"
    ],
    "name:epo_x_preferred":[
        "Livada"
    ],
    "name:fra_x_preferred":[
        "Livada"
    ],
    "name:hrv_x_preferred":[
        "Livada"
    ],
    "name:hun_x_preferred":[
        "Livada"
    ],
    "name:ita_x_preferred":[
        "Livada"
    ],
    "name:nld_x_preferred":[
        "Livada"
    ],
    "name:ron_x_preferred":[
        "Livada"
    ],
    "name:rus_x_preferred":[
        "\u041b\u0438\u0432\u0430\u0434\u0430"
    ],
    "name:slk_x_preferred":[
        "Livada"
    ],
    "name:srp_x_preferred":[
        "\u041b\u0438\u0432\u0430\u0434\u0430"
    ],
    "name:swe_x_preferred":[
        "Livada"
    ],
    "name:und_x_variant":[
        "Suwatite",
        "Suvatitye",
        "Suvatite"
    ],
    "wof:name":"Livada",
    "wof:placetype":"locality"
},
  "geometry": {"coordinates":[27.2189,42.44832],"type":"Point"}
}