{
  "type": "Feature",
  "properties": {
    "iso:country":"BG",
    "name:bul_x_preferred":[
        "\u0410\u0442\u0430\u043d\u0430\u0441\u043e\u0432\u0441\u043a\u043e \u0435\u0437\u0435\u0440\u043e"
    ],
    "name:bul_x_variant":[
        "\u0410\u0442\u0430\u043d\u0430\u0441\u043e\u0432\u043e"
    ],
    "name:ceb_x_preferred":[
        "Severno Atanasovsko Ezero"
    ],
    "name:deu_x_preferred":[
        "Atanassow-See"
    ],
    "name:eng_x_preferred":[
        "Atanasovo"
    ],
    "name:eng_x_variant":[
        "Atanas K'oy",
        "Atanaskioy",
        "Atanassowo",
        "Atnanas-Kioi"
    ],
    "name:ita_x_preferred":[
        "Lago Atanasovsko"
    ],
    "name:nno_x_preferred":[
        "Atanasovskosj\u00f8en"
    ],
    "name:ron_x_preferred":[
        "Lacul Atanasovsko"
    ],
    "name:spa_x_preferred":[
        "Lago Atanasovsko"
    ],
    "name:swe_x_preferred":[
        "Atanasovsko ezero"
    ],
    "name:unk_x_variant":[
        "Atanaskioy",
        "Atanasovo"
    ],
    "qs:gn_adm0_cc":"BG",
    "qs:gn_fcode":"PPLX",
    "qs:gn_local":732770,
    "qs:gn_namadm1":"39",
    "qs:gn_name":"Atanasovo",
    "qs:local_max":394,
    "qs:local_sum":394,
    "qs:localhoods":1,
    "qs:name":"Atanasovo",
    "qs:name_adm0":"Bulgaria",
    "qs:name_adm1":"Burgas",
    "qs:name_adm2":"Burgas",
    "qs:name_local":"Burgas",
    "qs:photo_max":63,
    "qs:photo_sum":394,
    "qs:placetype":"Suburb",
    "qs:quad_count":41,
    "qs:woe_adm0":23424771,
    "qs:woe_adm1":20070075,
    "qs:woe_adm2":55873729,
    "qs:woe_lau":0,
    "qs:woe_local":835315,
    "qs:woe_ver":"7.10.0",
    "wd:wordcount":304,
    "wof:lang":[
        "eng"
    ],
    "wof:name":"Atanasovo",
    "wof:placetype":"neighbourhood"
},
  "geometry": {"coordinates":[27.469017,42.509176],"type":"Point"}
}