{
  "type": "Feature",
  "properties": {
    "gn:admin1_code":"38",
    "gn:asciiname":"Sukali",
    "gn:country_code":"BG",
    "gn:dem":720,
    "gn:feature_class":"P",
    "gn:feature_code":"PPL",
    "gn:name":"Sukali",
    "gn:population":0,
    "gn:timezone":"Europe/Sofia",
    "iso:country":"BG",
    "name:bul_x_preferred":[
        "Sukali"
    ],
    "name:bul_x_variant":[
        "\u0421\u0443\u043a\u0430\u043b\u0438"
    ],
    "name:mya_x_preferred":[
        "\u1005\u102f\u1000\u101c\u102d\u1019\u103c\u102d\u102f\u1037"
    ],
    "name:shn_x_preferred":[
        "\u1078\u102f\u1075\u101c\u102d\u104a \u101d\u1035\u1004\u103a\u1038"
    ],
    "wof:name":"Sukali",
    "wof:placetype":"locality"
},
  "geometry": {"coordinates":[22.95675,41.90066],"type":"Point"}
}