{
  "type": "Feature",
  "properties": {
    "gn:admin1_code":"49",
    "gn:admin2_code":"PER32",
    "gn:admin3_code":"PER32-22",
    "gn:asciiname":"Rasnik",
    "gn:country_code":"BG",
    "gn:dem":806,
    "gn:feature_class":"P",
    "gn:feature_code":"PPL",
    "gn:name":"Rasnik",
    "gn:population":0,
    "gn:timezone":"Europe/Sofia",
    "iso:country":"BG",
    "name:bul_x_preferred":[
        "\u0420\u0430\u0441\u043d\u0438\u043a"
    ],
    "wof:name":"Rasnik",
    "wof:placetype":"locality"
},
  "geometry": {"coordinates":[22.99883,42.70327],"type":"Point"}
}