{
  "type": "Feature",
  "properties": {
    "gn:admin1_code":"57",
    "gn:asciiname":"Shipka",
    "gn:country_code":"BG",
    "gn:dem":1074,
    "gn:feature_class":"P",
    "gn:feature_code":"PPL",
    "gn:name":"Shipka",
    "gn:population":0,
    "gn:timezone":"Europe/Sofia",
    "iso:country":"BG",
    "name:bul_x_preferred":[
        "\u0428\u0438\u043f\u043a\u0430"
    ],
    "name:ceb_x_preferred":[
        "Shipka"
    ],
    "name:deu_x_preferred":[
        "Shipka"
    ],
    "name:pol_x_preferred":[
        "Shipka"
    ],
    "name:por_x_preferred":[
        "Shipka"
    ],
    "name:vie_x_preferred":[
        "Shipka"
    ],
    "wof:name":"Shipka",
    "wof:placetype":"locality"
},
  "geometry": {"coordinates":[25.01667,41.76667],"type":"Point"}
}