{
  "type": "Feature",
  "properties": {
    "gn:admin1_code":"62",
    "gn:admin2_code":"VTR14",
    "gn:asciiname":"Gorna Hadzhiyska",
    "gn:country_code":"BG",
    "gn:dem":339,
    "gn:feature_class":"P",
    "gn:feature_code":"PPL",
    "gn:name":"Gorna Hadzhiyska",
    "gn:population":0,
    "gn:timezone":"Europe/Sofia",
    "iso:country":"BG",
    "name:bul_x_preferred":[
        "\u0413\u043e\u0440\u043d\u0430 \u0425\u0430\u0434\u0436\u0438\u0439\u0441\u043a\u0430"
    ],
    "name:bul_x_variant":[
        "Gorna Hadzhiyska"
    ],
    "name:und_x_variant":[
        "Gorna-Chadshinska",
        "Khadzhi Makhle",
        "Gorna Khadzhiyska"
    ],
    "wof:name":"Gorna Hadzhiyska",
    "wof:placetype":"locality"
},
  "geometry": {"coordinates":[25.98333,43.03333],"type":"Point"}
}