{
  "type": "Feature",
  "properties": {
    "gn:admin1_code":"38",
    "gn:admin2_code":"BLG40",
    "gn:asciiname":"Piperitsa",
    "gn:country_code":"BG",
    "gn:dem":235,
    "gn:feature_class":"P",
    "gn:feature_code":"PPL",
    "gn:name":"Piperitsa",
    "gn:population":0,
    "gn:timezone":"Europe/Sofia",
    "iso:country":"BG",
    "name:bul_x_preferred":[
        "\u041f\u0438\u043f\u0435\u0440\u0438\u0446\u0430"
    ],
    "name:fas_x_preferred":[
        "\u067e\u06cc\u067e\u0631\u06cc\u062a\u0633\u0627"
    ],
    "name:kaz_x_preferred":[
        "\u041f\u0438\u043f\u0435\u0440\u0438\u0446\u0430"
    ],
    "name:mkd_x_preferred":[
        "\u041f\u0438\u043f\u0435\u0440\u0438\u0446\u0430"
    ],
    "name:pol_x_preferred":[
        "Piperica"
    ],
    "name:ron_x_preferred":[
        "Piperi\u021ba"
    ],
    "name:rus_x_preferred":[
        "\u041f\u0438\u043f\u0435\u0440\u0438\u0446\u0430"
    ],
    "name:ukr_x_preferred":[
        "\u041f\u0438\u043f\u0435\u0440\u0438\u0446\u044f"
    ],
    "name:und_x_variant":[
        "Piperiza",
        "Piperitsa"
    ],
    "wof:name":"Piperitsa",
    "wof:placetype":"locality"
},
  "geometry": {"coordinates":[23.43909,41.41058],"type":"Point"}
}