{
  "type": "Feature",
  "properties": {
    "gn:admin1_code":"55",
    "gn:admin2_code":"SLS34",
    "gn:admin3_code":"SLS34-04",
    "gn:asciiname":"Varnentsi",
    "gn:country_code":"BG",
    "gn:dem":123,
    "gn:feature_class":"P",
    "gn:feature_code":"PPL",
    "gn:name":"Varnentsi",
    "gn:population":0,
    "gn:timezone":"Europe/Sofia",
    "iso:country":"BG",
    "name:bul_x_preferred":[
        "\u0412\u0430\u0440\u043d\u0435\u043d\u0446\u0438"
    ],
    "name:und_x_variant":[
        "Denizler",
        "Denisler",
        "Varnentsi"
    ],
    "wof:name":"Varnentsi",
    "wof:placetype":"locality"
},
  "geometry": {"coordinates":[26.61892000000001,43.94244000000001],"type":"Point"}
}