{
  "type": "Feature",
  "properties": {
    "gn:admin1_code":"44",
    "gn:asciiname":"Datin",
    "gn:country_code":"BG",
    "gn:dem":387,
    "gn:feature_class":"P",
    "gn:feature_code":"PPL",
    "gn:name":"Datin",
    "gn:population":0,
    "gn:timezone":"Europe/Sofia",
    "iso:country":"BG",
    "name:bul_x_preferred":[
        "Datin"
    ],
    "name:bul_x_variant":[
        "\u0414\u0430\u0442\u0438\u043d"
    ],
    "name:por_x_preferred":[
        "Datin"
    ],
    "wof:name":"Datin",
    "wof:placetype":"locality"
},
  "geometry": {"coordinates":[25.57858,41.45426],"type":"Point"}
}