{
  "type": "Feature",
  "properties": {
    "gn:admin1_code":"57",
    "gn:admin2_code":"SML16",
    "gn:asciiname":"Tankoto",
    "gn:country_code":"BG",
    "gn:dem":996,
    "gn:feature_class":"P",
    "gn:feature_code":"PPL",
    "gn:name":"Tankoto",
    "gn:population":0,
    "gn:timezone":"Europe/Sofia",
    "iso:country":"BG",
    "name:bul_x_preferred":[
        "\u0422\u044a\u043d\u043a\u043e\u0442\u043e"
    ],
    "name:bul_x_variant":[
        "Tankoto"
    ],
    "name:und_x_variant":[
        "Kayryak\u016dt",
        "T\u0103nkoto",
        "T\u016dnkoto"
    ],
    "wof:name":"Tankoto",
    "wof:placetype":"locality"
},
  "geometry": {"coordinates":[24.97399,41.48736],"type":"Point"}
}