{
  "type": "Feature",
  "properties": {
    "gn:admin1_code":"39",
    "gn:admin2_code":"BGS17",
    "gn:admin3_code":"BGS17-10",
    "gn:asciiname":"Kamenar",
    "gn:country_code":"BG",
    "gn:dem":32,
    "gn:feature_class":"P",
    "gn:feature_code":"PPL",
    "gn:name":"Kamenar",
    "gn:population":0,
    "gn:timezone":"Europe/Sofia",
    "iso:country":"BG",
    "name:bul_x_preferred":[
        "\u041a\u0430\u043c\u0435\u043d\u0430\u0440"
    ],
    "name:ceb_x_preferred":[
        "Kamenar"
    ],
    "name:deu_x_preferred":[
        "Kamenar"
    ],
    "name:fra_x_preferred":[
        "Kamenar"
    ],
    "name:ron_x_preferred":[
        "Kamenar"
    ],
    "name:rus_x_preferred":[
        "\u041a\u0430\u043c\u0435\u043d\u0430\u0440"
    ],
    "name:swe_x_preferred":[
        "Kamenar"
    ],
    "name:ukr_x_preferred":[
        "\u041a\u0430\u043c\u0435\u043d\u0430\u0440"
    ],
    "name:und_x_variant":[
        "Alekariya",
        "Alahkaria",
        "Alikariya"
    ],
    "wof:name":"Kamenar",
    "wof:placetype":"locality"
},
  "geometry": {"coordinates":[27.57402,42.62678],"type":"Point"}
}