{
  "type": "Feature",
  "properties": {
    "gn:admin1_code":"62",
    "gn:asciiname":"Vitevtsi",
    "gn:cc2":"BG",
    "gn:country_code":"BG",
    "gn:dem":448,
    "gn:feature_class":"P",
    "gn:feature_code":"PPL",
    "gn:name":"Vitevtsi",
    "gn:population":0,
    "gn:timezone":"Europe/Sofia",
    "iso:country":"BG",
    "name:bul_x_preferred":[
        "\u0412\u0438\u0442\u0435\u0432\u0446\u0438"
    ],
    "name:und_x_variant":[
        "Vitevts\u016d",
        "Vitevtsi"
    ],
    "wof:name":"Vitevtsi",
    "wof:placetype":"locality"
},
  "geometry": {"coordinates":[25.81667,42.95],"type":"Point"}
}