{
  "type": "Feature",
  "properties": {
    "iso:country":"BG",
    "name:bul_x_preferred":[
        "\u0420\u043e\u0433\u0430\u0447"
    ],
    "name:eng_x_preferred":[
        "Rogach"
    ],
    "name:eng_x_variant":[
        "Rogatsch",
        "Yumer K'oy"
    ],
    "name:kaz_x_preferred":[
        "\u0420\u043e\u0433\u0430\u0447"
    ],
    "name:ron_x_preferred":[
        "Rogaci"
    ],
    "name:rum_x_preferred":[
        "Rogaci"
    ],
    "name:rus_x_preferred":[
        "\u0420\u043e\u0433\u0430\u0447"
    ],
    "name:ukr_x_preferred":[
        "\u0420\u043e\u0433\u0430\u0447"
    ],
    "name:unk_x_variant":[
        "Yumer K\u2019oy"
    ],
    "qs:a0":"\u0411\u044a\u043b\u0433\u0430\u0440\u0438\u044f",
    "qs:a1":"*\u041a\u044a\u0440\u0434\u0436\u0430\u043b\u0438",
    "qs:a1_alt":"Kardzhali",
    "qs:a1r":"0",
    "qs:adm0":"\u0411\u044a\u043b\u0433\u0430\u0440\u0438\u044f",
    "qs:la_lc":"*",
    "qs:level":"locality",
    "qs:loc":"\u0420\u043e\u0433\u0430\u0447",
    "qs:loc_alt":"Rogach",
    "qs:pop":0,
    "qs:type":"buffered point",
    "wd:wordcount":36,
    "wof:lang":[
        "eng"
    ],
    "wof:name":"\u0420\u043e\u0433\u0430\u0447",
    "wof:placetype":"locality"
},
  "geometry": {"coordinates":[25.686959,41.456279],"type":"Point"}
}