{
  "type": "Feature",
  "properties": {
    "gn:admin1_code":"44",
    "gn:asciiname":"Gubertsi",
    "gn:country_code":"BG",
    "gn:dem":454,
    "gn:feature_class":"P",
    "gn:feature_code":"PPL",
    "gn:name":"Gubertsi",
    "gn:population":0,
    "gn:timezone":"Europe/Sofia",
    "iso:country":"BG",
    "name:bul_x_preferred":[
        "Gubertsi"
    ],
    "name:bul_x_variant":[
        "\u0413\u0443\u0431\u0435\u0440\u0446\u0438"
    ],
    "wof:name":"Gubertsi",
    "wof:placetype":"locality"
},
  "geometry": {"coordinates":[25.31323,41.36494],"type":"Point"}
}