{
  "type": "Feature",
  "properties": {
    "gn:admin1_code":"41",
    "gn:admin2_code":"GAB35",
    "gn:asciiname":"Mrazetsi",
    "gn:country_code":"BG",
    "gn:dem":792,
    "gn:feature_class":"P",
    "gn:feature_code":"PPL",
    "gn:name":"Mrazetsi",
    "gn:population":0,
    "gn:timezone":"Europe/Sofia",
    "iso:country":"BG",
    "name:bul_x_preferred":[
        "\u041c\u0440\u044a\u0437\u0435\u0446\u0438"
    ],
    "name:bul_x_variant":[
        "Mrazetsi"
    ],
    "name:und_x_variant":[
        "Mrazets",
        "Mr\u016dzetsi"
    ],
    "wof:name":"Mrazetsi",
    "wof:placetype":"locality"
},
  "geometry": {"coordinates":[25.55,42.78333],"type":"Point"}
}