{
  "type": "Feature",
  "properties": {
    "gn:admin1_code":"41",
    "gn:admin2_code":"GAB35",
    "gn:asciiname":"Mrazetsi",
    "gn:country_code":"BG",
    "gn:dem":792,
    "gn:feature_class":"P",
    "gn:feature_code":"PPL",
    "gn:name":"Mrazetsi",
    "gn:population":0,
    "gn:timezone":"Europe/Sofia",
    "iso:country":"BG",
    "name:bul_x_preferred":[
        "\u041c\u0440\u044a\u0437\u0435\u0446\u0438"
    ],
    "name:bul_x_variant":[
        "Mrazetsi"
    ],
    "name:fas_x_preferred":[
        "\u0645\u0631\u0627\u0632\u062a\u0633\u06cc"
    ],
    "name:kaz_x_preferred":[
        "\u041c\u0440\u044b\u0437\u0435\u0446\u0438"
    ],
    "name:pol_x_preferred":[
        "Mryzeci"
    ],
    "name:ron_x_preferred":[
        "Mr\u0103ze\u021bi"
    ],
    "name:rus_x_preferred":[
        "\u041c\u0440\u044b\u0437\u0435\u0446\u0438"
    ],
    "name:ukr_x_preferred":[
        "\u041c\u0440\u0438\u0437\u0435\u0446\u0456"
    ],
    "name:und_x_variant":[
        "Mrazets",
        "Mr\u016dzetsi"
    ],
    "wof:name":"Mrazetsi",
    "wof:placetype":"locality"
},
  "geometry": {"coordinates":[25.55,42.78333],"type":"Point"}
}