{
  "type": "Feature",
  "properties": {
    "gn:admin1_code":"63",
    "gn:admin2_code":"VID15",
    "gn:asciiname":"Brankovtsi",
    "gn:country_code":"BG",
    "gn:dem":209,
    "gn:feature_class":"P",
    "gn:feature_code":"PPL",
    "gn:name":"Brankovtsi",
    "gn:population":0,
    "gn:timezone":"Europe/Sofia",
    "iso:country":"BG",
    "name:bul_x_preferred":[
        "\u0411\u0440\u0430\u043d\u043a\u043e\u0432\u0446\u0438"
    ],
    "name:und_x_variant":[
        "Brankowzi",
        "Brankovtsi"
    ],
    "wof:name":"Brankovtsi",
    "wof:placetype":"locality"
},
  "geometry": {"coordinates":[22.565,43.82645],"type":"Point"}
}