{
  "type": "Feature",
  "properties": {
    "gn:admin1_code":"44",
    "gn:asciiname":"Veli Pashalar",
    "gn:country_code":"BG",
    "gn:dem":654,
    "gn:feature_class":"P",
    "gn:feature_code":"PPL",
    "gn:name":"Veli Pashalar",
    "gn:population":0,
    "gn:timezone":"Europe/Sofia",
    "iso:country":"BG",
    "name:bul_x_preferred":[
        "\u0412\u0435\u043b\u0438 \u041f\u0430\u0448\u0430\u043b\u0430\u0440"
    ],
    "wof:name":"Veli Pashalar",
    "wof:placetype":"locality"
},
  "geometry": {"coordinates":[25.08333,41.55],"type":"Point"}
}