{
  "type": "Feature",
  "properties": {
    "gn:admin1_code":"61",
    "gn:admin2_code":"VAR09",
    "gn:asciiname":"Shtipsko",
    "gn:cc2":"BG",
    "gn:country_code":"BG",
    "gn:dem":240,
    "gn:feature_class":"P",
    "gn:feature_code":"PPL",
    "gn:name":"Shtipsko",
    "gn:population":0,
    "gn:timezone":"Europe/Sofia",
    "iso:country":"BG",
    "name:bul_x_preferred":[
        "\u0429\u0438\u043f\u0441\u043a\u043e"
    ],
    "name:und_x_variant":[
        "Khas\u016drdzhik",
        "Schtipsko",
        "Shtipsko"
    ],
    "wof:name":"Shtipsko",
    "wof:placetype":"locality"
},
  "geometry": {"coordinates":[27.53333,43.38333],"type":"Point"}
}