{
  "type": "Feature",
  "properties": {
    "gn:admin1_code":"65",
    "gn:admin2_code":"JAM25",
    "gn:admin3_code":"JAM25-46",
    "gn:asciiname":"Meden Kladenets",
    "gn:country_code":"BG",
    "gn:dem":188,
    "gn:feature_class":"P",
    "gn:feature_code":"PPL",
    "gn:name":"Meden Kladenets",
    "gn:population":0,
    "gn:timezone":"Europe/Sofia",
    "iso:country":"BG",
    "name:bul_x_preferred":[
        "\u041c\u0435\u0434\u0435\u043d \u041a\u043b\u0430\u0434\u0435\u043d\u0435\u0446"
    ],
    "name:und_x_variant":[
        "Bali Bunar",
        "Meden-Kladenez",
        "Ball\u016d Bunar",
        "Meden-Kladene",
        "Balli Bunar",
        "Ball\u0103-Bunar",
        "Meden Kladenets"
    ],
    "wof:name":"Meden Kladenets",
    "wof:placetype":"locality"
},
  "geometry": {"coordinates":[26.31667,42.31667],"type":"Point"}
}