{
  "type": "Feature",
  "properties": {
    "gn:admin1_code":"55",
    "gn:admin2_code":"SLS07",
    "gn:admin3_code":"SLS07-26",
    "gn:asciiname":"Valkan",
    "gn:country_code":"BG",
    "gn:dem":194,
    "gn:feature_class":"P",
    "gn:feature_code":"PPL",
    "gn:name":"Valkan",
    "gn:population":0,
    "gn:timezone":"Europe/Sofia",
    "iso:country":"BG",
    "name:bul_x_preferred":[
        "\u0412\u044a\u043b\u043a\u0430\u043d"
    ],
    "name:bul_x_variant":[
        "Valkan"
    ],
    "name:und_x_variant":[
        "Kurt Palar",
        "Balkan",
        "Curt-Palar",
        "V\u016dlkan"
    ],
    "wof:name":"Valkan",
    "wof:placetype":"locality"
},
  "geometry": {"coordinates":[26.88333,43.83333],"type":"Point"}
}