{
  "type": "Feature",
  "properties": {
    "gn:admin1_code":"63",
    "gn:admin2_code":"VID09",
    "gn:admin3_code":"VID09-29",
    "gn:asciiname":"Slana Bara",
    "gn:country_code":"BG",
    "gn:dem":35,
    "gn:feature_class":"P",
    "gn:feature_code":"PPL",
    "gn:name":"Slana Bara",
    "gn:population":0,
    "gn:timezone":"Europe/Sofia",
    "iso:country":"BG",
    "name:bul_x_preferred":[
        "\u0421\u043b\u0430\u043d\u0430 \u0411\u0430\u0440\u0430"
    ],
    "name:und_x_variant":[
        "Tatardzhik",
        "Slana",
        "Slana Bara"
    ],
    "wof:name":"Slana Bara",
    "wof:placetype":"locality"
},
  "geometry": {"coordinates":[22.80788,43.971],"type":"Point"}
}