{
  "type": "Feature",
  "properties": {
    "gn:admin1_code":"62",
    "gn:admin2_code":"VTR13",
    "gn:admin3_code":"VTR13-01",
    "gn:asciiname":"Bogdansko",
    "gn:cc2":"BG",
    "gn:country_code":"BG",
    "gn:dem":418,
    "gn:feature_class":"P",
    "gn:feature_code":"PPL",
    "gn:name":"Bogdansko",
    "gn:population":0,
    "gn:timezone":"Europe/Sofia",
    "iso:country":"BG",
    "name:bul_x_preferred":[
        "\u0411\u043e\u0433\u0434\u0430\u043d\u0441\u043a\u043e"
    ],
    "name:und_x_variant":[
        "Syulyumenchovtsi",
        "Bogdansko"
    ],
    "wof:name":"Bogdansko",
    "wof:placetype":"locality"
},
  "geometry": {"coordinates":[26.01667,42.95],"type":"Point"}
}