{
  "type": "Feature",
  "properties": {
    "gn:admin1_code":"41",
    "gn:admin2_code":"VTR04",
    "gn:admin3_code":"VTR04-09",
    "gn:asciiname":"Sarnentsi",
    "gn:country_code":"BG",
    "gn:dem":473,
    "gn:feature_class":"P",
    "gn:feature_code":"PPL",
    "gn:name":"Sarnentsi",
    "gn:population":0,
    "gn:timezone":"Europe/Sofia",
    "iso:country":"BG",
    "name:bul_x_preferred":[
        "\u0421\u044a\u0440\u043d\u0435\u043d\u0446\u0438"
    ],
    "name:bul_x_variant":[
        "Sarnentsi"
    ],
    "name:und_x_variant":[
        "Karadzhevts\u016d",
        "Karadzhovtsi",
        "S\u016drnentsi"
    ],
    "wof:name":"Sarnentsi",
    "wof:placetype":"locality"
},
  "geometry": {"coordinates":[25.61667000000001,42.86667],"type":"Point"}
}