{
  "type": "Feature",
  "properties": {
    "gn:admin1_code":"58",
    "gn:admin2_code":"SFO16",
    "gn:asciiname":"Letnitsa",
    "gn:country_code":"BG",
    "gn:dem":713,
    "gn:feature_class":"P",
    "gn:feature_code":"PPL",
    "gn:name":"Letnitsa",
    "gn:population":0,
    "gn:timezone":"Europe/Sofia",
    "iso:country":"BG",
    "name:bul_x_preferred":[
        "\u041b\u0435\u0442\u043d\u0438\u0446\u0430"
    ],
    "name:und_x_variant":[
        "Lyetnitsa",
        "Letniza",
        "Lepnitsa",
        "Letnitsa"
    ],
    "wof:name":"Letnitsa",
    "wof:placetype":"locality"
},
  "geometry": {"coordinates":[22.93037,42.95717],"type":"Point"}
}