{
  "type": "Feature",
  "properties": {
    "gn:admin1_code":"58",
    "gn:admin2_code":"SFO16",
    "gn:asciiname":"Letnitsa",
    "gn:country_code":"BG",
    "gn:dem":713,
    "gn:feature_class":"P",
    "gn:feature_code":"PPL",
    "gn:name":"Letnitsa",
    "gn:population":0,
    "gn:timezone":"Europe/Sofia",
    "iso:country":"BG",
    "name:azb_x_preferred":[
        "\u0644\u062a\u0646\u06cc\u062a\u0633\u0627"
    ],
    "name:bul_x_preferred":[
        "\u041b\u0435\u0442\u043d\u0438\u0446\u0430"
    ],
    "name:ceb_x_preferred":[
        "Obshtina Letnitsa"
    ],
    "name:ckb_x_preferred":[
        "\u0644\u06ce\u062a\u0646\u06cc\u062a\u0633\u0627"
    ],
    "name:fas_x_preferred":[
        "\u0644\u062a\u0646\u06cc\u062a\u0633\u0627"
    ],
    "name:fin_x_preferred":[
        "Letnitsa"
    ],
    "name:jpn_x_preferred":[
        "\u30ec\u30c8\u30cb\u30c4\u30a1"
    ],
    "name:kaz_x_preferred":[
        "\u041b\u0435\u0442\u043d\u0438\u0446\u0430"
    ],
    "name:pol_x_preferred":[
        "Letnica"
    ],
    "name:por_x_preferred":[
        "Letnica"
    ],
    "name:ron_x_preferred":[
        "Letni\u021ba"
    ],
    "name:rus_x_preferred":[
        "\u041b\u0435\u0442\u043d\u0438\u0446\u0430"
    ],
    "name:spa_x_preferred":[
        "Letnitsa"
    ],
    "name:srp_x_preferred":[
        "\u041b\u0435\u0442\u043d\u0438\u0446\u0430"
    ],
    "name:swe_x_preferred":[
        "Letnitsa"
    ],
    "name:tur_x_preferred":[
        "Letni\u00e7a"
    ],
    "name:ukr_x_preferred":[
        "\u041b\u0435\u0442\u043d\u0438\u0446\u044f"
    ],
    "name:und_x_variant":[
        "Lyetnitsa",
        "Letniza",
        "Lepnitsa"
    ],
    "name:vie_x_preferred":[
        "Letnitsa"
    ],
    "name:war_x_preferred":[
        "Letnitsa"
    ],
    "name:zho_x_preferred":[
        "\u840a\u7279\u5c3c\u5bdf"
    ],
    "wof:name":"Letnitsa",
    "wof:placetype":"locality"
},
  "geometry": {"coordinates":[22.93037,42.95717],"type":"Point"}
}