{
  "type": "Feature",
  "properties": {
    "gn:admin1_code":"58",
    "gn:admin2_code":"SFO45",
    "gn:asciiname":"Radulovtsi",
    "gn:country_code":"BG",
    "gn:dem":730,
    "gn:feature_class":"P",
    "gn:feature_code":"PPL",
    "gn:name":"Radulovtsi",
    "gn:population":0,
    "gn:timezone":"Europe/Sofia",
    "iso:country":"BG",
    "name:bul_x_preferred":[
        "\u0420\u0430\u0434\u0443\u043b\u043e\u0432\u0446\u0438"
    ],
    "name:und_x_variant":[
        "Radulowzi",
        "Radulovtsi"
    ],
    "wof:name":"Radulovtsi",
    "wof:placetype":"locality"
},
  "geometry": {"coordinates":[22.93093,42.82852000000001],"type":"Point"}
}