{
  "type": "Feature",
  "properties": {
    "gn:admin1_code":"45",
    "gn:asciiname":"Vranyantsi",
    "gn:country_code":"BG",
    "gn:dem":1489,
    "gn:feature_class":"P",
    "gn:feature_code":"PPL",
    "gn:name":"Vranyantsi",
    "gn:population":0,
    "gn:timezone":"Europe/Sofia",
    "iso:country":"BG",
    "name:bul_x_preferred":[
        "\u0412\u0440\u0430\u043d\u044f\u043d\u0446\u0438"
    ],
    "name:und_x_variant":[
        "Vranyantsy",
        "Vranyantsi"
    ],
    "wof:name":"Vranyantsi",
    "wof:placetype":"locality"
},
  "geometry": {"coordinates":[22.61014,42.16349],"type":"Point"}
}