{
  "type": "Feature",
  "properties": {
    "gn:admin1_code":"62",
    "gn:admin2_code":"TGV24",
    "gn:asciiname":"Manastiritsa",
    "gn:country_code":"BG",
    "gn:dem":125,
    "gn:feature_class":"P",
    "gn:feature_code":"PPL",
    "gn:name":"Manastiritsa",
    "gn:population":0,
    "gn:timezone":"Europe/Sofia",
    "iso:country":"BG",
    "name:bul_x_preferred":[
        "\u041c\u0430\u043d\u0430\u0441\u0442\u0438\u0440\u0438\u0446\u0430"
    ],
    "name:und_x_variant":[
        "Minsirkioy",
        "Manastiriza",
        "Mans\u016dr",
        "Manastiritsa"
    ],
    "wof:name":"Manastiritsa",
    "wof:placetype":"locality"
},
  "geometry": {"coordinates":[26.06667,43.25],"type":"Point"}
}