{
  "type": "Feature",
  "properties": {
    "gn:admin1_code":"43",
    "gn:asciiname":"Pozlata",
    "gn:country_code":"BG",
    "gn:dem":531,
    "gn:feature_class":"P",
    "gn:feature_code":"PPL",
    "gn:name":"Pozlata",
    "gn:population":0,
    "gn:timezone":"Europe/Sofia",
    "iso:country":"BG",
    "name:bul_x_preferred":[
        "\u041f\u043e\u0437\u043b\u0430\u0442\u0430"
    ],
    "wof:name":"Pozlata",
    "wof:placetype":"locality"
},
  "geometry": {"coordinates":[25.86667000000001,41.51667],"type":"Point"}
}