{
  "type": "Feature",
  "properties": {
    "gn:admin1_code":"63",
    "gn:admin2_code":"VID33",
    "gn:admin3_code":"VID33-07",
    "gn:asciiname":"Drazhintsi",
    "gn:country_code":"BG",
    "gn:dem":167,
    "gn:feature_class":"P",
    "gn:feature_code":"PPL",
    "gn:name":"Drazhintsi",
    "gn:population":0,
    "gn:timezone":"Europe/Sofia",
    "iso:country":"BG",
    "name:bul_x_preferred":[
        "\u0414\u0440\u0430\u0436\u0438\u043d\u0446\u0438"
    ],
    "name:und_x_variant":[
        "Drashinzi",
        "Drazhnitsi",
        "Drazhintsi"
    ],
    "wof:name":"Drazhintsi",
    "wof:placetype":"locality"
},
  "geometry": {"coordinates":[22.87506,43.63164],"type":"Point"}
}