{
  "type": "Feature",
  "properties": {
    "gn:admin1_code":"60",
    "gn:admin2_code":"TGV02",
    "gn:asciiname":"Cherna Voda",
    "gn:cc2":"BG",
    "gn:country_code":"BG",
    "gn:dem":321,
    "gn:feature_class":"P",
    "gn:feature_code":"PPL",
    "gn:name":"Cherna Voda",
    "gn:population":0,
    "gn:timezone":"Europe/Sofia",
    "iso:country":"BG",
    "name:bul_x_preferred":[
        "\u0427\u0435\u0440\u043d\u0430 \u0432\u043e\u0434\u0430"
    ],
    "name:und_x_variant":[
        "Gyundyuzleri",
        "Cherna Voda"
    ],
    "wof:name":"Cherna Voda",
    "wof:placetype":"locality"
},
  "geometry": {"coordinates":[26.16667,42.98333],"type":"Point"}
}