{
  "type": "Feature",
  "properties": {
    "gn:admin1_code":"44",
    "gn:asciiname":"Ratlina",
    "gn:country_code":"BG",
    "gn:dem":350,
    "gn:feature_class":"P",
    "gn:feature_code":"PPL",
    "gn:name":"Ratlina",
    "gn:population":0,
    "gn:timezone":"Europe/Sofia",
    "iso:country":"BG",
    "name:bul_x_preferred":[
        "\u0420\u044a\u0442\u043b\u0438\u043d\u0430"
    ],
    "name:bul_x_variant":[
        "Ratlina"
    ],
    "name:und_x_variant":[
        "R\u016dtlina"
    ],
    "wof:name":"Ratlina",
    "wof:placetype":"locality"
},
  "geometry": {"coordinates":[25.66667,41.55],"type":"Point"}
}