{
  "type": "Feature",
  "properties": {
    "gn:admin1_code":"61",
    "gn:admin2_code":"VAR16",
    "gn:admin3_code":"VAR16-13",
    "gn:asciiname":"Sava",
    "gn:cc2":"BG",
    "gn:country_code":"BG",
    "gn:dem":66,
    "gn:feature_class":"P",
    "gn:feature_code":"PPL",
    "gn:name":"Sava",
    "gn:population":0,
    "gn:timezone":"Europe/Sofia",
    "iso:country":"BG",
    "name:bul_x_preferred":[
        "\u0421\u0430\u0432\u0430"
    ],
    "name:und_x_variant":[
        "Savva",
        "Sawwa",
        "Sava"
    ],
    "wof:name":"Sava",
    "wof:placetype":"locality"
},
  "geometry": {"coordinates":[27.38333,43.03333],"type":"Point"}
}