{
  "type": "Feature",
  "properties": {
    "gn:admin1_code":"49",
    "gn:admin2_code":"PER36",
    "gn:admin3_code":"PER36-27",
    "gn:asciiname":"Dolni Rakovets",
    "gn:country_code":"BG",
    "gn:dem":639,
    "gn:feature_class":"P",
    "gn:feature_code":"PPL",
    "gn:name":"Dolni Rakovets",
    "gn:population":0,
    "gn:timezone":"Europe/Sofia",
    "iso:country":"BG",
    "name:bul_x_preferred":[
        "\u0414\u043e\u043b\u043d\u0438 \u0420\u0430\u043a\u043e\u0432\u0435\u0446"
    ],
    "name:und_x_variant":[
        "Rakovec",
        "Dolni Rakowez",
        "Dolni Rakovets"
    ],
    "wof:name":"Dolni Rakovets",
    "wof:placetype":"locality"
},
  "geometry": {"coordinates":[23.00616,42.47369000000001],"type":"Point"}
}