{
  "type": "Feature",
  "properties": {
    "gn:admin1_code":"63",
    "gn:admin2_code":"VID01",
    "gn:asciiname":"Krachimir",
    "gn:country_code":"BG",
    "gn:dem":478,
    "gn:feature_class":"P",
    "gn:feature_code":"PPL",
    "gn:name":"Krachimir",
    "gn:population":0,
    "gn:timezone":"Europe/Sofia",
    "iso:country":"BG",
    "name:bul_x_preferred":[
        "\u041a\u0440\u0430\u0447\u0438\u043c\u0438\u0440"
    ],
    "name:und_x_variant":[
        "Krachemir",
        "Krachimir"
    ],
    "wof:name":"Krachimir",
    "wof:placetype":"locality"
},
  "geometry": {"coordinates":[22.55507,43.58381],"type":"Point"}
}