{
  "type": "Feature",
  "properties": {
    "gn:admin1_code":"41",
    "gn:asciiname":"Karalite",
    "gn:cc2":"BG",
    "gn:country_code":"BG",
    "gn:dem":534,
    "gn:feature_class":"P",
    "gn:feature_code":"PPL",
    "gn:name":"Karalite",
    "gn:population":0,
    "gn:timezone":"Europe/Sofia",
    "iso:country":"BG",
    "name:bul_x_preferred":[
        "\u041a\u0430\u0440\u0430\u043b\u0438\u0442\u0435"
    ],
    "name:und_x_variant":[
        "Karal\u016dt\u016d",
        "Karalite"
    ],
    "wof:name":"Karalite",
    "wof:placetype":"locality"
},
  "geometry": {"coordinates":[25.38333,42.95],"type":"Point"}
}