{
  "type": "Feature",
  "properties": {
    "gn:admin1_code":"56",
    "gn:asciiname":"Bilo",
    "gn:cc2":"BG",
    "gn:country_code":"BG",
    "gn:dem":534,
    "gn:feature_class":"P",
    "gn:feature_code":"PPL",
    "gn:name":"Bilo",
    "gn:population":0,
    "gn:timezone":"Europe/Sofia",
    "iso:country":"BG",
    "name:bul_x_preferred":[
        "\u0411\u0438\u043b\u043e"
    ],
    "name:und_x_variant":[
        "S\u016drt K\u2019oy",
        "S\u016drdkioi",
        "Bilo"
    ],
    "wof:name":"Bilo",
    "wof:placetype":"locality"
},
  "geometry": {"coordinates":[26.08333,42.88333],"type":"Point"}
}