{
  "type": "Feature",
  "properties": {
    "gn:admin1_code":"41",
    "gn:admin2_code":"GAB12",
    "gn:asciiname":"Glushka",
    "gn:country_code":"BG",
    "gn:dem":630,
    "gn:feature_class":"P",
    "gn:feature_code":"PPL",
    "gn:name":"Glushka",
    "gn:population":0,
    "gn:timezone":"Europe/Sofia",
    "iso:country":"BG",
    "name:ara_x_preferred":[
        "\u063a\u0644\u064a\u0634\u0643\u0627"
    ],
    "name:bul_x_preferred":[
        "\u0413\u043b\u0443\u0448\u043a\u0430"
    ],
    "name:fas_x_preferred":[
        "\u06af\u0644\u0648\u0634\u06a9\u0627"
    ],
    "name:kaz_x_preferred":[
        "\u0413\u043b\u0443\u0448\u043a\u0430"
    ],
    "name:pol_x_preferred":[
        "G\u0142uszka"
    ],
    "name:ron_x_preferred":[
        "Glu\u0219ka"
    ],
    "name:rus_x_preferred":[
        "\u0413\u043b\u0443\u0448\u043a\u0430"
    ],
    "name:ukr_x_preferred":[
        "\u0413\u043b\u0443\u0448\u043a\u0430"
    ],
    "wof:name":"Glushka",
    "wof:placetype":"locality"
},
  "geometry": {"coordinates":[25.51667,42.95],"type":"Point"}
}