{
  "type": "Feature",
  "properties": {
    "gn:admin1_code":"60",
    "gn:admin2_code":"TGV35",
    "gn:admin3_code":"TGV35-09",
    "gn:asciiname":"Vasil Levski",
    "gn:country_code":"BG",
    "gn:dem":153,
    "gn:feature_class":"P",
    "gn:feature_code":"PPL",
    "gn:name":"Vasil Levski",
    "gn:population":0,
    "gn:timezone":"Europe/Sofia",
    "iso:country":"BG",
    "name:bul_x_preferred":[
        "\u0412\u0430\u0441\u0438\u043b \u041b\u0435\u0432\u0441\u043a\u0438"
    ],
    "name:und_x_variant":[
        "Wassil Lewski",
        "Yavashevo",
        "Yavashkioy",
        "Vasil Levski"
    ],
    "wof:name":"Vasil Levski",
    "wof:placetype":"locality"
},
  "geometry": {"coordinates":[26.61667000000001,43.26667],"type":"Point"}
}