{
  "type": "Feature",
  "properties": {
    "gn:admin1_code":"57",
    "gn:admin2_code":"SML31",
    "gn:admin3_code":"SML31-38",
    "gn:asciiname":"Taran",
    "gn:country_code":"BG",
    "gn:dem":689,
    "gn:feature_class":"P",
    "gn:feature_code":"PPL",
    "gn:name":"Taran",
    "gn:population":0,
    "gn:timezone":"Europe/Sofia",
    "iso:country":"BG",
    "name:bel_x_preferred":[
        "\u0422\u0430\u0440\u0430\u043d"
    ],
    "name:bul_x_preferred":[
        "\u0422\u044a\u0440\u044a\u043d"
    ],
    "name:bul_x_variant":[
        "Taran",
        "\u0422\u0430\u0440\u0430\u043d"
    ],
    "name:ceb_x_preferred":[
        "Taran"
    ],
    "name:deu_x_preferred":[
        "Taran"
    ],
    "name:heb_x_preferred":[
        "\u05d8\u05e8\u05df"
    ],
    "name:ita_x_preferred":[
        "Taran"
    ],
    "name:nds_x_preferred":[
        "Taran"
    ],
    "name:pol_x_preferred":[
        "Taran"
    ],
    "name:por_x_preferred":[
        "Taran"
    ],
    "name:rus_x_preferred":[
        "\u0422\u0430\u0440\u0430\u043d"
    ],
    "name:slk_x_preferred":[
        "Taran"
    ],
    "name:swe_x_preferred":[
        "Taran"
    ],
    "name:ukr_x_preferred":[
        "\u0422\u0430\u0440\u0430\u043d"
    ],
    "name:und_x_variant":[
        "Tirin",
        "T\u0103r\u0103n",
        "T\u016dr\u016dn"
    ],
    "name:uzb_x_preferred":[
        "Taran"
    ],
    "wof:name":"Taran",
    "wof:placetype":"locality"
},
  "geometry": {"coordinates":[24.88333,41.55],"type":"Point"}
}