{
  "type": "Feature",
  "properties": {
    "gn:admin1_code":"44",
    "gn:admin2_code":"KRZ16",
    "gn:admin3_code":"KRZ16-20",
    "gn:asciiname":"Chernyovtsi",
    "gn:country_code":"BG",
    "gn:dem":479,
    "gn:feature_class":"P",
    "gn:feature_code":"PPL",
    "gn:name":"Chernyovtsi",
    "gn:population":0,
    "gn:timezone":"Europe/Sofia",
    "iso:country":"BG",
    "name:bul_x_preferred":[
        "\u0427\u0435\u0440\u043d\u044c\u043e\u0432\u0446\u0438"
    ],
    "name:bul_x_variant":[
        "Chernyovtsi"
    ],
    "name:und_x_variant":[
        "Kara Musalar",
        "Tschernjowzi",
        "Chern\u2019ovtsi"
    ],
    "wof:name":"Chernyovtsi",
    "wof:placetype":"locality"
},
  "geometry": {"coordinates":[25.53333,41.73333],"type":"Point"}
}