{
  "type": "Feature",
  "properties": {
    "gn:admin1_code":"44",
    "gn:admin2_code":"KRZ16",
    "gn:admin3_code":"KRZ16-20",
    "gn:asciiname":"Chernyovtsi",
    "gn:country_code":"BG",
    "gn:dem":479,
    "gn:feature_class":"P",
    "gn:feature_code":"PPL",
    "gn:name":"Chernyovtsi",
    "gn:population":0,
    "gn:timezone":"Europe/Sofia",
    "iso:country":"BG",
    "name:bul_x_preferred":[
        "\u0427\u0435\u0440\u043d\u044c\u043e\u0432\u0446\u0438"
    ],
    "name:bul_x_variant":[
        "Chernyovtsi"
    ],
    "name:fas_x_preferred":[
        "\u0686\u0631\u0646\u06cc\u0648\u0648\u062a\u0633\u06cc"
    ],
    "name:kat_x_preferred":[
        "\u10e9\u10d4\u10e0\u10dc\u10d8\u10dd\u10d5\u10ea\u10d8"
    ],
    "name:pol_x_preferred":[
        "Czernjowci"
    ],
    "name:ron_x_preferred":[
        "Cernov\u021bi"
    ],
    "name:rus_x_preferred":[
        "\u0427\u0435\u0440\u043d\u0451\u0432\u0446\u0438"
    ],
    "name:ukr_x_preferred":[
        "\u0427\u0435\u0440\u043d\u044c\u043e\u0432\u0446\u0456"
    ],
    "name:und_x_variant":[
        "Kara Musalar",
        "Tschernjowzi",
        "Chern\u2019ovtsi"
    ],
    "wof:name":"Chernyovtsi",
    "wof:placetype":"locality"
},
  "geometry": {"coordinates":[25.53333,41.73333],"type":"Point"}
}