{
  "type": "Feature",
  "properties": {
    "gn:admin1_code":"55",
    "gn:admin2_code":"SLS10",
    "gn:admin3_code":"SLS10-10",
    "gn:asciiname":"Mezhden",
    "gn:cc2":"BG",
    "gn:country_code":"BG",
    "gn:dem":208,
    "gn:feature_class":"P",
    "gn:feature_code":"PPL",
    "gn:name":"Mezhden",
    "gn:population":0,
    "gn:timezone":"Europe/Sofia",
    "iso:country":"BG",
    "name:bul_x_preferred":[
        "\u041c\u0435\u0436\u0434\u0435\u043d"
    ],
    "name:und_x_variant":[
        "S\u016dn\u016dreni Makhle",
        "Me\u017eden",
        "S\u0103n\u0103r-Eni-Machle",
        "Sinirul Nou",
        "Mezhden"
    ],
    "wof:name":"Mezhden",
    "wof:placetype":"locality"
},
  "geometry": {"coordinates":[27.21667,43.81667],"type":"Point"}
}