{
  "type": "Feature",
  "properties": {
    "gn:admin1_code":"63",
    "gn:admin2_code":"VID33",
    "gn:admin3_code":"VID33-06",
    "gn:asciiname":"Roglets",
    "gn:country_code":"BG",
    "gn:dem":139,
    "gn:feature_class":"P",
    "gn:feature_code":"PPL",
    "gn:name":"Roglets",
    "gn:population":0,
    "gn:timezone":"Europe/Sofia",
    "iso:country":"BG",
    "name:bul_x_preferred":[
        "\u0420\u043e\u0433\u043b\u0435\u0446"
    ],
    "name:und_x_variant":[
        "Roglez",
        "Roglets"
    ],
    "wof:name":"Roglets",
    "wof:placetype":"locality"
},
  "geometry": {"coordinates":[22.93516,43.67064],"type":"Point"}
}