{
  "type": "Feature",
  "properties": {
    "gn:admin1_code":"38",
    "gn:admin2_code":"BLG11",
    "gn:admin3_code":"BLG11-01",
    "gn:asciiname":"Banichan",
    "gn:cc2":"BG",
    "gn:country_code":"BG",
    "gn:dem":565,
    "gn:feature_class":"P",
    "gn:feature_code":"PPL",
    "gn:name":"Banichan",
    "gn:population":0,
    "gn:timezone":"Europe/Sofia",
    "iso:country":"BG",
    "name:bul_x_preferred":[
        "\u0411\u0430\u043d\u0438\u0447\u0430\u043d"
    ],
    "name:ceb_x_preferred":[
        "Banichan"
    ],
    "name:fas_x_preferred":[
        "\u0628\u0627\u0646\u06cc\u0686\u0627\u0646"
    ],
    "name:kaz_x_preferred":[
        "\u0411\u0430\u043d\u0438\u0447\u0430\u043d"
    ],
    "name:mkd_x_preferred":[
        "\u0411\u0430\u043d\u0438\u0447\u0430\u043d"
    ],
    "name:ron_x_preferred":[
        "Banicean"
    ],
    "name:rus_x_preferred":[
        "\u0411\u0430\u043d\u0438\u0447\u0430\u043d"
    ],
    "name:ukr_x_preferred":[
        "\u0411\u0430\u043d\u0438\u0447\u0430\u043d"
    ],
    "name:und_x_variant":[
        "Banitschan"
    ],
    "wof:name":"Banichan",
    "wof:placetype":"locality"
},
  "geometry": {"coordinates":[23.73333,41.61667],"type":"Point"}
}