{
  "type": "Feature",
  "properties": {
    "gn:country":"BG",
    "gn:fcode":"PPL",
    "gn:population":374,
    "iso:country":"BG",
    "name:bul_x_preferred":[
        "\u0411\u0430\u0447\u043a\u043e\u0432\u043e"
    ],
    "name:eng_x_preferred":[
        "Bachkovo"
    ],
    "name:rus_x_preferred":[
        "\u0411\u0430\u0447\u043a\u043e\u0432\u043e"
    ],
    "name:und_x_variant":[
        "Batschkowo"
    ],
    "qs_pg:aaroncc":"BG",
    "qs_pg:gn_country":"BG",
    "qs_pg:gn_fcode":"PPL",
    "qs_pg:gn_pop":374,
    "qs_pg:name":"Bachkovo",
    "qs_pg:photos_9r":0,
    "qs_pg:photos_sr":0,
    "qs_pg:pop_sr":2,
    "qs_pg:qs_pg_placetype":"locality",
    "wof:name":"Bachkovo",
    "wof:placetype":"locality",
    "wof:population":374
},
  "geometry": {"coordinates":[24.86667,41.95],"type":"Point"}
}