{
  "type": "Feature",
  "properties": {
    "gn:admin1_code":"61",
    "gn:admin2_code":"VAR09",
    "gn:admin3_code":"VAR09-12",
    "gn:asciiname":"Karamanite",
    "gn:cc2":"BG",
    "gn:country_code":"BG",
    "gn:dem":220,
    "gn:feature_class":"P",
    "gn:feature_code":"PPL",
    "gn:name":"Karamanite",
    "gn:population":0,
    "gn:timezone":"Europe/Sofia",
    "iso:country":"BG",
    "name:bul_x_preferred":[
        "\u041a\u0430\u0440\u0430\u043c\u0430\u043d\u0438\u0442\u0435"
    ],
    "name:und_x_variant":[
        "Karamanlii",
        "Karamanli",
        "Karamanite"
    ],
    "wof:name":"Karamanite",
    "wof:placetype":"locality"
},
  "geometry": {"coordinates":[27.48333,43.48333],"type":"Point"}
}