{
  "type": "Feature",
  "properties": {
    "gn:admin1_code":"40",
    "gn:admin2_code":"DOB20",
    "gn:admin3_code":"DOB20-06",
    "gn:asciiname":"Efreytor Bakalovo",
    "gn:country_code":"BG",
    "gn:dem":188,
    "gn:feature_class":"P",
    "gn:feature_code":"PPL",
    "gn:name":"Efreytor Bakalovo",
    "gn:population":0,
    "gn:timezone":"Europe/Sofia",
    "iso:country":"BG",
    "name:bul_x_preferred":[
        "\u0415\u0444\u0440\u0435\u0439\u0442\u043e\u0440-\u0411\u0430\u043a\u0430\u043b\u043e\u0432\u043e"
    ],
    "name:bul_x_variant":[
        "Efreytor Bakalovo",
        "\u0415\u0444\u0440\u0435\u0439\u0442\u043e\u0440 \u0411\u0430\u043a\u0430\u043b\u043e\u0432\u043e"
    ],
    "name:fas_x_preferred":[
        "\u0627\u0641\u0631\u06cc\u062a\u0648\u0631 \u0628\u0627\u06a9\u0627\u0644\u0648\u0648\u0648"
    ],
    "name:kaz_x_preferred":[
        "\u0415\u0444\u0440\u0435\u0439\u0442\u043e\u0440-\u0411\u0430\u043a\u0430\u043b\u043e\u0432\u043e"
    ],
    "name:pol_x_preferred":[
        "Efrejtor Baka\u0142owo"
    ],
    "name:ron_x_preferred":[
        "Efreitor Bakalovo"
    ],
    "name:rus_x_preferred":[
        "\u0415\u0444\u0440\u0435\u0439\u0442\u043e\u0440-\u0411\u0430\u043a\u0430\u043b\u043e\u0432\u043e"
    ],
    "name:ukr_x_preferred":[
        "\u0404\u0444\u0440\u0435\u0439\u0442\u043e\u0440-\u0411\u0430\u043a\u0430\u043b\u043e\u0432\u043e"
    ],
    "name:und_x_variant":[
        "Baraclar",
        "Baraklar"
    ],
    "wof:name":"Efreytor Bakalovo",
    "wof:placetype":"locality"
},
  "geometry": {"coordinates":[27.60552,43.83431],"type":"Point"}
}