{
  "type": "Feature",
  "properties": {
    "gn:admin1_code":"45",
    "gn:admin2_code":"KNL31",
    "gn:asciiname":"Nedelkova Grashtitsa",
    "gn:country_code":"BG",
    "gn:dem":494,
    "gn:feature_class":"P",
    "gn:feature_code":"PPL",
    "gn:name":"Nedelkova Grashtitsa",
    "gn:population":0,
    "gn:timezone":"Europe/Sofia",
    "iso:country":"BG",
    "name:bul_x_preferred":[
        "\u041d\u0435\u0434\u0435\u043b\u043a\u043e\u0432\u0430 \u0413\u0440\u0430\u0449\u0438\u0446\u0430"
    ],
    "name:fas_x_preferred":[
        "\u0646\u062f\u0644\u06a9\u0648\u0648\u0627 \u06af\u0631\u0627\u0634\u062a\u06cc\u062a\u0633\u0627"
    ],
    "name:kaz_x_preferred":[
        "\u041d\u0435\u0434\u0435\u043b\u043a\u043e\u0432\u0430-\u0413\u0440\u0430\u0448\u0442\u0438\u0446\u0430"
    ],
    "name:ron_x_preferred":[
        "Nedelkova Gra\u0219ti\u021ba"
    ],
    "name:rus_x_preferred":[
        "\u041d\u0435\u0434\u0435\u043b\u043a\u043e\u0432\u0430-\u0413\u0440\u0430\u0448\u0442\u0438\u0446\u0430"
    ],
    "name:ukr_x_preferred":[
        "\u041d\u0435\u0434\u0435\u043b\u043a\u043e\u0432\u0430 \u0413\u0440\u0430\u0448\u0442\u0438\u0446\u044f"
    ],
    "name:und_x_variant":[
        "Graschtiza-Nedelkowa",
        "Grashatsa Nedyelkova",
        "Nedelkova Grashtitsa"
    ],
    "wof:name":"Nedelkova Grashtitsa",
    "wof:placetype":"locality"
},
  "geometry": {"coordinates":[22.80296,42.23785],"type":"Point"}
}