{
  "type": "Feature",
  "properties": {
    "gn:admin1_code":"60",
    "gn:admin2_code":"TGV35",
    "gn:admin3_code":"TGV35-06",
    "gn:asciiname":"Bratovo",
    "gn:country_code":"BG",
    "gn:dem":491,
    "gn:feature_class":"P",
    "gn:feature_code":"PPL",
    "gn:name":"Bratovo",
    "gn:population":0,
    "gn:timezone":"Europe/Sofia",
    "iso:country":"BG",
    "name:bul_x_preferred":[
        "\u0411\u0440\u0430\u0442\u043e\u0432\u043e"
    ],
    "wof:name":"Bratovo",
    "wof:placetype":"locality"
},
  "geometry": {"coordinates":[26.41667,43.18333],"type":"Point"}
}