{
  "type": "Feature",
  "properties": {
    "gn:admin1_code":"43",
    "gn:admin2_code":"HKV34",
    "gn:admin3_code":"HKV34-08",
    "gn:asciiname":"Galabets",
    "gn:country_code":"BG",
    "gn:dem":282,
    "gn:feature_class":"P",
    "gn:feature_code":"PPL",
    "gn:name":"Galabets",
    "gn:population":0,
    "gn:timezone":"Europe/Sofia",
    "iso:country":"BG",
    "name:bul_x_preferred":[
        "\u0413\u044a\u043b\u044a\u0431\u0435\u0446"
    ],
    "name:bul_x_variant":[
        "Galabets"
    ],
    "name:und_x_variant":[
        "G\u0103l\u0103bez",
        "Gyuvenchler",
        "G\u016dl\u016dbets"
    ],
    "wof:name":"Galabets",
    "wof:placetype":"locality"
},
  "geometry": {"coordinates":[25.43333,41.85],"type":"Point"}
}