{
  "type": "Feature",
  "properties": {
    "iso:country":"BG",
    "name:bul_x_variant":[
        "\u04101"
    ],
    "name:eng_x_preferred":[
        "\u041b\u044e\u043b\u044f\u0446\u0438\u0442\u0435"
    ],
    "wof:name":"Ljuljacite",
    "wof:placetype":"neighbourhood"
},
  "geometry": {"coordinates":[24.77639789498845,42.12641695008374],"type":"Point"}
}