{
  "type": "Feature",
  "properties": {
    "iso:country":"BG",
    "qs_pg:aaroncc":"BG",
    "qs_pg:name":"Devebair",
    "qs_pg:name_adm0":"Macedonia",
    "qs_pg:name_adm1":"Kriva Palanka",
    "qs_pg:photos":15,
    "qs_pg:photos_1k":3,
    "qs_pg:photos_9k":1,
    "qs_pg:photos_9r":1,
    "qs_pg:photos_all":15,
    "qs_pg:photos_sr":1,
    "qs_pg:pop_sr":0,
    "qs_pg:qs_pg_placetype":"locality",
    "qs_pg:qs_pg_placetype_gp":"Town",
    "qs_pg:woe_adm0":23424890,
    "woe:adm0_id":23424890,
    "woe:name_adm0":"Macedonia",
    "woe:name_adm1":"Kriva Palanka",
    "woe:placetype":"Town",
    "wof:name":"Devebair",
    "wof:placetype":"locality"
},
  "geometry": {"coordinates":[22.460732,42.218919],"type":"Point"}
}