{
  "type": "Feature",
  "properties": {
    "gn:admin1_code":"65",
    "gn:admin2_code":"JAM07",
    "gn:admin3_code":"JAM07-14",
    "gn:asciiname":"Melnitsa",
    "gn:cc2":"BG",
    "gn:country_code":"BG",
    "gn:dem":204,
    "gn:feature_class":"P",
    "gn:feature_code":"PPL",
    "gn:name":"Melnitsa",
    "gn:population":0,
    "gn:timezone":"Europe/Sofia",
    "iso:country":"BG",
    "name:bul_x_preferred":[
        "\u041c\u0435\u043b\u043d\u0438\u0446\u0430"
    ],
    "name:und_x_variant":[
        "Dermen-Dere",
        "Melniza",
        "Melnitsa"
    ],
    "wof:name":"Melnitsa",
    "wof:placetype":"locality"
},
  "geometry": {"coordinates":[26.56667,42.05],"type":"Point"}
}