{
  "type": "Feature",
  "properties": {
    "gn:admin1_code":"46",
    "gn:admin2_code":"LOV19",
    "gn:asciiname":"Daben",
    "gn:country_code":"BG",
    "gn:dem":223,
    "gn:feature_class":"P",
    "gn:feature_code":"PPL",
    "gn:name":"Daben",
    "gn:population":0,
    "gn:timezone":"Europe/Sofia",
    "iso:country":"BG",
    "name:bul_x_preferred":[
        "\u0414\u044a\u0431\u0435\u043d"
    ],
    "name:bul_x_variant":[
        "Daben"
    ],
    "name:und_x_variant":[
        "D\u0103ben",
        "D\u016dben"
    ],
    "wof:name":"Daben",
    "wof:placetype":"locality"
},
  "geometry": {"coordinates":[24.21667,43.13333],"type":"Point"}
}