{
  "type": "Feature",
  "properties": {
    "gn:admin1_code":"38",
    "gn:asciiname":"Mahala Polyana",
    "gn:country_code":"BG",
    "gn:dem":282,
    "gn:feature_class":"P",
    "gn:feature_code":"PPL",
    "gn:name":"Mahala Polyana",
    "gn:population":0,
    "gn:timezone":"Europe/Sofia",
    "iso:country":"BG",
    "name:bul_x_preferred":[
        "\u041c\u0430\u0445\u0430\u043b\u0430 \u041f\u043e\u043b\u044f\u043d\u0430"
    ],
    "name:bul_x_variant":[
        "Mahala Polyana"
    ],
    "name:und_x_variant":[
        "Makhala Polyana"
    ],
    "wof:name":"Mahala Polyana",
    "wof:placetype":"locality"
},
  "geometry": {"coordinates":[23.18333,41.73333],"type":"Point"}
}