{
  "type": "Feature",
  "properties": {
    "gn:admin1_code":"50",
    "gn:admin2_code":"PVN21",
    "gn:admin3_code":"PVN21-04",
    "gn:asciiname":"Debovo",
    "gn:country_code":"BG",
    "gn:dem":39,
    "gn:feature_class":"P",
    "gn:feature_code":"PPL",
    "gn:name":"Debovo",
    "gn:population":0,
    "gn:timezone":"Europe/Sofia",
    "iso:country":"BG",
    "name:bul_x_preferred":[
        "\u0414\u0435\u0431\u043e\u0432\u043e"
    ],
    "name:und_x_variant":[
        "Devovo",
        "Devowo",
        "Debovo"
    ],
    "wof:name":"Debovo",
    "wof:placetype":"locality"
},
  "geometry": {"coordinates":[24.87807,43.59104],"type":"Point"}
}