{
  "type": "Feature",
  "properties": {
    "gn:admin1_code":"57",
    "gn:admin2_code":"SML31",
    "gn:asciiname":"Bilyanska",
    "gn:country_code":"BG",
    "gn:dem":1134,
    "gn:feature_class":"P",
    "gn:feature_code":"PPL",
    "gn:name":"Bilyanska",
    "gn:population":0,
    "gn:timezone":"Europe/Sofia",
    "iso:country":"BG",
    "name:bul_x_preferred":[
        "\u0411\u0438\u043b\u044f\u043d\u0441\u043a\u0430"
    ],
    "name:fas_x_preferred":[
        "\u0628\u06cc\u0644\u06cc\u0627\u0646\u0633\u06a9\u0627"
    ],
    "name:kat_x_preferred":[
        "\u10d1\u10d8\u10da\u10d8\u10d0\u10dc\u10e1\u10d9\u10d0"
    ],
    "name:kaz_x_preferred":[
        "\u0411\u0438\u043b\u044f\u043d\u0441\u043a\u0430"
    ],
    "name:msa_x_preferred":[
        "Bilyanska"
    ],
    "name:ron_x_preferred":[
        "Bileanska"
    ],
    "name:rus_x_preferred":[
        "\u0411\u0438\u043b\u044f\u043d\u0441\u043a\u0430"
    ],
    "name:ukr_x_preferred":[
        "\u0411\u0438\u043b\u044f\u043d\u0441\u044c\u043a\u0430"
    ],
    "name:und_x_variant":[
        "Biljanka Machala"
    ],
    "wof:name":"Bilyanska",
    "wof:placetype":"locality"
},
  "geometry": {"coordinates":[24.61852,41.45027],"type":"Point"}
}