{
  "type": "Feature",
  "properties": {
    "gn:admin1_code":"61",
    "gn:admin2_code":"VAR24",
    "gn:admin3_code":"VAR24-17",
    "gn:asciiname":"Slaveykovo",
    "gn:country_code":"BG",
    "gn:dem":99,
    "gn:feature_class":"P",
    "gn:feature_code":"PPL",
    "gn:name":"Slaveykovo",
    "gn:population":0,
    "gn:timezone":"Europe/Sofia",
    "iso:country":"BG",
    "name:bul_x_preferred":[
        "\u0421\u043b\u0430\u0432\u0435\u0439\u043a\u043e\u0432\u043e"
    ],
    "wof:name":"Slaveykovo",
    "wof:placetype":"locality"
},
  "geometry": {"coordinates":[27.23333,43.11667],"type":"Point"}
}