{
  "type": "Feature",
  "properties": {
    "gn:admin1_code":"44",
    "gn:asciiname":"Dekovtsi",
    "gn:country_code":"BG",
    "gn:dem":552,
    "gn:feature_class":"P",
    "gn:feature_code":"PPL",
    "gn:name":"Dekovtsi",
    "gn:population":0,
    "gn:timezone":"Europe/Sofia",
    "iso:country":"BG",
    "name:bul_x_preferred":[
        "Dekovtsi"
    ],
    "name:bul_x_variant":[
        "\u0414\u0435\u043a\u043e\u0432\u0446\u0438"
    ],
    "wof:name":"Dekovtsi",
    "wof:placetype":"locality"
},
  "geometry": {"coordinates":[25.52838,41.33232],"type":"Point"}
}