{
  "type": "Feature",
  "properties": {
    "gn:admin1_code":"57",
    "gn:admin2_code":"SML31",
    "gn:asciiname":"Magardzhitsa",
    "gn:country_code":"BG",
    "gn:dem":1468,
    "gn:feature_class":"P",
    "gn:feature_code":"PPL",
    "gn:name":"Magardzhitsa",
    "gn:population":0,
    "gn:timezone":"Europe/Sofia",
    "iso:country":"BG",
    "name:bul_x_preferred":[
        "\u041c\u0430\u0433\u0430\u0440\u0434\u0436\u0438\u0446\u0430"
    ],
    "name:und_x_variant":[
        "Magardshiza",
        "Magardzhitsa"
    ],
    "wof:name":"Magardzhitsa",
    "wof:placetype":"locality"
},
  "geometry": {"coordinates":[24.56509,41.65192],"type":"Point"}
}