{
  "type": "Feature",
  "properties": {
    "gn:admin1_code":"45",
    "gn:admin2_code":"KNL04",
    "gn:asciiname":"Golema Fucha",
    "gn:country_code":"BG",
    "gn:dem":651,
    "gn:feature_class":"P",
    "gn:feature_code":"PPL",
    "gn:name":"Golema Fucha",
    "gn:population":0,
    "gn:timezone":"Europe/Sofia",
    "iso:country":"BG",
    "name:bul_x_preferred":[
        "\u0413\u043e\u043b\u0435\u043c\u0430 \u0444\u0443\u0447\u0430"
    ],
    "name:bul_x_variant":[
        "\u0413\u043e\u043b\u0435\u043c\u0430 \u0424\u0443\u0447\u0430"
    ],
    "name:und_x_variant":[
        "Golyema-Fucha",
        "Golema-Futscha",
        "Golyama Fucha",
        "Golema Fucha"
    ],
    "wof:name":"Golema Fucha",
    "wof:placetype":"locality"
},
  "geometry": {"coordinates":[22.94853,42.37498],"type":"Point"}
}