{
  "type": "Feature",
  "properties": {
    "iso:country":"BG",
    "name:bul_x_variant":[
        "A4"
    ],
    "name:eng_x_preferred":[
        "\u041a\u0430\u043d \u041a\u0440\u0443\u043c"
    ],
    "wof:name":"Kan Krum",
    "wof:placetype":"neighbourhood"
},
  "geometry": {"coordinates":[24.7895872174206,42.13034239241922],"type":"Point"}
}