{
  "type": "Feature",
  "properties": {
    "gn:admin1_code":"45",
    "gn:asciiname":"Papratska",
    "gn:cc2":"BG",
    "gn:country_code":"BG",
    "gn:dem":1206,
    "gn:feature_class":"P",
    "gn:feature_code":"PPL",
    "gn:name":"Papratska",
    "gn:population":0,
    "gn:timezone":"Europe/Sofia",
    "iso:country":"BG",
    "name:bul_x_preferred":[
        "\u041f\u0430\u043f\u0440\u0430\u0446\u043a\u0430"
    ],
    "name:bul_x_variant":[
        "\u041f\u0430\u043f\u0440\u0430\u0442\u0441\u043a\u0430"
    ],
    "name:und_x_variant":[
        "Papratska Makhala",
        "Papratska Mahala",
        "Papratska"
    ],
    "wof:name":"Papratska",
    "wof:placetype":"locality"
},
  "geometry": {"coordinates":[22.38444,42.32028],"type":"Point"}
}