{
  "type": "Feature",
  "properties": {
    "gn:admin1_code":"62",
    "gn:admin2_code":"VTR04",
    "gn:asciiname":"Tsonkovtsi",
    "gn:cc2":"BG",
    "gn:country_code":"BG",
    "gn:dem":545,
    "gn:feature_class":"P",
    "gn:feature_code":"PPL",
    "gn:name":"Tsonkovtsi",
    "gn:population":0,
    "gn:timezone":"Europe/Sofia",
    "iso:country":"BG",
    "name:bul_x_preferred":[
        "\u0426\u043e\u043d\u043a\u043e\u0432\u0446\u0438"
    ],
    "name:und_x_variant":[
        "Tsonkovts\u016d",
        "Tsonkovtsi"
    ],
    "wof:name":"Tsonkovtsi",
    "wof:placetype":"locality"
},
  "geometry": {"coordinates":[25.65,42.83333],"type":"Point"}
}