{
  "type": "Feature",
  "properties": {
    "gn:admin1_code":"45",
    "gn:admin2_code":"KNL05",
    "gn:admin3_code":"KNL05-08",
    "gn:asciiname":"Slatino",
    "gn:country_code":"BG",
    "gn:dem":432,
    "gn:feature_class":"P",
    "gn:feature_code":"PPL",
    "gn:name":"Slatino",
    "gn:population":0,
    "gn:timezone":"Europe/Sofia",
    "iso:country":"BG",
    "name:bul_x_preferred":[
        "\u0421\u043b\u0430\u0442\u0438\u043d\u043e"
    ],
    "wof:name":"Slatino",
    "wof:placetype":"locality"
},
  "geometry": {"coordinates":[23.0558,42.16098],"type":"Point"}
}