{
  "type": "Feature",
  "properties": {
    "gn:admin1_code":"39",
    "gn:asciiname":"Aheloy",
    "gn:country_code":"BG",
    "gn:dem":25,
    "gn:feature_class":"P",
    "gn:feature_code":"PPL",
    "gn:name":"Aheloy",
    "gn:population":2112,
    "gn:timezone":"Europe/Sofia",
    "iso:country":"BG",
    "name:azb_x_preferred":[
        "\u0627\u0647\u0644\u0648\u06cc"
    ],
    "name:bul_x_preferred":[
        "\u0410\u0445\u0435\u043b\u043e\u0439"
    ],
    "name:ceb_x_preferred":[
        "Aheloy"
    ],
    "name:fin_x_preferred":[
        "Aheloi"
    ],
    "name:kaz_x_preferred":[
        "\u0410\u0445\u0435\u043b\u043e\u0439"
    ],
    "name:por_x_preferred":[
        "Aheloj"
    ],
    "name:ron_x_preferred":[
        "Aheloi"
    ],
    "name:rus_x_preferred":[
        "\u0410\u0445\u0435\u043b\u043e\u0439"
    ],
    "name:swe_x_preferred":[
        "Aheloy"
    ],
    "name:ukr_x_preferred":[
        "\u0410\u0445\u0435\u043b\u043e\u0439"
    ],
    "name:vie_x_preferred":[
        "Aheloy"
    ],
    "name:zho_x_preferred":[
        "\u963f\u8d6b\u6d1b\u4f0a"
    ],
    "wof:name":"Aheloy",
    "wof:placetype":"locality",
    "wof:population":2112
},
  "geometry": {"coordinates":[27.64838,42.64987],"type":"Point"}
}