{
  "type": "Feature",
  "properties": {
    "gn:admin1_code":"39",
    "gn:asciiname":"Aheloy",
    "gn:country_code":"BG",
    "gn:dem":25,
    "gn:feature_class":"P",
    "gn:feature_code":"PPL",
    "gn:name":"Aheloy",
    "gn:population":2112,
    "gn:timezone":"Europe/Sofia",
    "iso:country":"BG",
    "name:rus_x_preferred":[
        "\u0410\u0445\u0435\u043b\u043e\u0439"
    ],
    "wof:name":"Aheloy",
    "wof:placetype":"locality",
    "wof:population":2112
},
  "geometry": {"coordinates":[27.64838,42.64987],"type":"Point"}
}