{
  "type": "Feature",
  "properties": {
    "gn:admin1_code":"59",
    "gn:admin2_code":"SZR31",
    "gn:asciiname":"Pastrovo",
    "gn:country_code":"BG",
    "gn:dem":397,
    "gn:feature_class":"P",
    "gn:feature_code":"PPL",
    "gn:name":"Pastrovo",
    "gn:population":0,
    "gn:timezone":"Europe/Sofia",
    "iso:country":"BG",
    "name:bul_x_preferred":[
        "\u041f\u044a\u0441\u0442\u0440\u043e\u0432\u043e"
    ],
    "name:bul_x_variant":[
        "Pastrovo"
    ],
    "name:und_x_variant":[
        "Alagyun",
        "P\u0103strowo",
        "Pestrovo",
        "P\u016dstrovo"
    ],
    "wof:name":"Pastrovo",
    "wof:placetype":"locality"
},
  "geometry": {"coordinates":[25.35,42.43333],"type":"Point"}
}