{
  "type": "Feature",
  "properties": {
    "gn:admin1_code":"44",
    "gn:admin2_code":"KRZ16",
    "gn:admin3_code":"KRZ16-34",
    "gn:asciiname":"Skalna Glava",
    "gn:cc2":"BG",
    "gn:country_code":"BG",
    "gn:dem":653,
    "gn:feature_class":"P",
    "gn:feature_code":"PPL",
    "gn:name":"Skalna Glava",
    "gn:population":0,
    "gn:timezone":"Europe/Sofia",
    "iso:country":"BG",
    "name:bul_x_preferred":[
        "\u0421\u043a\u0430\u043b\u043d\u0430 \u0413\u043b\u0430\u0432\u0430"
    ],
    "name:bul_x_variant":[
        "\u0421\u043a\u0430\u043b\u043d\u0430 \u0433\u043b\u0430\u0432\u0430"
    ],
    "name:ceb_x_preferred":[
        "Skalna glava"
    ],
    "name:fas_x_preferred":[
        "\u0633\u06a9\u0627\u0644\u0646\u0627 \u06af\u0644\u0627\u0648\u0627"
    ],
    "name:kat_x_preferred":[
        "\u10e1\u10d9\u10d0\u10da\u10dc\u10d0-\u10d2\u10da\u10d0\u10d5\u10d0"
    ],
    "name:kaz_x_preferred":[
        "\u0421\u043a\u0430\u043b\u043d\u0430-\u0413\u043b\u0430\u0432\u0430"
    ],
    "name:ron_x_preferred":[
        "Skalna Glava"
    ],
    "name:rus_x_preferred":[
        "\u0421\u043a\u0430\u043b\u043d\u0430-\u0413\u043b\u0430\u0432\u0430"
    ],
    "name:swe_x_preferred":[
        "Skalna glava"
    ],
    "name:ukr_x_preferred":[
        "\u0421\u043a\u0430\u043b\u043d\u0430 \u0413\u043b\u0430\u0432\u0430"
    ],
    "name:und_x_variant":[
        "Kaya Bashi",
        "Skalna Glawa"
    ],
    "wof:name":"Skalna Glava",
    "wof:placetype":"locality"
},
  "geometry": {"coordinates":[25.31667,41.68333],"type":"Point"}
}