{
  "type": "Feature",
  "properties": {
    "gn:admin1_code":"44",
    "gn:admin2_code":"KRZ16",
    "gn:admin3_code":"KRZ16-34",
    "gn:asciiname":"Skalna Glava",
    "gn:cc2":"BG",
    "gn:country_code":"BG",
    "gn:dem":653,
    "gn:feature_class":"P",
    "gn:feature_code":"PPL",
    "gn:name":"Skalna Glava",
    "gn:population":0,
    "gn:timezone":"Europe/Sofia",
    "iso:country":"BG",
    "name:bul_x_preferred":[
        "\u0421\u043a\u0430\u043b\u043d\u0430 \u0413\u043b\u0430\u0432\u0430"
    ],
    "name:und_x_variant":[
        "Kaya Bashi",
        "Skalna Glawa",
        "Skalna Glava"
    ],
    "wof:name":"Skalna Glava",
    "wof:placetype":"locality"
},
  "geometry": {"coordinates":[25.31667,41.68333],"type":"Point"}
}