{
  "type": "Feature",
  "properties": {
    "gn:admin1_code":"43",
    "gn:admin2_code":"HKV18",
    "gn:admin3_code":"HKV18-01",
    "gn:asciiname":"Malki Voden",
    "gn:country_code":"BG",
    "gn:dem":135,
    "gn:feature_class":"P",
    "gn:feature_code":"PPL",
    "gn:name":"Malki Voden",
    "gn:population":0,
    "gn:timezone":"Europe/Sofia",
    "iso:country":"BG",
    "name:bul_x_preferred":[
        "\u041c\u0430\u043b\u043a\u0438 \u0412\u043e\u0434\u0435\u043d"
    ],
    "name:fas_x_preferred":[
        "\u0645\u0627\u0644\u06a9\u06cc \u0648\u0648\u062f\u0646"
    ],
    "name:kaz_x_preferred":[
        "\u041c\u0430\u043b\u043a\u0438-\u0412\u043e\u0434\u0435\u043d"
    ],
    "name:pol_x_preferred":[
        "Ma\u0142ki Woden"
    ],
    "name:ron_x_preferred":[
        "Malki Voden"
    ],
    "name:rus_x_preferred":[
        "\u041c\u0430\u043b\u043a\u0438-\u0412\u043e\u0434\u0435\u043d"
    ],
    "name:ukr_x_preferred":[
        "\u041c\u0430\u043b\u043a\u0438\u0439 \u0412\u043e\u0434\u0435\u043d"
    ],
    "name:und_x_variant":[
        "Silbikyum",
        "Malki-Woden",
        "Sjuljaki\u00f6j",
        "Syulbyukyun",
        "Malki Voden"
    ],
    "wof:name":"Malki Voden",
    "wof:placetype":"locality"
},
  "geometry": {"coordinates":[25.95143,41.66947],"type":"Point"}
}