{
  "type": "Feature",
  "properties": {
    "gn:admin1_code":"48",
    "gn:asciiname":"Meche Korito",
    "gn:cc2":"BG",
    "gn:country_code":"BG",
    "gn:dem":1338,
    "gn:feature_class":"P",
    "gn:feature_code":"PPL",
    "gn:name":"Meche Korito",
    "gn:population":0,
    "gn:timezone":"Europe/Sofia",
    "iso:country":"BG",
    "name:bul_x_preferred":[
        "\u041c\u0435\u0447\u0435 \u041a\u043e\u0440\u0438\u0442\u043e"
    ],
    "name:und_x_variant":[
        "Metscho-Korito",
        "Mechekoritski",
        "Meche Korito"
    ],
    "wof:name":"Meche Korito",
    "wof:placetype":"locality"
},
  "geometry": {"coordinates":[23.88333,41.96667],"type":"Point"}
}