{
  "type": "Feature",
  "properties": {
    "gn:admin1_code":"39",
    "gn:admin2_code":"BGS17",
    "gn:asciiname":"Kozichino",
    "gn:cc2":"BG",
    "gn:country_code":"BG",
    "gn:dem":436,
    "gn:feature_class":"P",
    "gn:feature_code":"PPL",
    "gn:name":"Kozichino",
    "gn:population":0,
    "gn:timezone":"Europe/Sofia",
    "iso:country":"BG",
    "name:bul_x_preferred":[
        "\u041a\u043e\u0437\u0438\u0447\u0438\u043d\u043e"
    ],
    "name:und_x_variant":[
        "Erke\u010d",
        "Kositschino",
        "Erkech",
        "Kozichino"
    ],
    "wof:name":"Kozichino",
    "wof:placetype":"locality"
},
  "geometry": {"coordinates":[27.56667,42.83333],"type":"Point"}
}