{
  "type": "Feature",
  "properties": {
    "gn:admin1_code":"47",
    "gn:admin2_code":"MON29",
    "gn:admin3_code":"MON29-26",
    "gn:asciiname":"Sumer",
    "gn:country_code":"BG",
    "gn:dem":188,
    "gn:feature_class":"P",
    "gn:feature_code":"PPL",
    "gn:name":"Sumer",
    "gn:population":0,
    "gn:timezone":"Europe/Sofia",
    "iso:country":"BG",
    "name:bul_x_preferred":[
        "\u0421\u0443\u043c\u0435\u0440"
    ],
    "wof:name":"Sumer",
    "wof:placetype":"locality"
},
  "geometry": {"coordinates":[23.33278,43.33333],"type":"Point"}
}