{
  "type": "Feature",
  "properties": {
    "gn:admin1_code":"44",
    "gn:asciiname":"Dolnyane",
    "gn:country_code":"BG",
    "gn:dem":331,
    "gn:feature_class":"P",
    "gn:feature_code":"PPL",
    "gn:name":"Dolnyane",
    "gn:population":0,
    "gn:timezone":"Europe/Sofia",
    "iso:country":"BG",
    "name:bul_x_preferred":[
        "Dolnyane"
    ],
    "name:bul_x_variant":[
        "\u0414\u043e\u043b\u043d\u044f\u043d\u0435"
    ],
    "wof:name":"Dolnyane",
    "wof:placetype":"locality"
},
  "geometry": {"coordinates":[25.57927,41.47442],"type":"Point"}
}