{
  "type": "Feature",
  "properties": {
    "gn:admin1_code":"45",
    "gn:admin2_code":"KNL29",
    "gn:asciiname":"Lomnitsa",
    "gn:country_code":"BG",
    "gn:dem":875,
    "gn:feature_class":"P",
    "gn:feature_code":"PPLL",
    "gn:name":"Lomnitsa",
    "gn:population":0,
    "gn:timezone":"Europe/Sofia",
    "iso:country":"BG",
    "name:bul_x_preferred":[
        "\u041b\u043e\u043c\u043d\u0438\u0446\u0430"
    ],
    "name:und_x_variant":[
        "Lomniza",
        "Lomnitsa"
    ],
    "wof:name":"Lomnitsa",
    "wof:placetype":"locality"
},
  "geometry": {"coordinates":[22.55635,42.3781],"type":"Point"}
}