{
  "type": "Feature",
  "properties": {
    "gn:admin1_code":"45",
    "gn:asciiname":"Tarnyarska Mahala",
    "gn:country_code":"BG",
    "gn:dem":966,
    "gn:feature_class":"P",
    "gn:feature_code":"PPL",
    "gn:name":"Tarnyarska Mahala",
    "gn:population":0,
    "gn:timezone":"Europe/Sofia",
    "iso:country":"BG",
    "name:bul_x_preferred":[
        "\u0422\u0443\u0440\u043d\u044f\u0440\u0441\u043a\u0430 \u043c\u0430\u0445\u0430\u043b\u0430"
    ],
    "name:bul_x_variant":[
        "Turnyarska Mahala",
        "Tarnyarska Mahala",
        "\u0422\u044a\u0440\u043d\u044f\u0440\u0441\u043a\u0430 \u041c\u0430\u0445\u0430\u043b\u0430"
    ],
    "name:und_x_variant":[
        "Tarniarska Mahala",
        "Turnyarska Makhala"
    ],
    "wof:name":"Tarnyarska Mahala",
    "wof:placetype":"locality"
},
  "geometry": {"coordinates":[22.44861,42.32083],"type":"Point"}
}