{
  "type": "Feature",
  "properties": {
    "gn:admin1_code":"41",
    "gn:admin2_code":"GAB35",
    "gn:admin3_code":"GAB35-04",
    "gn:asciiname":"Marutsekovtsi",
    "gn:country_code":"BG",
    "gn:dem":651,
    "gn:feature_class":"P",
    "gn:feature_code":"PPL",
    "gn:name":"Marutsekovtsi",
    "gn:population":0,
    "gn:timezone":"Europe/Sofia",
    "iso:country":"BG",
    "name:bul_x_preferred":[
        "\u041c\u0430\u0440\u0443\u0446\u0435\u043a\u043e\u0432\u0446\u0438"
    ],
    "name:pol_x_preferred":[
        "Marucekowci"
    ],
    "name:ukr_x_preferred":[
        "\u041c\u0430\u0440\u0443\u0446\u0435\u043a\u043e\u0432\u0446\u0456"
    ],
    "wof:name":"Marutsekovtsi",
    "wof:placetype":"locality"
},
  "geometry": {"coordinates":[25.41833,42.81335],"type":"Point"}
}