{
  "type": "Feature",
  "properties": {
    "gn:admin1_code":"41",
    "gn:admin2_code":"GAB35",
    "gn:asciiname":"Velkovo",
    "gn:cc2":"BG",
    "gn:country_code":"BG",
    "gn:dem":422,
    "gn:feature_class":"P",
    "gn:feature_code":"PPL",
    "gn:name":"Velkovo",
    "gn:population":0,
    "gn:timezone":"Europe/Sofia",
    "iso:country":"BG",
    "name:bul_x_preferred":[
        "\u0412\u0435\u043b\u043a\u043e\u0432\u043e"
    ],
    "name:fas_x_preferred":[
        "\u0648\u0644\u06a9\u0648\u0648"
    ],
    "name:kaz_x_preferred":[
        "\u0412\u0435\u043b\u043a\u043e\u0432\u043e"
    ],
    "name:pol_x_preferred":[
        "We\u0142kowo"
    ],
    "name:ron_x_preferred":[
        "Velkovo"
    ],
    "name:rus_x_preferred":[
        "\u0412\u0435\u043b\u043a\u043e\u0432\u043e"
    ],
    "name:ukr_x_preferred":[
        "\u0412\u0435\u043b\u043a\u043e\u0432\u043e"
    ],
    "name:und_x_variant":[
        "Tsareto"
    ],
    "wof:name":"Velkovo",
    "wof:placetype":"locality"
},
  "geometry": {"coordinates":[25.56667,42.85],"type":"Point"}
}