{
  "type": "Feature",
  "properties": {
    "gn:admin1_code":"46",
    "gn:admin2_code":"LOV34",
    "gn:asciiname":"Belish",
    "gn:cc2":"BG",
    "gn:country_code":"BG",
    "gn:dem":460,
    "gn:feature_class":"P",
    "gn:feature_code":"PPL",
    "gn:name":"Belish",
    "gn:population":0,
    "gn:timezone":"Europe/Sofia",
    "iso:country":"BG",
    "name:bul_x_preferred":[
        "\u0411\u0435\u043b\u0438\u0448"
    ],
    "name:und_x_variant":[
        "Byelish",
        "Belisch",
        "Belish"
    ],
    "wof:name":"Belish",
    "wof:placetype":"locality"
},
  "geometry": {"coordinates":[24.73333,42.93333],"type":"Point"}
}