{
  "type": "Feature",
  "properties": {
    "gn:admin1_code":"43",
    "gn:admin2_code":"HKV11",
    "gn:asciiname":"Meden Buk",
    "gn:country_code":"BG",
    "gn:dem":126,
    "gn:feature_class":"P",
    "gn:feature_code":"PPL",
    "gn:name":"Meden Buk",
    "gn:population":0,
    "gn:timezone":"Europe/Sofia",
    "iso:country":"BG",
    "name:bul_x_preferred":[
        "\u041c\u0435\u0434\u0435\u043d \u0411\u0443\u043a"
    ],
    "name:bul_x_variant":[
        "\u041c\u0435\u0434\u0435\u043d \u0431\u0443\u043a"
    ],
    "name:ell_x_preferred":[
        "\u039c\u03b5\u03bd\u03c4\u03ad\u03bd \u039c\u03c0\u03bf\u03c5\u03ba"
    ],
    "name:fas_x_preferred":[
        "\u0645\u062f\u0646 \u0628\u0648\u06a9"
    ],
    "name:kaz_x_preferred":[
        "\u041c\u0435\u0434\u0435\u043d-\u0411\u0443\u043a"
    ],
    "name:pol_x_preferred":[
        "Meden buk"
    ],
    "name:ron_x_preferred":[
        "Meden Buk"
    ],
    "name:rus_x_preferred":[
        "\u041c\u0435\u0434\u0435\u043d-\u0411\u0443\u043a"
    ],
    "name:ukr_x_preferred":[
        "\u041c\u0435\u0434\u0435\u043d-\u0411\u0443\u043a"
    ],
    "name:und_x_variant":[
        "Baldzhi Buk",
        "Meden Buk"
    ],
    "wof:name":"Meden Buk",
    "wof:placetype":"locality"
},
  "geometry": {"coordinates":[26.0346,41.3757],"type":"Point"}
}