{
  "type": "Feature",
  "properties": {
    "gn:admin1_code":"39",
    "gn:admin2_code":"BGS06",
    "gn:asciiname":"Sinyo Kamene",
    "gn:country_code":"BG",
    "gn:dem":210,
    "gn:feature_class":"P",
    "gn:feature_code":"PPL",
    "gn:name":"Sinyo Kamene",
    "gn:population":0,
    "gn:timezone":"Europe/Sofia",
    "iso:country":"BG",
    "name:bul_x_preferred":[
        "\u0421\u0438\u043d\u044c\u043e \u041a\u0430\u043c\u0435\u043d\u0435"
    ],
    "name:bul_x_variant":[
        "Sinyo Kamene",
        "\u0421\u0438\u043d\u044c\u043e \u043a\u0430\u043c\u0435\u043d\u0435"
    ],
    "name:fas_x_preferred":[
        "\u0633\u06cc\u0646\u06cc\u0648 \u06a9\u0627\u0645\u0646\u0647"
    ],
    "name:kaz_x_preferred":[
        "\u0421\u0438\u043d\u0451-\u041a\u0430\u043c\u0435\u043d\u0435"
    ],
    "name:ron_x_preferred":[
        "Sino Kamene"
    ],
    "name:rus_x_preferred":[
        "\u0421\u0438\u043d\u0451-\u041a\u0430\u043c\u0435\u043d\u0435"
    ],
    "name:ukr_x_preferred":[
        "\u0421\u0438\u043d\u044c\u043e-\u041a\u0430\u043c\u0435\u043d\u0435"
    ],
    "name:und_x_variant":[
        "Iumrukkioy",
        "Yumruk Kaya",
        "Sinio-Kamene",
        "Sin\u2019o Kamene"
    ],
    "name:zho_x_preferred":[
        "\u65b0\u7ea6\u5361\u6885\u5185"
    ],
    "wof:name":"Sinyo Kamene",
    "wof:placetype":"locality"
},
  "geometry": {"coordinates":[26.98333,42.25],"type":"Point"}
}