{
  "type": "Feature",
  "properties": {
    "gn:admin1_code":"63",
    "gn:admin2_code":"VID15",
    "gn:asciiname":"Boyanovo",
    "gn:country_code":"BG",
    "gn:dem":210,
    "gn:feature_class":"P",
    "gn:feature_code":"PPL",
    "gn:name":"Boyanovo",
    "gn:population":0,
    "gn:timezone":"Europe/Sofia",
    "iso:country":"BG",
    "name:bul_x_preferred":[
        "\u0411\u043e\u044f\u043d\u043e\u0432\u043e"
    ],
    "name:che_x_preferred":[
        "\u0411\u043e\u044f\u043d\u043e\u0432\u043e"
    ],
    "name:rus_x_preferred":[
        "\u0411\u043e\u044f\u043d\u043e\u0432\u043e"
    ],
    "wof:name":"Boyanovo",
    "wof:placetype":"locality"
},
  "geometry": {"coordinates":[22.68805,43.87536],"type":"Point"}
}