{
  "type": "Feature",
  "properties": {
    "gn:admin1_code":"43",
    "gn:admin2_code":"HKV09",
    "gn:admin3_code":"HKV09-02",
    "gn:asciiname":"Brod",
    "gn:cc2":"BG",
    "gn:country_code":"BG",
    "gn:dem":121,
    "gn:feature_class":"P",
    "gn:feature_code":"PPL",
    "gn:name":"Brod",
    "gn:population":0,
    "gn:timezone":"Europe/Sofia",
    "iso:country":"BG",
    "name:bel_x_preferred":[
        "\u0411\u0440\u043e\u0434"
    ],
    "name:bos_x_preferred":[
        "Brod"
    ],
    "name:bul_x_preferred":[
        "\u0411\u0440\u043e\u0434"
    ],
    "name:ceb_x_preferred":[
        "Brod"
    ],
    "name:ces_x_preferred":[
        "Brod"
    ],
    "name:deu_x_preferred":[
        "Brod"
    ],
    "name:fra_x_preferred":[
        "Brod"
    ],
    "name:heb_x_preferred":[
        "\u05d1\u05e8\u05d5\u05d3"
    ],
    "name:hrv_x_preferred":[
        "Brod"
    ],
    "name:hye_x_preferred":[
        "\u0532\u0580\u0578\u0564"
    ],
    "name:ita_x_preferred":[
        "Brod"
    ],
    "name:kor_x_preferred":[
        "\ube0c\ub85c\ub4dc"
    ],
    "name:lit_x_preferred":[
        "Brodas"
    ],
    "name:mkd_x_preferred":[
        "\u0411\u0440\u043e\u0434"
    ],
    "name:nld_x_preferred":[
        "Brod"
    ],
    "name:pol_x_preferred":[
        "Brod"
    ],
    "name:por_x_preferred":[
        "Brod"
    ],
    "name:ron_x_preferred":[
        "Brod"
    ],
    "name:rue_x_preferred":[
        "\u0411\u0440\u043e\u0434"
    ],
    "name:rus_x_preferred":[
        "\u0411\u0440\u043e\u0434"
    ],
    "name:slk_x_preferred":[
        "Brod"
    ],
    "name:slv_x_preferred":[
        "Brod"
    ],
    "name:srp_x_preferred":[
        "\u0411\u0440\u043e\u0434"
    ],
    "name:swe_x_preferred":[
        "Brod"
    ],
    "name:ukr_x_preferred":[
        "\u0411\u0440\u043e\u0434"
    ],
    "name:und_x_variant":[
        "Gyucherliy",
        "Gyuchurlii",
        "Brod"
    ],
    "wof:name":"Brod",
    "wof:placetype":"locality"
},
  "geometry": {"coordinates":[25.68333,42.03333],"type":"Point"}
}