{
  "type": "Feature",
  "properties": {
    "gn:admin1_code":"45",
    "gn:admin2_code":"KNL29",
    "gn:asciiname":"Radlovtsi",
    "gn:cc2":"BG",
    "gn:country_code":"BG",
    "gn:dem":667,
    "gn:feature_class":"P",
    "gn:feature_code":"PPL",
    "gn:name":"Radlovtsi",
    "gn:population":0,
    "gn:timezone":"Europe/Sofia",
    "iso:country":"BG",
    "name:bul_x_preferred":[
        "\u0420\u0430\u0434\u043b\u043e\u0432\u0446\u0438"
    ],
    "name:und_x_variant":[
        "Radlowzi",
        "Radlovtsi"
    ],
    "wof:name":"Radlovtsi",
    "wof:placetype":"locality"
},
  "geometry": {"coordinates":[22.63639,42.31444000000001],"type":"Point"}
}