{
  "type": "Feature",
  "properties": {
    "gn:admin1_code":"47",
    "gn:admin2_code":"MON36",
    "gn:admin3_code":"MON36-10",
    "gn:asciiname":"Belimel",
    "gn:country_code":"BG",
    "gn:dem":285,
    "gn:feature_class":"P",
    "gn:feature_code":"PPL",
    "gn:name":"Belimel",
    "gn:population":0,
    "gn:timezone":"Europe/Sofia",
    "iso:country":"BG",
    "name:bul_x_preferred":[
        "\u0411\u0435\u043b\u0438\u043c\u0435\u043b"
    ],
    "name:ceb_x_preferred":[
        "Belimel"
    ],
    "name:kaz_x_preferred":[
        "\u0411\u0435\u043b\u0438\u043c\u0435\u043b"
    ],
    "name:msa_x_preferred":[
        "Belimel"
    ],
    "name:pol_x_preferred":[
        "Belime\u0142"
    ],
    "name:ron_x_preferred":[
        "Belimel"
    ],
    "name:rus_x_preferred":[
        "\u0411\u0435\u043b\u0438\u043c\u0435\u043b"
    ],
    "name:swe_x_preferred":[
        "Belimel"
    ],
    "name:ukr_x_preferred":[
        "\u0411\u0435\u043b\u0438\u043c\u0435\u043b"
    ],
    "name:und_x_variant":[
        "Byeli-Mel",
        "Bielimel",
        "Bjeli-Mel",
        "Belimel"
    ],
    "wof:name":"Belimel",
    "wof:placetype":"locality"
},
  "geometry": {"coordinates":[22.97342,43.43324000000001],"type":"Point"}
}