{
  "type": "Feature",
  "properties": {
    "gn:admin1_code":"41",
    "gn:admin2_code":"GAB05",
    "gn:asciiname":"Mihaylovtsi",
    "gn:country_code":"BG",
    "gn:dem":277,
    "gn:feature_class":"P",
    "gn:feature_code":"PPL",
    "gn:name":"Mihaylovtsi",
    "gn:population":0,
    "gn:timezone":"Europe/Sofia",
    "iso:country":"BG",
    "name:bul_x_preferred":[
        "\u041c\u0438\u0445\u0430\u0439\u043b\u043e\u0432\u0446\u0438"
    ],
    "name:bul_x_variant":[
        "Mihaylovtsi"
    ],
    "name:und_x_variant":[
        "Mikhailovtsi",
        "Mikhaylovtsi"
    ],
    "wof:name":"Mihaylovtsi",
    "wof:placetype":"locality"
},
  "geometry": {"coordinates":[25.21667,42.91667],"type":"Point"}
}