{
  "type": "Feature",
  "properties": {
    "gn:admin1_code":"41",
    "gn:admin2_code":"GAB05",
    "gn:asciiname":"Mihaylovtsi",
    "gn:country_code":"BG",
    "gn:dem":277,
    "gn:feature_class":"P",
    "gn:feature_code":"PPL",
    "gn:name":"Mihaylovtsi",
    "gn:population":0,
    "gn:timezone":"Europe/Sofia",
    "iso:country":"BG",
    "name:ara_x_preferred":[
        "\u0645\u064a\u0647\u0627\u064a\u0644\u0648\u0641\u062a\u0633\u064a"
    ],
    "name:bul_x_preferred":[
        "\u041c\u0438\u0445\u0430\u0439\u043b\u043e\u0432\u0446\u0438"
    ],
    "name:bul_x_variant":[
        "Mihaylovtsi"
    ],
    "name:fas_x_preferred":[
        "\u0645\u06cc\u0647\u0627\u06cc\u0644\u0648\u0648\u062a\u0633\u06cc"
    ],
    "name:kaz_x_preferred":[
        "\u041c\u0438\u0445\u0430\u0439\u043b\u043e\u0432\u0446\u0438"
    ],
    "name:pol_x_preferred":[
        "Michaj\u0142owci"
    ],
    "name:ron_x_preferred":[
        "Mihailov\u021bi"
    ],
    "name:rus_x_preferred":[
        "\u041c\u0438\u0445\u0430\u0439\u043b\u043e\u0432\u0446\u0438"
    ],
    "name:ukr_x_preferred":[
        "\u041c\u0438\u0445\u0430\u0439\u043b\u043e\u0432\u0446\u0456"
    ],
    "name:und_x_variant":[
        "Mikhailovtsi",
        "Mikhaylovtsi"
    ],
    "wof:name":"Mihaylovtsi",
    "wof:placetype":"locality"
},
  "geometry": {"coordinates":[25.21667,42.91667],"type":"Point"}
}