{
  "type": "Feature",
  "properties": {
    "gn:admin1_code":"44",
    "gn:asciiname":"Hrabrets",
    "gn:country_code":"BG",
    "gn:dem":343,
    "gn:feature_class":"P",
    "gn:feature_code":"PPL",
    "gn:name":"Hrabrets",
    "gn:population":0,
    "gn:timezone":"Europe/Sofia",
    "iso:country":"BG",
    "name:bul_x_preferred":[
        "Hrabrets"
    ],
    "name:bul_x_variant":[
        "\u0425\u0440\u0430\u0431\u0440\u0435\u0446"
    ],
    "name:und_x_variant":[
        "Khrabrets"
    ],
    "wof:name":"Hrabrets",
    "wof:placetype":"locality"
},
  "geometry": {"coordinates":[25.43961,41.37584],"type":"Point"}
}