{
  "type": "Feature",
  "properties": {
    "gn:gn_country":"BG",
    "gn:gn_fcode":"PPL",
    "gn:gn_pop":6427,
    "gn:population":6427,
    "iso:country":"BG",
    "name:bul_x_preferred":[
        "\u0421\u044a\u0435\u0434\u0438\u043d\u0435\u043d\u0438\u0435"
    ],
    "name:ces_x_preferred":[
        "S\u0103edinenie"
    ],
    "name:ckb_x_preferred":[
        "\u0633\u0627\u06cc\u06ce\u062f\u06cc\u0646\u06ce\u0646\u06cc\u06ce"
    ],
    "name:deu_x_preferred":[
        "Saedinenie"
    ],
    "name:eng_x_preferred":[
        "Saedinenie"
    ],
    "name:fas_x_preferred":[
        "\u0633\u0627\u0626\u062f\u06cc\u0646\u0646\u06cc\u0647\u060c \u0627\u0633\u062a\u0627\u0646 \u067e\u0644\u0648\u062f\u06cc\u0641"
    ],
    "name:heb_x_preferred":[
        "\u05e1\u05d3\u05d9\u05e0\u05e0\u05d9\u05d4"
    ],
    "name:jpn_x_preferred":[
        "\u30bb\u30a2\u30c7\u30a3\u30cd\u30cb\u30a8"
    ],
    "name:kaz_x_preferred":[
        "\u0421\u044b\u0435\u0434\u0438\u043d\u0435\u043d\u0438\u0435"
    ],
    "name:nld_x_preferred":[
        "Saedinenie"
    ],
    "name:pol_x_preferred":[
        "Syedinenie"
    ],
    "name:por_x_preferred":[
        "S\u0103edinenie"
    ],
    "name:ron_x_preferred":[
        "S\u0103edinenie"
    ],
    "name:rus_x_preferred":[
        "\u0421\u044b\u0435\u0434\u0438\u043d\u0435\u043d\u0438\u0435"
    ],
    "name:spa_x_preferred":[
        "Saedinenie"
    ],
    "name:srp_x_preferred":[
        "\u0421\u0458\u0435\u0434\u0438\u043d\u0435\u043d\u0438\u0458\u0435"
    ],
    "name:swe_x_preferred":[
        "Sedinenie"
    ],
    "name:tat_x_preferred":[
        "\u0421\u0430\u0435\u043d\u0434\u0438\u043d\u0435\u043d\u0438\u0435"
    ],
    "name:ukr_x_preferred":[
        "\u0421\u0438\u0454\u0434\u0438\u043d\u0435\u043d\u0456\u0454"
    ],
    "name:unk_x_variant":[
        "Golyamo Konare"
    ],
    "name:war_x_preferred":[
        "Saedinenie"
    ],
    "name:zho_x_preferred":[
        "\u806f\u5408\u93ae"
    ],
    "qs_pg:aaroncc":"BG",
    "qs_pg:gn_country":"BG",
    "qs_pg:gn_fcode":"PPL",
    "qs_pg:gn_pop":6427,
    "qs_pg:name":"Suedinenie",
    "qs_pg:name_adm0":"Bulgaria",
    "qs_pg:name_adm1":"Plovdiv",
    "qs_pg:photos_9k":1,
    "qs_pg:photos_9r":1,
    "qs_pg:photos_all":3,
    "qs_pg:photos_sr":0,
    "qs_pg:pop_sr":5,
    "qs_pg:qs_pg_placetype":"locality",
    "qs_pg:qs_pg_placetype_gp":"Town",
    "qs_pg:woe_adm0":23424771,
    "woe:adm0_id":23424771,
    "woe:name_adm0":"Bulgaria",
    "woe:name_adm1":"Plovdiv",
    "woe:placetype":"Town",
    "wof:name":"Suedinenie",
    "wof:placetype":"locality",
    "wof:population":6427
},
  "geometry": {"coordinates":[24.55,42.26667],"type":"Point"}
}