{
  "type": "Feature",
  "properties": {
    "gn:admin1_code":"61",
    "gn:admin2_code":"VAR01",
    "gn:admin3_code":"VAR01-14",
    "gn:asciiname":"Trastikovo",
    "gn:country_code":"BG",
    "gn:dem":13,
    "gn:feature_class":"P",
    "gn:feature_code":"PPL",
    "gn:name":"Trastikovo",
    "gn:population":0,
    "gn:timezone":"Europe/Sofia",
    "iso:country":"BG",
    "name:bul_x_preferred":[
        "\u0422\u0440\u044a\u0441\u0442\u0438\u043a\u043e\u0432\u043e"
    ],
    "name:bul_x_variant":[
        "Trastikovo"
    ],
    "name:und_x_variant":[
        "Karaach Sofular",
        "Tr\u0103stikowo",
        "Tr\u016dstikovo",
        "Surovo"
    ],
    "wof:name":"Trastikovo",
    "wof:placetype":"locality"
},
  "geometry": {"coordinates":[27.60044000000001,43.1434],"type":"Point"}
}