{
  "type": "Feature",
  "properties": {
    "gn:admin1_code":"56",
    "gn:admin2_code":"BGS23",
    "gn:admin3_code":"BGS23-19",
    "gn:asciiname":"Skala",
    "gn:country_code":"BG",
    "gn:dem":401,
    "gn:feature_class":"P",
    "gn:feature_code":"PPL",
    "gn:name":"Skala",
    "gn:population":0,
    "gn:timezone":"Europe/Sofia",
    "iso:country":"BG",
    "name:bul_x_preferred":[
        "\u0421\u043a\u0430\u043b\u0430"
    ],
    "name:und_x_variant":[
        "Kaya Bash",
        "Kayabashi",
        "Skala"
    ],
    "wof:name":"Skala",
    "wof:placetype":"locality"
},
  "geometry": {"coordinates":[26.68333,42.76667],"type":"Point"}
}