{
  "type": "Feature",
  "properties": {
    "gn:admin1_code":"56",
    "gn:admin2_code":"BGS23",
    "gn:admin3_code":"BGS23-19",
    "gn:asciiname":"Skala",
    "gn:country_code":"BG",
    "gn:dem":401,
    "gn:feature_class":"P",
    "gn:feature_code":"PPL",
    "gn:name":"Skala",
    "gn:population":0,
    "gn:timezone":"Europe/Sofia",
    "iso:country":"BG",
    "name:bel_x_preferred":[
        "\u0421\u043a\u0430\u043b\u0430"
    ],
    "name:bul_x_preferred":[
        "\u0421\u043a\u0430\u043b\u0430"
    ],
    "name:ceb_x_preferred":[
        "Skala"
    ],
    "name:ces_x_preferred":[
        "Skala"
    ],
    "name:cym_x_preferred":[
        "Skala"
    ],
    "name:dan_x_preferred":[
        "Skala"
    ],
    "name:deu_x_preferred":[
        "Skala"
    ],
    "name:ell_x_preferred":[
        "\u03a3\u03ba\u03ac\u03bb\u03b1"
    ],
    "name:fin_x_preferred":[
        "Skala"
    ],
    "name:fra_x_preferred":[
        "Skala"
    ],
    "name:hsb_x_preferred":[
        "Skala"
    ],
    "name:hye_x_preferred":[
        "\u054d\u056f\u0561\u056c\u0561"
    ],
    "name:lav_x_preferred":[
        "Skala"
    ],
    "name:nld_x_preferred":[
        "Skala"
    ],
    "name:nor_x_preferred":[
        "Skala"
    ],
    "name:pol_x_preferred":[
        "Skala"
    ],
    "name:rus_x_preferred":[
        "\u0421\u043a\u0430\u043b\u0430"
    ],
    "name:slk_x_preferred":[
        "Skala"
    ],
    "name:slv_x_preferred":[
        "Skala"
    ],
    "name:srp_x_preferred":[
        "\u0421\u043a\u0430\u043b\u0430"
    ],
    "name:swe_x_preferred":[
        "Skala"
    ],
    "name:ukr_x_preferred":[
        "\u0421\u043a\u0430\u043b\u0430"
    ],
    "name:und_x_variant":[
        "Kaya Bash",
        "Kayabashi"
    ],
    "wof:name":"Skala",
    "wof:placetype":"locality"
},
  "geometry": {"coordinates":[26.68333,42.76667],"type":"Point"}
}