{
  "type": "Feature",
  "properties": {
    "gn:admin1_code":"39",
    "gn:admin2_code":"BGS06",
    "gn:asciiname":"Kirovo",
    "gn:country_code":"BG",
    "gn:dem":283,
    "gn:feature_class":"P",
    "gn:feature_code":"PPL",
    "gn:name":"Kirovo",
    "gn:population":0,
    "gn:timezone":"Europe/Sofia",
    "iso:country":"BG",
    "name:bul_x_preferred":[
        "\u041a\u0438\u0440\u043e\u0432\u043e"
    ],
    "name:fas_x_preferred":[
        "\u06a9\u06cc\u0631\u0648\u0648\u0648"
    ],
    "name:kaz_x_preferred":[
        "\u041a\u0438\u0440\u043e\u0432\u043e"
    ],
    "name:ron_x_preferred":[
        "Kirovo"
    ],
    "name:rus_x_preferred":[
        "\u041a\u0438\u0440\u043e\u0432\u043e"
    ],
    "name:ukr_x_preferred":[
        "\u041a\u0438\u0440\u043e\u0432\u043e"
    ],
    "name:und_x_variant":[
        "Karovo",
        "Madlesh",
        "Madlesch"
    ],
    "wof:name":"Kirovo",
    "wof:placetype":"locality"
},
  "geometry": {"coordinates":[27.18659,42.15752],"type":"Point"}
}