{
  "type": "Feature",
  "properties": {
    "gn:admin1_code":"62",
    "gn:admin2_code":"VTR04",
    "gn:admin3_code":"VTR04-27",
    "gn:asciiname":"Pchelishte",
    "gn:cc2":"BG",
    "gn:country_code":"BG",
    "gn:dem":231,
    "gn:feature_class":"P",
    "gn:feature_code":"PPL",
    "gn:name":"Pchelishte",
    "gn:population":0,
    "gn:timezone":"Europe/Sofia",
    "iso:country":"BG",
    "name:bul_x_preferred":[
        "\u041f\u0447\u0435\u043b\u0438\u0449\u0435"
    ],
    "name:und_x_variant":[
        "Ptschelischte",
        "Kovanlika",
        "Pchelishte",
        "Kovanl\u016dk"
    ],
    "wof:name":"Pchelishte",
    "wof:placetype":"locality"
},
  "geometry": {"coordinates":[25.71667,43.03333],"type":"Point"}
}