{
  "type": "Feature",
  "properties": {
    "gn:admin1_code":"42",
    "gn:admin2_code":"SOF46",
    "gn:admin3_code":"SOF46-41",
    "gn:asciiname":"Katina",
    "gn:country_code":"BG",
    "gn:dem":627,
    "gn:feature_class":"P",
    "gn:feature_code":"PPL",
    "gn:name":"Katina",
    "gn:population":0,
    "gn:timezone":"Europe/Sofia",
    "iso:country":"BG",
    "name:bul_x_preferred":[
        "\u041a\u044a\u0442\u0438\u043d\u0430"
    ],
    "name:bul_x_variant":[
        "Katina"
    ],
    "name:srp_x_preferred":[
        "\u041a\u0430\u0442\u0438\u043d\u0430"
    ],
    "name:und_x_variant":[
        "K\u0103tina",
        "K\u016dtina"
    ],
    "wof:name":"Katina",
    "wof:placetype":"locality"
},
  "geometry": {"coordinates":[23.31667,42.83333],"type":"Point"}
}