{
  "type": "Feature",
  "properties": {
    "gn:admin1_code":"57",
    "gn:admin2_code":"SML02",
    "gn:asciiname":"Trave",
    "gn:cc2":"BG",
    "gn:country_code":"BG",
    "gn:dem":977,
    "gn:feature_class":"P",
    "gn:feature_code":"PPL",
    "gn:name":"Trave",
    "gn:population":0,
    "gn:timezone":"Europe/Sofia",
    "iso:country":"BG",
    "name:bul_x_preferred":[
        "\u0422\u0440\u0430\u0432\u0435"
    ],
    "name:und_x_variant":[
        "Trevya",
        "Trave"
    ],
    "wof:name":"Trave",
    "wof:placetype":"locality"
},
  "geometry": {"coordinates":[25.05,41.65],"type":"Point"}
}