{
  "type": "Feature",
  "properties": {
    "gn:admin1_code":"51",
    "gn:admin2_code":"PDV12",
    "gn:admin3_code":"PDV12-01",
    "gn:asciiname":"Begovo",
    "gn:cc2":"BG",
    "gn:country_code":"BG",
    "gn:dem":227,
    "gn:feature_class":"P",
    "gn:feature_code":"PPL",
    "gn:name":"Begovo",
    "gn:population":0,
    "gn:timezone":"Europe/Sofia",
    "iso:country":"BG",
    "name:bul_x_preferred":[
        "\u0411\u0435\u0433\u043e\u0432\u043e"
    ],
    "name:und_x_variant":[
        "Begowo",
        "Begovo"
    ],
    "wof:name":"Begovo",
    "wof:placetype":"locality"
},
  "geometry": {"coordinates":[24.81667,42.41667],"type":"Point"}
}