{
  "type": "Feature",
  "properties": {
    "gn:admin1_code":"44",
    "gn:asciiname":"Zelenikovo",
    "gn:cc2":"BG",
    "gn:country_code":"BG",
    "gn:dem":364,
    "gn:feature_class":"P",
    "gn:feature_code":"PPL",
    "gn:name":"Zelenikovo",
    "gn:population":0,
    "gn:timezone":"Europe/Sofia",
    "iso:country":"BG",
    "name:bul_x_preferred":[
        "\u0417\u0435\u043b\u0435\u043d\u0438\u043a\u043e\u0432\u043e"
    ],
    "name:und_x_variant":[
        "Selenikowo",
        "Kad\u016dr Meschit",
        "Zelenikovo"
    ],
    "wof:name":"Zelenikovo",
    "wof:placetype":"locality"
},
  "geometry": {"coordinates":[25.33333,41.66667],"type":"Point"}
}