{
  "type": "Feature",
  "properties": {
    "gn:admin1_code":"38",
    "gn:asciiname":"Ovnarska Mahala",
    "gn:country_code":"BG",
    "gn:dem":598,
    "gn:feature_class":"P",
    "gn:feature_code":"PPL",
    "gn:name":"Ovnarska Mahala",
    "gn:population":0,
    "gn:timezone":"Europe/Sofia",
    "iso:country":"BG",
    "name:bul_x_preferred":[
        "\u041e\u0432\u043d\u0430\u0440\u0446\u0438"
    ],
    "name:bul_x_variant":[
        "Ovnarska Mahala",
        "\u041e\u0432\u043d\u0430\u0440\u0441\u043a\u0430 \u041c\u0430\u0445\u0430\u043b\u0430"
    ],
    "name:und_x_variant":[
        "Ovnartsi",
        "Ovnarska Makhala"
    ],
    "wof:name":"Ovnarska Mahala",
    "wof:placetype":"locality"
},
  "geometry": {"coordinates":[23.0001,41.98666],"type":"Point"}
}