{
  "type": "Feature",
  "properties": {
    "iso:country":"BG",
    "name:bul_x_preferred":[
        "\u041e\u0431\u0435\u043b\u044f"
    ],
    "name:bul_x_variant":[
        "Obelja",
        "Obyelya"
    ],
    "name:eng_x_preferred":[
        "Obelya"
    ],
    "name:eng_x_variant":[
        "Obelja",
        "Obyelya"
    ],
    "name:nno_x_preferred":[
        "Obelyabreen"
    ],
    "name:zho_x_preferred":[
        "\u5967\u8c9d\u5229\u4e9e\u51b0\u5ddd"
    ],
    "qs:gn_adm0_cc":"BG",
    "qs:gn_local":727011,
    "qs:gn_nam_loc":"Sofiya, Sofia, Sofiya-Grad, BG",
    "qs:gn_namadm1":"42",
    "qs:local_max":4184,
    "qs:local_sum":18613,
    "qs:localhoods":26,
    "qs:name":"Obelya",
    "qs:name_adm0":"Bulgaria",
    "qs:name_adm1":"Sofiya-Grad",
    "qs:name_adm2":"Sofiya",
    "qs:name_local":"Sofia",
    "qs:photo_max":103,
    "qs:photo_sum":123,
    "qs:placetype":"Suburb",
    "qs:quad_count":6,
    "qs:woe_adm0":23424771,
    "qs:woe_adm1":20069794,
    "qs:woe_adm2":55873710,
    "qs:woe_lau":0,
    "qs:woe_local":839722,
    "qs:woe_ver":"7.10.0",
    "wd:wordcount":177,
    "wof:lang":[
        "eng"
    ],
    "wof:name":"Obelya",
    "wof:placetype":"neighbourhood"
},
  "geometry": {"coordinates":[23.274157,42.739681],"type":"Point"}
}