{
  "type": "Feature",
  "properties": {
    "gn:admin1_code":"40",
    "gn:admin2_code":"DOB12",
    "gn:admin3_code":"DOB12-29",
    "gn:asciiname":"Ravnets",
    "gn:country_code":"BG",
    "gn:dem":237,
    "gn:feature_class":"P",
    "gn:feature_code":"PPL",
    "gn:name":"Ravnets",
    "gn:population":0,
    "gn:timezone":"Europe/Sofia",
    "iso:country":"BG",
    "name:bul_x_preferred":[
        "\u0420\u0430\u0432\u043d\u0435\u0446"
    ],
    "name:ceb_x_preferred":[
        "Ravnets"
    ],
    "name:fra_x_preferred":[
        "Ravnets"
    ],
    "name:swe_x_preferred":[
        "Ravnets"
    ],
    "name:und_x_variant":[
        "Piri Fak\u016d",
        "Ravnec",
        "Perifaci"
    ],
    "wof:name":"Ravnets",
    "wof:placetype":"locality"
},
  "geometry": {"coordinates":[27.98724,43.68193],"type":"Point"}
}