{
  "type": "Feature",
  "properties": {
    "gn:admin1_code":"44",
    "gn:asciiname":"Chorbadzhiysko",
    "gn:country_code":"BG",
    "gn:dem":337,
    "gn:feature_class":"P",
    "gn:feature_code":"PPLL",
    "gn:name":"Chorbadzhiysko",
    "gn:population":0,
    "gn:timezone":"Europe/Sofia",
    "iso:country":"BG",
    "name:bul_x_preferred":[
        "Chorbadzhiysko"
    ],
    "name:bul_x_variant":[
        "\u0427\u043e\u0440\u0431\u0430\u0434\u0436\u0438\u0439\u0441\u043a\u043e"
    ],
    "name:ron_x_preferred":[
        "Ciorbadjiisko"
    ],
    "name:rus_x_preferred":[
        "\u0427\u043e\u0440\u0431\u0430\u0434\u0436\u0438\u0439\u0441\u043a\u043e"
    ],
    "name:ukr_x_preferred":[
        "\u0427\u043e\u0440\u0431\u0430\u0434\u0436\u0456\u0439\u0441\u044c\u043a\u043e"
    ],
    "wof:name":"Chorbadzhiysko",
    "wof:placetype":"locality"
},
  "geometry": {"coordinates":[25.4164,41.36773],"type":"Point"}
}