{
  "type": "Feature",
  "properties": {
    "gn:admin1_code":"38",
    "gn:admin2_code":"BLG28",
    "gn:admin3_code":"BLG28-05",
    "gn:asciiname":"Budiltsi",
    "gn:cc2":"BG",
    "gn:country_code":"BG",
    "gn:dem":655,
    "gn:feature_class":"P",
    "gn:feature_code":"PPL",
    "gn:name":"Budiltsi",
    "gn:population":0,
    "gn:timezone":"Europe/Sofia",
    "iso:country":"BG",
    "name:bul_x_preferred":[
        "\u0411\u0443\u0434\u0438\u043b\u0446\u0438"
    ],
    "name:und_x_variant":[
        "Budilzi",
        "Budiltsi"
    ],
    "wof:name":"Budiltsi",
    "wof:placetype":"locality"
},
  "geometry": {"coordinates":[23.11667000000001,41.68333],"type":"Point"}
}