{
  "type": "Feature",
  "properties": {
    "gn:admin1_code":"48",
    "gn:asciiname":"Soyka",
    "gn:cc2":"BG",
    "gn:country_code":"BG",
    "gn:dem":1209,
    "gn:feature_class":"P",
    "gn:feature_code":"PPL",
    "gn:name":"Soyka",
    "gn:population":0,
    "gn:timezone":"Europe/Sofia",
    "iso:country":"BG",
    "name:bul_x_preferred":[
        "\u0421\u043e\u0439\u043a\u0430"
    ],
    "name:und_x_variant":[
        "Yumerovi",
        "Soyka"
    ],
    "wof:name":"Soyka",
    "wof:placetype":"locality"
},
  "geometry": {"coordinates":[23.88333,42.03333],"type":"Point"}
}