{
  "type": "Feature",
  "properties": {
    "gn:admin1_code":"46",
    "gn:asciiname":"Kapinova Stoka",
    "gn:country_code":"BG",
    "gn:dem":460,
    "gn:feature_class":"P",
    "gn:feature_code":"PPL",
    "gn:name":"Kapinova Stoka",
    "gn:population":0,
    "gn:timezone":"Europe/Sofia",
    "iso:country":"BG",
    "name:bul_x_preferred":[
        "\u041a\u0430\u043f\u0438\u043d\u043e\u0432\u0441\u043a\u0430 \u0441\u0442\u043e\u043a\u0430"
    ],
    "wof:name":"Kapinova Stoka",
    "wof:placetype":"locality"
},
  "geometry": {"coordinates":[24.85,42.88333],"type":"Point"}
}