{
  "type": "Feature",
  "properties": {
    "gn:admin1_code":"57",
    "gn:admin2_code":"SML31",
    "gn:admin3_code":"SML31-20",
    "gn:asciiname":"Chamla",
    "gn:country_code":"BG",
    "gn:dem":1619,
    "gn:feature_class":"P",
    "gn:feature_code":"PPL",
    "gn:name":"Chamla",
    "gn:population":0,
    "gn:timezone":"Europe/Sofia",
    "iso:country":"BG",
    "name:bul_x_preferred":[
        "\u0427\u0430\u043c\u043b\u0430"
    ],
    "name:und_x_variant":[
        "Tschamla",
        "Chamla"
    ],
    "wof:name":"Chamla",
    "wof:placetype":"locality"
},
  "geometry": {"coordinates":[24.45497,41.62246],"type":"Point"}
}