{
  "type": "Feature",
  "properties": {
    "gn:admin1_code":"38",
    "gn:admin2_code":"BLG28",
    "gn:asciiname":"Vlahi",
    "gn:country_code":"BG",
    "gn:dem":591,
    "gn:feature_class":"P",
    "gn:feature_code":"PPL",
    "gn:name":"Vlahi",
    "gn:population":0,
    "gn:timezone":"Europe/Sofia",
    "iso:country":"BG",
    "name:bul_x_preferred":[
        "\u0412\u043b\u0430\u0445\u0438"
    ],
    "name:bul_x_variant":[
        "Vlahi"
    ],
    "name:und_x_variant":[
        "Wlachi",
        "Vlakhi"
    ],
    "wof:name":"Vlahi",
    "wof:placetype":"locality"
},
  "geometry": {"coordinates":[23.23333,41.73333],"type":"Point"}
}