{
  "type": "Feature",
  "properties": {
    "gn:admin1_code":"44",
    "gn:asciiname":"Poroy",
    "gn:country_code":"BG",
    "gn:dem":512,
    "gn:feature_class":"P",
    "gn:feature_code":"PPL",
    "gn:name":"Poroy",
    "gn:population":0,
    "gn:timezone":"Europe/Sofia",
    "iso:country":"BG",
    "name:bul_x_preferred":[
        "\u041f\u043e\u0440\u043e\u0439\u043d\u043e"
    ],
    "name:bul_x_variant":[
        "\u041f\u043e\u0440\u043e\u0439"
    ],
    "wof:name":"Poroy",
    "wof:placetype":"locality"
},
  "geometry": {"coordinates":[25.77978,41.45168],"type":"Point"}
}