{
  "type": "Feature",
  "properties": {
    "gn:admin1_code":"50",
    "gn:admin2_code":"PVN03",
    "gn:admin3_code":"PVN03-03",
    "gn:asciiname":"Kulina Voda",
    "gn:country_code":"BG",
    "gn:dem":103,
    "gn:feature_class":"P",
    "gn:feature_code":"PPL",
    "gn:name":"Kulina Voda",
    "gn:population":0,
    "gn:timezone":"Europe/Sofia",
    "iso:country":"BG",
    "name:bul_x_preferred":[
        "\u041a\u0443\u043b\u0438\u043d\u0430 \u0412\u043e\u0434\u0430"
    ],
    "name:und_x_variant":[
        "Kuminavoda",
        "Kuminawoda",
        "Kulino Voda",
        "Kulina Voda"
    ],
    "wof:name":"Kulina Voda",
    "wof:placetype":"locality"
},
  "geometry": {"coordinates":[25.0332,43.58713],"type":"Point"}
}