{
  "type": "Feature",
  "properties": {
    "gn:admin1_code":"44",
    "gn:admin2_code":"KRZ16",
    "gn:admin3_code":"KRZ16-08",
    "gn:asciiname":"Dolna Krepost",
    "gn:cc2":"BG",
    "gn:country_code":"BG",
    "gn:dem":406,
    "gn:feature_class":"P",
    "gn:feature_code":"PPL",
    "gn:name":"Dolna Krepost",
    "gn:population":0,
    "gn:timezone":"Europe/Sofia",
    "iso:country":"BG",
    "name:bul_x_preferred":[
        "\u0414\u043e\u043b\u043d\u0430 \u041a\u0440\u0435\u043f\u043e\u0441\u0442"
    ],
    "name:und_x_variant":[
        "Dere Makhle",
        "Dolna Krepost"
    ],
    "wof:name":"Dolna Krepost",
    "wof:placetype":"locality"
},
  "geometry": {"coordinates":[25.48333,41.73333],"type":"Point"}
}