{
  "type": "Feature",
  "properties": {
    "gn:admin1_code":"56",
    "gn:admin2_code":"SLV20",
    "gn:admin3_code":"SLV20-40",
    "gn:asciiname":"Strupets",
    "gn:cc2":"BG",
    "gn:country_code":"BG",
    "gn:dem":203,
    "gn:feature_class":"P",
    "gn:feature_code":"PPL",
    "gn:name":"Strupets",
    "gn:population":0,
    "gn:timezone":"Europe/Sofia",
    "iso:country":"BG",
    "name:bul_x_preferred":[
        "\u0421\u0442\u0440\u0443\u043f\u0435\u0446"
    ],
    "name:und_x_variant":[
        "Strupez",
        "Strupets"
    ],
    "wof:name":"Strupets",
    "wof:placetype":"locality"
},
  "geometry": {"coordinates":[26.11667000000001,42.61667],"type":"Point"}
}