{
  "type": "Feature",
  "properties": {
    "gn:admin1_code":"41",
    "gn:admin2_code":"GAB05",
    "gn:asciiname":"Fargovtsi",
    "gn:country_code":"BG",
    "gn:dem":401,
    "gn:feature_class":"P",
    "gn:feature_code":"PPL",
    "gn:name":"Fargovtsi",
    "gn:population":0,
    "gn:timezone":"Europe/Sofia",
    "iso:country":"BG",
    "name:ara_x_preferred":[
        "\u0641\u0648\u0631\u063a\u0648\u062a\u0633\u064a"
    ],
    "name:bul_x_preferred":[
        "\u0424\u044a\u0440\u0433\u043e\u0432\u0446\u0438"
    ],
    "name:bul_x_variant":[
        "Fargovtsi"
    ],
    "name:fas_x_preferred":[
        "\u0641\u0648\u0631\u06af\u0648\u0648\u062a\u0633\u06cc"
    ],
    "name:kaz_x_preferred":[
        "\u0424\u044b\u0440\u0433\u043e\u0432\u0446\u0438"
    ],
    "name:pol_x_preferred":[
        "Fyrgowci"
    ],
    "name:ron_x_preferred":[
        "F\u0103rgov\u021bi"
    ],
    "name:rus_x_preferred":[
        "\u0424\u044b\u0440\u0433\u043e\u0432\u0446\u0438"
    ],
    "name:ukr_x_preferred":[
        "\u0424\u0438\u0440\u0433\u043e\u0432\u0446\u0456"
    ],
    "name:und_x_variant":[
        "F\u016drgovtsi"
    ],
    "wof:name":"Fargovtsi",
    "wof:placetype":"locality"
},
  "geometry": {"coordinates":[25.31667,42.86667],"type":"Point"}
}