{
  "type": "Feature",
  "properties": {
    "gn:country":"BG",
    "gn:fcode":"PPL",
    "gn:population":0,
    "iso:country":"BG",
    "name:bul_x_preferred":[
        "\u0411\u0435\u043b\u0446\u043e\u0432"
    ],
    "name:und_x_variant":[
        "Byeltsovo"
    ],
    "qs_pg:aaroncc":"BG",
    "qs_pg:gn_country":"BG",
    "qs_pg:gn_fcode":"PPL",
    "qs_pg:gn_pop":0,
    "qs_pg:name":"Beltsov",
    "qs_pg:name_adm0":"Bulgaria",
    "qs_pg:name_adm1":"Ruse",
    "qs_pg:photos":9,
    "qs_pg:photos_1k":2,
    "qs_pg:photos_9k":1,
    "qs_pg:photos_9r":1,
    "qs_pg:photos_all":9,
    "qs_pg:photos_sr":1,
    "qs_pg:pop_sr":0,
    "qs_pg:qs_pg_placetype":"locality",
    "qs_pg:qs_pg_placetype_gp":"Town",
    "qs_pg:woe_adm0":23424771,
    "woe:adm0_id":23424771,
    "woe:name_adm0":"Bulgaria",
    "woe:name_adm1":"Ruse",
    "woe:placetype":"Town",
    "wof:name":"Beltsov",
    "wof:placetype":"locality"
},
  "geometry": {"coordinates":[25.63333,43.56667],"type":"Point"}
}