{
  "type": "Feature",
  "properties": {
    "gn:admin1_code":"43",
    "gn:admin2_code":"HKV32",
    "gn:asciiname":"Prisadets",
    "gn:country_code":"BG",
    "gn:dem":193,
    "gn:feature_class":"P",
    "gn:feature_code":"PPL",
    "gn:name":"Prisadets",
    "gn:population":0,
    "gn:timezone":"Europe/Sofia",
    "iso:country":"BG",
    "name:bul_x_preferred":[
        "\u041f\u0440\u0438\u0441\u0430\u0434\u0435\u0446"
    ],
    "name:fas_x_preferred":[
        "\u067e\u0631\u06cc\u0633\u0627\u062f\u062a\u0633"
    ],
    "name:kaz_x_preferred":[
        "\u041f\u0440\u0438\u0441\u0430\u0434\u0435\u0446"
    ],
    "name:pol_x_preferred":[
        "Prisadec"
    ],
    "name:ron_x_preferred":[
        "Prisade\u021b"
    ],
    "name:rus_x_preferred":[
        "\u041f\u0440\u0438\u0441\u0430\u0434\u0435\u0446"
    ],
    "name:ukr_x_preferred":[
        "\u041f\u0440\u0438\u0441\u0430\u0434\u0435\u0446\u044c"
    ],
    "name:und_x_variant":[
        "Armutlar",
        "Prissadez",
        "Prisadets"
    ],
    "wof:name":"Prisadets",
    "wof:placetype":"locality"
},
  "geometry": {"coordinates":[26.53558,41.89502],"type":"Point"}
}