{
  "type": "Feature",
  "properties": {
    "gn:admin1_code":"38",
    "gn:asciiname":"Kapetantsi",
    "gn:country_code":"BG",
    "gn:dem":1094,
    "gn:feature_class":"P",
    "gn:feature_code":"PPL",
    "gn:name":"Kapetantsi",
    "gn:population":0,
    "gn:timezone":"Europe/Sofia",
    "iso:country":"BG",
    "name:bul_x_preferred":[
        "Kapetantsi"
    ],
    "name:bul_x_variant":[
        "\u041a\u0430\u043f\u0435\u0442\u0430\u043d\u0446\u0438"
    ],
    "wof:name":"Kapetantsi",
    "wof:placetype":"locality"
},
  "geometry": {"coordinates":[22.9565,41.85627],"type":"Point"}
}