{
  "type": "Feature",
  "properties": {
    "gn:admin1_code":"56",
    "gn:admin2_code":"SLV20",
    "gn:admin3_code":"SLV20-21",
    "gn:asciiname":"Kaloyanovo",
    "gn:cc2":"BG",
    "gn:country_code":"BG",
    "gn:dem":156,
    "gn:feature_class":"P",
    "gn:feature_code":"PPL",
    "gn:name":"Kaloyanovo",
    "gn:population":0,
    "gn:timezone":"Europe/Sofia",
    "iso:country":"BG",
    "name:bul_x_preferred":[
        "\u041a\u0430\u043b\u043e\u044f\u043d\u043e\u0432\u043e"
    ],
    "name:ceb_x_preferred":[
        "Kaloyanovo"
    ],
    "name:fra_x_preferred":[
        "Kaloyanovo"
    ],
    "name:rus_x_preferred":[
        "\u041a\u0430\u043b\u043e\u044f\u043d\u043e\u0432\u043e"
    ],
    "name:swe_x_preferred":[
        "Kaloyanovo"
    ],
    "name:ukr_x_preferred":[
        "\u041a\u0430\u043b\u043e\u044f\u043d\u043e\u0432\u043e"
    ],
    "name:und_x_variant":[
        "Tutludzha",
        "Kalojanowo",
        "Kalayanovo",
        "Kaloyanovo"
    ],
    "wof:name":"Kaloyanovo",
    "wof:placetype":"locality"
},
  "geometry": {"coordinates":[26.46667,42.65],"type":"Point"}
}