{
  "type": "Feature",
  "properties": {
    "gn:admin1_code":"45",
    "gn:asciiname":"Torbantsi",
    "gn:country_code":"BG",
    "gn:dem":926,
    "gn:feature_class":"P",
    "gn:feature_code":"PPL",
    "gn:name":"Torbantsi",
    "gn:population":0,
    "gn:timezone":"Europe/Sofia",
    "iso:country":"BG",
    "name:bul_x_preferred":[
        "Torbantsi"
    ],
    "name:bul_x_variant":[
        "\u0422\u043e\u0440\u0431\u0430\u043d\u0446\u0438"
    ],
    "wof:name":"Torbantsi",
    "wof:placetype":"locality"
},
  "geometry": {"coordinates":[22.47253,42.24947],"type":"Point"}
}