{
  "type": "Feature",
  "properties": {
    "gn:admin1_code":"56",
    "gn:admin2_code":"SLV16",
    "gn:admin3_code":"SLV16-19",
    "gn:asciiname":"Omarchevo",
    "gn:cc2":"BG",
    "gn:country_code":"BG",
    "gn:dem":217,
    "gn:feature_class":"P",
    "gn:feature_code":"PPL",
    "gn:name":"Omarchevo",
    "gn:population":0,
    "gn:timezone":"Europe/Sofia",
    "iso:country":"BG",
    "name:bul_x_preferred":[
        "\u041e\u043c\u0430\u0440\u0447\u0435\u0432\u043e"
    ],
    "name:und_x_variant":[
        "Marcha",
        "Omar\u010devo",
        "Omartschewo",
        "Ormachevo",
        "Omarchevo"
    ],
    "wof:name":"Omarchevo",
    "wof:placetype":"locality"
},
  "geometry": {"coordinates":[26.13333,42.45],"type":"Point"}
}