{
  "type": "Feature",
  "properties": {
    "gn:admin1_code":"49",
    "gn:admin2_code":"PER19",
    "gn:asciiname":"Vranya Stena",
    "gn:country_code":"BG",
    "gn:dem":725,
    "gn:feature_class":"P",
    "gn:feature_code":"PPL",
    "gn:name":"Vranya Stena",
    "gn:population":0,
    "gn:timezone":"Europe/Sofia",
    "iso:country":"BG",
    "name:bul_x_preferred":[
        "\u0412\u0440\u0430\u043d\u044f \u0421\u0442\u0435\u043d\u0430"
    ],
    "name:und_x_variant":[
        "Wranja-Stena",
        "Vranya Styena",
        "Vranya Stena"
    ],
    "wof:name":"Vranya Stena",
    "wof:placetype":"locality"
},
  "geometry": {"coordinates":[22.73152,42.53289],"type":"Point"}
}