{
  "type": "Feature",
  "properties": {
    "gn:admin1_code":"51",
    "gn:admin2_code":"PDV15",
    "gn:asciiname":"Borovo",
    "gn:cc2":"BG",
    "gn:country_code":"BG",
    "gn:dem":1168,
    "gn:feature_class":"P",
    "gn:feature_code":"PPL",
    "gn:name":"Borovo",
    "gn:population":0,
    "gn:timezone":"Europe/Sofia",
    "iso:country":"BG",
    "name:bul_x_preferred":[
        "\u0411\u043e\u0440\u043e\u0432\u043e"
    ],
    "name:und_x_variant":[
        "Borowo",
        "Borovo"
    ],
    "wof:name":"Borovo",
    "wof:placetype":"locality"
},
  "geometry": {"coordinates":[24.88333,41.85],"type":"Point"}
}