{
  "type": "Feature",
  "properties": {
    "gn:admin1_code":"45",
    "gn:admin2_code":"KNL50",
    "gn:asciiname":"Brest",
    "gn:country_code":"BG",
    "gn:dem":945,
    "gn:feature_class":"P",
    "gn:feature_code":"PPL",
    "gn:name":"Brest",
    "gn:population":0,
    "gn:timezone":"Europe/Sofia",
    "iso:country":"BG",
    "name:ara_x_preferred":[
        "\u0628\u0631\u064a\u0633\u062a"
    ],
    "name:arg_x_preferred":[
        "Brest"
    ],
    "name:aze_x_preferred":[
        "Brest"
    ],
    "name:bel_x_preferred":[
        "\u0411\u0440\u044d\u0441\u0442"
    ],
    "name:bre_x_preferred":[
        "Brest"
    ],
    "name:bul_x_preferred":[
        "\u0411\u0440\u0435\u0441\u0442"
    ],
    "name:cat_x_preferred":[
        "Brest"
    ],
    "name:ceb_x_preferred":[
        "Brest"
    ],
    "name:ces_x_preferred":[
        "Brest"
    ],
    "name:dan_x_preferred":[
        "Brest"
    ],
    "name:deu_x_preferred":[
        "Brest"
    ],
    "name:ell_x_preferred":[
        "\u039c\u03c0\u03c1\u03b5\u03c3\u03c4"
    ],
    "name:epo_x_preferred":[
        "Brest"
    ],
    "name:est_x_preferred":[
        "Brest"
    ],
    "name:fas_x_preferred":[
        "\u0628\u0631\u0633\u062a"
    ],
    "name:fin_x_preferred":[
        "Brest"
    ],
    "name:fra_x_preferred":[
        "Brest"
    ],
    "name:frr_x_preferred":[
        "Brest"
    ],
    "name:fry_x_preferred":[
        "Brest"
    ],
    "name:glg_x_preferred":[
        "Brest"
    ],
    "name:glv_x_preferred":[
        "Brest"
    ],
    "name:heb_x_preferred":[
        "\u05d1\u05e8\u05e1\u05d8"
    ],
    "name:hrv_x_preferred":[
        "Brest"
    ],
    "name:hsb_x_preferred":[
        "Brest"
    ],
    "name:hun_x_preferred":[
        "Brest"
    ],
    "name:ind_x_preferred":[
        "Brest"
    ],
    "name:ita_x_preferred":[
        "Brest"
    ],
    "name:jpn_x_preferred":[
        "\u30d6\u30ec\u30b9\u30c8"
    ],
    "name:kat_x_preferred":[
        "\u10d1\u10e0\u10d4\u10e1\u10e2\u10d8"
    ],
    "name:kor_x_preferred":[
        "\ube0c\ub808\uc2a4\ud2b8"
    ],
    "name:lav_x_preferred":[
        "Bresta"
    ],
    "name:lit_x_preferred":[
        "Brestas"
    ],
    "name:lmo_x_preferred":[
        "Brest"
    ],
    "name:ltz_x_preferred":[
        "Brest"
    ],
    "name:mkd_x_preferred":[
        "\u0411\u0440\u0435\u0441\u0442"
    ],
    "name:nds_x_preferred":[
        "Brest"
    ],
    "name:nld_x_preferred":[
        "Brest"
    ],
    "name:nno_x_preferred":[
        "Brest"
    ],
    "name:nor_x_preferred":[
        "Brest"
    ],
    "name:pol_x_preferred":[
        "Brest"
    ],
    "name:por_x_preferred":[
        "Brest"
    ],
    "name:ron_x_preferred":[
        "Brest"
    ],
    "name:rus_x_preferred":[
        "\u0411\u0440\u0435\u0441\u0442"
    ],
    "name:sco_x_preferred":[
        "Brest"
    ],
    "name:slk_x_preferred":[
        "Brest"
    ],
    "name:slv_x_preferred":[
        "Brest"
    ],
    "name:spa_x_preferred":[
        "Brest"
    ],
    "name:srp_x_preferred":[
        "\u0411\u0440\u0435\u0441\u0442"
    ],
    "name:swe_x_preferred":[
        "Brest"
    ],
    "name:szl_x_preferred":[
        "Brest"
    ],
    "name:tur_x_preferred":[
        "Brest"
    ],
    "name:ukr_x_preferred":[
        "\u0411\u0440\u0435\u0441\u0442"
    ],
    "name:und_x_variant":[
        "Bryest"
    ],
    "name:uzb_x_preferred":[
        "Brest"
    ],
    "name:zho_x_preferred":[
        "\u5e03\u96f7\u65af\u7279"
    ],
    "wof:name":"Brest",
    "wof:placetype":"locality"
},
  "geometry": {"coordinates":[22.60625,42.46273],"type":"Point"}
}