{
  "type": "Feature",
  "properties": {
    "gn:admin1_code":"45",
    "gn:admin2_code":"KNL50",
    "gn:asciiname":"Brest",
    "gn:country_code":"BG",
    "gn:dem":945,
    "gn:feature_class":"P",
    "gn:feature_code":"PPL",
    "gn:name":"Brest",
    "gn:population":0,
    "gn:timezone":"Europe/Sofia",
    "iso:country":"BG",
    "name:bul_x_preferred":[
        "\u0411\u0440\u0435\u0441\u0442"
    ],
    "name:und_x_variant":[
        "Bryest",
        "Brest"
    ],
    "wof:name":"Brest",
    "wof:placetype":"locality"
},
  "geometry": {"coordinates":[22.60625,42.46273],"type":"Point"}
}