{
  "type": "Feature",
  "properties": {
    "gn:admin1_code":"41",
    "gn:asciiname":"Kumanovtsi",
    "gn:cc2":"BG",
    "gn:country_code":"BG",
    "gn:dem":368,
    "gn:feature_class":"P",
    "gn:feature_code":"PPL",
    "gn:name":"Kumanovtsi",
    "gn:population":0,
    "gn:timezone":"Europe/Sofia",
    "iso:country":"BG",
    "name:bul_x_preferred":[
        "\u041a\u0443\u043c\u0430\u043d\u043e\u0432\u0446\u0438"
    ],
    "name:und_x_variant":[
        "Kumanovts\u016d",
        "Kumanovtsi"
    ],
    "wof:name":"Kumanovtsi",
    "wof:placetype":"locality"
},
  "geometry": {"coordinates":[25.46667,42.93333],"type":"Point"}
}