{
  "type": "Feature",
  "properties": {
    "gn:admin1_code":"43",
    "gn:asciiname":"Pyasachevo",
    "gn:country_code":"BG",
    "gn:dem":99,
    "gn:feature_class":"P",
    "gn:feature_code":"PPL",
    "gn:name":"Pyasachevo",
    "gn:population":0,
    "gn:timezone":"Europe/Sofia",
    "iso:country":"BG",
    "name:bul_x_preferred":[
        "\u041f\u044f\u0441\u044a\u0447\u0435\u0432\u043e"
    ],
    "name:fas_x_preferred":[
        "\u067e\u06cc\u0627\u0633\u0627\u0686\u0648\u0648"
    ],
    "name:kaz_x_preferred":[
        "\u041f\u044f\u0441\u044b\u0447\u0435\u0432\u043e"
    ],
    "name:pol_x_preferred":[
        "Pjasyczewo"
    ],
    "name:ron_x_preferred":[
        "Peas\u0103cevo"
    ],
    "name:rus_x_preferred":[
        "\u041f\u044f\u0441\u044b\u0447\u0435\u0432\u043e"
    ],
    "name:ukr_x_preferred":[
        "\u041f\u044f\u0441\u0438\u0447\u0435\u0432\u043e"
    ],
    "wof:name":"Pyasachevo",
    "wof:placetype":"locality"
},
  "geometry": {"coordinates":[25.86392,42.1065],"type":"Point"}
}