{
  "type": "Feature",
  "properties": {
    "gn:admin1_code":"43",
    "gn:asciiname":"Pyasachevo",
    "gn:country_code":"BG",
    "gn:dem":99,
    "gn:feature_class":"P",
    "gn:feature_code":"PPL",
    "gn:name":"Pyasachevo",
    "gn:population":0,
    "gn:timezone":"Europe/Sofia",
    "iso:country":"BG",
    "wof:name":"Pyasachevo",
    "wof:placetype":"locality"
},
  "geometry": {"coordinates":[25.86392,42.1065],"type":"Point"}
}