{
  "type": "Feature",
  "properties": {
    "gn:admin1_code":"62",
    "gn:admin2_code":"VTR13",
    "gn:admin3_code":"VTR13-11",
    "gn:asciiname":"Tombeto",
    "gn:cc2":"BG",
    "gn:country_code":"BG",
    "gn:dem":436,
    "gn:feature_class":"P",
    "gn:feature_code":"PPL",
    "gn:name":"Tombeto",
    "gn:population":0,
    "gn:timezone":"Europe/Sofia",
    "iso:country":"BG",
    "name:bul_x_preferred":[
        "\u0422\u043e\u043c\u0431\u0435\u0442\u043e"
    ],
    "name:und_x_variant":[
        "Tyumbe Makhle",
        "Tombeto"
    ],
    "wof:name":"Tombeto",
    "wof:placetype":"locality"
},
  "geometry": {"coordinates":[26.06667,42.95],"type":"Point"}
}