{
  "type": "Feature",
  "properties": {
    "gn:admin1_code":"38",
    "gn:admin2_code":"BLG37",
    "gn:admin3_code":"BLG37-03",
    "gn:asciiname":"Godlevo",
    "gn:cc2":"BG",
    "gn:country_code":"BG",
    "gn:dem":939,
    "gn:feature_class":"P",
    "gn:feature_code":"PPL",
    "gn:name":"Godlevo",
    "gn:population":0,
    "gn:timezone":"Europe/Sofia",
    "iso:country":"BG",
    "name:bul_x_preferred":[
        "\u0413\u043e\u0434\u043b\u0435\u0432\u043e"
    ],
    "name:und_x_variant":[
        "Godlewo",
        "Godlevo"
    ],
    "wof:name":"Godlevo",
    "wof:placetype":"locality"
},
  "geometry": {"coordinates":[23.48333,41.93333],"type":"Point"}
}