{
  "type": "Feature",
  "properties": {
    "gn:gn_country":"BG",
    "gn:gn_fcode":"PPL",
    "gn:gn_pop":0,
    "iso:country":"BG",
    "name:bul_x_preferred":[
        "\u0411\u043e\u0436\u0438\u0447\u0435\u043d"
    ],
    "name:unk_x_variant":[
        "Boshitschen"
    ],
    "qs_pg:aaroncc":"BG",
    "qs_pg:gn_country":"BG",
    "qs_pg:gn_fcode":"PPL",
    "qs_pg:gn_pop":0,
    "qs_pg:name":"Bozhichen",
    "qs_pg:name_adm0":"Bulgaria",
    "qs_pg:name_adm1":"Ruse",
    "qs_pg:photos":60,
    "qs_pg:photos_1k":12,
    "qs_pg:photos_9k":1,
    "qs_pg:photos_9r":2,
    "qs_pg:photos_all":60,
    "qs_pg:photos_sr":2,
    "qs_pg:pop_sr":0,
    "qs_pg:qs_pg_placetype":"locality",
    "qs_pg:qs_pg_placetype_gp":"Town",
    "qs_pg:woe_adm0":23424771,
    "woe:adm0_id":23424771,
    "woe:name_adm0":"Bulgaria",
    "woe:name_adm1":"Ruse",
    "woe:placetype":"Town",
    "wof:name":"Bozhichen",
    "wof:placetype":"locality"
},
  "geometry": {"coordinates":[25.96667,43.71667],"type":"Point"}
}