{
  "type": "Feature",
  "properties": {
    "gn:admin1_code":"52",
    "gn:admin2_code":"RAZ16",
    "gn:admin3_code":"RAZ16-05",
    "gn:asciiname":"Zadruga",
    "gn:country_code":"BG",
    "gn:dem":144,
    "gn:feature_class":"P",
    "gn:feature_code":"PPL",
    "gn:name":"Zadruga",
    "gn:population":0,
    "gn:timezone":"Europe/Sofia",
    "iso:country":"BG",
    "name:bos_x_preferred":[
        "Zadruga"
    ],
    "name:bul_x_preferred":[
        "\u0417\u0430\u0434\u0440\u0443\u0433\u0430"
    ],
    "name:ces_x_preferred":[
        "Z\u00e1druha"
    ],
    "name:epo_x_preferred":[
        "Zadruga"
    ],
    "name:fra_x_preferred":[
        "Zadruga"
    ],
    "name:jpn_x_preferred":[
        "\u30b6\u30c9\u30eb\u30ac"
    ],
    "name:mkd_x_preferred":[
        "\u0417\u0430\u0434\u0440\u0443\u0433\u0430"
    ],
    "name:pol_x_preferred":[
        "Zadruga"
    ],
    "name:por_x_preferred":[
        "Zadruga eslava"
    ],
    "name:rus_x_preferred":[
        "\u0417\u0430\u0434\u0440\u0443\u0433\u0430"
    ],
    "name:spa_x_preferred":[
        "Zadruga"
    ],
    "name:srp_x_preferred":[
        "\u0417\u0430\u0434\u0440\u0443\u0433\u0430"
    ],
    "name:ukr_x_preferred":[
        "\u0417\u0430\u0434\u0440\u0443\u0433\u0430"
    ],
    "name:und_x_variant":[
        "Kishlakioy",
        "Sadruga",
        "K\u016dshla K\u2019oy",
        "Zadruga"
    ],
    "name:zho_x_preferred":[
        "\u672d\u5fb7\u9b6f\u52a0"
    ],
    "wof:name":"Zadruga",
    "wof:placetype":"locality"
},
  "geometry": {"coordinates":[26.50027,43.84838],"type":"Point"}
}