{
  "type": "Feature",
  "properties": {
    "gn:admin1_code":"52",
    "gn:admin2_code":"RAZ16",
    "gn:admin3_code":"RAZ16-05",
    "gn:asciiname":"Zadruga",
    "gn:country_code":"BG",
    "gn:dem":144,
    "gn:feature_class":"P",
    "gn:feature_code":"PPL",
    "gn:name":"Zadruga",
    "gn:population":0,
    "gn:timezone":"Europe/Sofia",
    "iso:country":"BG",
    "name:bul_x_preferred":[
        "\u0417\u0430\u0434\u0440\u0443\u0433\u0430"
    ],
    "name:und_x_variant":[
        "Kishlakioy",
        "Sadruga",
        "K\u016dshla K\u2019oy",
        "Zadruga"
    ],
    "wof:name":"Zadruga",
    "wof:placetype":"locality"
},
  "geometry": {"coordinates":[26.50027,43.84838],"type":"Point"}
}