{
  "type": "Feature",
  "properties": {
    "gn:admin1_code":"52",
    "gn:admin2_code":"RAZ16",
    "gn:admin3_code":"RAZ16-03",
    "gn:asciiname":"Bozhurovo",
    "gn:country_code":"BG",
    "gn:dem":114,
    "gn:feature_class":"P",
    "gn:feature_code":"PPL",
    "gn:name":"Bozhurovo",
    "gn:population":0,
    "gn:timezone":"Europe/Sofia",
    "iso:country":"BG",
    "name:bul_x_preferred":[
        "\u0411\u043e\u0436\u0443\u0440\u043e\u0432\u043e"
    ],
    "name:und_x_variant":[
        "Boshurowo",
        "Bunar Beshevli",
        "Bozhurovo"
    ],
    "wof:name":"Bozhurovo",
    "wof:placetype":"locality"
},
  "geometry": {"coordinates":[26.43676,43.88455],"type":"Point"}
}