{
  "type": "Feature",
  "properties": {
    "gn:admin1_code":"41",
    "gn:admin2_code":"GAB35",
    "gn:asciiname":"Chernovrah",
    "gn:country_code":"BG",
    "gn:dem":511,
    "gn:feature_class":"P",
    "gn:feature_code":"PPL",
    "gn:name":"Chernovrah",
    "gn:population":0,
    "gn:timezone":"Europe/Sofia",
    "iso:country":"BG",
    "name:bul_x_preferred":[
        "\u0427\u0435\u0440\u043d\u043e\u0432\u0440\u044a\u0445"
    ],
    "name:bul_x_variant":[
        "Chernovrah"
    ],
    "name:und_x_variant":[
        "Popovts\u016d",
        "Popowzi",
        "Popovtsi",
        "Chernovr\u016dkh"
    ],
    "wof:name":"Chernovrah",
    "wof:placetype":"locality"
},
  "geometry": {"coordinates":[25.51667,42.88333],"type":"Point"}
}