{
  "type": "Feature",
  "properties": {
    "gn:admin1_code":"55",
    "gn:admin2_code":"SLS07",
    "gn:admin3_code":"SLS07-21",
    "gn:asciiname":"Bashtino",
    "gn:cc2":"BG",
    "gn:country_code":"BG",
    "gn:dem":134,
    "gn:feature_class":"P",
    "gn:feature_code":"PPL",
    "gn:name":"Bashtino",
    "gn:population":0,
    "gn:timezone":"Europe/Sofia",
    "iso:country":"BG",
    "name:bul_x_preferred":[
        "\u0411\u0430\u0449\u0438\u043d\u043e"
    ],
    "name:und_x_variant":[
        "Pitracli",
        "P\u016dtraklii",
        "Chadshiolar",
        "Ba\u0161tica",
        "Bashtina",
        "Bashtino"
    ],
    "wof:name":"Bashtino",
    "wof:placetype":"locality"
},
  "geometry": {"coordinates":[26.93333,43.95],"type":"Point"}
}