{
  "type": "Feature",
  "properties": {
    "gn:admin1_code":"65",
    "gn:admin2_code":"JAM07",
    "gn:asciiname":"Lalkovo",
    "gn:country_code":"BG",
    "gn:dem":194,
    "gn:feature_class":"P",
    "gn:feature_code":"PPL",
    "gn:name":"Lalkovo",
    "gn:population":0,
    "gn:timezone":"Europe/Sofia",
    "iso:country":"BG",
    "name:bul_x_preferred":[
        "\u041b\u0430\u043b\u043a\u043e\u0432\u043e"
    ],
    "name:und_x_variant":[
        "Mal\u016dk-Dervent",
        "Lalkowo",
        "Laikovo",
        "Lalkovo"
    ],
    "wof:name":"Lalkovo",
    "wof:placetype":"locality"
},
  "geometry": {"coordinates":[26.72009000000001,42.07516],"type":"Point"}
}