{
  "type": "Feature",
  "properties": {
    "gn:admin1_code":"61",
    "gn:admin2_code":"VAR24",
    "gn:asciiname":"Kiten",
    "gn:cc2":"BG",
    "gn:country_code":"BG",
    "gn:dem":219,
    "gn:feature_class":"P",
    "gn:feature_code":"PPL",
    "gn:name":"Kiten",
    "gn:population":1115,
    "gn:timezone":"Europe/Sofia",
    "iso:country":"BG",
    "name:bul_x_preferred":[
        "\u041a\u0438\u0442\u0435\u043d"
    ],
    "name:und_x_variant":[
        "Mukhalii",
        "Kiten"
    ],
    "wof:name":"Kiten",
    "wof:placetype":"locality",
    "wof:population":1115
},
  "geometry": {"coordinates":[27.31667,43.08333],"type":"Point"}
}