{
  "type": "Feature",
  "properties": {
    "gn:admin1_code":"44",
    "gn:asciiname":"Lyulyakova Mahala",
    "gn:country_code":"BG",
    "gn:dem":446,
    "gn:feature_class":"P",
    "gn:feature_code":"PPL",
    "gn:name":"Lyulyakova Mahala",
    "gn:population":0,
    "gn:timezone":"Europe/Sofia",
    "iso:country":"BG",
    "name:bul_x_preferred":[
        "Lyulyakova Mahala"
    ],
    "name:bul_x_variant":[
        "\u041b\u044e\u043b\u044f\u043a\u043e\u0432\u0430 \u041c\u0430\u0445\u0430\u043b\u0430"
    ],
    "name:und_x_variant":[
        "Lyulyakova Makhala"
    ],
    "wof:name":"Lyulyakova Mahala",
    "wof:placetype":"locality"
},
  "geometry": {"coordinates":[25.68099,41.36136],"type":"Point"}
}