{
  "type": "Feature",
  "properties": {
    "gn:admin1_code":"43",
    "gn:admin2_code":"HKV29",
    "gn:asciiname":"Dryanovo",
    "gn:cc2":"BG",
    "gn:country_code":"BG",
    "gn:dem":157,
    "gn:feature_class":"P",
    "gn:feature_code":"PPL",
    "gn:name":"Dryanovo",
    "gn:population":0,
    "gn:timezone":"Europe/Sofia",
    "iso:country":"BG",
    "name:azb_x_preferred":[
        "\u062f\u0631\u06cc\u0627\u0646\u0648\u0648"
    ],
    "name:bul_x_preferred":[
        "\u0414\u0440\u044f\u043d\u043e\u0432\u043e"
    ],
    "name:ceb_x_preferred":[
        "Obshtina Dryanovo"
    ],
    "name:ckb_x_preferred":[
        "\u062f\u0631\u06cc\u0627\u0646\u06c6\u06a4\u06c6"
    ],
    "name:deu_x_preferred":[
        "Drjanowo"
    ],
    "name:est_x_preferred":[
        "Drjanovo"
    ],
    "name:fas_x_preferred":[
        "\u062f\u0631\u06cc\u0627\u0646\u0648\u0648\u0648"
    ],
    "name:fra_x_preferred":[
        "Dryanovo"
    ],
    "name:heb_x_preferred":[
        "\u05d3\u05e8\u05d9\u05d0\u05e0\u05d5\u05d1\u05d5"
    ],
    "name:jpn_x_preferred":[
        "\u30c9\u30ea\u30e3\u30ce\u30f4\u30a9"
    ],
    "name:kaz_x_preferred":[
        "\u0414\u0440\u044f\u043d\u043e\u0432\u043e"
    ],
    "name:nld_x_preferred":[
        "Drjanovo"
    ],
    "name:pol_x_preferred":[
        "Drjanowo"
    ],
    "name:por_x_preferred":[
        "Drjanovo"
    ],
    "name:ron_x_preferred":[
        "Dreanovo"
    ],
    "name:rus_x_preferred":[
        "\u0414\u0440\u044f\u043d\u043e\u0432\u043e"
    ],
    "name:spa_x_preferred":[
        "Dryanovo"
    ],
    "name:srp_x_preferred":[
        "\u0414\u0440\u0458\u0430\u043d\u043e\u0432\u043e"
    ],
    "name:swe_x_preferred":[
        "Obsjtina Drjanovo"
    ],
    "name:tur_x_preferred":[
        "Direnova"
    ],
    "name:ukr_x_preferred":[
        "\u0414\u0440\u044f\u043d\u043e\u0432\u043e"
    ],
    "name:und_x_variant":[
        "Drenowo",
        "Dryenovo",
        "Dryanovo"
    ],
    "name:vie_x_preferred":[
        "Dryanovo"
    ],
    "name:war_x_preferred":[
        "Dryanovo"
    ],
    "name:zho_x_preferred":[
        "\u5fb7\u91cc\u4e9e\u8afe\u6c83"
    ],
    "wof:name":"Dryanovo",
    "wof:placetype":"locality"
},
  "geometry": {"coordinates":[25.95,42.08333],"type":"Point"}
}