{
  "type": "Feature",
  "properties": {
    "gn:admin1_code":"43",
    "gn:admin2_code":"HKV29",
    "gn:asciiname":"Dryanovo",
    "gn:cc2":"BG",
    "gn:country_code":"BG",
    "gn:dem":157,
    "gn:feature_class":"P",
    "gn:feature_code":"PPL",
    "gn:name":"Dryanovo",
    "gn:population":0,
    "gn:timezone":"Europe/Sofia",
    "iso:country":"BG",
    "name:bul_x_preferred":[
        "\u0414\u0440\u044f\u043d\u043e\u0432\u043e"
    ],
    "name:und_x_variant":[
        "Drenowo",
        "Dryenovo",
        "Dryanovo"
    ],
    "wof:name":"Dryanovo",
    "wof:placetype":"locality"
},
  "geometry": {"coordinates":[25.95,42.08333],"type":"Point"}
}