{
  "type": "Feature",
  "properties": {
    "gn:admin1_code":"45",
    "gn:admin2_code":"KNL29",
    "gn:asciiname":"Gorno Uyno",
    "gn:country_code":"BG",
    "gn:dem":694,
    "gn:feature_class":"P",
    "gn:feature_code":"PPL",
    "gn:name":"Gorno Uyno",
    "gn:population":0,
    "gn:timezone":"Europe/Sofia",
    "iso:country":"BG",
    "name:bul_x_preferred":[
        "\u0413\u043e\u0440\u043d\u043e \u0423\u0439\u043d\u043e"
    ],
    "name:fas_x_preferred":[
        "\u06af\u0648\u0631\u0646\u0648 \u0627\u0648\u06cc\u0646\u0648"
    ],
    "name:kaz_x_preferred":[
        "\u0413\u043e\u0440\u043d\u043e-\u0423\u0439\u043d\u043e"
    ],
    "name:ron_x_preferred":[
        "Gorno Uino"
    ],
    "name:rus_x_preferred":[
        "\u0413\u043e\u0440\u043d\u043e-\u0423\u0439\u043d\u043e"
    ],
    "name:ukr_x_preferred":[
        "\u0413\u043e\u0440\u0456\u0448\u043d\u0454 \u0423\u0439\u043d\u043e"
    ],
    "name:und_x_variant":[
        "Ujno",
        "Gorno Uino",
        "Gorno Ujno",
        "Gorno Uyno"
    ],
    "wof:name":"Gorno Uyno",
    "wof:placetype":"locality"
},
  "geometry": {"coordinates":[22.57661,42.4464],"type":"Point"}
}