{
  "type": "Feature",
  "properties": {
    "gn:admin1_code":"54",
    "gn:admin2_code":"SHU30",
    "gn:admin3_code":"SHU30-23",
    "gn:asciiname":"Velino",
    "gn:cc2":"BG",
    "gn:country_code":"BG",
    "gn:dem":248,
    "gn:feature_class":"P",
    "gn:feature_code":"PPL",
    "gn:name":"Velino",
    "gn:population":0,
    "gn:timezone":"Europe/Sofia",
    "iso:country":"BG",
    "name:bul_x_preferred":[
        "\u0412\u0435\u043b\u0438\u043d\u043e"
    ],
    "name:cat_x_preferred":[
        "Velino"
    ],
    "name:ceb_x_preferred":[
        "Fiume Velino"
    ],
    "name:deu_x_preferred":[
        "Velino"
    ],
    "name:epo_x_preferred":[
        "Velino"
    ],
    "name:est_x_preferred":[
        "Velino j\u00f5gi"
    ],
    "name:fra_x_preferred":[
        "Velino"
    ],
    "name:ita_x_preferred":[
        "Velino"
    ],
    "name:lat_x_preferred":[
        "Velinus"
    ],
    "name:ota_x_preferred":[
        "\u0645\u06cc\u0631\u0627\u062e\u0648\u0631"
    ],
    "name:pol_x_preferred":[
        "Velino"
    ],
    "name:por_x_preferred":[
        "Rio Velino"
    ],
    "name:und_x_variant":[
        "Doktor Stambolsk",
        "Imrihor",
        "Doktor Stambolski",
        "Imrikhor",
        "Imrikhod",
        "Mirahur"
    ],
    "name:zho_x_preferred":[
        "\u97cb\u5229\u8afe\u6cb3"
    ],
    "wof:name":"Velino",
    "wof:placetype":"locality"
},
  "geometry": {"coordinates":[27.03333,43.41667],"type":"Point"}
}