{
  "type": "Feature",
  "properties": {
    "gn:admin1_code":"39",
    "gn:asciiname":"Morhovo",
    "gn:country_code":"BG",
    "gn:dem":402,
    "gn:feature_class":"P",
    "gn:feature_code":"PPL",
    "gn:name":"Morhovo",
    "gn:population":0,
    "gn:timezone":"Europe/Sofia",
    "iso:country":"BG",
    "name:bul_x_preferred":[
        "Morhovo"
    ],
    "name:bul_x_variant":[
        "\u041c\u043e\u0440\u0445\u043e\u0432\u043e"
    ],
    "wof:name":"Morhovo",
    "wof:placetype":"locality"
},
  "geometry": {"coordinates":[27.56125,41.93308],"type":"Point"}
}