{
  "type": "Feature",
  "properties": {
    "gn:admin1_code":"44",
    "gn:admin2_code":"KRZ35",
    "gn:admin3_code":"KRZ35-05",
    "gn:asciiname":"Bedrovo",
    "gn:cc2":"BG",
    "gn:country_code":"BG",
    "gn:dem":424,
    "gn:feature_class":"P",
    "gn:feature_code":"PPL",
    "gn:name":"Bedrovo",
    "gn:population":0,
    "gn:timezone":"Europe/Sofia",
    "iso:country":"BG",
    "name:bul_x_preferred":[
        "\u0411\u0435\u0434\u0440\u043e\u0432\u043e"
    ],
    "name:kaz_x_preferred":[
        "\u0411\u0435\u0434\u0440\u043e\u0432\u043e"
    ],
    "name:rus_x_preferred":[
        "\u0411\u0435\u0434\u0440\u043e\u0432\u043e"
    ],
    "name:ukr_x_preferred":[
        "\u0411\u0435\u0434\u0440\u043e\u0432\u043e"
    ],
    "name:und_x_variant":[
        "Bedrowo",
        "Badzhaklar",
        "Bedrovo"
    ],
    "wof:name":"Bedrovo",
    "wof:placetype":"locality"
},
  "geometry": {"coordinates":[25.36667000000001,41.75],"type":"Point"}
}