{
  "type": "Feature",
  "properties": {
    "gn:admin1_code":"62",
    "gn:admin2_code":"VTR26",
    "gn:asciiname":"Varzulitsa",
    "gn:country_code":"BG",
    "gn:dem":112,
    "gn:feature_class":"P",
    "gn:feature_code":"PPL",
    "gn:name":"Varzulitsa",
    "gn:population":0,
    "gn:timezone":"Europe/Sofia",
    "iso:country":"BG",
    "name:bul_x_preferred":[
        "\u0412\u044a\u0440\u0437\u0443\u043b\u0438\u0446\u0430"
    ],
    "name:bul_x_variant":[
        "Varzulitsa"
    ],
    "name:und_x_variant":[
        "W\u0103rsuliza",
        "V\u016drzulitsa"
    ],
    "wof:name":"Varzulitsa",
    "wof:placetype":"locality"
},
  "geometry": {"coordinates":[25.46667,43.43333],"type":"Point"}
}