{
  "type": "Feature",
  "properties": {
    "gn:admin1_code":"44",
    "gn:admin2_code":"KRZ02",
    "gn:admin3_code":"KRZ02-27",
    "gn:asciiname":"Borovitsa",
    "gn:cc2":"BG",
    "gn:country_code":"BG",
    "gn:dem":905,
    "gn:feature_class":"P",
    "gn:feature_code":"PPL",
    "gn:name":"Borovitsa",
    "gn:population":0,
    "gn:timezone":"Europe/Sofia",
    "iso:country":"BG",
    "name:bul_x_preferred":[
        "\u0411\u043e\u0440\u043e\u0432\u0438\u0446\u0430"
    ],
    "name:und_x_variant":[
        "Chamdere",
        "Borovitsa"
    ],
    "wof:name":"Borovitsa",
    "wof:placetype":"locality"
},
  "geometry": {"coordinates":[25.18333,41.71667],"type":"Point"}
}