{
  "type": "Feature",
  "properties": {
    "gn:admin1_code":"64",
    "gn:admin2_code":"VRC27",
    "gn:asciiname":"Gorna Beshovitsa",
    "gn:cc2":"BG",
    "gn:country_code":"BG",
    "gn:dem":497,
    "gn:feature_class":"P",
    "gn:feature_code":"PPL",
    "gn:name":"Gorna Beshovitsa",
    "gn:population":0,
    "gn:timezone":"Europe/Sofia",
    "iso:country":"BG",
    "name:bul_x_preferred":[
        "\u0413\u043e\u0440\u043d\u0430 \u0411\u0435\u0448\u043e\u0432\u0438\u0446\u0430"
    ],
    "name:und_x_variant":[
        "Gorna Beschowiza",
        "Gorna Beshovitsa"
    ],
    "wof:name":"Gorna Beshovitsa",
    "wof:placetype":"locality"
},
  "geometry": {"coordinates":[23.81667,43.21667],"type":"Point"}
}