{
  "type": "Feature",
  "properties": {
    "gn:admin1_code":"55",
    "gn:admin2_code":"SLS31",
    "gn:admin3_code":"SLS31-02",
    "gn:asciiname":"Babuk",
    "gn:country_code":"BG",
    "gn:dem":77,
    "gn:feature_class":"P",
    "gn:feature_code":"PPL",
    "gn:name":"Babuk",
    "gn:population":0,
    "gn:timezone":"Europe/Sofia",
    "iso:country":"BG",
    "name:bul_x_preferred":[
        "\u0411\u0430\u0431\u0443\u043a"
    ],
    "name:und_x_variant":[
        "Babuc",
        "Babuk"
    ],
    "wof:name":"Babuk",
    "wof:placetype":"locality"
},
  "geometry": {"coordinates":[27.24813,44.01119],"type":"Point"}
}