{
  "type": "Feature",
  "properties": {
    "gn:admin1_code":"46",
    "gn:admin2_code":"LOV18",
    "gn:asciiname":"Chiflik",
    "gn:country_code":"BG",
    "gn:dem":655,
    "gn:feature_class":"P",
    "gn:feature_code":"PPL",
    "gn:name":"Chiflik",
    "gn:population":0,
    "gn:timezone":"Europe/Sofia",
    "iso:country":"BG",
    "name:bul_x_preferred":[
        "\u0427\u0438\u0444\u043b\u0438\u043a"
    ],
    "name:ell_x_preferred":[
        "\u03a4\u03c3\u03b9\u03c6\u03bb\u03af\u03ba\u03b9"
    ],
    "name:fra_x_preferred":[
        "Tchiflik"
    ],
    "name:mkd_x_preferred":[
        "\u0427\u0438\u0444\u043b\u0438\u0433"
    ],
    "name:rus_x_preferred":[
        "\u0427\u0438\u0444\u0442\u043b\u0438\u043a"
    ],
    "name:sqi_x_preferred":[
        "\u00c7ifligu"
    ],
    "name:srp_x_preferred":[
        "\u0427\u0438\u0442\u043b\u0443\u043a"
    ],
    "wof:name":"Chiflik",
    "wof:placetype":"locality"
},
  "geometry": {"coordinates":[24.58294,42.83368],"type":"Point"}
}