{
  "type": "Feature",
  "properties": {
    "gn:admin1_code":"44",
    "gn:admin2_code":"KRZ14",
    "gn:admin3_code":"KRZ14-23",
    "gn:asciiname":"Lozengradtsi",
    "gn:cc2":"BG",
    "gn:country_code":"BG",
    "gn:dem":554,
    "gn:feature_class":"P",
    "gn:feature_code":"PPL",
    "gn:name":"Lozengradtsi",
    "gn:population":0,
    "gn:timezone":"Europe/Sofia",
    "iso:country":"BG",
    "name:bul_x_preferred":[
        "\u041b\u043e\u0437\u0435\u043d\u0433\u0440\u0430\u0434\u0446\u0438"
    ],
    "name:ceb_x_preferred":[
        "Lozengradci"
    ],
    "name:fas_x_preferred":[
        "\u0644\u0648\u0632\u0646\u06af\u0631\u0627\u062f\u062a\u0633\u06cc"
    ],
    "name:kaz_x_preferred":[
        "\u041b\u043e\u0437\u0435\u043d\u0433\u0440\u0430\u0434\u0446\u0438"
    ],
    "name:ron_x_preferred":[
        "Lozengrad\u021bi"
    ],
    "name:rus_x_preferred":[
        "\u041b\u043e\u0437\u0435\u043d\u0433\u0440\u0430\u0434\u0446\u0438"
    ],
    "name:swe_x_preferred":[
        "Lozengradtsi"
    ],
    "name:ukr_x_preferred":[
        "\u041b\u043e\u0437\u0435\u043d\u0433\u0440\u0430\u0434\u0446\u0456"
    ],
    "name:und_x_variant":[
        "Karakash",
        "Losengradzi",
        "Lozengradtsi"
    ],
    "wof:name":"Lozengradtsi",
    "wof:placetype":"locality"
},
  "geometry": {"coordinates":[25.39899,41.29578],"type":"Point"}
}