{
  "type": "Feature",
  "properties": {
    "gn:admin1_code":"60",
    "gn:admin2_code":"TGV35",
    "gn:asciiname":"Gorna Kabda",
    "gn:cc2":"BG",
    "gn:country_code":"BG",
    "gn:dem":454,
    "gn:feature_class":"P",
    "gn:feature_code":"PPL",
    "gn:name":"Gorna Kabda",
    "gn:population":0,
    "gn:timezone":"Europe/Sofia",
    "iso:country":"BG",
    "name:bul_x_preferred":[
        "\u0413\u043e\u0440\u043d\u0430 \u041a\u0430\u0431\u0434\u0430"
    ],
    "name:und_x_variant":[
        "Gorna Yukarki",
        "Gorna Kabda"
    ],
    "wof:name":"Gorna Kabda",
    "wof:placetype":"locality"
},
  "geometry": {"coordinates":[26.35,43.21667],"type":"Point"}
}