{
  "type": "Feature",
  "properties": {
    "gn:admin1_code":"44",
    "gn:admin2_code":"KRZ15",
    "gn:admin3_code":"KRZ15-05",
    "gn:asciiname":"Malka Chinka",
    "gn:country_code":"BG",
    "gn:dem":409,
    "gn:feature_class":"P",
    "gn:feature_code":"PPLL",
    "gn:name":"Malka Chinka",
    "gn:population":0,
    "gn:timezone":"Europe/Sofia",
    "iso:country":"BG",
    "name:bul_x_preferred":[
        "\u041c\u0430\u043b\u043a\u0430 \u0427\u0438\u043d\u043a\u0430"
    ],
    "name:und_x_variant":[
        "Yakbasan Syatir",
        "Malka Chinka"
    ],
    "wof:name":"Malka Chinka",
    "wof:placetype":"locality"
},
  "geometry": {"coordinates":[25.52873,41.39728],"type":"Point"}
}