{
  "type": "Feature",
  "properties": {
    "gn:admin1_code":"64",
    "gn:admin2_code":"VRC21",
    "gn:admin3_code":"VRC21-07",
    "gn:asciiname":"Dobrusha",
    "gn:cc2":"BG",
    "gn:country_code":"BG",
    "gn:dem":154,
    "gn:feature_class":"P",
    "gn:feature_code":"PPL",
    "gn:name":"Dobrusha",
    "gn:population":0,
    "gn:timezone":"Europe/Sofia",
    "iso:country":"BG",
    "name:bul_x_preferred":[
        "\u0414\u043e\u0431\u0440\u0443\u0448\u0430"
    ],
    "name:und_x_variant":[
        "Dobruscha",
        "Dobrusha"
    ],
    "wof:name":"Dobrusha",
    "wof:placetype":"locality"
},
  "geometry": {"coordinates":[23.42972,43.44056],"type":"Point"}
}