{
  "type": "Feature",
  "properties": {
    "gn:admin1_code":"62",
    "gn:admin2_code":"VTR13",
    "gn:asciiname":"Yakovtsi",
    "gn:cc2":"BG",
    "gn:country_code":"BG",
    "gn:dem":357,
    "gn:feature_class":"P",
    "gn:feature_code":"PPL",
    "gn:name":"Yakovtsi",
    "gn:population":0,
    "gn:timezone":"Europe/Sofia",
    "iso:country":"BG",
    "name:bul_x_preferred":[
        "\u042f\u043a\u043e\u0432\u0446\u0438"
    ],
    "name:und_x_variant":[
        "Yanovtsi",
        "Yakovts\u016d",
        "Yakovtsi"
    ],
    "wof:name":"Yakovtsi",
    "wof:placetype":"locality"
},
  "geometry": {"coordinates":[25.81667,42.93333],"type":"Point"}
}