{
  "type": "Feature",
  "properties": {
    "gn:admin1_code":"38",
    "gn:admin2_code":"BLG40",
    "gn:admin3_code":"BLG40-39",
    "gn:asciiname":"Struma",
    "gn:country_code":"BG",
    "gn:dem":124,
    "gn:feature_class":"P",
    "gn:feature_code":"PPL",
    "gn:name":"Struma",
    "gn:population":0,
    "gn:timezone":"Europe/Sofia",
    "iso:country":"BG",
    "name:bul_x_preferred":[
        "\u0421\u0442\u0440\u0443\u043c\u0430"
    ],
    "name:fas_x_preferred":[
        "\u0633\u062a\u0631\u0648\u0645\u0627"
    ],
    "name:kaz_x_preferred":[
        "\u0421\u0442\u0440\u0443\u043c\u0430"
    ],
    "name:mkd_x_preferred":[
        "\u0421\u0442\u0440\u0443\u043c\u0430"
    ],
    "name:pol_x_preferred":[
        "Struma"
    ],
    "name:ron_x_preferred":[
        "Struma"
    ],
    "name:rus_x_preferred":[
        "\u0421\u0442\u0440\u0443\u043c\u0430"
    ],
    "name:ukr_x_preferred":[
        "\u0421\u0442\u0440\u0443\u043c\u0430"
    ],
    "wof:name":"Struma",
    "wof:placetype":"locality"
},
  "geometry": {"coordinates":[23.23333,41.55],"type":"Point"}
}