{
  "type": "Feature",
  "properties": {
    "iso:country":"BG",
    "name:ara_x_preferred":[
        "\u062f\u0631\u0641\u0646\u064a\u062a\u0633\u0627"
    ],
    "name:bul_x_preferred":[
        "\u0414\u044a\u0440\u0432\u0435\u043d\u0438\u0446\u0430L"
    ],
    "name:bul_x_variant":[
        "Dimitur Gruncharov",
        "D\u00e6rweniza",
        "D\u00fervenitsa",
        "\u0414\u044a\u0440\u0432\u0435\u043d\u0438\u0446\u0430",
        "Darvenitsa"
    ],
    "name:eng_x_colloquial":[
        "Darweniza",
        "Dtrvenitsa",
        "Dthrvenitsa",
        "Daerweniza",
        "Durvenitsa"
    ],
    "name:eng_x_preferred":[
        "D\u00fervenitsa"
    ],
    "name:eng_x_variant":[
        "Dervenitsa",
        "D\u00e6rweniza",
        "Dimitur Gruncharov",
        "Darvenitsa"
    ],
    "name:nld_x_preferred":[
        "Darvenitsa"
    ],
    "qs:gn_adm0_cc":"BG",
    "qs:gn_fcode":"PPLX",
    "qs:gn_local":727011,
    "qs:gn_nam_loc":"Sofiya, Sofia, Sofiya-Grad, BG",
    "qs:gn_namadm1":"42",
    "qs:gn_name":"D\u016drvenitsa",
    "qs:local_max":4184,
    "qs:local_sum":18613,
    "qs:localhoods":26,
    "qs:name":"D\u00fervenitsa",
    "qs:name_adm0":"Bulgaria",
    "qs:name_adm1":"Sofiya-Grad",
    "qs:name_adm2":"Sofiya",
    "qs:name_local":"Sofia",
    "qs:photo_max":24,
    "qs:photo_sum":93,
    "qs:placetype":"Suburb",
    "qs:quad_count":16,
    "qs:woe_adm0":23424771,
    "qs:woe_adm1":20069794,
    "qs:woe_adm2":55873710,
    "qs:woe_lau":0,
    "qs:woe_local":839722,
    "qs:woe_ver":"7.10.0",
    "wof:lang":[
        "eng"
    ],
    "wof:name":"Darvenitsa",
    "wof:placetype":"neighbourhood"
},
  "geometry": {"coordinates":[23.366398,42.657325],"type":"Point"}
}