{
  "type": "Feature",
  "properties": {
    "gn:admin1_code":"49",
    "gn:admin2_code":"PER51",
    "gn:asciiname":"Dzhinchovtsi",
    "gn:country_code":"BG",
    "gn:dem":830,
    "gn:feature_class":"P",
    "gn:feature_code":"PPL",
    "gn:name":"Dzhinchovtsi",
    "gn:population":0,
    "gn:timezone":"Europe/Sofia",
    "iso:country":"BG",
    "name:bul_x_preferred":[
        "\u0414\u0436\u0438\u043d\u0447\u043e\u0432\u0446\u0438"
    ],
    "name:bul_x_variant":[
        "Dzhinchovtsi"
    ],
    "wof:name":"Dzhinchovtsi",
    "wof:placetype":"locality"
},
  "geometry": {"coordinates":[22.46673,42.78352],"type":"Point"}
}