{
  "type": "Feature",
  "properties": {
    "gn:admin1_code":"38",
    "gn:admin2_code":"BLG33",
    "gn:asciiname":"Drenovitsa",
    "gn:country_code":"BG",
    "gn:dem":352,
    "gn:feature_class":"P",
    "gn:feature_code":"PPL",
    "gn:name":"Drenovitsa",
    "gn:population":0,
    "gn:timezone":"Europe/Sofia",
    "iso:country":"BG",
    "name:bul_x_preferred":[
        "\u0414\u0440\u0435\u043d\u043e\u0432\u0438\u0446\u0430"
    ],
    "name:und_x_variant":[
        "Drenovets"
    ],
    "wof:name":"Drenovitsa",
    "wof:placetype":"locality"
},
  "geometry": {"coordinates":[23.06978,41.41294],"type":"Point"}
}