{
  "type": "Feature",
  "properties": {
    "gn:admin1_code":"38",
    "gn:asciiname":"Ivanovtsi",
    "gn:country_code":"BG",
    "gn:dem":983,
    "gn:feature_class":"P",
    "gn:feature_code":"PPL",
    "gn:name":"Ivanovtsi",
    "gn:population":0,
    "gn:timezone":"Europe/Sofia",
    "iso:country":"BG",
    "name:bul_x_preferred":[
        "Ivanovtsi"
    ],
    "name:bul_x_variant":[
        "\u0418\u0432\u0430\u043d\u043e\u0432\u0446\u0438"
    ],
    "wof:name":"Ivanovtsi",
    "wof:placetype":"locality"
},
  "geometry": {"coordinates":[22.91244,41.97068],"type":"Point"}
}