{
  "type": "Feature",
  "properties": {
    "gn:admin1_code":"40",
    "gn:admin2_code":"DOB17",
    "gn:admin3_code":"DOB17-15",
    "gn:asciiname":"Septemvriytsi",
    "gn:country_code":"BG",
    "gn:dem":100,
    "gn:feature_class":"P",
    "gn:feature_code":"PPL",
    "gn:name":"Septemvriytsi",
    "gn:population":0,
    "gn:timezone":"Europe/Sofia",
    "iso:country":"BG",
    "name:bul_x_preferred":[
        "\u0421\u0435\u043f\u0442\u0435\u043c\u0432\u0440\u0438\u0439\u0446\u0438"
    ],
    "name:ceb_x_preferred":[
        "\u0421\u0435\u043f\u0442\u0435\u043c\u0432\u0440\u0438\u0439\u0446\u0438"
    ],
    "name:fra_x_preferred":[
        "Septemvri\u00eftsi"
    ],
    "name:ron_x_preferred":[
        "Septemvrii\u021bi"
    ],
    "name:rus_x_preferred":[
        "\u0421\u0435\u043f\u0442\u0435\u043c\u0432\u0440\u0438\u0439\u0446\u0438"
    ],
    "name:und_x_variant":[
        "Borisovo",
        "Tsar Boris",
        "Clo\u015fca",
        "Tar Boris",
        "Tsar Borisovo",
        "Septemvriytsi"
    ],
    "wof:name":"Septemvriytsi",
    "wof:placetype":"locality"
},
  "geometry": {"coordinates":[28.36313,43.60865],"type":"Point"}
}