{
  "type": "Feature",
  "properties": {
    "gn:gn_country":"BG",
    "gn:gn_fcode":"PPL",
    "gn:gn_pop":250,
    "gn:population":250,
    "iso:country":"BG",
    "name:ara_x_preferred":[
        "\u0645\u064a\u0644\u0646\u064a\u0643"
    ],
    "name:bul_x_preferred":[
        "\u041c\u0435\u043b\u043d\u0438\u043a"
    ],
    "name:cat_x_preferred":[
        "Melnik"
    ],
    "name:chi_x_preferred":[
        "\u6885\u723e\u5c3c\u514b"
    ],
    "name:chu_x_preferred":[
        "\u041c\u0454\u043b\u044c\u043d\u0438\u043a\u044a"
    ],
    "name:cze_x_preferred":[
        "Melnik"
    ],
    "name:dut_x_preferred":[
        "Melnik"
    ],
    "name:eng_x_preferred":[
        "Melnik"
    ],
    "name:epo_x_preferred":[
        "Melnik"
    ],
    "name:fre_x_preferred":[
        "Melnik"
    ],
    "name:ger_x_preferred":[
        "Melnik"
    ],
    "name:gre_x_preferred":[
        "\u039c\u03b5\u03bb\u03ad\u03bd\u03b9\u03ba\u03bf"
    ],
    "name:heb_x_preferred":[
        "\u05de\u05dc\u05e0\u05d9\u05e7"
    ],
    "name:jpn_x_preferred":[
        "\u30e1\u30eb\u30cb\u30af"
    ],
    "name:kaz_x_preferred":[
        "\u041c\u0435\u043b\u043d\u0438\u043a"
    ],
    "name:lit_x_preferred":[
        "Melnikas"
    ],
    "name:mac_x_preferred":[
        "\u041c\u0435\u043b\u043d\u0438\u043a"
    ],
    "name:per_x_preferred":[
        "\u0645\u0644\u0646\u06cc\u06a9"
    ],
    "name:pol_x_preferred":[
        "Melnik"
    ],
    "name:por_x_preferred":[
        "Melnik"
    ],
    "name:rum_x_preferred":[
        "Melnik"
    ],
    "name:rus_x_preferred":[
        "\u041c\u0435\u043b\u043d\u0438\u043a"
    ],
    "name:spa_x_preferred":[
        "Melnik"
    ],
    "name:srp_x_preferred":[
        "\u041c\u0435\u043b\u043d\u0438\u043a"
    ],
    "name:swe_x_preferred":[
        "Melnik"
    ],
    "name:tat_x_preferred":[
        "\u041c\u0435\u043b\u043d\u0438\u043a"
    ],
    "name:tur_x_preferred":[
        "Melnik"
    ],
    "name:ukr_x_preferred":[
        "\u041c\u0435\u043b\u043d\u0438\u043a"
    ],
    "name:war_x_preferred":[
        "Melnik"
    ],
    "qs_pg:aaroncc":"BG",
    "qs_pg:gn_country":"BG",
    "qs_pg:gn_fcode":"PPL",
    "qs_pg:gn_pop":250,
    "qs_pg:name":"Melnik",
    "qs_pg:name_adm0":"Bulgaria",
    "qs_pg:name_adm1":"Blagoevgrad",
    "qs_pg:photos":173,
    "qs_pg:photos_1k":35,
    "qs_pg:photos_9k":1,
    "qs_pg:photos_9r":4,
    "qs_pg:photos_all":173,
    "qs_pg:photos_sr":4,
    "qs_pg:pop_sr":2,
    "qs_pg:qs_pg_placetype":"locality",
    "qs_pg:qs_pg_placetype_gp":"Town",
    "qs_pg:woe_adm0":23424771,
    "woe:adm0_id":23424771,
    "woe:name_adm0":"Bulgaria",
    "woe:name_adm1":"Blagoevgrad",
    "woe:placetype":"Town",
    "wof:name":"Melnik",
    "wof:placetype":"locality",
    "wof:population":250
},
  "geometry": {"coordinates":[23.39326,41.52302],"type":"Point"}
}