{
  "type": "Feature",
  "properties": {
    "gn:admin1_code":"62",
    "gn:admin2_code":"VTR04",
    "gn:asciiname":"Ushovtsi",
    "gn:cc2":"BG",
    "gn:country_code":"BG",
    "gn:dem":392,
    "gn:feature_class":"P",
    "gn:feature_code":"PPL",
    "gn:name":"Ushovtsi",
    "gn:population":0,
    "gn:timezone":"Europe/Sofia",
    "iso:country":"BG",
    "name:bul_x_preferred":[
        "\u0423\u0448\u0435\u0432\u0446\u0438"
    ],
    "name:und_x_variant":[
        "Ushevtsi",
        "Ushovtsi"
    ],
    "wof:name":"Ushovtsi",
    "wof:placetype":"locality"
},
  "geometry": {"coordinates":[25.65,42.86667],"type":"Point"}
}