{
  "type": "Feature",
  "properties": {
    "gn:admin1_code":"40",
    "gn:admin2_code":"DOB15",
    "gn:asciiname":"Orlova Mogila",
    "gn:country_code":"BG",
    "gn:dem":241,
    "gn:feature_class":"P",
    "gn:feature_code":"PPL",
    "gn:name":"Orlova Mogila",
    "gn:population":0,
    "gn:timezone":"Europe/Sofia",
    "iso:country":"BG",
    "name:bul_x_preferred":[
        "\u041e\u0440\u043b\u043e\u0432\u0430 \u041c\u043e\u0433\u0438\u043b\u0430"
    ],
    "name:und_x_variant":[
        "Orlowa Mogila",
        "Serdimen",
        "Serdiment",
        "Orlova Mogila"
    ],
    "wof:name":"Orlova Mogila",
    "wof:placetype":"locality"
},
  "geometry": {"coordinates":[27.60137000000001,43.54983],"type":"Point"}
}