{
  "type": "Feature",
  "properties": {
    "gn:admin1_code":"39",
    "gn:admin2_code":"BGS08",
    "gn:asciiname":"Vratitsa",
    "gn:country_code":"BG",
    "gn:dem":124,
    "gn:feature_class":"P",
    "gn:feature_code":"PPL",
    "gn:name":"Vratitsa",
    "gn:population":0,
    "gn:timezone":"Europe/Sofia",
    "iso:country":"BG",
    "name:bul_x_preferred":[
        "\u0412\u0440\u0430\u0442\u0438\u0446\u0430"
    ],
    "name:fas_x_preferred":[
        "\u0648\u0631\u0627\u062a\u06cc\u062a\u0633\u0627"
    ],
    "name:kaz_x_preferred":[
        "\u0412\u0440\u0430\u0442\u0438\u0446\u0430"
    ],
    "name:ron_x_preferred":[
        "Vrati\u021ba"
    ],
    "name:rus_x_preferred":[
        "\u0412\u0440\u0430\u0442\u0438\u0446\u0430"
    ],
    "name:ukr_x_preferred":[
        "\u0412\u0440\u0430\u0442\u0438\u0446\u044f"
    ],
    "name:und_x_variant":[
        "Kapedzhik-Kioi",
        "Wratiza",
        "Kapudzhik",
        "Kap\u016ddzhik-K\u2019oy",
        "Kapudzhi K\u2019oy",
        "Vratitsa"
    ],
    "wof:name":"Vratitsa",
    "wof:placetype":"locality"
},
  "geometry": {"coordinates":[27.16137,42.59215],"type":"Point"}
}