{
  "type": "Feature",
  "properties": {
    "gn:admin1_code":"57",
    "gn:admin2_code":"SML02",
    "gn:asciiname":"Debelyanovo",
    "gn:cc2":"BG",
    "gn:country_code":"BG",
    "gn:dem":850,
    "gn:feature_class":"P",
    "gn:feature_code":"PPL",
    "gn:name":"Debelyanovo",
    "gn:population":0,
    "gn:timezone":"Europe/Sofia",
    "iso:country":"BG",
    "name:bul_x_preferred":[
        "\u0414\u0435\u0431\u0435\u043b\u044f\u043d\u043e\u0432\u043e"
    ],
    "name:und_x_variant":[
        "Kaba Ach",
        "Debeljanowo",
        "Debelyanovo"
    ],
    "wof:name":"Debelyanovo",
    "wof:placetype":"locality"
},
  "geometry": {"coordinates":[24.98333,41.66667],"type":"Point"}
}