{
  "type": "Feature",
  "properties": {
    "gn:admin1_code":"60",
    "gn:admin2_code":"TGV35",
    "gn:asciiname":"Bistra",
    "gn:cc2":"BG",
    "gn:country_code":"BG",
    "gn:dem":169,
    "gn:feature_class":"P",
    "gn:feature_code":"PPL",
    "gn:name":"Bistra",
    "gn:population":0,
    "gn:timezone":"Europe/Sofia",
    "iso:country":"BG",
    "name:bos_x_preferred":[
        "Bistra"
    ],
    "name:bul_x_preferred":[
        "\u0411\u0438\u0441\u0442\u0440\u0430"
    ],
    "name:ceb_x_preferred":[
        "Bistra"
    ],
    "name:deu_x_preferred":[
        "Bistra"
    ],
    "name:epo_x_preferred":[
        "Bistra"
    ],
    "name:fra_x_preferred":[
        "Bistra"
    ],
    "name:hrv_x_preferred":[
        "Bistra"
    ],
    "name:hun_x_preferred":[
        "Bistra"
    ],
    "name:ita_x_preferred":[
        "Bistra"
    ],
    "name:nld_x_preferred":[
        "Bistra"
    ],
    "name:pol_x_preferred":[
        "Bistra"
    ],
    "name:por_x_preferred":[
        "Bistra"
    ],
    "name:ron_x_preferred":[
        "Bistra"
    ],
    "name:rus_x_preferred":[
        "\u0411\u0438\u0441\u0442\u0440\u0430"
    ],
    "name:slv_x_preferred":[
        "Bistra"
    ],
    "name:srp_x_preferred":[
        "\u0411\u0438\u0441\u0442\u0440\u0430"
    ],
    "name:swe_x_preferred":[
        "Bistra"
    ],
    "name:ukr_x_preferred":[
        "\u0411\u0456\u0441\u0442\u0440\u0430"
    ],
    "name:und_x_variant":[
        "Ayla D\u016dn",
        "Aylid\u016dn"
    ],
    "name:vol_x_preferred":[
        "Bistra"
    ],
    "wof:name":"Bistra",
    "wof:placetype":"locality"
},
  "geometry": {"coordinates":[26.56667,43.33333],"type":"Point"}
}