{
  "type": "Feature",
  "properties": {
    "gn:admin1_code":"61",
    "gn:admin2_code":"VAR16",
    "gn:admin3_code":"VAR16-11",
    "gn:asciiname":"Polyatsite",
    "gn:cc2":"BG",
    "gn:country_code":"BG",
    "gn:dem":234,
    "gn:feature_class":"P",
    "gn:feature_code":"PPL",
    "gn:name":"Polyatsite",
    "gn:population":0,
    "gn:timezone":"Europe/Sofia",
    "iso:country":"BG",
    "name:bul_x_preferred":[
        "\u041f\u043e\u043b\u044f\u0446\u0438\u0442\u0435"
    ],
    "name:und_x_variant":[
        "Bekchi",
        "Poliazite",
        "Bekchii",
        "Polyatsite"
    ],
    "wof:name":"Polyatsite",
    "wof:placetype":"locality"
},
  "geometry": {"coordinates":[27.11667000000001,42.98333],"type":"Point"}
}