{
  "type": "Feature",
  "properties": {
    "gn:admin1_code":"46",
    "gn:admin2_code":"LOV34",
    "gn:admin3_code":"LOV34-05",
    "gn:asciiname":"Borima",
    "gn:country_code":"BG",
    "gn:dem":456,
    "gn:feature_class":"P",
    "gn:feature_code":"PPL",
    "gn:name":"Borima",
    "gn:population":0,
    "gn:timezone":"Europe/Sofia",
    "iso:country":"BG",
    "name:bul_x_preferred":[
        "\u0411\u043e\u0440\u0438\u043c\u0430"
    ],
    "name:ceb_x_preferred":[
        "Borima"
    ],
    "name:fas_x_preferred":[
        "\u0628\u0648\u0631\u06cc\u0645\u0627"
    ],
    "name:kaz_x_preferred":[
        "\u0411\u043e\u0440\u0438\u043c\u0430"
    ],
    "name:pol_x_preferred":[
        "Borima"
    ],
    "name:ron_x_preferred":[
        "Borima"
    ],
    "name:rus_x_preferred":[
        "\u0411\u043e\u0440\u0438\u043c\u0430"
    ],
    "name:swe_x_preferred":[
        "Borima"
    ],
    "name:ukr_x_preferred":[
        "\u0411\u043e\u0440\u0438\u043c\u0430"
    ],
    "wof:name":"Borima",
    "wof:placetype":"locality"
},
  "geometry": {"coordinates":[24.56667,42.96667],"type":"Point"}
}