{
  "type": "Feature",
  "properties": {
    "gn:admin1_code":"45",
    "gn:admin2_code":"KNL50",
    "gn:asciiname":"Gorni Koriten",
    "gn:cc2":"BG",
    "gn:country_code":"BG",
    "gn:dem":1015,
    "gn:feature_class":"P",
    "gn:feature_code":"PPL",
    "gn:name":"Gorni Koriten",
    "gn:population":0,
    "gn:timezone":"Europe/Sofia",
    "iso:country":"BG",
    "name:bul_x_preferred":[
        "\u0413\u043e\u0440\u043d\u0438 \u041a\u043e\u0440\u0438\u0442\u0435\u043d"
    ],
    "name:fas_x_preferred":[
        "\u06af\u0648\u0631\u0646\u06cc \u06a9\u0648\u0631\u06cc\u062a\u0646"
    ],
    "name:kaz_x_preferred":[
        "\u0413\u043e\u0440\u043d\u0438-\u041a\u043e\u0440\u0438\u0442\u0435\u043d"
    ],
    "name:ron_x_preferred":[
        "Gorni Koriten"
    ],
    "name:rus_x_preferred":[
        "\u0413\u043e\u0440\u043d\u0438-\u041a\u043e\u0440\u0438\u0442\u0435\u043d"
    ],
    "name:ukr_x_preferred":[
        "\u0413\u043e\u0440\u0456\u0448\u043d\u0456\u0439 \u041a\u043e\u0440\u0438\u0442\u0435\u043d"
    ],
    "name:und_x_variant":[
        "Koriten Gorni",
        "Gorni Koriten"
    ],
    "wof:name":"Gorni Koriten",
    "wof:placetype":"locality"
},
  "geometry": {"coordinates":[22.57222,42.50472],"type":"Point"}
}