{
  "type": "Feature",
  "properties": {
    "gn:admin1_code":"39",
    "gn:admin2_code":"BGS27",
    "gn:admin3_code":"BGS27-03",
    "gn:asciiname":"Yasna Polyana",
    "gn:country_code":"BG",
    "gn:dem":60,
    "gn:feature_class":"P",
    "gn:feature_code":"PPL",
    "gn:name":"Yasna Polyana",
    "gn:population":0,
    "gn:timezone":"Europe/Sofia",
    "iso:country":"BG",
    "name:bul_x_preferred":[
        "\u042f\u0441\u043d\u0430 \u041f\u043e\u043b\u044f\u043d\u0430"
    ],
    "name:bul_x_variant":[
        "\u042f\u0441\u043d\u0430 \u043f\u043e\u043b\u044f\u043d\u0430"
    ],
    "name:ces_x_preferred":[
        "Jasna Poljana"
    ],
    "name:deu_x_preferred":[
        "Jasna Poljana"
    ],
    "name:fas_x_preferred":[
        "\u06cc\u0627\u0633\u0646\u0627 \u067e\u0648\u0644\u06cc\u0627\u0646\u0627"
    ],
    "name:kaz_x_preferred":[
        "\u042f\u0441\u043d\u0430-\u041f\u043e\u043b\u044f\u043d\u0430"
    ],
    "name:ron_x_preferred":[
        "Iasna Poleana"
    ],
    "name:rus_x_preferred":[
        "\u042f\u0441\u043d\u0430-\u041f\u043e\u043b\u044f\u043d\u0430"
    ],
    "name:spa_x_preferred":[
        "Yasna Polyana"
    ],
    "name:ukr_x_preferred":[
        "\u042f\u0441\u043d\u0430 \u041f\u043e\u043b\u044f\u043d\u0430"
    ],
    "name:und_x_variant":[
        "Alan-Kajrjak",
        "Alan Kairjak",
        "Alan-Kayryak",
        "Alan Kajrak",
        "Al\u00e1n Kairi\u00e1k"
    ],
    "name:urd_x_preferred":[
        "\u06cc\u0633\u0646\u0627 \u067e\u0648\u0644\u06cc\u0627\u0646\u0627"
    ],
    "wof:name":"Yasna Polyana",
    "wof:placetype":"locality"
},
  "geometry": {"coordinates":[27.61381,42.28074],"type":"Point"}
}