{
  "type": "Feature",
  "properties": {
    "gn:admin1_code":"39",
    "gn:admin2_code":"BGS27",
    "gn:admin3_code":"BGS27-03",
    "gn:asciiname":"Yasna Polyana",
    "gn:country_code":"BG",
    "gn:dem":60,
    "gn:feature_class":"P",
    "gn:feature_code":"PPL",
    "gn:name":"Yasna Polyana",
    "gn:population":0,
    "gn:timezone":"Europe/Sofia",
    "iso:country":"BG",
    "name:bul_x_preferred":[
        "\u042f\u0441\u043d\u0430 \u041f\u043e\u043b\u044f\u043d\u0430"
    ],
    "name:und_x_variant":[
        "Jasna Poljana",
        "Alan-Kajrjak",
        "Alan Kairjak",
        "Alan-Kayryak",
        "Alan Kajrak",
        "Al\u00e1n Kairi\u00e1k",
        "Yasna Polyana"
    ],
    "wof:name":"Yasna Polyana",
    "wof:placetype":"locality"
},
  "geometry": {"coordinates":[27.61381,42.28074],"type":"Point"}
}