{
  "type": "Feature",
  "properties": {
    "gn:admin1_code":"54",
    "gn:asciiname":"Doyrantsi",
    "gn:cc2":"BG",
    "gn:country_code":"BG",
    "gn:dem":253,
    "gn:feature_class":"P",
    "gn:feature_code":"PPL",
    "gn:name":"Doyrantsi",
    "gn:population":0,
    "gn:timezone":"Europe/Sofia",
    "iso:country":"BG",
    "name:bul_x_preferred":[
        "\u0414\u043e\u0439\u0440\u0430\u043d\u0446\u0438"
    ],
    "name:fas_x_preferred":[
        "\u062f\u0648\u06cc\u0631\u0627\u0646\u062a\u0633\u06cc"
    ],
    "name:kat_x_preferred":[
        "\u10d3\u10dd\u10d8\u10e0\u10d0\u10dc\u10ea\u10d8"
    ],
    "name:kaz_x_preferred":[
        "\u0414\u043e\u0439\u0440\u0430\u043d\u0446\u0438"
    ],
    "name:ron_x_preferred":[
        "Doiran\u021bi"
    ],
    "name:rus_x_preferred":[
        "\u0414\u043e\u0439\u0440\u0430\u043d\u0446\u0438"
    ],
    "name:ukr_x_preferred":[
        "\u0414\u043e\u0439\u0440\u0430\u043d\u0446\u0456"
    ],
    "name:und_x_variant":[
        "Doiranzi",
        "Doyranlar",
        "Doyrantsi"
    ],
    "wof:name":"Doyrantsi",
    "wof:placetype":"locality"
},
  "geometry": {"coordinates":[27.16667,43.61667],"type":"Point"}
}