{
  "type": "Feature",
  "properties": {
    "gn:admin1_code":"44",
    "gn:asciiname":"Dangovo",
    "gn:country_code":"BG",
    "gn:dem":504,
    "gn:feature_class":"P",
    "gn:feature_code":"PPL",
    "gn:name":"Dangovo",
    "gn:population":0,
    "gn:timezone":"Europe/Sofia",
    "iso:country":"BG",
    "name:bul_x_preferred":[
        "\u0414\u044a\u043d\u0433\u043e\u0432\u043e"
    ],
    "name:bul_x_variant":[
        "Dangovo"
    ],
    "name:fas_x_preferred":[
        "\u062f\u0648\u0646\u06af\u0648\u0648\u0648"
    ],
    "name:kat_x_preferred":[
        "\u10d3\u10d8\u10dc\u10d2\u10dd\u10d5\u10dd"
    ],
    "name:kaz_x_preferred":[
        "\u0414\u044b\u043d\u0433\u043e\u0432\u043e"
    ],
    "name:ron_x_preferred":[
        "D\u0103ngovo"
    ],
    "name:rus_x_preferred":[
        "\u0414\u044b\u043d\u0433\u043e\u0432\u043e"
    ],
    "name:ukr_x_preferred":[
        "\u0414\u0438\u043d\u0433\u043e\u0432\u043e"
    ],
    "name:und_x_variant":[
        "Ts\u016dngarlar",
        "Dengevo",
        "D\u016dngarlar",
        "D\u0103ngowo",
        "D\u016dngovo"
    ],
    "wof:name":"Dangovo",
    "wof:placetype":"locality"
},
  "geometry": {"coordinates":[25.33333,41.56667],"type":"Point"}
}