{
  "type": "Feature",
  "properties": {
    "gn:admin1_code":"54",
    "gn:admin2_code":"SHU23",
    "gn:asciiname":"Osmar",
    "gn:cc2":"BG",
    "gn:country_code":"BG",
    "gn:dem":165,
    "gn:feature_class":"P",
    "gn:feature_code":"PPL",
    "gn:name":"Osmar",
    "gn:population":0,
    "gn:timezone":"Europe/Sofia",
    "iso:country":"BG",
    "name:bul_x_preferred":[
        "\u041e\u0441\u043c\u0430\u0440"
    ],
    "name:und_x_variant":[
        "Osman",
        "Osmar"
    ],
    "wof:name":"Osmar",
    "wof:placetype":"locality"
},
  "geometry": {"coordinates":[26.85,43.21667],"type":"Point"}
}