{
  "type": "Feature",
  "properties": {
    "gn:admin1_code":"58",
    "gn:admin2_code":"SFO10",
    "gn:admin3_code":"SFO10-02",
    "gn:asciiname":"Baylovo",
    "gn:cc2":"BG",
    "gn:country_code":"BG",
    "gn:dem":714,
    "gn:feature_class":"P",
    "gn:feature_code":"PPL",
    "gn:name":"Baylovo",
    "gn:population":0,
    "gn:timezone":"Europe/Sofia",
    "iso:country":"BG",
    "name:aze_x_preferred":[
        "Baylovo"
    ],
    "name:bul_x_preferred":[
        "\u0411\u0430\u0439\u043b\u043e\u0432\u043e"
    ],
    "name:fra_x_preferred":[
        "Bailovo"
    ],
    "name:kaz_x_preferred":[
        "\u0411\u0430\u0439\u043b\u043e\u0432\u043e"
    ],
    "name:ron_x_preferred":[
        "Bailovo"
    ],
    "name:rus_x_preferred":[
        "\u0411\u0430\u0439\u043b\u043e\u0432\u043e"
    ],
    "name:ukr_x_preferred":[
        "\u0411\u0430\u0439\u043b\u043e\u0432\u043e"
    ],
    "name:und_x_variant":[
        "Bailowo",
        "Baylovo"
    ],
    "wof:name":"Baylovo",
    "wof:placetype":"locality"
},
  "geometry": {"coordinates":[23.81667,42.65],"type":"Point"}
}