{
  "type": "Feature",
  "properties": {
    "gn:admin1_code":"64",
    "gn:asciiname":"Smolevitsa",
    "gn:cc2":"BG",
    "gn:country_code":"BG",
    "gn:dem":861,
    "gn:feature_class":"P",
    "gn:feature_code":"PPL",
    "gn:name":"Smolevitsa",
    "gn:population":0,
    "gn:timezone":"Europe/Sofia",
    "iso:country":"BG",
    "name:bul_x_preferred":[
        "\u0421\u043c\u043e\u043b\u0435\u0432\u0438\u0446\u0430"
    ],
    "name:und_x_variant":[
        "Smolewiza",
        "Smolevitsa"
    ],
    "wof:name":"Smolevitsa",
    "wof:placetype":"locality"
},
  "geometry": {"coordinates":[23.96667,43.05],"type":"Point"}
}