{
  "type": "Feature",
  "properties": {
    "gn:admin1_code":"48",
    "gn:admin2_code":"PAZ14",
    "gn:admin3_code":"PAZ14-06",
    "gn:asciiname":"Shtarkovo",
    "gn:country_code":"BG",
    "gn:dem":256,
    "gn:feature_class":"P",
    "gn:feature_code":"PPL",
    "gn:name":"Shtarkovo",
    "gn:population":0,
    "gn:timezone":"Europe/Sofia",
    "iso:country":"BG",
    "name:bul_x_preferred":[
        "\u0429\u044a\u0440\u043a\u043e\u0432\u043e"
    ],
    "name:bul_x_variant":[
        "Shtarkovo"
    ],
    "name:und_x_variant":[
        "Sh\u016drkovo",
        "Shterkovo",
        "Scht\u0103rkowo",
        "Sht\u016drkovo"
    ],
    "wof:name":"Shtarkovo",
    "wof:placetype":"locality"
},
  "geometry": {"coordinates":[24.23532,42.30172],"type":"Point"}
}