{
  "type": "Feature",
  "properties": {
    "gn:admin1_code":"41",
    "gn:admin2_code":"GAB29",
    "gn:asciiname":"Marinovtsi",
    "gn:cc2":"BG",
    "gn:country_code":"BG",
    "gn:dem":434,
    "gn:feature_class":"P",
    "gn:feature_code":"PPL",
    "gn:name":"Marinovtsi",
    "gn:population":0,
    "gn:timezone":"Europe/Sofia",
    "iso:country":"BG",
    "name:ara_x_preferred":[
        "\u0645\u0627\u0631\u064a\u0646\u0648\u0641\u062a\u0633\u064a"
    ],
    "name:bul_x_preferred":[
        "\u041c\u0430\u0440\u0438\u043d\u043e\u0432\u0446\u0438"
    ],
    "name:fas_x_preferred":[
        "\u0645\u0627\u0631\u06cc\u0646\u0648\u0648\u062a\u0633\u06cc"
    ],
    "name:kaz_x_preferred":[
        "\u041c\u0430\u0440\u0438\u043d\u043e\u0432\u0446\u0438"
    ],
    "name:pol_x_preferred":[
        "Marinowci"
    ],
    "name:ron_x_preferred":[
        "Marinov\u021bi"
    ],
    "name:rus_x_preferred":[
        "\u041c\u0430\u0440\u0438\u043d\u043e\u0432\u0446\u0438"
    ],
    "name:ukr_x_preferred":[
        "\u041c\u0430\u0440\u0438\u043d\u043e\u0432\u0446\u0456"
    ],
    "name:und_x_variant":[
        "Marinosko",
        "Marinowzi",
        "Marinovtsi"
    ],
    "wof:name":"Marinovtsi",
    "wof:placetype":"locality"
},
  "geometry": {"coordinates":[24.91667,42.91667],"type":"Point"}
}