{
  "type": "Feature",
  "properties": {
    "gn:admin1_code":"61",
    "gn:admin2_code":"VAR02",
    "gn:asciiname":"Voditsa",
    "gn:country_code":"BG",
    "gn:dem":290,
    "gn:feature_class":"P",
    "gn:feature_code":"PPL",
    "gn:name":"Voditsa",
    "gn:population":0,
    "gn:timezone":"Europe/Sofia",
    "iso:country":"BG",
    "name:bul_x_preferred":[
        "\u0412\u043e\u0434\u0438\u0446\u0430"
    ],
    "name:und_x_variant":[
        "Sudzhas-Kioi",
        "Wodiza",
        "Sudzhas K\u2019oy",
        "Voditsa"
    ],
    "wof:name":"Voditsa",
    "wof:placetype":"locality"
},
  "geometry": {"coordinates":[27.73861,43.36896],"type":"Point"}
}