{
  "type": "Feature",
  "properties": {
    "iso:country":"BG",
    "name:bul_x_variant":[
        "A12"
    ],
    "name:eng_x_preferred":[
        "\u041b\u0430\u0443\u0442\u0430"
    ],
    "wof:name":"Lauta",
    "wof:placetype":"neighbourhood"
},
  "geometry": {"coordinates":[24.77722759206119,42.13390690754927],"type":"Point"}
}