{
  "type": "Feature",
  "properties": {
    "gn:admin1_code":"48",
    "gn:admin2_code":"PAZ19",
    "gn:admin3_code":"PAZ19-19",
    "gn:asciiname":"Ognyanovo",
    "gn:cc2":"BG",
    "gn:country_code":"BG",
    "gn:dem":193,
    "gn:feature_class":"P",
    "gn:feature_code":"PPL",
    "gn:name":"Ognyanovo",
    "gn:population":0,
    "gn:timezone":"Europe/Sofia",
    "iso:country":"BG",
    "name:bul_x_preferred":[
        "\u041e\u0433\u043d\u044f\u043d\u043e\u0432\u043e"
    ],
    "name:fra_x_preferred":[
        "Ognyanovo"
    ],
    "name:pol_x_preferred":[
        "Ognjanowo"
    ],
    "name:ron_x_preferred":[
        "Ogneanovo"
    ],
    "name:rus_x_preferred":[
        "\u041e\u0433\u043d\u044f\u043d\u043e\u0432\u043e"
    ],
    "name:ukr_x_preferred":[
        "\u041e\u0433\u043d\u044f\u043d\u043e\u0432\u043e"
    ],
    "name:und_x_variant":[
        "Mariza",
        "Saladinovo",
        "Maritsa",
        "Ognyanovo"
    ],
    "wof:name":"Ognyanovo",
    "wof:placetype":"locality"
},
  "geometry": {"coordinates":[24.41667,42.15],"type":"Point"}
}