{
  "type": "Feature",
  "properties": {
    "gn:admin1_code":"50",
    "gn:admin2_code":"PVN21",
    "gn:admin3_code":"PVN21-16",
    "gn:asciiname":"Asenovo",
    "gn:country_code":"BG",
    "gn:dem":62,
    "gn:feature_class":"P",
    "gn:feature_code":"PPL",
    "gn:name":"Asenovo",
    "gn:population":0,
    "gn:timezone":"Europe/Sofia",
    "iso:country":"BG",
    "name:bul_x_preferred":[
        "\u0410\u0441\u0435\u043d\u043e\u0432\u043e"
    ],
    "name:ceb_x_preferred":[
        "Asenovo"
    ],
    "name:fas_x_preferred":[
        "\u0622\u0633\u0646\u0648\u0648\u0648"
    ],
    "name:kat_x_preferred":[
        "\u10d0\u10e1\u10d4\u10dc\u10dd\u10d5\u10dd"
    ],
    "name:ron_x_preferred":[
        "Asenovo"
    ],
    "name:rus_x_preferred":[
        "\u0410\u0441\u0435\u043d\u043e\u0432\u043e"
    ],
    "name:swe_x_preferred":[
        "Asenovo"
    ],
    "name:ukr_x_preferred":[
        "\u0410\u0441\u0435\u043d\u043e\u0432\u043e"
    ],
    "name:und_x_variant":[
        "Asseniowo",
        "Asenovo"
    ],
    "wof:name":"Asenovo",
    "wof:placetype":"locality"
},
  "geometry": {"coordinates":[24.8658,43.55512],"type":"Point"}
}