{
  "type": "Feature",
  "properties": {
    "gn:admin1_code":"58",
    "gn:admin2_code":"SFO20",
    "gn:admin3_code":"SFO20-16",
    "gn:asciiname":"Chernyovo",
    "gn:country_code":"BG",
    "gn:dem":717,
    "gn:feature_class":"P",
    "gn:feature_code":"PPL",
    "gn:name":"Chernyovo",
    "gn:population":0,
    "gn:timezone":"Europe/Sofia",
    "iso:country":"BG",
    "name:bul_x_preferred":[
        "\u0427\u0435\u0440\u043d\u044c\u043e\u0432\u043e"
    ],
    "name:bul_x_variant":[
        "Chernyovo"
    ],
    "name:und_x_variant":[
        "Karalar",
        "Tscherniowo",
        "Chern\u2019ovo"
    ],
    "wof:name":"Chernyovo",
    "wof:placetype":"locality"
},
  "geometry": {"coordinates":[23.75,42.41667],"type":"Point"}
}