{
  "type": "Feature",
  "properties": {
    "gn:admin1_code":"59",
    "gn:admin2_code":"SZR31",
    "gn:asciiname":"Pshenichevo",
    "gn:cc2":"BG",
    "gn:country_code":"BG",
    "gn:dem":120,
    "gn:feature_class":"P",
    "gn:feature_code":"PPL",
    "gn:name":"Pshenichevo",
    "gn:population":0,
    "gn:timezone":"Europe/Sofia",
    "iso:country":"BG",
    "name:bul_x_preferred":[
        "\u041f\u0448\u0435\u043d\u0438\u0447\u0435\u0432\u043e"
    ],
    "name:und_x_variant":[
        "Golyem Duvandzhiy",
        "Ssokolowo",
        "Golyamo Duvandzhii",
        "Sokolovo",
        "Pshenichevo"
    ],
    "wof:name":"Pshenichevo",
    "wof:placetype":"locality"
},
  "geometry": {"coordinates":[25.86667000000001,42.36667],"type":"Point"}
}