{
  "type": "Feature",
  "properties": {
    "gn:admin1_code":"57",
    "gn:asciiname":"Lesiche",
    "gn:country_code":"BG",
    "gn:dem":1019,
    "gn:feature_class":"P",
    "gn:feature_code":"PPL",
    "gn:name":"Lesiche",
    "gn:population":0,
    "gn:timezone":"Europe/Sofia",
    "iso:country":"BG",
    "name:bul_x_preferred":[
        "\u041b\u0435\u0441\u0438\u0447\u0435"
    ],
    "wof:name":"Lesiche",
    "wof:placetype":"locality"
},
  "geometry": {"coordinates":[24.96667,41.66667],"type":"Point"}
}