{
  "type": "Feature",
  "properties": {
    "gn:admin1_code":"59",
    "gn:admin2_code":"SZR04",
    "gn:asciiname":"Malko Dryanovo",
    "gn:cc2":"BG",
    "gn:country_code":"BG",
    "gn:dem":418,
    "gn:feature_class":"P",
    "gn:feature_code":"PPL",
    "gn:name":"Malko Dryanovo",
    "gn:population":0,
    "gn:timezone":"Europe/Sofia",
    "iso:country":"BG",
    "name:bul_x_preferred":[
        "\u041c\u0430\u043b\u043a\u043e \u0414\u0440\u044f\u043d\u043e\u0432\u043e"
    ],
    "name:und_x_variant":[
        "Khadzhiolari",
        "Malko-Dryenovo",
        "Khadzhiolar",
        "Malko Drenowo",
        "Malko Dryanovo"
    ],
    "wof:name":"Malko Dryanovo",
    "wof:placetype":"locality"
},
  "geometry": {"coordinates":[25.28333,42.41667],"type":"Point"}
}