{
  "type": "Feature",
  "properties": {
    "gn:admin1_code":"64",
    "gn:admin2_code":"VRC08",
    "gn:admin3_code":"VRC08-12",
    "gn:asciiname":"Sokolare",
    "gn:country_code":"BG",
    "gn:dem":166,
    "gn:feature_class":"P",
    "gn:feature_code":"PPL",
    "gn:name":"Sokolare",
    "gn:population":0,
    "gn:timezone":"Europe/Sofia",
    "iso:country":"BG",
    "name:bul_x_preferred":[
        "\u0421\u043e\u043a\u043e\u043b\u0430\u0440\u0435"
    ],
    "wof:name":"Sokolare",
    "wof:placetype":"locality"
},
  "geometry": {"coordinates":[23.86667000000001,43.43333],"type":"Point"}
}