{
  "type": "Feature",
  "properties": {
    "gn:admin1_code":"39",
    "gn:admin2_code":"BGS18",
    "gn:admin3_code":"BGS18-35",
    "gn:asciiname":"Cheresha",
    "gn:cc2":"BG",
    "gn:country_code":"BG",
    "gn:dem":165,
    "gn:feature_class":"P",
    "gn:feature_code":"PPL",
    "gn:name":"Cheresha",
    "gn:population":0,
    "gn:timezone":"Europe/Sofia",
    "iso:country":"BG",
    "name:bul_x_preferred":[
        "\u0427\u0435\u0440\u0435\u0448\u0430"
    ],
    "name:ceb_x_preferred":[
        "Cheresha"
    ],
    "name:fas_x_preferred":[
        "\u0686\u0631\u0634\u0627"
    ],
    "name:kaz_x_preferred":[
        "\u0427\u0435\u0440\u0435\u0448\u0430"
    ],
    "name:ron_x_preferred":[
        "Cere\u0219a"
    ],
    "name:rus_x_preferred":[
        "\u0427\u0435\u0440\u0435\u0448\u0430"
    ],
    "name:swe_x_preferred":[
        "Tjeresja"
    ],
    "name:ukr_x_preferred":[
        "\u0427\u0435\u0440\u0435\u0448\u0430"
    ],
    "name:und_x_variant":[
        "Tscherescha",
        "Ichmey Vak\u016dv",
        "Ichme Vak\u0103v",
        "Ichime-Vakev",
        "Ichne-Vakuv"
    ],
    "wof:name":"Cheresha",
    "wof:placetype":"locality"
},
  "geometry": {"coordinates":[27.13333,42.81667],"type":"Point"}
}