{
  "type": "Feature",
  "properties": {
    "gn:admin1_code":"58",
    "gn:admin2_code":"SFO39",
    "gn:admin3_code":"SFO39-03",
    "gn:asciiname":"Belchin",
    "gn:cc2":"BG",
    "gn:country_code":"BG",
    "gn:dem":925,
    "gn:feature_class":"P",
    "gn:feature_code":"PPL",
    "gn:name":"Belchin",
    "gn:population":0,
    "gn:timezone":"Europe/Sofia",
    "iso:country":"BG",
    "name:bul_x_preferred":[
        "\u0411\u0435\u043b\u0447\u0438\u043d"
    ],
    "name:und_x_variant":[
        "Byelchin",
        "Bel\u010din",
        "Beltschin",
        "Belchin Banya",
        "Belchin"
    ],
    "wof:name":"Belchin",
    "wof:placetype":"locality"
},
  "geometry": {"coordinates":[23.38088,42.36121],"type":"Point"}
}