{
  "type": "Feature",
  "properties": {
    "gn:admin1_code":"59",
    "gn:admin2_code":"SZR37",
    "gn:asciiname":"Dvorishte",
    "gn:cc2":"BG",
    "gn:country_code":"BG",
    "gn:dem":494,
    "gn:feature_class":"P",
    "gn:feature_code":"PPL",
    "gn:name":"Dvorishte",
    "gn:population":0,
    "gn:timezone":"Europe/Sofia",
    "iso:country":"BG",
    "name:bul_x_preferred":[
        "\u0414\u0432\u043e\u0440\u0438\u0449\u0435"
    ],
    "name:und_x_variant":[
        "Mlyekarevo",
        "Yurta",
        "Dworischte",
        "Dvorishte"
    ],
    "wof:name":"Dvorishte",
    "wof:placetype":"locality"
},
  "geometry": {"coordinates":[25.71667,42.66667],"type":"Point"}
}