{
  "type": "Feature",
  "properties": {
    "gn:admin1_code":"40",
    "gn:admin2_code":"DOB20",
    "gn:admin3_code":"DOB20-13",
    "gn:asciiname":"Severnyak",
    "gn:country_code":"BG",
    "gn:dem":132,
    "gn:feature_class":"P",
    "gn:feature_code":"PPL",
    "gn:name":"Severnyak",
    "gn:population":0,
    "gn:timezone":"Europe/Sofia",
    "iso:country":"BG",
    "name:bul_x_preferred":[
        "\u0421\u0435\u0432\u0435\u0440\u043d\u044f\u043a"
    ],
    "name:fas_x_preferred":[
        "\u0633\u0648\u0631\u0646\u06cc\u0627\u06a9"
    ],
    "name:kaz_x_preferred":[
        "\u0421\u0435\u0432\u0435\u0440\u043d\u044f\u043a"
    ],
    "name:ron_x_preferred":[
        "Severneak"
    ],
    "name:rus_x_preferred":[
        "\u0421\u0435\u0432\u0435\u0440\u043d\u044f\u043a"
    ],
    "name:ukr_x_preferred":[
        "\u0421\u0435\u0432\u0435\u0440\u043d\u044f\u043a"
    ],
    "name:und_x_variant":[
        "Ters Cindu",
        "Severnjak",
        "Ters Kondu",
        "Tereskondu",
        "Severnyak"
    ],
    "wof:name":"Severnyak",
    "wof:placetype":"locality"
},
  "geometry": {"coordinates":[27.78382,43.94781],"type":"Point"}
}