{
  "type": "Feature",
  "properties": {
    "gn:admin1_code":"65",
    "gn:admin2_code":"JAM25",
    "gn:admin3_code":"JAM25-16",
    "gn:asciiname":"Kabile",
    "gn:cc2":"BG",
    "gn:country_code":"BG",
    "gn:dem":148,
    "gn:feature_class":"P",
    "gn:feature_code":"PPL",
    "gn:name":"Kabile",
    "gn:population":0,
    "gn:timezone":"Europe/Sofia",
    "iso:country":"BG",
    "name:bul_x_preferred":[
        "\u041a\u0430\u0431\u0438\u043b\u0435"
    ],
    "name:und_x_variant":[
        "Tavshan-Tepe",
        "Iswor",
        "Izvor",
        "Kabile"
    ],
    "wof:name":"Kabile",
    "wof:placetype":"locality"
},
  "geometry": {"coordinates":[26.48333,42.53333],"type":"Point"}
}