{
  "type": "Feature",
  "properties": {
    "gn:admin1_code":"44",
    "gn:asciiname":"Babintsi",
    "gn:country_code":"BG",
    "gn:dem":595,
    "gn:feature_class":"P",
    "gn:feature_code":"PPL",
    "gn:name":"Babintsi",
    "gn:population":0,
    "gn:timezone":"Europe/Sofia",
    "iso:country":"BG",
    "name:bul_x_preferred":[
        "Babintsi"
    ],
    "name:bul_x_variant":[
        "\u0411\u0430\u0431\u0438\u043d\u0446\u0438"
    ],
    "name:ceb_x_preferred":[
        "Babinci"
    ],
    "name:fas_x_preferred":[
        "\u0628\u0627\u0628\u06cc\u0646\u062a\u0633\u06cc"
    ],
    "name:kaz_x_preferred":[
        "\u0411\u0430\u0431\u0438\u043d\u0446\u0438"
    ],
    "name:ron_x_preferred":[
        "Babin\u021bi"
    ],
    "name:rus_x_preferred":[
        "\u0411\u0430\u0431\u0438\u043d\u0446\u0438"
    ],
    "name:swe_x_preferred":[
        "Babintsi"
    ],
    "name:ukr_x_preferred":[
        "\u0411\u0430\u0431\u0438\u043d\u0446\u0456"
    ],
    "wof:name":"Babintsi",
    "wof:placetype":"locality"
},
  "geometry": {"coordinates":[25.51889,41.36587],"type":"Point"}
}