{
  "type": "Feature",
  "properties": {
    "gn:admin1_code":"55",
    "gn:admin2_code":"SLS10",
    "gn:admin3_code":"SLS10-07",
    "gn:asciiname":"Zlatoklas",
    "gn:cc2":"BG",
    "gn:country_code":"BG",
    "gn:dem":127,
    "gn:feature_class":"P",
    "gn:feature_code":"PPL",
    "gn:name":"Zlatoklas",
    "gn:population":0,
    "gn:timezone":"Europe/Sofia",
    "iso:country":"BG",
    "name:bul_x_preferred":[
        "\u0417\u043b\u0430\u0442\u043e\u043a\u043b\u0430\u0441"
    ],
    "name:und_x_variant":[
        "Balabanlar",
        "Zlatoklas"
    ],
    "wof:name":"Zlatoklas",
    "wof:placetype":"locality"
},
  "geometry": {"coordinates":[27.05,43.91667],"type":"Point"}
}