{
  "type": "Feature",
  "properties": {
    "gn:admin1_code":"40",
    "gn:asciiname":"Asenovets",
    "gn:cc2":"BG",
    "gn:country_code":"BG",
    "gn:dem":177,
    "gn:feature_class":"P",
    "gn:feature_code":"PPL",
    "gn:name":"Asenovets",
    "gn:population":0,
    "gn:timezone":"Europe/Sofia",
    "iso:country":"BG",
    "name:bul_x_preferred":[
        "\u0410\u0441\u0435\u043d\u043e\u0432\u0435\u0446"
    ],
    "name:und_x_variant":[
        "Khasancha",
        "Hasancea",
        "Asenovec",
        "Asenovets"
    ],
    "wof:name":"Asenovets",
    "wof:placetype":"locality"
},
  "geometry": {"coordinates":[27.93333,43.95],"type":"Point"}
}