{
  "type": "Feature",
  "properties": {
    "gn:admin1_code":"54",
    "gn:admin2_code":"SHU11",
    "gn:admin3_code":"SHU11-15",
    "gn:asciiname":"Slivak",
    "gn:cc2":"BG",
    "gn:country_code":"BG",
    "gn:dem":365,
    "gn:feature_class":"P",
    "gn:feature_code":"PPL",
    "gn:name":"Slivak",
    "gn:population":0,
    "gn:timezone":"Europe/Sofia",
    "iso:country":"BG",
    "name:bul_x_preferred":[
        "\u0421\u043b\u0438\u0432\u0430\u043a"
    ],
    "name:und_x_variant":[
        "Erilclie",
        "Sliwak",
        "Slivak"
    ],
    "wof:name":"Slivak",
    "wof:placetype":"locality"
},
  "geometry": {"coordinates":[26.93333,43.45],"type":"Point"}
}