{
  "type": "Feature",
  "properties": {
    "gn:admin1_code":"47",
    "gn:admin2_code":"MON04",
    "gn:admin3_code":"MON04-10",
    "gn:asciiname":"Ohrid",
    "gn:country_code":"BG",
    "gn:dem":108,
    "gn:feature_class":"P",
    "gn:feature_code":"PPL",
    "gn:name":"Ohrid",
    "gn:population":0,
    "gn:timezone":"Europe/Sofia",
    "iso:country":"BG",
    "name:bul_x_preferred":[
        "\u041e\u0445\u0440\u0438\u0434"
    ],
    "name:bul_x_variant":[
        "Ohrid"
    ],
    "name:und_x_variant":[
        "Ochrid",
        "Okhrid"
    ],
    "wof:name":"Ohrid",
    "wof:placetype":"locality"
},
  "geometry": {"coordinates":[23.38167,43.45417],"type":"Point"}
}