{
  "type": "Feature",
  "properties": {
    "gn:admin1_code":"50",
    "gn:admin2_code":"PVN21",
    "gn:admin3_code":"PVN21-05",
    "gn:asciiname":"Dragash Voyvoda",
    "gn:country_code":"BG",
    "gn:dem":70,
    "gn:feature_class":"P",
    "gn:feature_code":"PPL",
    "gn:name":"Dragash Voyvoda",
    "gn:population":0,
    "gn:timezone":"Europe/Sofia",
    "iso:country":"BG",
    "name:bul_x_preferred":[
        "\u0414\u0440\u0430\u0433\u0430\u0448 \u0432\u043e\u0439\u0432\u043e\u0434\u0430"
    ],
    "name:bul_x_variant":[
        "\u0414\u0440\u0430\u0433\u0430\u0448 \u0412\u043e\u0439\u0432\u043e\u0434\u0430"
    ],
    "name:und_x_variant":[
        "Ermenluy",
        "Dragasch-Woiwoda",
        "Dragash Voyvoda"
    ],
    "wof:name":"Dragash Voyvoda",
    "wof:placetype":"locality"
},
  "geometry": {"coordinates":[24.95953,43.67847],"type":"Point"}
}